Workbook

Sheet Plataformas Credito
A1: ID | B1: DC | C1: Proveedor | D1: Hostname | E1: Nombre DNS | F1: Dirección IP | G1: Ambiente | H1: Software MDW | I1: Aplicación | J1: Servicio de Negocio | K1: Estado | L1: Categoría | M1: Tipo | N1: Número de Serie | O1: Categoría S.O | P1: Familia S.O | Q1: Sistema operativo | R1: EOL (API) | S1: Update Disponible | U1: Obsolescencia SO | V1: Obsolescencia SW MDW y/o APP | W1: Obsolescencia HW | X1: Obsolescencia BBDD | Y1: Grado de Obsolescencia Global | Z1: Proyecto Obsolescencia | AA1: Fecha Compromiso | AB1: G. Responsable Plan | AC1: Líder | AD1: Expuesto | AE1: Antivirus | AF1: DSVO | AG1: Central Desktop | AH1: Sysmon | AI1: Usuario Negocio | AJ1: Líder Gerencia | AK1: Indicador Proyecto | AM1: Cr | AN1: BIA
A2: 16 | B2: GCVE | C2: GCVE | D2: ADFS-TAKAHE-PRO | E2: takahe | F2: 10.23.4.228 | G2: Producción | H2: Sin Software MDW | I2: ADFS | J2: ADFS | K2: Encendido | L2: Virtual | M2: Máquina Virtual VmWare | N2: No aplica | O2: Microsoft Windows | P2: Microsoft Windows Server 2012 | Q2: Microsoft Windows Server 2012 (64-bit) | R2: =verificarVersionOS(Q2) -> #NAME? | S2: =IFERROR( IF(ISNUMBER(FIND("Soporte hasta: ", R2)), IF(VALUE(MID(R2,16,10))<TODAY(),"🟥 Obsoleto", IF(YEAR(VALUE(MID(R2,16,10)))=YEAR(TODAY()),"Actualizaciones disponibles", IF(YEAR(VALUE(MID(R2,16,10)))-YEAR(TODAY())=1,"Actualizaciones disponibles", IF(YEAR(VALUE(MID(R2,16,10)))-YEAR(TODAY())=2,"Actualizaciones disponibles", "Actualizaciones disponibles" ) ) ) ), "⛔ Sin datos" ), "⛔ Error en fecha" ) -> ⛔ Sin datos | T2: =IF(OR(S2 = "🟥 Obsoleto",S2 = "⛔ Sin datos"), "Ya no cuenta con actualizaciones", IFERROR( CONCATENATE( "E" & IFERROR(CHOOSE(MATCH(INDEX(ControlMensual!H:H, MATCH(F2, ControlMensual!B:B, 0)), {"ok";"no";"pendiente"}, 0),"✅","❌","🕓"), "⛔") & " ", "F" & IFERROR(CHOOSE(MATCH(INDEX(ControlMensual!I:I, MATCH(F2, ControlMensual!B:B, 0)), {"ok";"no";"pendiente"}, 0),"✅","❌","🕓"), "⛔") & " ", "M" & IFERROR(CHOOSE(MATCH(INDEX(ControlMensual!J:J, MATCH(F2, ControlMensual!B:B, 0)), {"ok";"no";"pendiente"}, 0),"✅","❌","🕓"), "⛔") & " ", "A" & IFERROR(CHOOSE(MATCH(INDEX(ControlMensual!K:K, MATCH(F2, ControlMensual!B:B, 0)), {"ok";"no";"pendiente"}, 0),"✅","❌","🕓"), "⛔") & " ", "M" & IFERROR(CHOOSE(MATCH(INDEX(ControlMensual!L:L, MATCH(F2, ControlMensual!B:B, 0)), {"ok";"no";"pendiente"}, 0),"✅","❌","🕓"), "⛔") & " ", "J" & IFERROR(CHOOSE(MATCH(INDEX(ControlMensual!M:M, MATCH(F2, ControlMensual!B:B, 0)), {"ok";"no";"pendiente"}, 0),"✅","❌","🕓"), "⛔") & " ", "J" & IFERROR(CHOOSE(MATCH(INDEX(ControlMensual!N:N, MATCH(F2, ControlMensual!B:B, 0)), {"ok";"no";"pendiente"}, 0),"✅","❌","🕓"), "⛔") & " ", "A" & IFERROR(CHOOSE(MATCH(INDEX(ControlMensual!O:O, MATCH(F2, ControlMensual!B:B, 0)), {"ok";"no";"pendiente"}, 0),"✅","❌","🕓"), "⛔") & " ", "S" & IFERROR(CHOOSE(MATCH(INDEX(ControlMensual!P:P, MATCH(F2, ControlMensual!B:B, 0)), {"ok";"no";"pendiente"}, 0),"✅","❌","🕓"), "⛔") & " ", "O" & IFERROR(CHOOSE(MATCH(INDEX(ControlMensual!Q:Q, MATCH(F2, ControlMensual!B:B, 0)), {"ok";"no";"pendiente"}, 0),"✅","❌","🕓"), "⛔") & " ", "N" & IFERROR(CHOOSE(MATCH(INDEX(ControlMensual!R:R, MATCH(F2, ControlMensual!B:B, 0)), {"ok";"no";"pendiente"}, 0),"✅","❌","🕓"), "⛔") & " ", "D" & IFERROR(CHOOSE(MATCH(INDEX(ControlMensual!S:S, MATCH(F2, ControlMensual!B:B, 0)), {"ok";"no";"pendiente"}, 0),"✅","❌","🕓"), "⛔") ) ,"") ) -> Ya no cuenta con actualizaciones | U2: Si | V2: No | W2: No | X2: No Aplica | Y2: =COUNTIF(U2:X2,"Si")/(COUNTIF(U2:X2,"Si")+COUNTIF(U2:X2,"No")) -> 0.33333333 | Z2: Migración FICO | AA2: 45930 | AB2: Sistemas Financieros | AC2: Claudia León | AD2: No | AE2: =VLOOKUP(E2,Falcon!B$2:C$558,2,FALSE) -> #REF! | AF2: =VLOOKUP(E2,VisionOne!B$2:C$229,2,FALSE) -> #REF! | AG2: =VLOOKUP(E2,Central!B$2:C$217,2,FALSE) -> #REF! | AH2: Si | AJ2: Patricio Alegría | AK2: Si | AL2: x | AM2: =VLOOKUP(D2,'Copia de vInfo 2'!A:A,1,FALSE) -> #REF!
A3: 19 | B3: GCVE | C3: GCVE | D3: RIESGO-BACHELOR-PRO | E3: BACHELOR | F3: 10.23.2.119 | G3: Producción | H3: Sin Software MDW | I3: Análisis Datos Riesgo | J3: Análisis Datos Riesgo | K3: Encendido | L3: Virtual | M3: Máquina Virtual VmWare | N3: No aplica | O3: Microsoft Windows | P3: Microsoft Windows Server 2008 | Q3: Microsoft Windows Server 2008 R2 (64-bit) | R3: =verificarVersionOS(Q3) -> #NAME? | S3: =IFERROR( IF(ISNUMBER(FIND("Soporte hasta: ", R3)), IF(VALUE(MID(R3,16,10))<TODAY(),"🟥 Obsoleto", IF(YEAR(VALUE(MID(R3,16,10)))=YEAR(TODAY()),"Actualizaciones disponibles", IF(YEAR(VALUE(MID(R3,16,10)))-YEAR(TODAY())=1,"Actualizaciones disponibles", IF(YEAR(VALUE(MID(R3,16,10)))-YEAR(TODAY())=2,"Actualizaciones disponibles", "Actualizaciones disponibles" ) ) ) ), "⛔ Sin datos" ), "⛔ Error en fecha" ) -> ⛔ Sin datos | T3: =IF(OR(S3 = "🟥 Obsoleto",S3 = "⛔ Sin datos"), "Ya no cuenta con actualizaciones", IFERROR( CONCATENATE( "E" & IFERROR(CHOOSE(MATCH(INDEX(ControlMensual!H:H, MATCH(F3, ControlMensual!B:B, 0)), {"ok";"no";"pendiente"}, 0),"✅","❌","🕓"), "⛔") & " ", "F" & IFERROR(CHOOSE(MATCH(INDEX(ControlMensual!I:I, MATCH(F3, ControlMensual!B:B, 0)), {"ok";"no";"pendiente"}, 0),"✅","❌","🕓"), "⛔") & " ", "M" & IFERROR(CHOOSE(MATCH(INDEX(ControlMensual!J:J, MATCH(F3, ControlMensual!B:B, 0)), {"ok";"no";"pendiente"}, 0),"✅","❌","🕓"), "⛔") & " ", "A" & IFERROR(CHOOSE(MATCH(INDEX(ControlMensual!K:K, MATCH(F3, ControlMensual!B:B, 0)), {"ok";"no";"pendiente"}, 0),"✅","❌","🕓"), "⛔") & " ", "M" & IFERROR(CHOOSE(MATCH(INDEX(ControlMensual!L:L, MATCH(F3, ControlMensual!B:B, 0)), {"ok";"no";"pendiente"}, 0),"✅","❌","🕓"), "⛔") & " ", "J" & IFERROR(CHOOSE(MATCH(INDEX(ControlMensual!M:M, MATCH(F3, ControlMensual!B:B, 0)), {"ok";"no";"pendiente"}, 0),"✅","❌","🕓"), "⛔") & " ", "J" & IFERROR(CHOOSE(MATCH(INDEX(ControlMensual!N:N, MATCH(F3, ControlMensual!B:B, 0)), {"ok";"no";"pendiente"}, 0),"✅","❌","🕓"), "⛔") & " ", "A" & IFERROR(CHOOSE(MATCH(INDEX(ControlMensual!O:O, MATCH(F3, ControlMensual!B:B, 0)), {"ok";"no";"pendiente"}, 0),"✅","❌","🕓"), "⛔") & " ", "S" & IFERROR(CHOOSE(MATCH(INDEX(ControlMensual!P:P, MATCH(F3, ControlMensual!B:B, 0)), {"ok";"no";"pendiente"}, 0),"✅","❌","🕓"), "⛔") & " ", "O" & IFERROR(CHOOSE(MATCH(INDEX(ControlMensual!Q:Q, MATCH(F3, ControlMensual!B:B, 0)), {"ok";"no";"pendiente"}, 0),"✅","❌","🕓"), "⛔") & " ", "N" & IFERROR(CHOOSE(MATCH(INDEX(ControlMensual!R:R, MATCH(F3, ControlMensual!B:B, 0)), {"ok";"no";"pendiente"}, 0),"✅","❌","🕓"), "⛔") & " ", "D" & IFERROR(CHOOSE(MATCH(INDEX(ControlMensual!S:S, MATCH(F3, ControlMensual!B:B, 0)), {"ok";"no";"pendiente"}, 0),"✅","❌","🕓"), "⛔") ) ,"") ) -> Ya no cuenta con actualizaciones | U3: Si | V3: Si | W3: No | X3: No aplica | Y3: =COUNTIF(U3:X3,"Si")/(COUNTIF(U3:X3,"Si")+COUNTIF(U3:X3,"No")) -> 0.66666667 | Z3: Sin Proyecto | AA3: Sin Fecha | AB3: Riesgos | AC3: Sin Asignación | AD3: No | AE3: =VLOOKUP(E3,Falcon!B$2:C$558,2,FALSE) -> #REF! | AF3: =VLOOKUP(E3,VisionOne!B$2:C$229,2,FALSE) -> #REF! | AG3: =VLOOKUP(E3,Central!B$2:C$217,2,FALSE) -> #REF! | AH3: No | AJ3: Cristian Rosales | AK3: No | AM3: =VLOOKUP(D3,'Copia de vInfo 2'!A:A,1,FALSE) -> #REF!
A4: 21 | B4: GCVE | C4: GCVE | D4: RIESGO-COPIAPO-PRO | E4: COPIAPO | F4: 10.23.2.158 | G4: Producción | H4: Sin Software MDW | I4: Análisis Datos Riesgo | J4: Análisis Datos Riesgo | K4: Encendido | L4: Virtual | M4: Máquina Virtual VmWare | N4: No aplica | O4: Microsoft Windows | P4: Microsoft Windows Server 2008 | Q4: Microsoft Windows Server 2008 R2 (64-bit) | R4: =verificarVersionOS(Q4) -> #NAME? | S4: =IFERROR( IF(ISNUMBER(FIND("Soporte hasta: ", R4)), IF(VALUE(MID(R4,16,10))<TODAY(),"🟥 Obsoleto", IF(YEAR(VALUE(MID(R4,16,10)))=YEAR(TODAY()),"Actualizaciones disponibles", IF(YEAR(VALUE(MID(R4,16,10)))-YEAR(TODAY())=1,"Actualizaciones disponibles", IF(YEAR(VALUE(MID(R4,16,10)))-YEAR(TODAY())=2,"Actualizaciones disponibles", "Actualizaciones disponibles" ) ) ) ), "⛔ Sin datos" ), "⛔ Error en fecha" ) -> ⛔ Sin datos | T4: =IF(OR(S4 = "🟥 Obsoleto",S4 = "⛔ Sin datos"), "Ya no cuenta con actualizaciones", IFERROR( CONCATENATE( "E" & IFERROR(CHOOSE(MATCH(INDEX(ControlMensual!H:H, MATCH(F4, ControlMensual!B:B, 0)), {"ok";"no";"pendiente"}, 0),"✅","❌","🕓"), "⛔") & " ", "F" & IFERROR(CHOOSE(MATCH(INDEX(ControlMensual!I:I, MATCH(F4, ControlMensual!B:B, 0)), {"ok";"no";"pendiente"}, 0),"✅","❌","🕓"), "⛔") & " ", "M" & IFERROR(CHOOSE(MATCH(INDEX(ControlMensual!J:J, MATCH(F4, ControlMensual!B:B, 0)), {"ok";"no";"pendiente"}, 0),"✅","❌","🕓"), "⛔") & " ", "A" & IFERROR(CHOOSE(MATCH(INDEX(ControlMensual!K:K, MATCH(F4, ControlMensual!B:B, 0)), {"ok";"no";"pendiente"}, 0),"✅","❌","🕓"), "⛔") & " ", "M" & IFERROR(CHOOSE(MATCH(INDEX(ControlMensual!L:L, MATCH(F4, ControlMensual!B:B, 0)), {"ok";"no";"pendiente"}, 0),"✅","❌","🕓"), "⛔") & " ", "J" & IFERROR(CHOOSE(MATCH(INDEX(ControlMensual!M:M, MATCH(F4, ControlMensual!B:B, 0)), {"ok";"no";"pendiente"}, 0),"✅","❌","🕓"), "⛔") & " ", "J" & IFERROR(CHOOSE(MATCH(INDEX(ControlMensual!N:N, MATCH(F4, ControlMensual!B:B, 0)), {"ok";"no";"pendiente"}, 0),"✅","❌","🕓"), "⛔") & " ", "A" & IFERROR(CHOOSE(MATCH(INDEX(ControlMensual!O:O, MATCH(F4, ControlMensual!B:B, 0)), {"ok";"no";"pendiente"}, 0),"✅","❌","🕓"), "⛔") & " ", "S" & IFERROR(CHOOSE(MATCH(INDEX(ControlMensual!P:P, MATCH(F4, ControlMensual!B:B, 0)), {"ok";"no";"pendiente"}, 0),"✅","❌","🕓"), "⛔") & " ", "O" & IFERROR(CHOOSE(MATCH(INDEX(ControlMensual!Q:Q, MATCH(F4, ControlMensual!B:B, 0)), {"ok";"no";"pendiente"}, 0),"✅","❌","🕓"), "⛔") & " ", "N" & IFERROR(CHOOSE(MATCH(INDEX(ControlMensual!R:R, MATCH(F4, ControlMensual!B:B, 0)), {"ok";"no";"pendiente"}, 0),"✅","❌","🕓"), "⛔") & " ", "D" & IFERROR(CHOOSE(MATCH(INDEX(ControlMensual!S:S, MATCH(F4, ControlMensual!B:B, 0)), {"ok";"no";"pendiente"}, 0),"✅","❌","🕓"), "⛔") ) ,"") ) -> Ya no cuenta con actualizaciones | U4: Si | V4: Si | W4: No | X4: Si | Y4: =COUNTIF(U4:X4,"Si")/(COUNTIF(U4:X4,"Si")+COUNTIF(U4:X4,"No")) -> 0.75 | Z4: Sin Proyecto | AA4: Sin Fecha | AB4: Riesgos | AC4: Santiago Galleguillos | AD4: No | AE4: =VLOOKUP(E4,Falcon!B$2:C$558,2,FALSE) -> #REF! | AF4: =VLOOKUP(E4,VisionOne!B$2:C$229,2,FALSE) -> #REF! | AG4: =VLOOKUP(E4,Central!B$2:C$217,2,FALSE) -> #REF! | AH4: No | AI4: Santiago Galleguillos | AJ4: Cristian Rosales | AK4: No | AM4: =VLOOKUP(D4,'Copia de vInfo 2'!A:A,1,FALSE) -> #REF!
A5: 47 | B5: GCVE | C5: GCVE | D5: CREDIGI-COCHONS-DEV | E5: cochons | F5: 10.23.2.213 | G5: Desarrollo | H5: Sin Software MDW | I5: Crédito Digital | J5: Crédito Digital | K5: Encendido | L5: Virtual | M5: Máquina Virtual VmWare | N5: No aplica | O5: Linux | P5: Centos 4/5/6/7 | Q5: CentOS 7 (64-bit) | R5: =verificarVersionOS(Q5) -> #NAME? | S5: =IFERROR( IF(ISNUMBER(FIND("Soporte hasta: ", R5)), IF(VALUE(MID(R5,16,10))<TODAY(),"🟥 Obsoleto", IF(YEAR(VALUE(MID(R5,16,10)))=YEAR(TODAY()),"Actualizaciones disponibles", IF(YEAR(VALUE(MID(R5,16,10)))-YEAR(TODAY())=1,"Actualizaciones disponibles", IF(YEAR(VALUE(MID(R5,16,10)))-YEAR(TODAY())=2,"Actualizaciones disponibles", "Actualizaciones disponibles" ) ) ) ), "⛔ Sin datos" ), "⛔ Error en fecha" ) -> ⛔ Sin datos | T5: =IF(OR(S5 = "🟥 Obsoleto",S5 = "⛔ Sin datos"), "Ya no cuenta con actualizaciones", IFERROR( CONCATENATE( "E" & IFERROR(CHOOSE(MATCH(INDEX(ControlMensual!H:H, MATCH(F5, ControlMensual!B:B, 0)), {"ok";"no";"pendiente"}, 0),"✅","❌","🕓"), "⛔") & " ", "F" & IFERROR(CHOOSE(MATCH(INDEX(ControlMensual!I:I, MATCH(F5, ControlMensual!B:B, 0)), {"ok";"no";"pendiente"}, 0),"✅","❌","🕓"), "⛔") & " ", "M" & IFERROR(CHOOSE(MATCH(INDEX(ControlMensual!J:J, MATCH(F5, ControlMensual!B:B, 0)), {"ok";"no";"pendiente"}, 0),"✅","❌","🕓"), "⛔") & " ", "A" & IFERROR(CHOOSE(MATCH(INDEX(ControlMensual!K:K, MATCH(F5, ControlMensual!B:B, 0)), {"ok";"no";"pendiente"}, 0),"✅","❌","🕓"), "⛔") & " ", "M" & IFERROR(CHOOSE(MATCH(INDEX(ControlMensual!L:L, MATCH(F5, ControlMensual!B:B, 0)), {"ok";"no";"pendiente"}, 0),"✅","❌","🕓"), "⛔") & " ", "J" & IFERROR(CHOOSE(MATCH(INDEX(ControlMensual!M:M, MATCH(F5, ControlMensual!B:B, 0)), {"ok";"no";"pendiente"}, 0),"✅","❌","🕓"), "⛔") & " ", "J" & IFERROR(CHOOSE(MATCH(INDEX(ControlMensual!N:N, MATCH(F5, ControlMensual!B:B, 0)), {"ok";"no";"pendiente"}, 0),"✅","❌","🕓"), "⛔") & " ", "A" & IFERROR(CHOOSE(MATCH(INDEX(ControlMensual!O:O, MATCH(F5, ControlMensual!B:B, 0)), {"ok";"no";"pendiente"}, 0),"✅","❌","🕓"), "⛔") & " ", "S" & IFERROR(CHOOSE(MATCH(INDEX(ControlMensual!P:P, MATCH(F5, ControlMensual!B:B, 0)), {"ok";"no";"pendiente"}, 0),"✅","❌","🕓"), "⛔") & " ", "O" & IFERROR(CHOOSE(MATCH(INDEX(ControlMensual!Q:Q, MATCH(F5, ControlMensual!B:B, 0)), {"ok";"no";"pendiente"}, 0),"✅","❌","🕓"), "⛔") & " ", "N" & IFERROR(CHOOSE(MATCH(INDEX(ControlMensual!R:R, MATCH(F5, ControlMensual!B:B, 0)), {"ok";"no";"pendiente"}, 0),"✅","❌","🕓"), "⛔") & " ", "D" & IFERROR(CHOOSE(MATCH(INDEX(ControlMensual!S:S, MATCH(F5, ControlMensual!B:B, 0)), {"ok";"no";"pendiente"}, 0),"✅","❌","🕓"), "⛔") ) ,"") ) -> Ya no cuenta con actualizaciones | U5: Si | V5: Si | W5: No | X5: No Aplica | Y5: =COUNTIF(U5:X5,"Si")/(COUNTIF(U5:X5,"Si")+COUNTIF(U5:X5,"No")) -> 0.66666667 | Z5: Sin Proyecto | AA5: Sin Fecha | AB5: Sistemas Financieros | AC5: Sin Asignación | AD5: No | AE5: =VLOOKUP(E6,Falcon!B$2:C$558,2,FALSE) -> #REF! | AF5: =VLOOKUP(E5,VisionOne!B$2:C$229,2,FALSE) -> #REF! | AG5: =VLOOKUP(E5,Central!B$2:C$217,2,FALSE) -> #REF! | AH5: No | AJ5: Patricio Alegría | AK5: No
A6: 48 | B6: GCVE | C6: GCVE | D6: CREDIGI-SANPAUL-DEV | E6: sanpaul | F6: 10.23.2.212 | G6: Desarrollo | H6: Sin Software MDW | I6: Crédito Digital | J6: Crédito Digital | K6: Encendido | L6: Virtual | M6: Máquina Virtual VmWare | N6: No aplica | O6: Linux | P6: Centos 4/5/6/7 | Q6: CentOS 7 (64-bit) | R6: =verificarVersionOS(Q6) -> #NAME? | S6: =IFERROR( IF(ISNUMBER(FIND("Soporte hasta: ", R6)), IF(VALUE(MID(R6,16,10))<TODAY(),"🟥 Obsoleto", IF(YEAR(VALUE(MID(R6,16,10)))=YEAR(TODAY()),"Actualizaciones disponibles", IF(YEAR(VALUE(MID(R6,16,10)))-YEAR(TODAY())=1,"Actualizaciones disponibles", IF(YEAR(VALUE(MID(R6,16,10)))-YEAR(TODAY())=2,"Actualizaciones disponibles", "Actualizaciones disponibles" ) ) ) ), "⛔ Sin datos" ), "⛔ Error en fecha" ) -> ⛔ Sin datos | T6: =IF(OR(S6 = "🟥 Obsoleto",S6 = "⛔ Sin datos"), "Ya no cuenta con actualizaciones", IFERROR( CONCATENATE( "E" & IFERROR(CHOOSE(MATCH(INDEX(ControlMensual!H:H, MATCH(F6, ControlMensual!B:B, 0)), {"ok";"no";"pendiente"}, 0),"✅","❌","🕓"), "⛔") & " ", "F" & IFERROR(CHOOSE(MATCH(INDEX(ControlMensual!I:I, MATCH(F6, ControlMensual!B:B, 0)), {"ok";"no";"pendiente"}, 0),"✅","❌","🕓"), "⛔") & " ", "M" & IFERROR(CHOOSE(MATCH(INDEX(ControlMensual!J:J, MATCH(F6, ControlMensual!B:B, 0)), {"ok";"no";"pendiente"}, 0),"✅","❌","🕓"), "⛔") & " ", "A" & IFERROR(CHOOSE(MATCH(INDEX(ControlMensual!K:K, MATCH(F6, ControlMensual!B:B, 0)), {"ok";"no";"pendiente"}, 0),"✅","❌","🕓"), "⛔") & " ", "M" & IFERROR(CHOOSE(MATCH(INDEX(ControlMensual!L:L, MATCH(F6, ControlMensual!B:B, 0)), {"ok";"no";"pendiente"}, 0),"✅","❌","🕓"), "⛔") & " ", "J" & IFERROR(CHOOSE(MATCH(INDEX(ControlMensual!M:M, MATCH(F6, ControlMensual!B:B, 0)), {"ok";"no";"pendiente"}, 0),"✅","❌","🕓"), "⛔") & " ", "J" & IFERROR(CHOOSE(MATCH(INDEX(ControlMensual!N:N, MATCH(F6, ControlMensual!B:B, 0)), {"ok";"no";"pendiente"}, 0),"✅","❌","🕓"), "⛔") & " ", "A" & IFERROR(CHOOSE(MATCH(INDEX(ControlMensual!O:O, MATCH(F6, ControlMensual!B:B, 0)), {"ok";"no";"pendiente"}, 0),"✅","❌","🕓"), "⛔") & " ", "S" & IFERROR(CHOOSE(MATCH(INDEX(ControlMensual!P:P, MATCH(F6, ControlMensual!B:B, 0)), {"ok";"no";"pendiente"}, 0),"✅","❌","🕓"), "⛔") & " ", "O" & IFERROR(CHOOSE(MATCH(INDEX(ControlMensual!Q:Q, MATCH(F6, ControlMensual!B:B, 0)), {"ok";"no";"pendiente"}, 0),"✅","❌","🕓"), "⛔") & " ", "N" & IFERROR(CHOOSE(MATCH(INDEX(ControlMensual!R:R, MATCH(F6, ControlMensual!B:B, 0)), {"ok";"no";"pendiente"}, 0),"✅","❌","🕓"), "⛔") & " ", "D" & IFERROR(CHOOSE(MATCH(INDEX(ControlMensual!S:S, MATCH(F6, ControlMensual!B:B, 0)), {"ok";"no";"pendiente"}, 0),"✅","❌","🕓"), "⛔") ) ,"") ) -> Ya no cuenta con actualizaciones | U6: Si | V6: Si | W6: No | X6: No Aplica | Y6: =COUNTIF(U6:X6,"Si")/(COUNTIF(U6:X6,"Si")+COUNTIF(U6:X6,"No")) -> 0.66666667 | Z6: Sin Proyecto | AA6: Sin Fecha | AB6: Sistemas Financieros | AC6: Sin Asignación | AD6: No | AF6: =VLOOKUP(E6,VisionOne!B$2:C$229,2,FALSE) -> #REF! | AG6: =VLOOKUP(E6,Central!B$2:C$217,2,FALSE) -> #REF! | AH6: No | AJ6: Patricio Alegría | AK6: No | AM6: =VLOOKUP(D6,'Copia de vInfo 2'!A:A,1,FALSE) -> #REF!
A7: 172 | B7: Alonso Ovalle | C7: Alonso Ovalle | D7: DESA-WEBLOGIC-BORALE | E7: borale | F7: 10.23.4.98 | G7: Desarrollo | H7: =VLOOKUP(D7,'Inventario Plataformas OLD 260325'!I:Q,2,FALSE) -> #REF! | I7: Weblogic Transversal | J7: Servicios Transversales MDW | K7: Encendido | L7: Virtual | M7: Máquina Virtual VmWare | N7: No aplica | O7: Linux | P7: Red Hat Enterprise Linux 6 | Q7: Red Hat Enterprise Linux 6 (64-bit) | R7: =verificarVersionOS(Q7) -> #NAME? | S7: =IFERROR( IF(ISNUMBER(FIND("Soporte hasta: ", R7)), IF(VALUE(MID(R7,16,10))<TODAY(),"🟥 Obsoleto", IF(YEAR(VALUE(MID(R7,16,10)))=YEAR(TODAY()),"Actualizaciones disponibles", IF(YEAR(VALUE(MID(R7,16,10)))-YEAR(TODAY())=1,"Actualizaciones disponibles", IF(YEAR(VALUE(MID(R7,16,10)))-YEAR(TODAY())=2,"Actualizaciones disponibles", "Actualizaciones disponibles" ) ) ) ), "⛔ Sin datos" ), "⛔ Error en fecha" ) -> ⛔ Sin datos | T7: =IF(OR(S7 = "🟥 Obsoleto",S7 = "⛔ Sin datos"), "Ya no cuenta con actualizaciones", IFERROR( CONCATENATE( "E" & IFERROR(CHOOSE(MATCH(INDEX(ControlMensual!H:H, MATCH(F7, ControlMensual!B:B, 0)), {"ok";"no";"pendiente"}, 0),"✅","❌","🕓"), "⛔") & " ", "F" & IFERROR(CHOOSE(MATCH(INDEX(ControlMensual!I:I, MATCH(F7, ControlMensual!B:B, 0)), {"ok";"no";"pendiente"}, 0),"✅","❌","🕓"), "⛔") & " ", "M" & IFERROR(CHOOSE(MATCH(INDEX(ControlMensual!J:J, MATCH(F7, ControlMensual!B:B, 0)), {"ok";"no";"pendiente"}, 0),"✅","❌","🕓"), "⛔") & " ", "A" & IFERROR(CHOOSE(MATCH(INDEX(ControlMensual!K:K, MATCH(F7, ControlMensual!B:B, 0)), {"ok";"no";"pendiente"}, 0),"✅","❌","🕓"), "⛔") & " ", "M" & IFERROR(CHOOSE(MATCH(INDEX(ControlMensual!L:L, MATCH(F7, ControlMensual!B:B, 0)), {"ok";"no";"pendiente"}, 0),"✅","❌","🕓"), "⛔") & " ", "J" & IFERROR(CHOOSE(MATCH(INDEX(ControlMensual!M:M, MATCH(F7, ControlMensual!B:B, 0)), {"ok";"no";"pendiente"}, 0),"✅","❌","🕓"), "⛔") & " ", "J" & IFERROR(CHOOSE(MATCH(INDEX(ControlMensual!N:N, MATCH(F7, ControlMensual!B:B, 0)), {"ok";"no";"pendiente"}, 0),"✅","❌","🕓"), "⛔") & " ", "A" & IFERROR(CHOOSE(MATCH(INDEX(ControlMensual!O:O, MATCH(F7, ControlMensual!B:B, 0)), {"ok";"no";"pendiente"}, 0),"✅","❌","🕓"), "⛔") & " ", "S" & IFERROR(CHOOSE(MATCH(INDEX(ControlMensual!P:P, MATCH(F7, ControlMensual!B:B, 0)), {"ok";"no";"pendiente"}, 0),"✅","❌","🕓"), "⛔") & " ", "O" & IFERROR(CHOOSE(MATCH(INDEX(ControlMensual!Q:Q, MATCH(F7, ControlMensual!B:B, 0)), {"ok";"no";"pendiente"}, 0),"✅","❌","🕓"), "⛔") & " ", "N" & IFERROR(CHOOSE(MATCH(INDEX(ControlMensual!R:R, MATCH(F7, ControlMensual!B:B, 0)), {"ok";"no";"pendiente"}, 0),"✅","❌","🕓"), "⛔") & " ", "D" & IFERROR(CHOOSE(MATCH(INDEX(ControlMensual!S:S, MATCH(F7, ControlMensual!B:B, 0)), {"ok";"no";"pendiente"}, 0),"✅","❌","🕓"), "⛔") ) ,"") ) -> Ya no cuenta con actualizaciones | U7: Si | V7: Si | W7: No | X7: No Aplica | Y7: =COUNTIF(U7:X7,"Si")/(COUNTIF(U7:X7,"Si")+COUNTIF(U7:X7,"No")) -> 0.66666667 | Z7: Sin Proyecto | AA7: Sin Fecha | AB7: Sistemas de Negocio | AC7: Sin Asignación | AD7: No | AE7: =VLOOKUP(E7,Falcon!B$2:C$558,2,FALSE) -> #REF! | AF7: =VLOOKUP(E7,VisionOne!B$2:C$229,2,FALSE) -> #REF! | AG7: =VLOOKUP(E7,Central!B$2:C$217,2,FALSE) -> #REF! | AH7: No | AJ7: Sin Asignación | AK7: No | AM7: =VLOOKUP(D7,'Copia de vInfo 2'!A:A,1,FALSE) -> #REF!
A8: 189 | B8: Alonso Ovalle | C8: Alonso Ovalle | D8: M2CAPPRD2 | E8: m2capprd2 | F8: 10.23.3.32 | G8: Producción | H8: Menú Andes (Pivote) | I8: Menú Andes (Pivote) | J8: Menú Andes | K8: Encendido | L8: Virtual | M8: Máquina Virtual VmWare | N8: No aplica | O8: Linux | P8: Oracle Linux 7 | Q8: Oracle Linux 7 (64-bit) | R8: =verificarVersionOS(Q8) -> #NAME? | S8: =IFERROR( IF(ISNUMBER(FIND("Soporte hasta: ", R8)), IF(VALUE(MID(R8,16,10))<TODAY(),"🟥 Obsoleto", IF(YEAR(VALUE(MID(R8,16,10)))=YEAR(TODAY()),"Actualizaciones disponibles", IF(YEAR(VALUE(MID(R8,16,10)))-YEAR(TODAY())=1,"Actualizaciones disponibles", IF(YEAR(VALUE(MID(R8,16,10)))-YEAR(TODAY())=2,"Actualizaciones disponibles", "Actualizaciones disponibles" ) ) ) ), "⛔ Sin datos" ), "⛔ Error en fecha" ) -> ⛔ Sin datos | T8: =IF(OR(S8 = "🟥 Obsoleto",S8 = "⛔ Sin datos"), "Ya no cuenta con actualizaciones", IFERROR( CONCATENATE( "E" & IFERROR(CHOOSE(MATCH(INDEX(ControlMensual!H:H, MATCH(F8, ControlMensual!B:B, 0)), {"ok";"no";"pendiente"}, 0),"✅","❌","🕓"), "⛔") & " ", "F" & IFERROR(CHOOSE(MATCH(INDEX(ControlMensual!I:I, MATCH(F8, ControlMensual!B:B, 0)), {"ok";"no";"pendiente"}, 0),"✅","❌","🕓"), "⛔") & " ", "M" & IFERROR(CHOOSE(MATCH(INDEX(ControlMensual!J:J, MATCH(F8, ControlMensual!B:B, 0)), {"ok";"no";"pendiente"}, 0),"✅","❌","🕓"), "⛔") & " ", "A" & IFERROR(CHOOSE(MATCH(INDEX(ControlMensual!K:K, MATCH(F8, ControlMensual!B:B, 0)), {"ok";"no";"pendiente"}, 0),"✅","❌","🕓"), "⛔") & " ", "M" & IFERROR(CHOOSE(MATCH(INDEX(ControlMensual!L:L, MATCH(F8, ControlMensual!B:B, 0)), {"ok";"no";"pendiente"}, 0),"✅","❌","🕓"), "⛔") & " ", "J" & IFERROR(CHOOSE(MATCH(INDEX(ControlMensual!M:M, MATCH(F8, ControlMensual!B:B, 0)), {"ok";"no";"pendiente"}, 0),"✅","❌","🕓"), "⛔") & " ", "J" & IFERROR(CHOOSE(MATCH(INDEX(ControlMensual!N:N, MATCH(F8, ControlMensual!B:B, 0)), {"ok";"no";"pendiente"}, 0),"✅","❌","🕓"), "⛔") & " ", "A" & IFERROR(CHOOSE(MATCH(INDEX(ControlMensual!O:O, MATCH(F8, ControlMensual!B:B, 0)), {"ok";"no";"pendiente"}, 0),"✅","❌","🕓"), "⛔") & " ", "S" & IFERROR(CHOOSE(MATCH(INDEX(ControlMensual!P:P, MATCH(F8, ControlMensual!B:B, 0)), {"ok";"no";"pendiente"}, 0),"✅","❌","🕓"), "⛔") & " ", "O" & IFERROR(CHOOSE(MATCH(INDEX(ControlMensual!Q:Q, MATCH(F8, ControlMensual!B:B, 0)), {"ok";"no";"pendiente"}, 0),"✅","❌","🕓"), "⛔") & " ", "N" & IFERROR(CHOOSE(MATCH(INDEX(ControlMensual!R:R, MATCH(F8, ControlMensual!B:B, 0)), {"ok";"no";"pendiente"}, 0),"✅","❌","🕓"), "⛔") & " ", "D" & IFERROR(CHOOSE(MATCH(INDEX(ControlMensual!S:S, MATCH(F8, ControlMensual!B:B, 0)), {"ok";"no";"pendiente"}, 0),"✅","❌","🕓"), "⛔") ) ,"") ) -> Ya no cuenta con actualizaciones | U8: Si | V8: Si | W8: No | X8: No aplica | Y8: =COUNTIF(U8:X8,"Si")/(COUNTIF(U8:X8,"Si")+COUNTIF(U8:X8,"No")) -> 0.66666667 | Z8: Sin Proyecto | AA8: Sin Fecha | AB8: Legales y Complementarios | AC8: Cristian Vera | AD8: No | AE8: =VLOOKUP(E8,Falcon!B$2:C$558,2,FALSE) -> #REF! | AF8: =VLOOKUP(E8,VisionOne!B$2:C$229,2,FALSE) -> #REF! | AG8: =VLOOKUP(D8,Central!B$2:C$217,2,FALSE) -> #REF! | AH8: No | AJ8: Cristian Vera | AK8: No | AM8: =VLOOKUP(D8,'Copia de vInfo 2'!A:A,1,FALSE) -> #REF! | AN8: Si
A9: 216 | B9: Alonso Ovalle | C9: Alonso Ovalle | D9: QA-WEBLOGIC-KURUB-RES | E9: kurub | F9: 10.23.4.99 | G9: QA | H9: =VLOOKUP(D9,'Inventario Plataformas OLD 260325'!I:Q,2,FALSE) -> #REF! | I9: Weblogic Transversal | J9: Servicios Transversales MDW | K9: Encendido | L9: Virtual | M9: Máquina Virtual VmWare | N9: No aplica | O9: Linux | P9: Red Hat Enterprise Linux 6 | Q9: Red Hat Enterprise Linux 6 (64-bit) | R9: =verificarVersionOS(Q9) -> #NAME? | S9: =IFERROR( IF(ISNUMBER(FIND("Soporte hasta: ", R9)), IF(VALUE(MID(R9,16,10))<TODAY(),"🟥 Obsoleto", IF(YEAR(VALUE(MID(R9,16,10)))=YEAR(TODAY()),"Actualizaciones disponibles", IF(YEAR(VALUE(MID(R9,16,10)))-YEAR(TODAY())=1,"Actualizaciones disponibles", IF(YEAR(VALUE(MID(R9,16,10)))-YEAR(TODAY())=2,"Actualizaciones disponibles", "Actualizaciones disponibles" ) ) ) ), "⛔ Sin datos" ), "⛔ Error en fecha" ) -> ⛔ Sin datos | T9: =IF(OR(S9 = "🟥 Obsoleto",S9 = "⛔ Sin datos"), "Ya no cuenta con actualizaciones", IFERROR( CONCATENATE( "E" & IFERROR(CHOOSE(MATCH(INDEX(ControlMensual!H:H, MATCH(F9, ControlMensual!B:B, 0)), {"ok";"no";"pendiente"}, 0),"✅","❌","🕓"), "⛔") & " ", "F" & IFERROR(CHOOSE(MATCH(INDEX(ControlMensual!I:I, MATCH(F9, ControlMensual!B:B, 0)), {"ok";"no";"pendiente"}, 0),"✅","❌","🕓"), "⛔") & " ", "M" & IFERROR(CHOOSE(MATCH(INDEX(ControlMensual!J:J, MATCH(F9, ControlMensual!B:B, 0)), {"ok";"no";"pendiente"}, 0),"✅","❌","🕓"), "⛔") & " ", "A" & IFERROR(CHOOSE(MATCH(INDEX(ControlMensual!K:K, MATCH(F9, ControlMensual!B:B, 0)), {"ok";"no";"pendiente"}, 0),"✅","❌","🕓"), "⛔") & " ", "M" & IFERROR(CHOOSE(MATCH(INDEX(ControlMensual!L:L, MATCH(F9, ControlMensual!B:B, 0)), {"ok";"no";"pendiente"}, 0),"✅","❌","🕓"), "⛔") & " ", "J" & IFERROR(CHOOSE(MATCH(INDEX(ControlMensual!M:M, MATCH(F9, ControlMensual!B:B, 0)), {"ok";"no";"pendiente"}, 0),"✅","❌","🕓"), "⛔") & " ", "J" & IFERROR(CHOOSE(MATCH(INDEX(ControlMensual!N:N, MATCH(F9, ControlMensual!B:B, 0)), {"ok";"no";"pendiente"}, 0),"✅","❌","🕓"), "⛔") & " ", "A" & IFERROR(CHOOSE(MATCH(INDEX(ControlMensual!O:O, MATCH(F9, ControlMensual!B:B, 0)), {"ok";"no";"pendiente"}, 0),"✅","❌","🕓"), "⛔") & " ", "S" & IFERROR(CHOOSE(MATCH(INDEX(ControlMensual!P:P, MATCH(F9, ControlMensual!B:B, 0)), {"ok";"no";"pendiente"}, 0),"✅","❌","🕓"), "⛔") & " ", "O" & IFERROR(CHOOSE(MATCH(INDEX(ControlMensual!Q:Q, MATCH(F9, ControlMensual!B:B, 0)), {"ok";"no";"pendiente"}, 0),"✅","❌","🕓"), "⛔") & " ", "N" & IFERROR(CHOOSE(MATCH(INDEX(ControlMensual!R:R, MATCH(F9, ControlMensual!B:B, 0)), {"ok";"no";"pendiente"}, 0),"✅","❌","🕓"), "⛔") & " ", "D" & IFERROR(CHOOSE(MATCH(INDEX(ControlMensual!S:S, MATCH(F9, ControlMensual!B:B, 0)), {"ok";"no";"pendiente"}, 0),"✅","❌","🕓"), "⛔") ) ,"") ) -> Ya no cuenta con actualizaciones | U9: Si | V9: Si | W9: No | X9: No aplica | Y9: =COUNTIF(U9:X9,"Si")/(COUNTIF(U9:X9,"Si")+COUNTIF(U9:X9,"No")) -> 0.66666667 | Z9: Sin Proyecto | AA9: Sin Fecha | AB9: Sistemas de Negocio | AC9: Sin Asignación | AD9: No | AE9: =VLOOKUP(E9,Falcon!B$2:C$558,2,FALSE) -> #REF! | AF9: =VLOOKUP(E9,VisionOne!B$2:C$229,2,FALSE) -> #REF! | AG9: =VLOOKUP(E9,Central!B$2:C$217,2,FALSE) -> #REF! | AH9: No | AJ9: Sin Asignación | AK9: No | AM9: =VLOOKUP(D9,'Copia de vInfo 2'!A:A,1,FALSE) -> #REF!
A10: 235 | B10: Alonso Ovalle | C10: Alonso Ovalle | D10: WEB-GORELY-DEV | E10: GORELY | F10: 10.23.1.214 | G10: Desarrollo | H10: Sin Software MDW | I10: Sucursal Virtual | J10: Portal Web Publico y SVP (1.0 | 1.5) | K10: Encendido | L10: Virtual | M10: Máquina Virtual VmWare | N10: No aplica | O10: Microsoft Windows | P10: Microsoft Windows Server 2008 | Q10: Microsoft Windows Server 2008 R2 (64-bit) | R10: =verificarVersionOS(Q10) -> #NAME? | S10: =IFERROR( IF(ISNUMBER(FIND("Soporte hasta: ", R10)), IF(VALUE(MID(R10,16,10))<TODAY(),"🟥 Obsoleto", IF(YEAR(VALUE(MID(R10,16,10)))=YEAR(TODAY()),"Actualizaciones disponibles", IF(YEAR(VALUE(MID(R10,16,10)))-YEAR(TODAY())=1,"Actualizaciones disponibles", IF(YEAR(VALUE(MID(R10,16,10)))-YEAR(TODAY())=2,"Actualizaciones disponibles", "Actualizaciones disponibles" ) ) ) ), "⛔ Sin datos" ), "⛔ Error en fecha" ) -> ⛔ Sin datos | T10: =IF(OR(S10 = "🟥 Obsoleto",S10 = "⛔ Sin datos"), "Ya no cuenta con actualizaciones", IFERROR( CONCATENATE( "E" & IFERROR(CHOOSE(MATCH(INDEX(ControlMensual!H:H, MATCH(F10, ControlMensual!B:B, 0)), {"ok";"no";"pendiente"}, 0),"✅","❌","🕓"), "⛔") & " ", "F" & IFERROR(CHOOSE(MATCH(INDEX(ControlMensual!I:I, MATCH(F10, ControlMensual!B:B, 0)), {"ok";"no";"pendiente"}, 0),"✅","❌","🕓"), "⛔") & " ", "M" & IFERROR(CHOOSE(MATCH(INDEX(ControlMensual!J:J, MATCH(F10, ControlMensual!B:B, 0)), {"ok";"no";"pendiente"}, 0),"✅","❌","🕓"), "⛔") & " ", "A" & IFERROR(CHOOSE(MATCH(INDEX(ControlMensual!K:K, MATCH(F10, ControlMensual!B:B, 0)), {"ok";"no";"pendiente"}, 0),"✅","❌","🕓"), "⛔") & " ", "M" & IFERROR(CHOOSE(MATCH(INDEX(ControlMensual!L:L, MATCH(F10, ControlMensual!B:B, 0)), {"ok";"no";"pendiente"}, 0),"✅","❌","🕓"), "⛔") & " ", "J" & IFERROR(CHOOSE(MATCH(INDEX(ControlMensual!M:M, MATCH(F10, ControlMensual!B:B, 0)), {"ok";"no";"pendiente"}, 0),"✅","❌","🕓"), "⛔") & " ", "J" & IFERROR(CHOOSE(MATCH(INDEX(ControlMensual!N:N, MATCH(F10, ControlMensual!B:B, 0)), {"ok";"no";"pendiente"}, 0),"✅","❌","🕓"), "⛔") & " ", "A" & IFERROR(CHOOSE(MATCH(INDEX(ControlMensual!O:O, MATCH(F10, ControlMensual!B:B, 0)), {"ok";"no";"pendiente"}, 0),"✅","❌","🕓"), "⛔") & " ", "S" & IFERROR(CHOOSE(MATCH(INDEX(ControlMensual!P:P, MATCH(F10, ControlMensual!B:B, 0)), {"ok";"no";"pendiente"}, 0),"✅","❌","🕓"), "⛔") & " ", "O" & IFERROR(CHOOSE(MATCH(INDEX(ControlMensual!Q:Q, MATCH(F10, ControlMensual!B:B, 0)), {"ok";"no";"pendiente"}, 0),"✅","❌","🕓"), "⛔") & " ", "N" & IFERROR(CHOOSE(MATCH(INDEX(ControlMensual!R:R, MATCH(F10, ControlMensual!B:B, 0)), {"ok";"no";"pendiente"}, 0),"✅","❌","🕓"), "⛔") & " ", "D" & IFERROR(CHOOSE(MATCH(INDEX(ControlMensual!S:S, MATCH(F10, ControlMensual!B:B, 0)), {"ok";"no";"pendiente"}, 0),"✅","❌","🕓"), "⛔") ) ,"") ) -> Ya no cuenta con actualizaciones | U10: Si | V10: No | W10: No | X10: No aplica | Y10: =COUNTIF(U10:X10,"Si")/(COUNTIF(U10:X10,"Si")+COUNTIF(U10:X10,"No")) -> 0.33333333 | Z10: Migración Portal Web Publico y SVP (1.0 | 1.5) | AA10: 45930 | AB10: Legales y Complementarios | AC10: Cristian Vera | AD10: Si | AE10: =VLOOKUP(D10,Falcon!B$2:C$558,2,FALSE) -> #REF! | AF10: =VLOOKUP(E10,VisionOne!B$2:C$229,2,FALSE) -> #REF! | AG10: =VLOOKUP(E10,Central!B$2:C$217,2,FALSE) -> #REF! | AH10: No | AJ10: Cristian Vera | AK10: Si | AL10: x | AM10: =VLOOKUP(D10,'Copia de vInfo 2'!A:A,1,FALSE) -> #REF! | AN10: Sí
A11: 236 | B11: Alonso Ovalle | C11: Alonso Ovalle | D11: WEB-KONE-QA | E11: KONE | F11: 10.23.1.240 | G11: QA | H11: Sin Software MDW | I11: Sucursal Virtual | J11: Portal Web Publico y SVP (1.0 | 1.5) | K11: Encendido | L11: Virtual | M11: Máquina Virtual VmWare | N11: No aplica | O11: Microsoft Windows | P11: Microsoft Windows Server 2008 | Q11: Microsoft Windows Server 2008 R2 (64-bit) | R11: =verificarVersionOS(Q11) -> #NAME? | S11: =IFERROR( IF(ISNUMBER(FIND("Soporte hasta: ", R11)), IF(VALUE(MID(R11,16,10))<TODAY(),"🟥 Obsoleto", IF(YEAR(VALUE(MID(R11,16,10)))=YEAR(TODAY()),"Actualizaciones disponibles", IF(YEAR(VALUE(MID(R11,16,10)))-YEAR(TODAY())=1,"Actualizaciones disponibles", IF(YEAR(VALUE(MID(R11,16,10)))-YEAR(TODAY())=2,"Actualizaciones disponibles", "Actualizaciones disponibles" ) ) ) ), "⛔ Sin datos" ), "⛔ Error en fecha" ) -> ⛔ Sin datos | T11: =IF(OR(S11 = "🟥 Obsoleto",S11 = "⛔ Sin datos"), "Ya no cuenta con actualizaciones", IFERROR( CONCATENATE( "E" & IFERROR(CHOOSE(MATCH(INDEX(ControlMensual!H:H, MATCH(F11, ControlMensual!B:B, 0)), {"ok";"no";"pendiente"}, 0),"✅","❌","🕓"), "⛔") & " ", "F" & IFERROR(CHOOSE(MATCH(INDEX(ControlMensual!I:I, MATCH(F11, ControlMensual!B:B, 0)), {"ok";"no";"pendiente"}, 0),"✅","❌","🕓"), "⛔") & " ", "M" & IFERROR(CHOOSE(MATCH(INDEX(ControlMensual!J:J, MATCH(F11, ControlMensual!B:B, 0)), {"ok";"no";"pendiente"}, 0),"✅","❌","🕓"), "⛔") & " ", "A" & IFERROR(CHOOSE(MATCH(INDEX(ControlMensual!K:K, MATCH(F11, ControlMensual!B:B, 0)), {"ok";"no";"pendiente"}, 0),"✅","❌","🕓"), "⛔") & " ", "M" & IFERROR(CHOOSE(MATCH(INDEX(ControlMensual!L:L, MATCH(F11, ControlMensual!B:B, 0)), {"ok";"no";"pendiente"}, 0),"✅","❌","🕓"), "⛔") & " ", "J" & IFERROR(CHOOSE(MATCH(INDEX(ControlMensual!M:M, MATCH(F11, ControlMensual!B:B, 0)), {"ok";"no";"pendiente"}, 0),"✅","❌","🕓"), "⛔") & " ", "J" & IFERROR(CHOOSE(MATCH(INDEX(ControlMensual!N:N, MATCH(F11, ControlMensual!B:B, 0)), {"ok";"no";"pendiente"}, 0),"✅","❌","🕓"), "⛔") & " ", "A" & IFERROR(CHOOSE(MATCH(INDEX(ControlMensual!O:O, MATCH(F11, ControlMensual!B:B, 0)), {"ok";"no";"pendiente"}, 0),"✅","❌","🕓"), "⛔") & " ", "S" & IFERROR(CHOOSE(MATCH(INDEX(ControlMensual!P:P, MATCH(F11, ControlMensual!B:B, 0)), {"ok";"no";"pendiente"}, 0),"✅","❌","🕓"), "⛔") & " ", "O" & IFERROR(CHOOSE(MATCH(INDEX(ControlMensual!Q:Q, MATCH(F11, ControlMensual!B:B, 0)), {"ok";"no";"pendiente"}, 0),"✅","❌","🕓"), "⛔") & " ", "N" & IFERROR(CHOOSE(MATCH(INDEX(ControlMensual!R:R, MATCH(F11, ControlMensual!B:B, 0)), {"ok";"no";"pendiente"}, 0),"✅","❌","🕓"), "⛔") & " ", "D" & IFERROR(CHOOSE(MATCH(INDEX(ControlMensual!S:S, MATCH(F11, ControlMensual!B:B, 0)), {"ok";"no";"pendiente"}, 0),"✅","❌","🕓"), "⛔") ) ,"") ) -> Ya no cuenta con actualizaciones | U11: Si | V11: No | W11: No | X11: No aplica | Y11: =COUNTIF(U11:X11,"Si")/(COUNTIF(U11:X11,"Si")+COUNTIF(U11:X11,"No")) -> 0.33333333 | Z11: Migración Portal Web Publico y SVP (1.0 | 1.5) | AA11: 45930 | AB11: Legales y Complementarios | AC11: Cristian Vera | AD11: Si | AE11: =VLOOKUP(D11,Falcon!B$2:C$558,2,FALSE) -> #REF! | AF11: =VLOOKUP(E11,VisionOne!B$2:C$229,2,FALSE) -> #REF! | AG11: =VLOOKUP(E11,Central!B$2:C$217,2,FALSE) -> #REF! | AH11: No | AJ11: Cristian Vera | AK11: Si | AL11: x | AM11: =VLOOKUP(D11,'Copia de vInfo 2'!A:A,1,FALSE) -> #REF! | AN11: Sí
A12: 240 | B12: Alonso Ovalle | C12: Alonso Ovalle | D12: WEB1.5-SANJOSE-DESA | E12: sanjose | F12: 10.23.1.43 | G12: Desarrollo | H12: Sin Software MDW | I12: Sucursal Virtual | J12: Portal Web Publico y SVP (1.0 | 1.5) | K12: Encendido | L12: Virtual | M12: Máquina Virtual VmWare | N12: No aplica | O12: Microsoft Windows | P12: Microsoft Windows Server 2003 | Q12: Microsoft Windows Server 2003 (32-bit) | R12: =verificarVersionOS(Q12) -> #NAME? | S12: =IFERROR( IF(ISNUMBER(FIND("Soporte hasta: ", R12)), IF(VALUE(MID(R12,16,10))<TODAY(),"🟥 Obsoleto", IF(YEAR(VALUE(MID(R12,16,10)))=YEAR(TODAY()),"Actualizaciones disponibles", IF(YEAR(VALUE(MID(R12,16,10)))-YEAR(TODAY())=1,"Actualizaciones disponibles", IF(YEAR(VALUE(MID(R12,16,10)))-YEAR(TODAY())=2,"Actualizaciones disponibles", "Actualizaciones disponibles" ) ) ) ), "⛔ Sin datos" ), "⛔ Error en fecha" ) -> ⛔ Sin datos | T12: =IF(OR(S12 = "🟥 Obsoleto",S12 = "⛔ Sin datos"), "Ya no cuenta con actualizaciones", IFERROR( CONCATENATE( "E" & IFERROR(CHOOSE(MATCH(INDEX(ControlMensual!H:H, MATCH(F12, ControlMensual!B:B, 0)), {"ok";"no";"pendiente"}, 0),"✅","❌","🕓"), "⛔") & " ", "F" & IFERROR(CHOOSE(MATCH(INDEX(ControlMensual!I:I, MATCH(F12, ControlMensual!B:B, 0)), {"ok";"no";"pendiente"}, 0),"✅","❌","🕓"), "⛔") & " ", "M" & IFERROR(CHOOSE(MATCH(INDEX(ControlMensual!J:J, MATCH(F12, ControlMensual!B:B, 0)), {"ok";"no";"pendiente"}, 0),"✅","❌","🕓"), "⛔") & " ", "A" & IFERROR(CHOOSE(MATCH(INDEX(ControlMensual!K:K, MATCH(F12, ControlMensual!B:B, 0)), {"ok";"no";"pendiente"}, 0),"✅","❌","🕓"), "⛔") & " ", "M" & IFERROR(CHOOSE(MATCH(INDEX(ControlMensual!L:L, MATCH(F12, ControlMensual!B:B, 0)), {"ok";"no";"pendiente"}, 0),"✅","❌","🕓"), "⛔") & " ", "J" & IFERROR(CHOOSE(MATCH(INDEX(ControlMensual!M:M, MATCH(F12, ControlMensual!B:B, 0)), {"ok";"no";"pendiente"}, 0),"✅","❌","🕓"), "⛔") & " ", "J" & IFERROR(CHOOSE(MATCH(INDEX(ControlMensual!N:N, MATCH(F12, ControlMensual!B:B, 0)), {"ok";"no";"pendiente"}, 0),"✅","❌","🕓"), "⛔") & " ", "A" & IFERROR(CHOOSE(MATCH(INDEX(ControlMensual!O:O, MATCH(F12, ControlMensual!B:B, 0)), {"ok";"no";"pendiente"}, 0),"✅","❌","🕓"), "⛔") & " ", "S" & IFERROR(CHOOSE(MATCH(INDEX(ControlMensual!P:P, MATCH(F12, ControlMensual!B:B, 0)), {"ok";"no";"pendiente"}, 0),"✅","❌","🕓"), "⛔") & " ", "O" & IFERROR(CHOOSE(MATCH(INDEX(ControlMensual!Q:Q, MATCH(F12, ControlMensual!B:B, 0)), {"ok";"no";"pendiente"}, 0),"✅","❌","🕓"), "⛔") & " ", "N" & IFERROR(CHOOSE(MATCH(INDEX(ControlMensual!R:R, MATCH(F12, ControlMensual!B:B, 0)), {"ok";"no";"pendiente"}, 0),"✅","❌","🕓"), "⛔") & " ", "D" & IFERROR(CHOOSE(MATCH(INDEX(ControlMensual!S:S, MATCH(F12, ControlMensual!B:B, 0)), {"ok";"no";"pendiente"}, 0),"✅","❌","🕓"), "⛔") ) ,"") ) -> Ya no cuenta con actualizaciones | U12: Si | V12: No | W12: No | X12: No aplica | Y12: =COUNTIF(U12:X12,"Si")/(COUNTIF(U12:X12,"Si")+COUNTIF(U12:X12,"No")) -> 0.33333333 | Z12: Migración Portal Web Publico y SVP (1.0 | 1.5) | AA12: 45930 | AB12: Legales y Complementarios | AC12: Cristian Vera | AD12: Si | AE12: =VLOOKUP(E12,Falcon!B$2:C$558,2,FALSE) -> #REF! | AF12: =VLOOKUP(E12,VisionOne!B$2:C$229,2,FALSE) -> #REF! | AG12: =VLOOKUP(E12,Central!B$2:C$217,2,FALSE) -> #REF! | AH12: No | AJ12: Cristian Vera | AK12: Si | AL12: x | AM12: =VLOOKUP(D12,'Copia de vInfo 2'!A:A,1,FALSE) -> #REF! | AN12: Sí
A13: 342 | B13: Sonda Cloud Privado | C13: Sonda | D13: BBDD-PUNTIAGUDO-PRO | E13: puntiagudo | F13: 10.23.4.91 | G13: Producción | H13: Sin Software MDW | I13: BD ADFS (Consumido por FICO) | J13: Motor de decisión FICO | K13: Encendido | L13: Virtual | M13: Máquina Virtual VmWare | N13: No aplica | O13: Microsoft Windows | P13: Microsoft Windows Server 2012 | Q13: Microsoft Windows Server 2012 (64-bit) | R13: =verificarVersionOS(Q13) -> #NAME? | S13: =IFERROR( IF(ISNUMBER(FIND("Soporte hasta: ", R13)), IF(VALUE(MID(R13,16,10))<TODAY(),"🟥 Obsoleto", IF(YEAR(VALUE(MID(R13,16,10)))=YEAR(TODAY()),"Actualizaciones disponibles", IF(YEAR(VALUE(MID(R13,16,10)))-YEAR(TODAY())=1,"Actualizaciones disponibles", IF(YEAR(VALUE(MID(R13,16,10)))-YEAR(TODAY())=2,"Actualizaciones disponibles", "Actualizaciones disponibles" ) ) ) ), "⛔ Sin datos" ), "⛔ Error en fecha" ) -> ⛔ Sin datos | T13: =IF(OR(S13 = "🟥 Obsoleto",S13 = "⛔ Sin datos"), "Ya no cuenta con actualizaciones", IFERROR( CONCATENATE( "E" & IFERROR(CHOOSE(MATCH(INDEX(ControlMensual!H:H, MATCH(F13, ControlMensual!B:B, 0)), {"ok";"no";"pendiente"}, 0),"✅","❌","🕓"), "⛔") & " ", "F" & IFERROR(CHOOSE(MATCH(INDEX(ControlMensual!I:I, MATCH(F13, ControlMensual!B:B, 0)), {"ok";"no";"pendiente"}, 0),"✅","❌","🕓"), "⛔") & " ", "M" & IFERROR(CHOOSE(MATCH(INDEX(ControlMensual!J:J, MATCH(F13, ControlMensual!B:B, 0)), {"ok";"no";"pendiente"}, 0),"✅","❌","🕓"), "⛔") & " ", "A" & IFERROR(CHOOSE(MATCH(INDEX(ControlMensual!K:K, MATCH(F13, ControlMensual!B:B, 0)), {"ok";"no";"pendiente"}, 0),"✅","❌","🕓"), "⛔") & " ", "M" & IFERROR(CHOOSE(MATCH(INDEX(ControlMensual!L:L, MATCH(F13, ControlMensual!B:B, 0)), {"ok";"no";"pendiente"}, 0),"✅","❌","🕓"), "⛔") & " ", "J" & IFERROR(CHOOSE(MATCH(INDEX(ControlMensual!M:M, MATCH(F13, ControlMensual!B:B, 0)), {"ok";"no";"pendiente"}, 0),"✅","❌","🕓"), "⛔") & " ", "J" & IFERROR(CHOOSE(MATCH(INDEX(ControlMensual!N:N, MATCH(F13, ControlMensual!B:B, 0)), {"ok";"no";"pendiente"}, 0),"✅","❌","🕓"), "⛔") & " ", "A" & IFERROR(CHOOSE(MATCH(INDEX(ControlMensual!O:O, MATCH(F13, ControlMensual!B:B, 0)), {"ok";"no";"pendiente"}, 0),"✅","❌","🕓"), "⛔") & " ", "S" & IFERROR(CHOOSE(MATCH(INDEX(ControlMensual!P:P, MATCH(F13, ControlMensual!B:B, 0)), {"ok";"no";"pendiente"}, 0),"✅","❌","🕓"), "⛔") & " ", "O" & IFERROR(CHOOSE(MATCH(INDEX(ControlMensual!Q:Q, MATCH(F13, ControlMensual!B:B, 0)), {"ok";"no";"pendiente"}, 0),"✅","❌","🕓"), "⛔") & " ", "N" & IFERROR(CHOOSE(MATCH(INDEX(ControlMensual!R:R, MATCH(F13, ControlMensual!B:B, 0)), {"ok";"no";"pendiente"}, 0),"✅","❌","🕓"), "⛔") & " ", "D" & IFERROR(CHOOSE(MATCH(INDEX(ControlMensual!S:S, MATCH(F13, ControlMensual!B:B, 0)), {"ok";"no";"pendiente"}, 0),"✅","❌","🕓"), "⛔") ) ,"") ) -> Ya no cuenta con actualizaciones | U13: Si | V13: Si | W13: No | X13: No aplica | Y13: =COUNTIF(U13:X13,"Si")/(COUNTIF(U13:X13,"Si")+COUNTIF(U13:X13,"No")) -> 0.66666667 | Z13: Migración FICO | AA13: 45930 | AB13: Sistemas Financieros | AC13: Claudia León | AD13: No | AE13: =VLOOKUP(D13,Falcon!B$2:C$558,2,FALSE) -> #REF! | AF13: =VLOOKUP(E13,VisionOne!B$2:C$229,2,FALSE) -> #REF! | AG13: =VLOOKUP(E13,Central!B$2:C$217,2,FALSE) -> #REF! | AH13: No | AJ13: Patricio Alegría | AK13: Si | AL13: x | AM13: =VLOOKUP(D13,'Copia de vInfo 2'!A:A,1,FALSE) -> #REF! | AN13: Sí
A14: 372 | B14: Sonda Cloud Privado | C14: Sonda | D14: dmpsprd1gtw | E14: dmpsprd1gtw | F14: 172.29.191.66 | G14: Producción | H14: DMPS 4 (FICO) | I14: Motor de decisión FICO | J14: Motor de decisión FICO | K14: Encendido | L14: Virtual | M14: Máquina Virtual VmWare | N14: No aplica | O14: Linux | P14: Red Hat Enterprise Linux 7 | Q14: Red Hat Enterprise Linux 7 (64-bit) | R14: =verificarVersionOS(Q14) -> #NAME? | S14: =IFERROR( IF(ISNUMBER(FIND("Soporte hasta: ", R14)), IF(VALUE(MID(R14,16,10))<TODAY(),"🟥 Obsoleto", IF(YEAR(VALUE(MID(R14,16,10)))=YEAR(TODAY()),"Actualizaciones disponibles", IF(YEAR(VALUE(MID(R14,16,10)))-YEAR(TODAY())=1,"Actualizaciones disponibles", IF(YEAR(VALUE(MID(R14,16,10)))-YEAR(TODAY())=2,"Actualizaciones disponibles", "Actualizaciones disponibles" ) ) ) ), "⛔ Sin datos" ), "⛔ Error en fecha" ) -> ⛔ Sin datos | T14: =IF(OR(S14 = "🟥 Obsoleto",S14 = "⛔ Sin datos"), "Ya no cuenta con actualizaciones", IFERROR( CONCATENATE( "E" & IFERROR(CHOOSE(MATCH(INDEX(ControlMensual!H:H, MATCH(F14, ControlMensual!B:B, 0)), {"ok";"no";"pendiente"}, 0),"✅","❌","🕓"), "⛔") & " ", "F" & IFERROR(CHOOSE(MATCH(INDEX(ControlMensual!I:I, MATCH(F14, ControlMensual!B:B, 0)), {"ok";"no";"pendiente"}, 0),"✅","❌","🕓"), "⛔") & " ", "M" & IFERROR(CHOOSE(MATCH(INDEX(ControlMensual!J:J, MATCH(F14, ControlMensual!B:B, 0)), {"ok";"no";"pendiente"}, 0),"✅","❌","🕓"), "⛔") & " ", "A" & IFERROR(CHOOSE(MATCH(INDEX(ControlMensual!K:K, MATCH(F14, ControlMensual!B:B, 0)), {"ok";"no";"pendiente"}, 0),"✅","❌","🕓"), "⛔") & " ", "M" & IFERROR(CHOOSE(MATCH(INDEX(ControlMensual!L:L, MATCH(F14, ControlMensual!B:B, 0)), {"ok";"no";"pendiente"}, 0),"✅","❌","🕓"), "⛔") & " ", "J" & IFERROR(CHOOSE(MATCH(INDEX(ControlMensual!M:M, MATCH(F14, ControlMensual!B:B, 0)), {"ok";"no";"pendiente"}, 0),"✅","❌","🕓"), "⛔") & " ", "J" & IFERROR(CHOOSE(MATCH(INDEX(ControlMensual!N:N, MATCH(F14, ControlMensual!B:B, 0)), {"ok";"no";"pendiente"}, 0),"✅","❌","🕓"), "⛔") & " ", "A" & IFERROR(CHOOSE(MATCH(INDEX(ControlMensual!O:O, MATCH(F14, ControlMensual!B:B, 0)), {"ok";"no";"pendiente"}, 0),"✅","❌","🕓"), "⛔") & " ", "S" & IFERROR(CHOOSE(MATCH(INDEX(ControlMensual!P:P, MATCH(F14, ControlMensual!B:B, 0)), {"ok";"no";"pendiente"}, 0),"✅","❌","🕓"), "⛔") & " ", "O" & IFERROR(CHOOSE(MATCH(INDEX(ControlMensual!Q:Q, MATCH(F14, ControlMensual!B:B, 0)), {"ok";"no";"pendiente"}, 0),"✅","❌","🕓"), "⛔") & " ", "N" & IFERROR(CHOOSE(MATCH(INDEX(ControlMensual!R:R, MATCH(F14, ControlMensual!B:B, 0)), {"ok";"no";"pendiente"}, 0),"✅","❌","🕓"), "⛔") & " ", "D" & IFERROR(CHOOSE(MATCH(INDEX(ControlMensual!S:S, MATCH(F14, ControlMensual!B:B, 0)), {"ok";"no";"pendiente"}, 0),"✅","❌","🕓"), "⛔") ) ,"") ) -> Ya no cuenta con actualizaciones | U14: Si | V14: Si | W14: No | X14: No aplica | Y14: =COUNTIF(U14:X14,"Si")/(COUNTIF(U14:X14,"Si")+COUNTIF(U14:X14,"No")) -> 0.66666667 | Z14: Migración FICO | AA14: 45930 | AB14: Sistemas Financieros | AC14: Claudia León | AD14: No | AE14: =VLOOKUP(D14,Falcon!B$2:C$558,2,FALSE) -> #REF! | AF14: =VLOOKUP(E14,VisionOne!B$2:C$229,2,FALSE) -> #REF! | AG14: =VLOOKUP(D14,Central!B$2:C$217,2,FALSE) -> #REF! | AH14: No | AJ14: Patricio Alegría | AK14: Si | AL14: x | AM14: =VLOOKUP(D14,'Copia de vInfo 2'!A:A,1,FALSE) -> #REF! | AN14: Sí
A15: 373 | B15: Sonda Cloud Privado | C15: Sonda | D15: dmpsprd2dpc | E15: dmpsprd2dpc | F15: 172.29.191.67 | G15: Producción | H15: DMPS 4 (FICO) | I15: Motor de decisión FICO | J15: Motor de decisión FICO | K15: Encendido | L15: Virtual | M15: Máquina Virtual VmWare | N15: No aplica | O15: Linux | P15: Red Hat Enterprise Linux 7 | Q15: Red Hat Enterprise Linux 7 (64-bit) | R15: =verificarVersionOS(Q15) -> #NAME? | S15: =IFERROR( IF(ISNUMBER(FIND("Soporte hasta: ", R15)), IF(VALUE(MID(R15,16,10))<TODAY(),"🟥 Obsoleto", IF(YEAR(VALUE(MID(R15,16,10)))=YEAR(TODAY()),"Actualizaciones disponibles", IF(YEAR(VALUE(MID(R15,16,10)))-YEAR(TODAY())=1,"Actualizaciones disponibles", IF(YEAR(VALUE(MID(R15,16,10)))-YEAR(TODAY())=2,"Actualizaciones disponibles", "Actualizaciones disponibles" ) ) ) ), "⛔ Sin datos" ), "⛔ Error en fecha" ) -> ⛔ Sin datos | T15: =IF(OR(S15 = "🟥 Obsoleto",S15 = "⛔ Sin datos"), "Ya no cuenta con actualizaciones", IFERROR( CONCATENATE( "E" & IFERROR(CHOOSE(MATCH(INDEX(ControlMensual!H:H, MATCH(F15, ControlMensual!B:B, 0)), {"ok";"no";"pendiente"}, 0),"✅","❌","🕓"), "⛔") & " ", "F" & IFERROR(CHOOSE(MATCH(INDEX(ControlMensual!I:I, MATCH(F15, ControlMensual!B:B, 0)), {"ok";"no";"pendiente"}, 0),"✅","❌","🕓"), "⛔") & " ", "M" & IFERROR(CHOOSE(MATCH(INDEX(ControlMensual!J:J, MATCH(F15, ControlMensual!B:B, 0)), {"ok";"no";"pendiente"}, 0),"✅","❌","🕓"), "⛔") & " ", "A" & IFERROR(CHOOSE(MATCH(INDEX(ControlMensual!K:K, MATCH(F15, ControlMensual!B:B, 0)), {"ok";"no";"pendiente"}, 0),"✅","❌","🕓"), "⛔") & " ", "M" & IFERROR(CHOOSE(MATCH(INDEX(ControlMensual!L:L, MATCH(F15, ControlMensual!B:B, 0)), {"ok";"no";"pendiente"}, 0),"✅","❌","🕓"), "⛔") & " ", "J" & IFERROR(CHOOSE(MATCH(INDEX(ControlMensual!M:M, MATCH(F15, ControlMensual!B:B, 0)), {"ok";"no";"pendiente"}, 0),"✅","❌","🕓"), "⛔") & " ", "J" & IFERROR(CHOOSE(MATCH(INDEX(ControlMensual!N:N, MATCH(F15, ControlMensual!B:B, 0)), {"ok";"no";"pendiente"}, 0),"✅","❌","🕓"), "⛔") & " ", "A" & IFERROR(CHOOSE(MATCH(INDEX(ControlMensual!O:O, MATCH(F15, ControlMensual!B:B, 0)), {"ok";"no";"pendiente"}, 0),"✅","❌","🕓"), "⛔") & " ", "S" & IFERROR(CHOOSE(MATCH(INDEX(ControlMensual!P:P, MATCH(F15, ControlMensual!B:B, 0)), {"ok";"no";"pendiente"}, 0),"✅","❌","🕓"), "⛔") & " ", "O" & IFERROR(CHOOSE(MATCH(INDEX(ControlMensual!Q:Q, MATCH(F15, ControlMensual!B:B, 0)), {"ok";"no";"pendiente"}, 0),"✅","❌","🕓"), "⛔") & " ", "N" & IFERROR(CHOOSE(MATCH(INDEX(ControlMensual!R:R, MATCH(F15, ControlMensual!B:B, 0)), {"ok";"no";"pendiente"}, 0),"✅","❌","🕓"), "⛔") & " ", "D" & IFERROR(CHOOSE(MATCH(INDEX(ControlMensual!S:S, MATCH(F15, ControlMensual!B:B, 0)), {"ok";"no";"pendiente"}, 0),"✅","❌","🕓"), "⛔") ) ,"") ) -> Ya no cuenta con actualizaciones | U15: Si | V15: Si | W15: No | X15: No aplica | Y15: =COUNTIF(U15:X15,"Si")/(COUNTIF(U15:X15,"Si")+COUNTIF(U15:X15,"No")) -> 0.66666667 | Z15: Migración FICO | AA15: 45930 | AB15: Sistemas Financieros | AC15: Claudia León | AD15: No | AE15: =VLOOKUP(D15,Falcon!B$2:C$558,2,FALSE) -> #REF! | AF15: =VLOOKUP(E15,VisionOne!B$2:C$229,2,FALSE) -> #REF! | AG15: =VLOOKUP(D15,Central!B$2:C$217,2,FALSE) -> #REF! | AH15: No | AJ15: Patricio Alegría | AK15: Si | AL15: x | AM15: =VLOOKUP(D15,'Copia de vInfo 2'!A:A,1,FALSE) -> #REF! | AN15: Sí
A16: 374 | B16: Sonda Cloud Privado | C16: Sonda | D16: dmpsprd3vsc | E16: dmpsprd3vsc | F16: 172.29.191.68 | G16: Producción | H16: DMPS 4 (FICO) | I16: Motor de decisión FICO | J16: Motor de decisión FICO | K16: Encendido | L16: Virtual | M16: Máquina Virtual VmWare | N16: No aplica | O16: Linux | P16: Red Hat Enterprise Linux 7 | Q16: Red Hat Enterprise Linux 7 (64-bit) | R16: =verificarVersionOS(Q16) -> #NAME? | S16: =IFERROR( IF(ISNUMBER(FIND("Soporte hasta: ", R16)), IF(VALUE(MID(R16,16,10))<TODAY(),"🟥 Obsoleto", IF(YEAR(VALUE(MID(R16,16,10)))=YEAR(TODAY()),"Actualizaciones disponibles", IF(YEAR(VALUE(MID(R16,16,10)))-YEAR(TODAY())=1,"Actualizaciones disponibles", IF(YEAR(VALUE(MID(R16,16,10)))-YEAR(TODAY())=2,"Actualizaciones disponibles", "Actualizaciones disponibles" ) ) ) ), "⛔ Sin datos" ), "⛔ Error en fecha" ) -> ⛔ Sin datos | T16: =IF(OR(S16 = "🟥 Obsoleto",S16 = "⛔ Sin datos"), "Ya no cuenta con actualizaciones", IFERROR( CONCATENATE( "E" & IFERROR(CHOOSE(MATCH(INDEX(ControlMensual!H:H, MATCH(F16, ControlMensual!B:B, 0)), {"ok";"no";"pendiente"}, 0),"✅","❌","🕓"), "⛔") & " ", "F" & IFERROR(CHOOSE(MATCH(INDEX(ControlMensual!I:I, MATCH(F16, ControlMensual!B:B, 0)), {"ok";"no";"pendiente"}, 0),"✅","❌","🕓"), "⛔") & " ", "M" & IFERROR(CHOOSE(MATCH(INDEX(ControlMensual!J:J, MATCH(F16, ControlMensual!B:B, 0)), {"ok";"no";"pendiente"}, 0),"✅","❌","🕓"), "⛔") & " ", "A" & IFERROR(CHOOSE(MATCH(INDEX(ControlMensual!K:K, MATCH(F16, ControlMensual!B:B, 0)), {"ok";"no";"pendiente"}, 0),"✅","❌","🕓"), "⛔") & " ", "M" & IFERROR(CHOOSE(MATCH(INDEX(ControlMensual!L:L, MATCH(F16, ControlMensual!B:B, 0)), {"ok";"no";"pendiente"}, 0),"✅","❌","🕓"), "⛔") & " ", "J" & IFERROR(CHOOSE(MATCH(INDEX(ControlMensual!M:M, MATCH(F16, ControlMensual!B:B, 0)), {"ok";"no";"pendiente"}, 0),"✅","❌","🕓"), "⛔") & " ", "J" & IFERROR(CHOOSE(MATCH(INDEX(ControlMensual!N:N, MATCH(F16, ControlMensual!B:B, 0)), {"ok";"no";"pendiente"}, 0),"✅","❌","🕓"), "⛔") & " ", "A" & IFERROR(CHOOSE(MATCH(INDEX(ControlMensual!O:O, MATCH(F16, ControlMensual!B:B, 0)), {"ok";"no";"pendiente"}, 0),"✅","❌","🕓"), "⛔") & " ", "S" & IFERROR(CHOOSE(MATCH(INDEX(ControlMensual!P:P, MATCH(F16, ControlMensual!B:B, 0)), {"ok";"no";"pendiente"}, 0),"✅","❌","🕓"), "⛔") & " ", "O" & IFERROR(CHOOSE(MATCH(INDEX(ControlMensual!Q:Q, MATCH(F16, ControlMensual!B:B, 0)), {"ok";"no";"pendiente"}, 0),"✅","❌","🕓"), "⛔") & " ", "N" & IFERROR(CHOOSE(MATCH(INDEX(ControlMensual!R:R, MATCH(F16, ControlMensual!B:B, 0)), {"ok";"no";"pendiente"}, 0),"✅","❌","🕓"), "⛔") & " ", "D" & IFERROR(CHOOSE(MATCH(INDEX(ControlMensual!S:S, MATCH(F16, ControlMensual!B:B, 0)), {"ok";"no";"pendiente"}, 0),"✅","❌","🕓"), "⛔") ) ,"") ) -> Ya no cuenta con actualizaciones | U16: Si | V16: Si | W16: No | X16: No aplica | Y16: =COUNTIF(U16:X16,"Si")/(COUNTIF(U16:X16,"Si")+COUNTIF(U16:X16,"No")) -> 0.66666667 | Z16: Migración FICO | AA16: 45930 | AB16: Sistemas Financieros | AC16: Claudia León | AD16: No | AE16: =VLOOKUP(D16,Falcon!B$2:C$558,2,FALSE) -> #REF! | AF16: =VLOOKUP(E16,VisionOne!B$2:C$229,2,FALSE) -> #REF! | AG16: =VLOOKUP(D16,Central!B$2:C$217,2,FALSE) -> #REF! | AH16: No | AJ16: Patricio Alegría | AK16: Si | AL16: x | AM16: =VLOOKUP(D16,'Copia de vInfo 2'!A:A,1,FALSE) -> #REF! | AN16: Sí
A17: 375 | B17: Sonda Cloud Privado | C17: Sonda | D17: dmpsprd4dpm | E17: dmpsprd4dpm | F17: 172.29.191.69 | G17: Producción | H17: DMPS 4 (FICO) | I17: Motor de decisión FICO | J17: Motor de decisión FICO | K17: Encendido | L17: Virtual | M17: Máquina Virtual VmWare | N17: No aplica | O17: Linux | P17: Red Hat Enterprise Linux 7 | Q17: Red Hat Enterprise Linux 7 (64-bit) | R17: =verificarVersionOS(Q17) -> #NAME? | S17: =IFERROR( IF(ISNUMBER(FIND("Soporte hasta: ", R17)), IF(VALUE(MID(R17,16,10))<TODAY(),"🟥 Obsoleto", IF(YEAR(VALUE(MID(R17,16,10)))=YEAR(TODAY()),"Actualizaciones disponibles", IF(YEAR(VALUE(MID(R17,16,10)))-YEAR(TODAY())=1,"Actualizaciones disponibles", IF(YEAR(VALUE(MID(R17,16,10)))-YEAR(TODAY())=2,"Actualizaciones disponibles", "Actualizaciones disponibles" ) ) ) ), "⛔ Sin datos" ), "⛔ Error en fecha" ) -> ⛔ Sin datos | T17: =IF(OR(S17 = "🟥 Obsoleto",S17 = "⛔ Sin datos"), "Ya no cuenta con actualizaciones", IFERROR( CONCATENATE( "E" & IFERROR(CHOOSE(MATCH(INDEX(ControlMensual!H:H, MATCH(F17, ControlMensual!B:B, 0)), {"ok";"no";"pendiente"}, 0),"✅","❌","🕓"), "⛔") & " ", "F" & IFERROR(CHOOSE(MATCH(INDEX(ControlMensual!I:I, MATCH(F17, ControlMensual!B:B, 0)), {"ok";"no";"pendiente"}, 0),"✅","❌","🕓"), "⛔") & " ", "M" & IFERROR(CHOOSE(MATCH(INDEX(ControlMensual!J:J, MATCH(F17, ControlMensual!B:B, 0)), {"ok";"no";"pendiente"}, 0),"✅","❌","🕓"), "⛔") & " ", "A" & IFERROR(CHOOSE(MATCH(INDEX(ControlMensual!K:K, MATCH(F17, ControlMensual!B:B, 0)), {"ok";"no";"pendiente"}, 0),"✅","❌","🕓"), "⛔") & " ", "M" & IFERROR(CHOOSE(MATCH(INDEX(ControlMensual!L:L, MATCH(F17, ControlMensual!B:B, 0)), {"ok";"no";"pendiente"}, 0),"✅","❌","🕓"), "⛔") & " ", "J" & IFERROR(CHOOSE(MATCH(INDEX(ControlMensual!M:M, MATCH(F17, ControlMensual!B:B, 0)), {"ok";"no";"pendiente"}, 0),"✅","❌","🕓"), "⛔") & " ", "J" & IFERROR(CHOOSE(MATCH(INDEX(ControlMensual!N:N, MATCH(F17, ControlMensual!B:B, 0)), {"ok";"no";"pendiente"}, 0),"✅","❌","🕓"), "⛔") & " ", "A" & IFERROR(CHOOSE(MATCH(INDEX(ControlMensual!O:O, MATCH(F17, ControlMensual!B:B, 0)), {"ok";"no";"pendiente"}, 0),"✅","❌","🕓"), "⛔") & " ", "S" & IFERROR(CHOOSE(MATCH(INDEX(ControlMensual!P:P, MATCH(F17, ControlMensual!B:B, 0)), {"ok";"no";"pendiente"}, 0),"✅","❌","🕓"), "⛔") & " ", "O" & IFERROR(CHOOSE(MATCH(INDEX(ControlMensual!Q:Q, MATCH(F17, ControlMensual!B:B, 0)), {"ok";"no";"pendiente"}, 0),"✅","❌","🕓"), "⛔") & " ", "N" & IFERROR(CHOOSE(MATCH(INDEX(ControlMensual!R:R, MATCH(F17, ControlMensual!B:B, 0)), {"ok";"no";"pendiente"}, 0),"✅","❌","🕓"), "⛔") & " ", "D" & IFERROR(CHOOSE(MATCH(INDEX(ControlMensual!S:S, MATCH(F17, ControlMensual!B:B, 0)), {"ok";"no";"pendiente"}, 0),"✅","❌","🕓"), "⛔") ) ,"") ) -> Ya no cuenta con actualizaciones | U17: Si | V17: Si | W17: No | X17: No aplica | Y17: =COUNTIF(U17:X17,"Si")/(COUNTIF(U17:X17,"Si")+COUNTIF(U17:X17,"No")) -> 0.66666667 | Z17: Migración FICO | AA17: 45930 | AB17: Sistemas Financieros | AC17: Claudia León | AD17: No | AE17: =VLOOKUP(D17,Falcon!B$2:C$558,2,FALSE) -> #REF! | AF17: =VLOOKUP(E17,VisionOne!B$2:C$229,2,FALSE) -> #REF! | AG17: =VLOOKUP(D17,Central!B$2:C$217,2,FALSE) -> #REF! | AH17: No | AJ17: Patricio Alegría | AK17: Si | AL17: x | AN17: Sí
A18: 376 | B18: Sonda Cloud Privado | C18: Sonda | D18: dmpsprd5dcp | E18: dmpsprd5dcp | F18: 172.29.191.70 | G18: Producción | H18: DMPS 4 (FICO) | I18: Motor de decisión FICO | J18: Motor de decisión FICO | K18: Encendido | L18: Virtual | M18: Máquina Virtual VmWare | N18: No aplica | O18: Linux | P18: Red Hat Enterprise Linux 7 | Q18: Red Hat Enterprise Linux 7 (64-bit) | R18: =verificarVersionOS(Q18) -> #NAME? | S18: =IFERROR( IF(ISNUMBER(FIND("Soporte hasta: ", R18)), IF(VALUE(MID(R18,16,10))<TODAY(),"🟥 Obsoleto", IF(YEAR(VALUE(MID(R18,16,10)))=YEAR(TODAY()),"Actualizaciones disponibles", IF(YEAR(VALUE(MID(R18,16,10)))-YEAR(TODAY())=1,"Actualizaciones disponibles", IF(YEAR(VALUE(MID(R18,16,10)))-YEAR(TODAY())=2,"Actualizaciones disponibles", "Actualizaciones disponibles" ) ) ) ), "⛔ Sin datos" ), "⛔ Error en fecha" ) -> ⛔ Sin datos | T18: =IF(OR(S18 = "🟥 Obsoleto",S18 = "⛔ Sin datos"), "Ya no cuenta con actualizaciones", IFERROR( CONCATENATE( "E" & IFERROR(CHOOSE(MATCH(INDEX(ControlMensual!H:H, MATCH(F18, ControlMensual!B:B, 0)), {"ok";"no";"pendiente"}, 0),"✅","❌","🕓"), "⛔") & " ", "F" & IFERROR(CHOOSE(MATCH(INDEX(ControlMensual!I:I, MATCH(F18, ControlMensual!B:B, 0)), {"ok";"no";"pendiente"}, 0),"✅","❌","🕓"), "⛔") & " ", "M" & IFERROR(CHOOSE(MATCH(INDEX(ControlMensual!J:J, MATCH(F18, ControlMensual!B:B, 0)), {"ok";"no";"pendiente"}, 0),"✅","❌","🕓"), "⛔") & " ", "A" & IFERROR(CHOOSE(MATCH(INDEX(ControlMensual!K:K, MATCH(F18, ControlMensual!B:B, 0)), {"ok";"no";"pendiente"}, 0),"✅","❌","🕓"), "⛔") & " ", "M" & IFERROR(CHOOSE(MATCH(INDEX(ControlMensual!L:L, MATCH(F18, ControlMensual!B:B, 0)), {"ok";"no";"pendiente"}, 0),"✅","❌","🕓"), "⛔") & " ", "J" & IFERROR(CHOOSE(MATCH(INDEX(ControlMensual!M:M, MATCH(F18, ControlMensual!B:B, 0)), {"ok";"no";"pendiente"}, 0),"✅","❌","🕓"), "⛔") & " ", "J" & IFERROR(CHOOSE(MATCH(INDEX(ControlMensual!N:N, MATCH(F18, ControlMensual!B:B, 0)), {"ok";"no";"pendiente"}, 0),"✅","❌","🕓"), "⛔") & " ", "A" & IFERROR(CHOOSE(MATCH(INDEX(ControlMensual!O:O, MATCH(F18, ControlMensual!B:B, 0)), {"ok";"no";"pendiente"}, 0),"✅","❌","🕓"), "⛔") & " ", "S" & IFERROR(CHOOSE(MATCH(INDEX(ControlMensual!P:P, MATCH(F18, ControlMensual!B:B, 0)), {"ok";"no";"pendiente"}, 0),"✅","❌","🕓"), "⛔") & " ", "O" & IFERROR(CHOOSE(MATCH(INDEX(ControlMensual!Q:Q, MATCH(F18, ControlMensual!B:B, 0)), {"ok";"no";"pendiente"}, 0),"✅","❌","🕓"), "⛔") & " ", "N" & IFERROR(CHOOSE(MATCH(INDEX(ControlMensual!R:R, MATCH(F18, ControlMensual!B:B, 0)), {"ok";"no";"pendiente"}, 0),"✅","❌","🕓"), "⛔") & " ", "D" & IFERROR(CHOOSE(MATCH(INDEX(ControlMensual!S:S, MATCH(F18, ControlMensual!B:B, 0)), {"ok";"no";"pendiente"}, 0),"✅","❌","🕓"), "⛔") ) ,"") ) -> Ya no cuenta con actualizaciones | U18: Si | V18: Si | W18: No | X18: No aplica | Y18: =COUNTIF(U18:X18,"Si")/(COUNTIF(U18:X18,"Si")+COUNTIF(U18:X18,"No")) -> 0.66666667 | Z18: Migración FICO | AA18: 45930 | AB18: Sistemas Financieros | AC18: Claudia León | AD18: No | AE18: =VLOOKUP(E18,Falcon!B$2:C$558,2,FALSE) -> #REF! | AF18: =VLOOKUP(E18,VisionOne!B$2:C$229,2,FALSE) -> #REF! | AG18: =VLOOKUP(E18,Central!B$2:C$217,2,FALSE) -> #REF! | AH18: No | AJ18: Patricio Alegría | AK18: Si | AL18: x | AM18: =VLOOKUP(D18,'Copia de vInfo 2'!A:A,1,FALSE) -> #REF! | AN18: Sí
A19: 377 | B19: Sonda Cloud Privado | C19: Sonda | D19: dmpsprd6dcm | E19: dmpsprd6dcm | F19: 172.29.191.71 | G19: Producción | H19: DMPS 4 (FICO) | I19: Motor de decisión FICO | J19: Motor de decisión FICO | K19: Encendido | L19: Virtual | M19: Máquina Virtual VmWare | N19: No aplica | O19: Linux | P19: Red Hat Enterprise Linux 7 | Q19: Red Hat Enterprise Linux 7 (64-bit) | R19: =verificarVersionOS(Q19) -> #NAME? | S19: =IFERROR( IF(ISNUMBER(FIND("Soporte hasta: ", R19)), IF(VALUE(MID(R19,16,10))<TODAY(),"🟥 Obsoleto", IF(YEAR(VALUE(MID(R19,16,10)))=YEAR(TODAY()),"Actualizaciones disponibles", IF(YEAR(VALUE(MID(R19,16,10)))-YEAR(TODAY())=1,"Actualizaciones disponibles", IF(YEAR(VALUE(MID(R19,16,10)))-YEAR(TODAY())=2,"Actualizaciones disponibles", "Actualizaciones disponibles" ) ) ) ), "⛔ Sin datos" ), "⛔ Error en fecha" ) -> ⛔ Sin datos | T19: =IF(OR(S19 = "🟥 Obsoleto",S19 = "⛔ Sin datos"), "Ya no cuenta con actualizaciones", IFERROR( CONCATENATE( "E" & IFERROR(CHOOSE(MATCH(INDEX(ControlMensual!H:H, MATCH(F19, ControlMensual!B:B, 0)), {"ok";"no";"pendiente"}, 0),"✅","❌","🕓"), "⛔") & " ", "F" & IFERROR(CHOOSE(MATCH(INDEX(ControlMensual!I:I, MATCH(F19, ControlMensual!B:B, 0)), {"ok";"no";"pendiente"}, 0),"✅","❌","🕓"), "⛔") & " ", "M" & IFERROR(CHOOSE(MATCH(INDEX(ControlMensual!J:J, MATCH(F19, ControlMensual!B:B, 0)), {"ok";"no";"pendiente"}, 0),"✅","❌","🕓"), "⛔") & " ", "A" & IFERROR(CHOOSE(MATCH(INDEX(ControlMensual!K:K, MATCH(F19, ControlMensual!B:B, 0)), {"ok";"no";"pendiente"}, 0),"✅","❌","🕓"), "⛔") & " ", "M" & IFERROR(CHOOSE(MATCH(INDEX(ControlMensual!L:L, MATCH(F19, ControlMensual!B:B, 0)), {"ok";"no";"pendiente"}, 0),"✅","❌","🕓"), "⛔") & " ", "J" & IFERROR(CHOOSE(MATCH(INDEX(ControlMensual!M:M, MATCH(F19, ControlMensual!B:B, 0)), {"ok";"no";"pendiente"}, 0),"✅","❌","🕓"), "⛔") & " ", "J" & IFERROR(CHOOSE(MATCH(INDEX(ControlMensual!N:N, MATCH(F19, ControlMensual!B:B, 0)), {"ok";"no";"pendiente"}, 0),"✅","❌","🕓"), "⛔") & " ", "A" & IFERROR(CHOOSE(MATCH(INDEX(ControlMensual!O:O, MATCH(F19, ControlMensual!B:B, 0)), {"ok";"no";"pendiente"}, 0),"✅","❌","🕓"), "⛔") & " ", "S" & IFERROR(CHOOSE(MATCH(INDEX(ControlMensual!P:P, MATCH(F19, ControlMensual!B:B, 0)), {"ok";"no";"pendiente"}, 0),"✅","❌","🕓"), "⛔") & " ", "O" & IFERROR(CHOOSE(MATCH(INDEX(ControlMensual!Q:Q, MATCH(F19, ControlMensual!B:B, 0)), {"ok";"no";"pendiente"}, 0),"✅","❌","🕓"), "⛔") & " ", "N" & IFERROR(CHOOSE(MATCH(INDEX(ControlMensual!R:R, MATCH(F19, ControlMensual!B:B, 0)), {"ok";"no";"pendiente"}, 0),"✅","❌","🕓"), "⛔") & " ", "D" & IFERROR(CHOOSE(MATCH(INDEX(ControlMensual!S:S, MATCH(F19, ControlMensual!B:B, 0)), {"ok";"no";"pendiente"}, 0),"✅","❌","🕓"), "⛔") ) ,"") ) -> Ya no cuenta con actualizaciones | U19: Si | V19: Si | W19: No | X19: No aplica | Y19: =COUNTIF(U19:X19,"Si")/(COUNTIF(U19:X19,"Si")+COUNTIF(U19:X19,"No")) -> 0.66666667 | Z19: Migración FICO | AA19: 45930 | AB19: Sistemas Financieros | AC19: Claudia León | AD19: No | AE19: =VLOOKUP(E19,Falcon!B$2:C$558,2,FALSE) -> #REF! | AF19: =VLOOKUP(E19,VisionOne!B$2:C$229,2,FALSE) -> #REF! | AG19: =VLOOKUP(E19,Central!B$2:C$217,2,FALSE) -> #REF! | AH19: No | AJ19: Patricio Alegría | AK19: Si | AL19: x | AM19: =VLOOKUP(D19,'Copia de vInfo 2'!A:A,1,FALSE) -> #REF! | AN19: Sí
A20: 378 | B20: Sonda Cloud Privado | C20: Sonda | D20: dmpsprd7dmc | E20: dmpsprd7dmc | F20: 172.29.191.72 | G20: Producción | H20: DMPS 4 (FICO) | I20: Motor de decisión FICO | J20: Motor de decisión FICO | K20: Encendido | L20: Virtual | M20: Máquina Virtual VmWare | N20: No aplica | O20: Linux | P20: Red Hat Enterprise Linux 7 | Q20: Red Hat Enterprise Linux 7 (64-bit) | R20: =verificarVersionOS(Q20) -> #NAME? | S20: =IFERROR( IF(ISNUMBER(FIND("Soporte hasta: ", R20)), IF(VALUE(MID(R20,16,10))<TODAY(),"🟥 Obsoleto", IF(YEAR(VALUE(MID(R20,16,10)))=YEAR(TODAY()),"Actualizaciones disponibles", IF(YEAR(VALUE(MID(R20,16,10)))-YEAR(TODAY())=1,"Actualizaciones disponibles", IF(YEAR(VALUE(MID(R20,16,10)))-YEAR(TODAY())=2,"Actualizaciones disponibles", "Actualizaciones disponibles" ) ) ) ), "⛔ Sin datos" ), "⛔ Error en fecha" ) -> ⛔ Sin datos | T20: =IF(OR(S20 = "🟥 Obsoleto",S20 = "⛔ Sin datos"), "Ya no cuenta con actualizaciones", IFERROR( CONCATENATE( "E" & IFERROR(CHOOSE(MATCH(INDEX(ControlMensual!H:H, MATCH(F20, ControlMensual!B:B, 0)), {"ok";"no";"pendiente"}, 0),"✅","❌","🕓"), "⛔") & " ", "F" & IFERROR(CHOOSE(MATCH(INDEX(ControlMensual!I:I, MATCH(F20, ControlMensual!B:B, 0)), {"ok";"no";"pendiente"}, 0),"✅","❌","🕓"), "⛔") & " ", "M" & IFERROR(CHOOSE(MATCH(INDEX(ControlMensual!J:J, MATCH(F20, ControlMensual!B:B, 0)), {"ok";"no";"pendiente"}, 0),"✅","❌","🕓"), "⛔") & " ", "A" & IFERROR(CHOOSE(MATCH(INDEX(ControlMensual!K:K, MATCH(F20, ControlMensual!B:B, 0)), {"ok";"no";"pendiente"}, 0),"✅","❌","🕓"), "⛔") & " ", "M" & IFERROR(CHOOSE(MATCH(INDEX(ControlMensual!L:L, MATCH(F20, ControlMensual!B:B, 0)), {"ok";"no";"pendiente"}, 0),"✅","❌","🕓"), "⛔") & " ", "J" & IFERROR(CHOOSE(MATCH(INDEX(ControlMensual!M:M, MATCH(F20, ControlMensual!B:B, 0)), {"ok";"no";"pendiente"}, 0),"✅","❌","🕓"), "⛔") & " ", "J" & IFERROR(CHOOSE(MATCH(INDEX(ControlMensual!N:N, MATCH(F20, ControlMensual!B:B, 0)), {"ok";"no";"pendiente"}, 0),"✅","❌","🕓"), "⛔") & " ", "A" & IFERROR(CHOOSE(MATCH(INDEX(ControlMensual!O:O, MATCH(F20, ControlMensual!B:B, 0)), {"ok";"no";"pendiente"}, 0),"✅","❌","🕓"), "⛔") & " ", "S" & IFERROR(CHOOSE(MATCH(INDEX(ControlMensual!P:P, MATCH(F20, ControlMensual!B:B, 0)), {"ok";"no";"pendiente"}, 0),"✅","❌","🕓"), "⛔") & " ", "O" & IFERROR(CHOOSE(MATCH(INDEX(ControlMensual!Q:Q, MATCH(F20, ControlMensual!B:B, 0)), {"ok";"no";"pendiente"}, 0),"✅","❌","🕓"), "⛔") & " ", "N" & IFERROR(CHOOSE(MATCH(INDEX(ControlMensual!R:R, MATCH(F20, ControlMensual!B:B, 0)), {"ok";"no";"pendiente"}, 0),"✅","❌","🕓"), "⛔") & " ", "D" & IFERROR(CHOOSE(MATCH(INDEX(ControlMensual!S:S, MATCH(F20, ControlMensual!B:B, 0)), {"ok";"no";"pendiente"}, 0),"✅","❌","🕓"), "⛔") ) ,"") ) -> Ya no cuenta con actualizaciones | U20: Si | V20: Si | W20: No | X20: No aplica | Y20: =COUNTIF(U20:X20,"Si")/(COUNTIF(U20:X20,"Si")+COUNTIF(U20:X20,"No")) -> 0.66666667 | Z20: Migración FICO | AA20: 45930 | AB20: Sistemas Financieros | AC20: Claudia León | AD20: No | AE20: =VLOOKUP(E20,Falcon!B$2:C$558,2,FALSE) -> #REF! | AF20: =VLOOKUP(E20,VisionOne!B$2:C$229,2,FALSE) -> #REF! | AG20: =VLOOKUP(E20,Central!B$2:C$217,2,FALSE) -> #REF! | AH20: No | AJ20: Patricio Alegría | AK20: Si | AL20: x | AM20: =VLOOKUP(D20,'Copia de vInfo 2'!A:A,1,FALSE) -> #REF! | AN20: Sí
A21: 379 | B21: Sonda Cloud Privado | C21: Sonda | D21: dmpsprd8smc | E21: dmpsprd8smc | F21: 172.29.191.73 | G21: Producción | H21: DMPS 4 (FICO) | I21: Motor de decisión FICO | J21: Motor de decisión FICO | K21: Encendido | L21: Virtual | M21: Máquina Virtual VmWare | N21: No aplica | O21: Linux | P21: Red Hat Enterprise Linux 7 | Q21: Red Hat Enterprise Linux 7 (64-bit) | R21: =verificarVersionOS(Q21) -> #NAME? | S21: =IFERROR( IF(ISNUMBER(FIND("Soporte hasta: ", R21)), IF(VALUE(MID(R21,16,10))<TODAY(),"🟥 Obsoleto", IF(YEAR(VALUE(MID(R21,16,10)))=YEAR(TODAY()),"Actualizaciones disponibles", IF(YEAR(VALUE(MID(R21,16,10)))-YEAR(TODAY())=1,"Actualizaciones disponibles", IF(YEAR(VALUE(MID(R21,16,10)))-YEAR(TODAY())=2,"Actualizaciones disponibles", "Actualizaciones disponibles" ) ) ) ), "⛔ Sin datos" ), "⛔ Error en fecha" ) -> ⛔ Sin datos | T21: =IF(OR(S21 = "🟥 Obsoleto",S21 = "⛔ Sin datos"), "Ya no cuenta con actualizaciones", IFERROR( CONCATENATE( "E" & IFERROR(CHOOSE(MATCH(INDEX(ControlMensual!H:H, MATCH(F21, ControlMensual!B:B, 0)), {"ok";"no";"pendiente"}, 0),"✅","❌","🕓"), "⛔") & " ", "F" & IFERROR(CHOOSE(MATCH(INDEX(ControlMensual!I:I, MATCH(F21, ControlMensual!B:B, 0)), {"ok";"no";"pendiente"}, 0),"✅","❌","🕓"), "⛔") & " ", "M" & IFERROR(CHOOSE(MATCH(INDEX(ControlMensual!J:J, MATCH(F21, ControlMensual!B:B, 0)), {"ok";"no";"pendiente"}, 0),"✅","❌","🕓"), "⛔") & " ", "A" & IFERROR(CHOOSE(MATCH(INDEX(ControlMensual!K:K, MATCH(F21, ControlMensual!B:B, 0)), {"ok";"no";"pendiente"}, 0),"✅","❌","🕓"), "⛔") & " ", "M" & IFERROR(CHOOSE(MATCH(INDEX(ControlMensual!L:L, MATCH(F21, ControlMensual!B:B, 0)), {"ok";"no";"pendiente"}, 0),"✅","❌","🕓"), "⛔") & " ", "J" & IFERROR(CHOOSE(MATCH(INDEX(ControlMensual!M:M, MATCH(F21, ControlMensual!B:B, 0)), {"ok";"no";"pendiente"}, 0),"✅","❌","🕓"), "⛔") & " ", "J" & IFERROR(CHOOSE(MATCH(INDEX(ControlMensual!N:N, MATCH(F21, ControlMensual!B:B, 0)), {"ok";"no";"pendiente"}, 0),"✅","❌","🕓"), "⛔") & " ", "A" & IFERROR(CHOOSE(MATCH(INDEX(ControlMensual!O:O, MATCH(F21, ControlMensual!B:B, 0)), {"ok";"no";"pendiente"}, 0),"✅","❌","🕓"), "⛔") & " ", "S" & IFERROR(CHOOSE(MATCH(INDEX(ControlMensual!P:P, MATCH(F21, ControlMensual!B:B, 0)), {"ok";"no";"pendiente"}, 0),"✅","❌","🕓"), "⛔") & " ", "O" & IFERROR(CHOOSE(MATCH(INDEX(ControlMensual!Q:Q, MATCH(F21, ControlMensual!B:B, 0)), {"ok";"no";"pendiente"}, 0),"✅","❌","🕓"), "⛔") & " ", "N" & IFERROR(CHOOSE(MATCH(INDEX(ControlMensual!R:R, MATCH(F21, ControlMensual!B:B, 0)), {"ok";"no";"pendiente"}, 0),"✅","❌","🕓"), "⛔") & " ", "D" & IFERROR(CHOOSE(MATCH(INDEX(ControlMensual!S:S, MATCH(F21, ControlMensual!B:B, 0)), {"ok";"no";"pendiente"}, 0),"✅","❌","🕓"), "⛔") ) ,"") ) -> Ya no cuenta con actualizaciones | U21: Si | V21: Si | W21: No | X21: No aplica | Y21: =COUNTIF(U21:X21,"Si")/(COUNTIF(U21:X21,"Si")+COUNTIF(U21:X21,"No")) -> 0.66666667 | Z21: Migración FICO | AA21: 45930 | AB21: Sistemas Financieros | AC21: Claudia León | AD21: No | AE21: =VLOOKUP(E21,Falcon!B$2:C$558,2,FALSE) -> #REF! | AF21: =VLOOKUP(E21,VisionOne!B$2:C$229,2,FALSE) -> #REF! | AG21: =VLOOKUP(E21,Central!B$2:C$217,2,FALSE) -> #REF! | AH21: No | AJ21: Patricio Alegría | AK21: Si | AL21: x | AM21: =VLOOKUP(D21,'Copia de vInfo 2'!A:A,1,FALSE) -> #REF! | AN21: Sí
A22: 380 | B22: Sonda Cloud Privado | C22: Sonda | D22: dmpsprd9cdb | E22: dmpsprd9cdb | F22: 172.29.191.74 | G22: Producción | H22: DMPS 4 (FICO) | I22: Motor de decisión FICO | J22: Motor de decisión FICO | K22: Encendido | L22: Virtual | M22: Máquina Virtual VmWare | N22: No aplica | O22: Linux | P22: Red Hat Enterprise Linux 7 | Q22: Red Hat Enterprise Linux 7 (64-bit) | R22: =verificarVersionOS(Q22) -> #NAME? | S22: =IFERROR( IF(ISNUMBER(FIND("Soporte hasta: ", R22)), IF(VALUE(MID(R22,16,10))<TODAY(),"🟥 Obsoleto", IF(YEAR(VALUE(MID(R22,16,10)))=YEAR(TODAY()),"Actualizaciones disponibles", IF(YEAR(VALUE(MID(R22,16,10)))-YEAR(TODAY())=1,"Actualizaciones disponibles", IF(YEAR(VALUE(MID(R22,16,10)))-YEAR(TODAY())=2,"Actualizaciones disponibles", "Actualizaciones disponibles" ) ) ) ), "⛔ Sin datos" ), "⛔ Error en fecha" ) -> ⛔ Sin datos | T22: =IF(OR(S22 = "🟥 Obsoleto",S22 = "⛔ Sin datos"), "Ya no cuenta con actualizaciones", IFERROR( CONCATENATE( "E" & IFERROR(CHOOSE(MATCH(INDEX(ControlMensual!H:H, MATCH(F22, ControlMensual!B:B, 0)), {"ok";"no";"pendiente"}, 0),"✅","❌","🕓"), "⛔") & " ", "F" & IFERROR(CHOOSE(MATCH(INDEX(ControlMensual!I:I, MATCH(F22, ControlMensual!B:B, 0)), {"ok";"no";"pendiente"}, 0),"✅","❌","🕓"), "⛔") & " ", "M" & IFERROR(CHOOSE(MATCH(INDEX(ControlMensual!J:J, MATCH(F22, ControlMensual!B:B, 0)), {"ok";"no";"pendiente"}, 0),"✅","❌","🕓"), "⛔") & " ", "A" & IFERROR(CHOOSE(MATCH(INDEX(ControlMensual!K:K, MATCH(F22, ControlMensual!B:B, 0)), {"ok";"no";"pendiente"}, 0),"✅","❌","🕓"), "⛔") & " ", "M" & IFERROR(CHOOSE(MATCH(INDEX(ControlMensual!L:L, MATCH(F22, ControlMensual!B:B, 0)), {"ok";"no";"pendiente"}, 0),"✅","❌","🕓"), "⛔") & " ", "J" & IFERROR(CHOOSE(MATCH(INDEX(ControlMensual!M:M, MATCH(F22, ControlMensual!B:B, 0)), {"ok";"no";"pendiente"}, 0),"✅","❌","🕓"), "⛔") & " ", "J" & IFERROR(CHOOSE(MATCH(INDEX(ControlMensual!N:N, MATCH(F22, ControlMensual!B:B, 0)), {"ok";"no";"pendiente"}, 0),"✅","❌","🕓"), "⛔") & " ", "A" & IFERROR(CHOOSE(MATCH(INDEX(ControlMensual!O:O, MATCH(F22, ControlMensual!B:B, 0)), {"ok";"no";"pendiente"}, 0),"✅","❌","🕓"), "⛔") & " ", "S" & IFERROR(CHOOSE(MATCH(INDEX(ControlMensual!P:P, MATCH(F22, ControlMensual!B:B, 0)), {"ok";"no";"pendiente"}, 0),"✅","❌","🕓"), "⛔") & " ", "O" & IFERROR(CHOOSE(MATCH(INDEX(ControlMensual!Q:Q, MATCH(F22, ControlMensual!B:B, 0)), {"ok";"no";"pendiente"}, 0),"✅","❌","🕓"), "⛔") & " ", "N" & IFERROR(CHOOSE(MATCH(INDEX(ControlMensual!R:R, MATCH(F22, ControlMensual!B:B, 0)), {"ok";"no";"pendiente"}, 0),"✅","❌","🕓"), "⛔") & " ", "D" & IFERROR(CHOOSE(MATCH(INDEX(ControlMensual!S:S, MATCH(F22, ControlMensual!B:B, 0)), {"ok";"no";"pendiente"}, 0),"✅","❌","🕓"), "⛔") ) ,"") ) -> Ya no cuenta con actualizaciones | U22: Si | V22: Si | W22: No | X22: No aplica | Y22: =COUNTIF(U22:X22,"Si")/(COUNTIF(U22:X22,"Si")+COUNTIF(U22:X22,"No")) -> 0.66666667 | Z22: Migración FICO | AA22: 45930 | AB22: Sistemas Financieros | AC22: Claudia León | AD22: No | AE22: =VLOOKUP(D22,Falcon!B$2:C$558,2,FALSE) -> #REF! | AF22: =VLOOKUP(E22,VisionOne!B$2:C$229,2,FALSE) -> #REF! | AG22: =VLOOKUP(E22,Central!B$2:C$217,2,FALSE) -> #REF! | AH22: No | AJ22: Patricio Alegría | AK22: Si | AL22: x | AM22: =VLOOKUP(D22,'Copia de vInfo 2'!A:A,1,FALSE) -> #REF! | AN22: Sí
A23: 383 | B23: Sonda Cloud Privado | C23: Sonda | D23: PRO-WEBLOGIC-GROPPO | E23: groppo | F23: 10.23.4.117 | G23: Producción | H23: =VLOOKUP(D23,'Inventario Plataformas OLD 260325'!I:Q,2,FALSE) -> #REF! | I23: Weblogic Transversal | J23: Servicios Transversales MDW | K23: Encendido | L23: Virtual | M23: Máquina Virtual VmWare | N23: No aplica | O23: Linux | P23: Red Hat Enterprise Linux 6 | Q23: Red Hat Enterprise Linux 6 (64-bit) | R23: =verificarVersionOS(Q23) -> #NAME? | S23: =IFERROR( IF(ISNUMBER(FIND("Soporte hasta: ", R23)), IF(VALUE(MID(R23,16,10))<TODAY(),"🟥 Obsoleto", IF(YEAR(VALUE(MID(R23,16,10)))=YEAR(TODAY()),"Actualizaciones disponibles", IF(YEAR(VALUE(MID(R23,16,10)))-YEAR(TODAY())=1,"Actualizaciones disponibles", IF(YEAR(VALUE(MID(R23,16,10)))-YEAR(TODAY())=2,"Actualizaciones disponibles", "Actualizaciones disponibles" ) ) ) ), "⛔ Sin datos" ), "⛔ Error en fecha" ) -> ⛔ Sin datos | T23: =IF(OR(S23 = "🟥 Obsoleto",S23 = "⛔ Sin datos"), "Ya no cuenta con actualizaciones", IFERROR( CONCATENATE( "E" & IFERROR(CHOOSE(MATCH(INDEX(ControlMensual!H:H, MATCH(F23, ControlMensual!B:B, 0)), {"ok";"no";"pendiente"}, 0),"✅","❌","🕓"), "⛔") & " ", "F" & IFERROR(CHOOSE(MATCH(INDEX(ControlMensual!I:I, MATCH(F23, ControlMensual!B:B, 0)), {"ok";"no";"pendiente"}, 0),"✅","❌","🕓"), "⛔") & " ", "M" & IFERROR(CHOOSE(MATCH(INDEX(ControlMensual!J:J, MATCH(F23, ControlMensual!B:B, 0)), {"ok";"no";"pendiente"}, 0),"✅","❌","🕓"), "⛔") & " ", "A" & IFERROR(CHOOSE(MATCH(INDEX(ControlMensual!K:K, MATCH(F23, ControlMensual!B:B, 0)), {"ok";"no";"pendiente"}, 0),"✅","❌","🕓"), "⛔") & " ", "M" & IFERROR(CHOOSE(MATCH(INDEX(ControlMensual!L:L, MATCH(F23, ControlMensual!B:B, 0)), {"ok";"no";"pendiente"}, 0),"✅","❌","🕓"), "⛔") & " ", "J" & IFERROR(CHOOSE(MATCH(INDEX(ControlMensual!M:M, MATCH(F23, ControlMensual!B:B, 0)), {"ok";"no";"pendiente"}, 0),"✅","❌","🕓"), "⛔") & " ", "J" & IFERROR(CHOOSE(MATCH(INDEX(ControlMensual!N:N, MATCH(F23, ControlMensual!B:B, 0)), {"ok";"no";"pendiente"}, 0),"✅","❌","🕓"), "⛔") & " ", "A" & IFERROR(CHOOSE(MATCH(INDEX(ControlMensual!O:O, MATCH(F23, ControlMensual!B:B, 0)), {"ok";"no";"pendiente"}, 0),"✅","❌","🕓"), "⛔") & " ", "S" & IFERROR(CHOOSE(MATCH(INDEX(ControlMensual!P:P, MATCH(F23, ControlMensual!B:B, 0)), {"ok";"no";"pendiente"}, 0),"✅","❌","🕓"), "⛔") & " ", "O" & IFERROR(CHOOSE(MATCH(INDEX(ControlMensual!Q:Q, MATCH(F23, ControlMensual!B:B, 0)), {"ok";"no";"pendiente"}, 0),"✅","❌","🕓"), "⛔") & " ", "N" & IFERROR(CHOOSE(MATCH(INDEX(ControlMensual!R:R, MATCH(F23, ControlMensual!B:B, 0)), {"ok";"no";"pendiente"}, 0),"✅","❌","🕓"), "⛔") & " ", "D" & IFERROR(CHOOSE(MATCH(INDEX(ControlMensual!S:S, MATCH(F23, ControlMensual!B:B, 0)), {"ok";"no";"pendiente"}, 0),"✅","❌","🕓"), "⛔") ) ,"") ) -> Ya no cuenta con actualizaciones | U23: Si | V23: Si | W23: No | X23: No aplica | Y23: =COUNTIF(U23:X23,"Si")/(COUNTIF(U23:X23,"Si")+COUNTIF(U23:X23,"No")) -> 0.66666667 | Z23: Sin Proyecto | AA23: Sin Fecha | AB23: Sistemas de Negocio | AC23: Sin Asignación | AD23: No | AE23: =VLOOKUP(E23,Falcon!B$2:C$558,2,FALSE) -> #REF! | AF23: =VLOOKUP(E23,VisionOne!B$2:C$229,2,FALSE) -> #REF! | AG23: =VLOOKUP(E23,Central!B$2:C$217,2,FALSE) -> #REF! | AH23: No | AJ23: Sin Asignación | AK23: No | AM23: =VLOOKUP(D23,'Copia de vInfo 2'!A:A,1,FALSE) -> #REF!
A24: 384 | B24: Sonda Cloud Privado | C24: Sonda | D24: PRO-WEBLOGIC-KASBEK | E24: kasbek | F24: 10.23.4.116 | G24: Producción | H24: =VLOOKUP(D24,'Inventario Plataformas OLD 260325'!I:Q,2,FALSE) -> #REF! | I24: Weblogic Transversal | J24: Servicios Transversales MDW | K24: Encendido | L24: Virtual | M24: Máquina Virtual VmWare | N24: No aplica | O24: Linux | P24: Red Hat Enterprise Linux 6 | Q24: Red Hat Enterprise Linux 6 (64-bit) | R24: =verificarVersionOS(Q24) -> #NAME? | S24: =IFERROR( IF(ISNUMBER(FIND("Soporte hasta: ", R24)), IF(VALUE(MID(R24,16,10))<TODAY(),"🟥 Obsoleto", IF(YEAR(VALUE(MID(R24,16,10)))=YEAR(TODAY()),"Actualizaciones disponibles", IF(YEAR(VALUE(MID(R24,16,10)))-YEAR(TODAY())=1,"Actualizaciones disponibles", IF(YEAR(VALUE(MID(R24,16,10)))-YEAR(TODAY())=2,"Actualizaciones disponibles", "Actualizaciones disponibles" ) ) ) ), "⛔ Sin datos" ), "⛔ Error en fecha" ) -> ⛔ Sin datos | T24: =IF(OR(S24 = "🟥 Obsoleto",S24 = "⛔ Sin datos"), "Ya no cuenta con actualizaciones", IFERROR( CONCATENATE( "E" & IFERROR(CHOOSE(MATCH(INDEX(ControlMensual!H:H, MATCH(F24, ControlMensual!B:B, 0)), {"ok";"no";"pendiente"}, 0),"✅","❌","🕓"), "⛔") & " ", "F" & IFERROR(CHOOSE(MATCH(INDEX(ControlMensual!I:I, MATCH(F24, ControlMensual!B:B, 0)), {"ok";"no";"pendiente"}, 0),"✅","❌","🕓"), "⛔") & " ", "M" & IFERROR(CHOOSE(MATCH(INDEX(ControlMensual!J:J, MATCH(F24, ControlMensual!B:B, 0)), {"ok";"no";"pendiente"}, 0),"✅","❌","🕓"), "⛔") & " ", "A" & IFERROR(CHOOSE(MATCH(INDEX(ControlMensual!K:K, MATCH(F24, ControlMensual!B:B, 0)), {"ok";"no";"pendiente"}, 0),"✅","❌","🕓"), "⛔") & " ", "M" & IFERROR(CHOOSE(MATCH(INDEX(ControlMensual!L:L, MATCH(F24, ControlMensual!B:B, 0)), {"ok";"no";"pendiente"}, 0),"✅","❌","🕓"), "⛔") & " ", "J" & IFERROR(CHOOSE(MATCH(INDEX(ControlMensual!M:M, MATCH(F24, ControlMensual!B:B, 0)), {"ok";"no";"pendiente"}, 0),"✅","❌","🕓"), "⛔") & " ", "J" & IFERROR(CHOOSE(MATCH(INDEX(ControlMensual!N:N, MATCH(F24, ControlMensual!B:B, 0)), {"ok";"no";"pendiente"}, 0),"✅","❌","🕓"), "⛔") & " ", "A" & IFERROR(CHOOSE(MATCH(INDEX(ControlMensual!O:O, MATCH(F24, ControlMensual!B:B, 0)), {"ok";"no";"pendiente"}, 0),"✅","❌","🕓"), "⛔") & " ", "S" & IFERROR(CHOOSE(MATCH(INDEX(ControlMensual!P:P, MATCH(F24, ControlMensual!B:B, 0)), {"ok";"no";"pendiente"}, 0),"✅","❌","🕓"), "⛔") & " ", "O" & IFERROR(CHOOSE(MATCH(INDEX(ControlMensual!Q:Q, MATCH(F24, ControlMensual!B:B, 0)), {"ok";"no";"pendiente"}, 0),"✅","❌","🕓"), "⛔") & " ", "N" & IFERROR(CHOOSE(MATCH(INDEX(ControlMensual!R:R, MATCH(F24, ControlMensual!B:B, 0)), {"ok";"no";"pendiente"}, 0),"✅","❌","🕓"), "⛔") & " ", "D" & IFERROR(CHOOSE(MATCH(INDEX(ControlMensual!S:S, MATCH(F24, ControlMensual!B:B, 0)), {"ok";"no";"pendiente"}, 0),"✅","❌","🕓"), "⛔") ) ,"") ) -> Ya no cuenta con actualizaciones | U24: Si | V24: Si | W24: No | X24: No aplica | Y24: =COUNTIF(U24:X24,"Si")/(COUNTIF(U24:X24,"Si")+COUNTIF(U24:X24,"No")) -> 0.66666667 | Z24: Sin Proyecto | AA24: Sin Fecha | AB24: Sistemas de Negocio | AC24: Sin Asignación | AD24: No | AE24: =VLOOKUP(D24,Falcon!B$2:C$558,2,FALSE) -> #REF! | AF24: =VLOOKUP(E24,VisionOne!B$2:C$229,2,FALSE) -> #REF! | AG24: =VLOOKUP(E24,Central!B$2:C$217,2,FALSE) -> #REF! | AH24: No | AJ24: Sin Asignación | AK24: No | AM24: =VLOOKUP(D24,'Copia de vInfo 2'!A:A,1,FALSE) -> #REF!
A25: 425 | B25: Sonda Cloud Privado | C25: Sonda | D25: COBAPPPRD1 | E25: cobappprd1 | F25: 172.29.217.5 | G25: Producción | H25: WebLogic Server Version: 12.2.1.3.0 | I25: Weblogic Transversal | J25: Servicios Transversales MDW | K25: Encendido | L25: Virtual | M25: Máquina Virtual VmWare | N25: No aplica | O25: Linux | P25: Red Hat Enterprise Linux 6 | Q25: Red Hat Enterprise Linux 6 (32-bit) | R25: =verificarVersionOS(Q25) -> #NAME? | S25: =IFERROR( IF(ISNUMBER(FIND("Soporte hasta: ", R25)), IF(VALUE(MID(R25,16,10))<TODAY(),"🟥 Obsoleto", IF(YEAR(VALUE(MID(R25,16,10)))=YEAR(TODAY()),"Actualizaciones disponibles", IF(YEAR(VALUE(MID(R25,16,10)))-YEAR(TODAY())=1,"Actualizaciones disponibles", IF(YEAR(VALUE(MID(R25,16,10)))-YEAR(TODAY())=2,"Actualizaciones disponibles", "Actualizaciones disponibles" ) ) ) ), "⛔ Sin datos" ), "⛔ Error en fecha" ) -> ⛔ Sin datos | T25: =IF(OR(S25 = "🟥 Obsoleto",S25 = "⛔ Sin datos"), "Ya no cuenta con actualizaciones", IFERROR( CONCATENATE( "E" & IFERROR(CHOOSE(MATCH(INDEX(ControlMensual!H:H, MATCH(F25, ControlMensual!B:B, 0)), {"ok";"no";"pendiente"}, 0),"✅","❌","🕓"), "⛔") & " ", "F" & IFERROR(CHOOSE(MATCH(INDEX(ControlMensual!I:I, MATCH(F25, ControlMensual!B:B, 0)), {"ok";"no";"pendiente"}, 0),"✅","❌","🕓"), "⛔") & " ", "M" & IFERROR(CHOOSE(MATCH(INDEX(ControlMensual!J:J, MATCH(F25, ControlMensual!B:B, 0)), {"ok";"no";"pendiente"}, 0),"✅","❌","🕓"), "⛔") & " ", "A" & IFERROR(CHOOSE(MATCH(INDEX(ControlMensual!K:K, MATCH(F25, ControlMensual!B:B, 0)), {"ok";"no";"pendiente"}, 0),"✅","❌","🕓"), "⛔") & " ", "M" & IFERROR(CHOOSE(MATCH(INDEX(ControlMensual!L:L, MATCH(F25, ControlMensual!B:B, 0)), {"ok";"no";"pendiente"}, 0),"✅","❌","🕓"), "⛔") & " ", "J" & IFERROR(CHOOSE(MATCH(INDEX(ControlMensual!M:M, MATCH(F25, ControlMensual!B:B, 0)), {"ok";"no";"pendiente"}, 0),"✅","❌","🕓"), "⛔") & " ", "J" & IFERROR(CHOOSE(MATCH(INDEX(ControlMensual!N:N, MATCH(F25, ControlMensual!B:B, 0)), {"ok";"no";"pendiente"}, 0),"✅","❌","🕓"), "⛔") & " ", "A" & IFERROR(CHOOSE(MATCH(INDEX(ControlMensual!O:O, MATCH(F25, ControlMensual!B:B, 0)), {"ok";"no";"pendiente"}, 0),"✅","❌","🕓"), "⛔") & " ", "S" & IFERROR(CHOOSE(MATCH(INDEX(ControlMensual!P:P, MATCH(F25, ControlMensual!B:B, 0)), {"ok";"no";"pendiente"}, 0),"✅","❌","🕓"), "⛔") & " ", "O" & IFERROR(CHOOSE(MATCH(INDEX(ControlMensual!Q:Q, MATCH(F25, ControlMensual!B:B, 0)), {"ok";"no";"pendiente"}, 0),"✅","❌","🕓"), "⛔") & " ", "N" & IFERROR(CHOOSE(MATCH(INDEX(ControlMensual!R:R, MATCH(F25, ControlMensual!B:B, 0)), {"ok";"no";"pendiente"}, 0),"✅","❌","🕓"), "⛔") & " ", "D" & IFERROR(CHOOSE(MATCH(INDEX(ControlMensual!S:S, MATCH(F25, ControlMensual!B:B, 0)), {"ok";"no";"pendiente"}, 0),"✅","❌","🕓"), "⛔") ) ,"") ) -> Ya no cuenta con actualizaciones | U25: Si | V25: Si | W25: No | X25: No aplica | Y25: =COUNTIF(U25:X25,"Si")/(COUNTIF(U25:X25,"Si")+COUNTIF(U25:X25,"No")) -> 0.66666667 | Z25: Sin Proyecto | AA25: Sin Fecha | AB25: Sistemas de Negocio | AC25: Sin Asignación | AD25: No | AE25: =VLOOKUP(E25,Falcon!B$2:C$558,2,FALSE) -> #REF! | AF25: =VLOOKUP(E25,VisionOne!B$2:C$229,2,FALSE) -> #REF! | AG25: =VLOOKUP(E25,Central!B$2:C$217,2,FALSE) -> #REF! | AH25: No | AJ25: Sin Asignación | AK25: No | AM25: =VLOOKUP(D25,'Copia de vInfo 2'!A:A,1,FALSE) -> #REF!
A26: 426 | B26: Sonda Cloud Privado | C26: Sonda | D26: COBAPPPRD2 | E26: cobappprd2 | F26: 172.29.217.6 | G26: Producción | H26: WebLogic Server Version: 12.2.1.3.0 | I26: Weblogic Transversal | J26: Servicios Transversales MDW | K26: Encendido | L26: Virtual | M26: Máquina Virtual VmWare | N26: No aplica | O26: Linux | P26: Red Hat Enterprise Linux 6 | Q26: Red Hat Enterprise Linux 6 (32-bit) | R26: =verificarVersionOS(Q26) -> #NAME? | S26: =IFERROR( IF(ISNUMBER(FIND("Soporte hasta: ", R26)), IF(VALUE(MID(R26,16,10))<TODAY(),"🟥 Obsoleto", IF(YEAR(VALUE(MID(R26,16,10)))=YEAR(TODAY()),"Actualizaciones disponibles", IF(YEAR(VALUE(MID(R26,16,10)))-YEAR(TODAY())=1,"Actualizaciones disponibles", IF(YEAR(VALUE(MID(R26,16,10)))-YEAR(TODAY())=2,"Actualizaciones disponibles", "Actualizaciones disponibles" ) ) ) ), "⛔ Sin datos" ), "⛔ Error en fecha" ) -> ⛔ Sin datos | T26: =IF(OR(S26 = "🟥 Obsoleto",S26 = "⛔ Sin datos"), "Ya no cuenta con actualizaciones", IFERROR( CONCATENATE( "E" & IFERROR(CHOOSE(MATCH(INDEX(ControlMensual!H:H, MATCH(F26, ControlMensual!B:B, 0)), {"ok";"no";"pendiente"}, 0),"✅","❌","🕓"), "⛔") & " ", "F" & IFERROR(CHOOSE(MATCH(INDEX(ControlMensual!I:I, MATCH(F26, ControlMensual!B:B, 0)), {"ok";"no";"pendiente"}, 0),"✅","❌","🕓"), "⛔") & " ", "M" & IFERROR(CHOOSE(MATCH(INDEX(ControlMensual!J:J, MATCH(F26, ControlMensual!B:B, 0)), {"ok";"no";"pendiente"}, 0),"✅","❌","🕓"), "⛔") & " ", "A" & IFERROR(CHOOSE(MATCH(INDEX(ControlMensual!K:K, MATCH(F26, ControlMensual!B:B, 0)), {"ok";"no";"pendiente"}, 0),"✅","❌","🕓"), "⛔") & " ", "M" & IFERROR(CHOOSE(MATCH(INDEX(ControlMensual!L:L, MATCH(F26, ControlMensual!B:B, 0)), {"ok";"no";"pendiente"}, 0),"✅","❌","🕓"), "⛔") & " ", "J" & IFERROR(CHOOSE(MATCH(INDEX(ControlMensual!M:M, MATCH(F26, ControlMensual!B:B, 0)), {"ok";"no";"pendiente"}, 0),"✅","❌","🕓"), "⛔") & " ", "J" & IFERROR(CHOOSE(MATCH(INDEX(ControlMensual!N:N, MATCH(F26, ControlMensual!B:B, 0)), {"ok";"no";"pendiente"}, 0),"✅","❌","🕓"), "⛔") & " ", "A" & IFERROR(CHOOSE(MATCH(INDEX(ControlMensual!O:O, MATCH(F26, ControlMensual!B:B, 0)), {"ok";"no";"pendiente"}, 0),"✅","❌","🕓"), "⛔") & " ", "S" & IFERROR(CHOOSE(MATCH(INDEX(ControlMensual!P:P, MATCH(F26, ControlMensual!B:B, 0)), {"ok";"no";"pendiente"}, 0),"✅","❌","🕓"), "⛔") & " ", "O" & IFERROR(CHOOSE(MATCH(INDEX(ControlMensual!Q:Q, MATCH(F26, ControlMensual!B:B, 0)), {"ok";"no";"pendiente"}, 0),"✅","❌","🕓"), "⛔") & " ", "N" & IFERROR(CHOOSE(MATCH(INDEX(ControlMensual!R:R, MATCH(F26, ControlMensual!B:B, 0)), {"ok";"no";"pendiente"}, 0),"✅","❌","🕓"), "⛔") & " ", "D" & IFERROR(CHOOSE(MATCH(INDEX(ControlMensual!S:S, MATCH(F26, ControlMensual!B:B, 0)), {"ok";"no";"pendiente"}, 0),"✅","❌","🕓"), "⛔") ) ,"") ) -> Ya no cuenta con actualizaciones | U26: Si | V26: Si | W26: No | X26: No aplica | Y26: =COUNTIF(U26:X26,"Si")/(COUNTIF(U26:X26,"Si")+COUNTIF(U26:X26,"No")) -> 0.66666667 | Z26: Sin Proyecto | AA26: Sin Fecha | AB26: Sistemas de Negocio | AC26: Sin Asignación | AD26: No | AE26: =VLOOKUP(E26,Falcon!B$2:C$558,2,FALSE) -> #REF! | AF26: =VLOOKUP(E26,VisionOne!B$2:C$229,2,FALSE) -> #REF! | AG26: =VLOOKUP(E26,Central!B$2:C$217,2,FALSE) -> #REF! | AH26: No | AJ26: Sin Asignación | AK26: No | AM26: =VLOOKUP(D26,'Copia de vInfo 2'!A:A,1,FALSE) -> #REF!
A27: 427 | B27: Sonda Cloud Privado | C27: Sonda | D27: COBAPPPRD3 | E27: cobappprd3 | F27: 172.29.217.7 | G27: Producción | H27: WebLogic Server Version: 12.2.1.3.0 | I27: Weblogic Transversal | J27: Servicios Transversales MDW | K27: Encendido | L27: Virtual | M27: Máquina Virtual VmWare | N27: No aplica | O27: Linux | P27: Red Hat Enterprise Linux 6 | Q27: Red Hat Enterprise Linux 6 (32-bit) | R27: =verificarVersionOS(Q27) -> #NAME? | S27: =IFERROR( IF(ISNUMBER(FIND("Soporte hasta: ", R27)), IF(VALUE(MID(R27,16,10))<TODAY(),"🟥 Obsoleto", IF(YEAR(VALUE(MID(R27,16,10)))=YEAR(TODAY()),"Actualizaciones disponibles", IF(YEAR(VALUE(MID(R27,16,10)))-YEAR(TODAY())=1,"Actualizaciones disponibles", IF(YEAR(VALUE(MID(R27,16,10)))-YEAR(TODAY())=2,"Actualizaciones disponibles", "Actualizaciones disponibles" ) ) ) ), "⛔ Sin datos" ), "⛔ Error en fecha" ) -> ⛔ Sin datos | T27: =IF(OR(S27 = "🟥 Obsoleto",S27 = "⛔ Sin datos"), "Ya no cuenta con actualizaciones", IFERROR( CONCATENATE( "E" & IFERROR(CHOOSE(MATCH(INDEX(ControlMensual!H:H, MATCH(F27, ControlMensual!B:B, 0)), {"ok";"no";"pendiente"}, 0),"✅","❌","🕓"), "⛔") & " ", "F" & IFERROR(CHOOSE(MATCH(INDEX(ControlMensual!I:I, MATCH(F27, ControlMensual!B:B, 0)), {"ok";"no";"pendiente"}, 0),"✅","❌","🕓"), "⛔") & " ", "M" & IFERROR(CHOOSE(MATCH(INDEX(ControlMensual!J:J, MATCH(F27, ControlMensual!B:B, 0)), {"ok";"no";"pendiente"}, 0),"✅","❌","🕓"), "⛔") & " ", "A" & IFERROR(CHOOSE(MATCH(INDEX(ControlMensual!K:K, MATCH(F27, ControlMensual!B:B, 0)), {"ok";"no";"pendiente"}, 0),"✅","❌","🕓"), "⛔") & " ", "M" & IFERROR(CHOOSE(MATCH(INDEX(ControlMensual!L:L, MATCH(F27, ControlMensual!B:B, 0)), {"ok";"no";"pendiente"}, 0),"✅","❌","🕓"), "⛔") & " ", "J" & IFERROR(CHOOSE(MATCH(INDEX(ControlMensual!M:M, MATCH(F27, ControlMensual!B:B, 0)), {"ok";"no";"pendiente"}, 0),"✅","❌","🕓"), "⛔") & " ", "J" & IFERROR(CHOOSE(MATCH(INDEX(ControlMensual!N:N, MATCH(F27, ControlMensual!B:B, 0)), {"ok";"no";"pendiente"}, 0),"✅","❌","🕓"), "⛔") & " ", "A" & IFERROR(CHOOSE(MATCH(INDEX(ControlMensual!O:O, MATCH(F27, ControlMensual!B:B, 0)), {"ok";"no";"pendiente"}, 0),"✅","❌","🕓"), "⛔") & " ", "S" & IFERROR(CHOOSE(MATCH(INDEX(ControlMensual!P:P, MATCH(F27, ControlMensual!B:B, 0)), {"ok";"no";"pendiente"}, 0),"✅","❌","🕓"), "⛔") & " ", "O" & IFERROR(CHOOSE(MATCH(INDEX(ControlMensual!Q:Q, MATCH(F27, ControlMensual!B:B, 0)), {"ok";"no";"pendiente"}, 0),"✅","❌","🕓"), "⛔") & " ", "N" & IFERROR(CHOOSE(MATCH(INDEX(ControlMensual!R:R, MATCH(F27, ControlMensual!B:B, 0)), {"ok";"no";"pendiente"}, 0),"✅","❌","🕓"), "⛔") & " ", "D" & IFERROR(CHOOSE(MATCH(INDEX(ControlMensual!S:S, MATCH(F27, ControlMensual!B:B, 0)), {"ok";"no";"pendiente"}, 0),"✅","❌","🕓"), "⛔") ) ,"") ) -> Ya no cuenta con actualizaciones | U27: Si | V27: Si | W27: No | X27: No aplica | Y27: =COUNTIF(U27:X27,"Si")/(COUNTIF(U27:X27,"Si")+COUNTIF(U27:X27,"No")) -> 0.66666667 | Z27: Sin Proyecto | AA27: Sin Fecha | AB27: Sistemas de Negocio | AC27: Sin Asignación | AD27: No | AE27: =VLOOKUP(E27,Falcon!B$2:C$558,2,FALSE) -> #REF! | AF27: =VLOOKUP(E27,VisionOne!B$2:C$229,2,FALSE) -> #REF! | AG27: =VLOOKUP(E27,Central!B$2:C$217,2,FALSE) -> #REF! | AH27: No | AJ27: Sin Asignación | AK27: No | AM27: =VLOOKUP(D27,'Copia de vInfo 2'!A:A,1,FALSE) -> #REF!
A28: 448 | B28: Sonda Cloud Público | C28: Sonda | D28: MDEAPPDEV1 | E28: mdeappdev1 | F28: 172.29.191.34 | G28: Desarrollo | H28: DMPS 4 (FICO) | I28: Motor de decisión FICO | J28: Motor de decisión FICO | K28: Encendido | L28: Virtual | M28: Máquina Virtual VmWare | N28: No aplica | O28: Linux | P28: Red Hat Enterprise Linux 7 | Q28: Red Hat Enterprise Linux 7 (64-bit) | R28: =verificarVersionOS(Q28) -> #NAME? | S28: =IFERROR( IF(ISNUMBER(FIND("Soporte hasta: ", R28)), IF(VALUE(MID(R28,16,10))<TODAY(),"🟥 Obsoleto", IF(YEAR(VALUE(MID(R28,16,10)))=YEAR(TODAY()),"Actualizaciones disponibles", IF(YEAR(VALUE(MID(R28,16,10)))-YEAR(TODAY())=1,"Actualizaciones disponibles", IF(YEAR(VALUE(MID(R28,16,10)))-YEAR(TODAY())=2,"Actualizaciones disponibles", "Actualizaciones disponibles" ) ) ) ), "⛔ Sin datos" ), "⛔ Error en fecha" ) -> ⛔ Sin datos | T28: =IF(OR(S28 = "🟥 Obsoleto",S28 = "⛔ Sin datos"), "Ya no cuenta con actualizaciones", IFERROR( CONCATENATE( "E" & IFERROR(CHOOSE(MATCH(INDEX(ControlMensual!H:H, MATCH(F28, ControlMensual!B:B, 0)), {"ok";"no";"pendiente"}, 0),"✅","❌","🕓"), "⛔") & " ", "F" & IFERROR(CHOOSE(MATCH(INDEX(ControlMensual!I:I, MATCH(F28, ControlMensual!B:B, 0)), {"ok";"no";"pendiente"}, 0),"✅","❌","🕓"), "⛔") & " ", "M" & IFERROR(CHOOSE(MATCH(INDEX(ControlMensual!J:J, MATCH(F28, ControlMensual!B:B, 0)), {"ok";"no";"pendiente"}, 0),"✅","❌","🕓"), "⛔") & " ", "A" & IFERROR(CHOOSE(MATCH(INDEX(ControlMensual!K:K, MATCH(F28, ControlMensual!B:B, 0)), {"ok";"no";"pendiente"}, 0),"✅","❌","🕓"), "⛔") & " ", "M" & IFERROR(CHOOSE(MATCH(INDEX(ControlMensual!L:L, MATCH(F28, ControlMensual!B:B, 0)), {"ok";"no";"pendiente"}, 0),"✅","❌","🕓"), "⛔") & " ", "J" & IFERROR(CHOOSE(MATCH(INDEX(ControlMensual!M:M, MATCH(F28, ControlMensual!B:B, 0)), {"ok";"no";"pendiente"}, 0),"✅","❌","🕓"), "⛔") & " ", "J" & IFERROR(CHOOSE(MATCH(INDEX(ControlMensual!N:N, MATCH(F28, ControlMensual!B:B, 0)), {"ok";"no";"pendiente"}, 0),"✅","❌","🕓"), "⛔") & " ", "A" & IFERROR(CHOOSE(MATCH(INDEX(ControlMensual!O:O, MATCH(F28, ControlMensual!B:B, 0)), {"ok";"no";"pendiente"}, 0),"✅","❌","🕓"), "⛔") & " ", "S" & IFERROR(CHOOSE(MATCH(INDEX(ControlMensual!P:P, MATCH(F28, ControlMensual!B:B, 0)), {"ok";"no";"pendiente"}, 0),"✅","❌","🕓"), "⛔") & " ", "O" & IFERROR(CHOOSE(MATCH(INDEX(ControlMensual!Q:Q, MATCH(F28, ControlMensual!B:B, 0)), {"ok";"no";"pendiente"}, 0),"✅","❌","🕓"), "⛔") & " ", "N" & IFERROR(CHOOSE(MATCH(INDEX(ControlMensual!R:R, MATCH(F28, ControlMensual!B:B, 0)), {"ok";"no";"pendiente"}, 0),"✅","❌","🕓"), "⛔") & " ", "D" & IFERROR(CHOOSE(MATCH(INDEX(ControlMensual!S:S, MATCH(F28, ControlMensual!B:B, 0)), {"ok";"no";"pendiente"}, 0),"✅","❌","🕓"), "⛔") ) ,"") ) -> Ya no cuenta con actualizaciones | U28: Si | V28: Si | W28: No | X28: No aplica | Y28: =COUNTIF(U28:X28,"Si")/(COUNTIF(U28:X28,"Si")+COUNTIF(U28:X28,"No")) -> 0.66666667 | Z28: Migración FICO | AA28: 45930 | AB28: Sistemas Financieros | AC28: Claudia León | AD28: No | AE28: =VLOOKUP(D28,Falcon!B$2:C$558,2,FALSE) -> #REF! | AF28: =VLOOKUP(E28,VisionOne!B$2:C$229,2,FALSE) -> #REF! | AG28: =VLOOKUP(E28,Central!B$2:C$217,2,FALSE) -> #REF! | AH28: No | AJ28: Patricio Alegría | AK28: Si | AL28: x | AM28: =VLOOKUP(D28,'Copia de vInfo 2'!A:A,1,FALSE) -> #REF!
A29: 449 | B29: Sonda Cloud Público | C29: Sonda | D29: MDEBLZDEV1 | E29: mdeblzdev1 | F29: 172.29.191.46 | G29: Desarrollo | H29: BLAZE | I29: Motor de decisión FICO | J29: Motor de decisión FICO | K29: Encendido | L29: Virtual | M29: Máquina Virtual VmWare | N29: No aplica | O29: Linux | P29: Red Hat Enterprise Linux 7 | Q29: Red Hat Enterprise Linux 7 (64-bit) | R29: =verificarVersionOS(Q29) -> #NAME? | S29: =IFERROR( IF(ISNUMBER(FIND("Soporte hasta: ", R29)), IF(VALUE(MID(R29,16,10))<TODAY(),"🟥 Obsoleto", IF(YEAR(VALUE(MID(R29,16,10)))=YEAR(TODAY()),"Actualizaciones disponibles", IF(YEAR(VALUE(MID(R29,16,10)))-YEAR(TODAY())=1,"Actualizaciones disponibles", IF(YEAR(VALUE(MID(R29,16,10)))-YEAR(TODAY())=2,"Actualizaciones disponibles", "Actualizaciones disponibles" ) ) ) ), "⛔ Sin datos" ), "⛔ Error en fecha" ) -> ⛔ Sin datos | T29: =IF(OR(S29 = "🟥 Obsoleto",S29 = "⛔ Sin datos"), "Ya no cuenta con actualizaciones", IFERROR( CONCATENATE( "E" & IFERROR(CHOOSE(MATCH(INDEX(ControlMensual!H:H, MATCH(F29, ControlMensual!B:B, 0)), {"ok";"no";"pendiente"}, 0),"✅","❌","🕓"), "⛔") & " ", "F" & IFERROR(CHOOSE(MATCH(INDEX(ControlMensual!I:I, MATCH(F29, ControlMensual!B:B, 0)), {"ok";"no";"pendiente"}, 0),"✅","❌","🕓"), "⛔") & " ", "M" & IFERROR(CHOOSE(MATCH(INDEX(ControlMensual!J:J, MATCH(F29, ControlMensual!B:B, 0)), {"ok";"no";"pendiente"}, 0),"✅","❌","🕓"), "⛔") & " ", "A" & IFERROR(CHOOSE(MATCH(INDEX(ControlMensual!K:K, MATCH(F29, ControlMensual!B:B, 0)), {"ok";"no";"pendiente"}, 0),"✅","❌","🕓"), "⛔") & " ", "M" & IFERROR(CHOOSE(MATCH(INDEX(ControlMensual!L:L, MATCH(F29, ControlMensual!B:B, 0)), {"ok";"no";"pendiente"}, 0),"✅","❌","🕓"), "⛔") & " ", "J" & IFERROR(CHOOSE(MATCH(INDEX(ControlMensual!M:M, MATCH(F29, ControlMensual!B:B, 0)), {"ok";"no";"pendiente"}, 0),"✅","❌","🕓"), "⛔") & " ", "J" & IFERROR(CHOOSE(MATCH(INDEX(ControlMensual!N:N, MATCH(F29, ControlMensual!B:B, 0)), {"ok";"no";"pendiente"}, 0),"✅","❌","🕓"), "⛔") & " ", "A" & IFERROR(CHOOSE(MATCH(INDEX(ControlMensual!O:O, MATCH(F29, ControlMensual!B:B, 0)), {"ok";"no";"pendiente"}, 0),"✅","❌","🕓"), "⛔") & " ", "S" & IFERROR(CHOOSE(MATCH(INDEX(ControlMensual!P:P, MATCH(F29, ControlMensual!B:B, 0)), {"ok";"no";"pendiente"}, 0),"✅","❌","🕓"), "⛔") & " ", "O" & IFERROR(CHOOSE(MATCH(INDEX(ControlMensual!Q:Q, MATCH(F29, ControlMensual!B:B, 0)), {"ok";"no";"pendiente"}, 0),"✅","❌","🕓"), "⛔") & " ", "N" & IFERROR(CHOOSE(MATCH(INDEX(ControlMensual!R:R, MATCH(F29, ControlMensual!B:B, 0)), {"ok";"no";"pendiente"}, 0),"✅","❌","🕓"), "⛔") & " ", "D" & IFERROR(CHOOSE(MATCH(INDEX(ControlMensual!S:S, MATCH(F29, ControlMensual!B:B, 0)), {"ok";"no";"pendiente"}, 0),"✅","❌","🕓"), "⛔") ) ,"") ) -> Ya no cuenta con actualizaciones | U29: Si | V29: Si | W29: No | X29: No aplica | Y29: =COUNTIF(U29:X29,"Si")/(COUNTIF(U29:X29,"Si")+COUNTIF(U29:X29,"No")) -> 0.66666667 | Z29: Migración FICO | AA29: 45930 | AB29: Sistemas Financieros | AC29: Claudia León | AD29: No | AE29: =VLOOKUP(D29,Falcon!B$2:C$558,2,FALSE) -> #REF! | AF29: =VLOOKUP(E29,VisionOne!B$2:C$229,2,FALSE) -> #REF! | AG29: =VLOOKUP(E29,Central!B$2:C$217,2,FALSE) -> #REF! | AH29: No | AJ29: Patricio Alegría | AK29: Si | AL29: x | AM29: =VLOOKUP(D29,'Copia de vInfo 2'!A:A,1,FALSE) -> #REF!
A30: 450 | B30: Sonda Cloud Público | C30: Sonda | D30: MDEDMPQA3 | E30: mdepupqa3 | F30: 172.29.191.37 | G30: QA | H30: DMPS 4 (FICO) | I30: Motor de decisión FICO | J30: Motor de decisión FICO | K30: Encendido | L30: Virtual | M30: Máquina Virtual VmWare | N30: No aplica | O30: Linux | P30: Red Hat Enterprise Linux 7 | Q30: Red Hat Enterprise Linux 7 (64-bit) | R30: =verificarVersionOS(Q30) -> #NAME? | S30: =IFERROR( IF(ISNUMBER(FIND("Soporte hasta: ", R30)), IF(VALUE(MID(R30,16,10))<TODAY(),"🟥 Obsoleto", IF(YEAR(VALUE(MID(R30,16,10)))=YEAR(TODAY()),"Actualizaciones disponibles", IF(YEAR(VALUE(MID(R30,16,10)))-YEAR(TODAY())=1,"Actualizaciones disponibles", IF(YEAR(VALUE(MID(R30,16,10)))-YEAR(TODAY())=2,"Actualizaciones disponibles", "Actualizaciones disponibles" ) ) ) ), "⛔ Sin datos" ), "⛔ Error en fecha" ) -> ⛔ Sin datos | T30: =IF(OR(S30 = "🟥 Obsoleto",S30 = "⛔ Sin datos"), "Ya no cuenta con actualizaciones", IFERROR( CONCATENATE( "E" & IFERROR(CHOOSE(MATCH(INDEX(ControlMensual!H:H, MATCH(F30, ControlMensual!B:B, 0)), {"ok";"no";"pendiente"}, 0),"✅","❌","🕓"), "⛔") & " ", "F" & IFERROR(CHOOSE(MATCH(INDEX(ControlMensual!I:I, MATCH(F30, ControlMensual!B:B, 0)), {"ok";"no";"pendiente"}, 0),"✅","❌","🕓"), "⛔") & " ", "M" & IFERROR(CHOOSE(MATCH(INDEX(ControlMensual!J:J, MATCH(F30, ControlMensual!B:B, 0)), {"ok";"no";"pendiente"}, 0),"✅","❌","🕓"), "⛔") & " ", "A" & IFERROR(CHOOSE(MATCH(INDEX(ControlMensual!K:K, MATCH(F30, ControlMensual!B:B, 0)), {"ok";"no";"pendiente"}, 0),"✅","❌","🕓"), "⛔") & " ", "M" & IFERROR(CHOOSE(MATCH(INDEX(ControlMensual!L:L, MATCH(F30, ControlMensual!B:B, 0)), {"ok";"no";"pendiente"}, 0),"✅","❌","🕓"), "⛔") & " ", "J" & IFERROR(CHOOSE(MATCH(INDEX(ControlMensual!M:M, MATCH(F30, ControlMensual!B:B, 0)), {"ok";"no";"pendiente"}, 0),"✅","❌","🕓"), "⛔") & " ", "J" & IFERROR(CHOOSE(MATCH(INDEX(ControlMensual!N:N, MATCH(F30, ControlMensual!B:B, 0)), {"ok";"no";"pendiente"}, 0),"✅","❌","🕓"), "⛔") & " ", "A" & IFERROR(CHOOSE(MATCH(INDEX(ControlMensual!O:O, MATCH(F30, ControlMensual!B:B, 0)), {"ok";"no";"pendiente"}, 0),"✅","❌","🕓"), "⛔") & " ", "S" & IFERROR(CHOOSE(MATCH(INDEX(ControlMensual!P:P, MATCH(F30, ControlMensual!B:B, 0)), {"ok";"no";"pendiente"}, 0),"✅","❌","🕓"), "⛔") & " ", "O" & IFERROR(CHOOSE(MATCH(INDEX(ControlMensual!Q:Q, MATCH(F30, ControlMensual!B:B, 0)), {"ok";"no";"pendiente"}, 0),"✅","❌","🕓"), "⛔") & " ", "N" & IFERROR(CHOOSE(MATCH(INDEX(ControlMensual!R:R, MATCH(F30, ControlMensual!B:B, 0)), {"ok";"no";"pendiente"}, 0),"✅","❌","🕓"), "⛔") & " ", "D" & IFERROR(CHOOSE(MATCH(INDEX(ControlMensual!S:S, MATCH(F30, ControlMensual!B:B, 0)), {"ok";"no";"pendiente"}, 0),"✅","❌","🕓"), "⛔") ) ,"") ) -> Ya no cuenta con actualizaciones | U30: Si | V30: Si | W30: No | X30: No aplica | Y30: =COUNTIF(U30:X30,"Si")/(COUNTIF(U30:X30,"Si")+COUNTIF(U30:X30,"No")) -> 0.66666667 | Z30: Migración FICO | AA30: 45930 | AB30: Sistemas Financieros | AC30: Claudia León | AD30: No | AE30: =VLOOKUP(E30,Falcon!B$2:C$558,2,FALSE) -> #REF! | AF30: =VLOOKUP(E30,VisionOne!B$2:C$229,2,FALSE) -> #REF! | AG30: =VLOOKUP(E30,Central!B$2:C$217,2,FALSE) -> #REF! | AH30: No | AJ30: Patricio Alegría | AK30: Si | AL30: x | AM30: =VLOOKUP(D30,'Copia de vInfo 2'!A:A,1,FALSE) -> #REF!
A31: 451 | B31: Sonda Cloud Público | C31: Sonda | D31: MDEDMPQA4 | E31: mdepupqa4 | F31: 172.29.191.38 | G31: QA | H31: DMPS 4 (FICO) | I31: Motor de decisión FICO | J31: Motor de decisión FICO | K31: Encendido | L31: Virtual | M31: Máquina Virtual VmWare | N31: No aplica | O31: Linux | P31: Red Hat Enterprise Linux 7 | Q31: Red Hat Enterprise Linux 7 (64-bit) | R31: =verificarVersionOS(Q31) -> #NAME? | S31: =IFERROR( IF(ISNUMBER(FIND("Soporte hasta: ", R31)), IF(VALUE(MID(R31,16,10))<TODAY(),"🟥 Obsoleto", IF(YEAR(VALUE(MID(R31,16,10)))=YEAR(TODAY()),"Actualizaciones disponibles", IF(YEAR(VALUE(MID(R31,16,10)))-YEAR(TODAY())=1,"Actualizaciones disponibles", IF(YEAR(VALUE(MID(R31,16,10)))-YEAR(TODAY())=2,"Actualizaciones disponibles", "Actualizaciones disponibles" ) ) ) ), "⛔ Sin datos" ), "⛔ Error en fecha" ) -> ⛔ Sin datos | T31: =IF(OR(S31 = "🟥 Obsoleto",S31 = "⛔ Sin datos"), "Ya no cuenta con actualizaciones", IFERROR( CONCATENATE( "E" & IFERROR(CHOOSE(MATCH(INDEX(ControlMensual!H:H, MATCH(F31, ControlMensual!B:B, 0)), {"ok";"no";"pendiente"}, 0),"✅","❌","🕓"), "⛔") & " ", "F" & IFERROR(CHOOSE(MATCH(INDEX(ControlMensual!I:I, MATCH(F31, ControlMensual!B:B, 0)), {"ok";"no";"pendiente"}, 0),"✅","❌","🕓"), "⛔") & " ", "M" & IFERROR(CHOOSE(MATCH(INDEX(ControlMensual!J:J, MATCH(F31, ControlMensual!B:B, 0)), {"ok";"no";"pendiente"}, 0),"✅","❌","🕓"), "⛔") & " ", "A" & IFERROR(CHOOSE(MATCH(INDEX(ControlMensual!K:K, MATCH(F31, ControlMensual!B:B, 0)), {"ok";"no";"pendiente"}, 0),"✅","❌","🕓"), "⛔") & " ", "M" & IFERROR(CHOOSE(MATCH(INDEX(ControlMensual!L:L, MATCH(F31, ControlMensual!B:B, 0)), {"ok";"no";"pendiente"}, 0),"✅","❌","🕓"), "⛔") & " ", "J" & IFERROR(CHOOSE(MATCH(INDEX(ControlMensual!M:M, MATCH(F31, ControlMensual!B:B, 0)), {"ok";"no";"pendiente"}, 0),"✅","❌","🕓"), "⛔") & " ", "J" & IFERROR(CHOOSE(MATCH(INDEX(ControlMensual!N:N, MATCH(F31, ControlMensual!B:B, 0)), {"ok";"no";"pendiente"}, 0),"✅","❌","🕓"), "⛔") & " ", "A" & IFERROR(CHOOSE(MATCH(INDEX(ControlMensual!O:O, MATCH(F31, ControlMensual!B:B, 0)), {"ok";"no";"pendiente"}, 0),"✅","❌","🕓"), "⛔") & " ", "S" & IFERROR(CHOOSE(MATCH(INDEX(ControlMensual!P:P, MATCH(F31, ControlMensual!B:B, 0)), {"ok";"no";"pendiente"}, 0),"✅","❌","🕓"), "⛔") & " ", "O" & IFERROR(CHOOSE(MATCH(INDEX(ControlMensual!Q:Q, MATCH(F31, ControlMensual!B:B, 0)), {"ok";"no";"pendiente"}, 0),"✅","❌","🕓"), "⛔") & " ", "N" & IFERROR(CHOOSE(MATCH(INDEX(ControlMensual!R:R, MATCH(F31, ControlMensual!B:B, 0)), {"ok";"no";"pendiente"}, 0),"✅","❌","🕓"), "⛔") & " ", "D" & IFERROR(CHOOSE(MATCH(INDEX(ControlMensual!S:S, MATCH(F31, ControlMensual!B:B, 0)), {"ok";"no";"pendiente"}, 0),"✅","❌","🕓"), "⛔") ) ,"") ) -> Ya no cuenta con actualizaciones | U31: Si | V31: Si | W31: No | X31: No aplica | Y31: =COUNTIF(U31:X31,"Si")/(COUNTIF(U31:X31,"Si")+COUNTIF(U31:X31,"No")) -> 0.66666667 | Z31: Migración FICO | AA31: 45930 | AB31: Sistemas Financieros | AC31: Claudia León | AD31: No | AE31: =VLOOKUP(E31,Falcon!B$2:C$558,2,FALSE) -> #REF! | AF31: =VLOOKUP(E31,VisionOne!B$2:C$229,2,FALSE) -> #REF! | AG31: =VLOOKUP(E31,Central!B$2:C$217,2,FALSE) -> #REF! | AH31: No | AJ31: Patricio Alegría | AK31: Si | AL31: x | AM31: =VLOOKUP(D31,'Copia de vInfo 2'!A:A,1,FALSE) -> #REF!
A32: 452 | B32: Sonda Cloud Público | C32: Sonda | D32: MDEDMPQA5 | E32: mdepupqa5 | F32: 172.29.191.39 | G32: QA | H32: DMPS 4 (FICO) | I32: Motor de decisión FICO | J32: Motor de decisión FICO | K32: Encendido | L32: Virtual | M32: Máquina Virtual VmWare | N32: No aplica | O32: Linux | P32: Red Hat Enterprise Linux 7 | Q32: Red Hat Enterprise Linux 7 (64-bit) | R32: =verificarVersionOS(Q32) -> #NAME? | S32: =IFERROR( IF(ISNUMBER(FIND("Soporte hasta: ", R32)), IF(VALUE(MID(R32,16,10))<TODAY(),"🟥 Obsoleto", IF(YEAR(VALUE(MID(R32,16,10)))=YEAR(TODAY()),"Actualizaciones disponibles", IF(YEAR(VALUE(MID(R32,16,10)))-YEAR(TODAY())=1,"Actualizaciones disponibles", IF(YEAR(VALUE(MID(R32,16,10)))-YEAR(TODAY())=2,"Actualizaciones disponibles", "Actualizaciones disponibles" ) ) ) ), "⛔ Sin datos" ), "⛔ Error en fecha" ) -> ⛔ Sin datos | T32: =IF(OR(S32 = "🟥 Obsoleto",S32 = "⛔ Sin datos"), "Ya no cuenta con actualizaciones", IFERROR( CONCATENATE( "E" & IFERROR(CHOOSE(MATCH(INDEX(ControlMensual!H:H, MATCH(F32, ControlMensual!B:B, 0)), {"ok";"no";"pendiente"}, 0),"✅","❌","🕓"), "⛔") & " ", "F" & IFERROR(CHOOSE(MATCH(INDEX(ControlMensual!I:I, MATCH(F32, ControlMensual!B:B, 0)), {"ok";"no";"pendiente"}, 0),"✅","❌","🕓"), "⛔") & " ", "M" & IFERROR(CHOOSE(MATCH(INDEX(ControlMensual!J:J, MATCH(F32, ControlMensual!B:B, 0)), {"ok";"no";"pendiente"}, 0),"✅","❌","🕓"), "⛔") & " ", "A" & IFERROR(CHOOSE(MATCH(INDEX(ControlMensual!K:K, MATCH(F32, ControlMensual!B:B, 0)), {"ok";"no";"pendiente"}, 0),"✅","❌","🕓"), "⛔") & " ", "M" & IFERROR(CHOOSE(MATCH(INDEX(ControlMensual!L:L, MATCH(F32, ControlMensual!B:B, 0)), {"ok";"no";"pendiente"}, 0),"✅","❌","🕓"), "⛔") & " ", "J" & IFERROR(CHOOSE(MATCH(INDEX(ControlMensual!M:M, MATCH(F32, ControlMensual!B:B, 0)), {"ok";"no";"pendiente"}, 0),"✅","❌","🕓"), "⛔") & " ", "J" & IFERROR(CHOOSE(MATCH(INDEX(ControlMensual!N:N, MATCH(F32, ControlMensual!B:B, 0)), {"ok";"no";"pendiente"}, 0),"✅","❌","🕓"), "⛔") & " ", "A" & IFERROR(CHOOSE(MATCH(INDEX(ControlMensual!O:O, MATCH(F32, ControlMensual!B:B, 0)), {"ok";"no";"pendiente"}, 0),"✅","❌","🕓"), "⛔") & " ", "S" & IFERROR(CHOOSE(MATCH(INDEX(ControlMensual!P:P, MATCH(F32, ControlMensual!B:B, 0)), {"ok";"no";"pendiente"}, 0),"✅","❌","🕓"), "⛔") & " ", "O" & IFERROR(CHOOSE(MATCH(INDEX(ControlMensual!Q:Q, MATCH(F32, ControlMensual!B:B, 0)), {"ok";"no";"pendiente"}, 0),"✅","❌","🕓"), "⛔") & " ", "N" & IFERROR(CHOOSE(MATCH(INDEX(ControlMensual!R:R, MATCH(F32, ControlMensual!B:B, 0)), {"ok";"no";"pendiente"}, 0),"✅","❌","🕓"), "⛔") & " ", "D" & IFERROR(CHOOSE(MATCH(INDEX(ControlMensual!S:S, MATCH(F32, ControlMensual!B:B, 0)), {"ok";"no";"pendiente"}, 0),"✅","❌","🕓"), "⛔") ) ,"") ) -> Ya no cuenta con actualizaciones | U32: Si | V32: Si | W32: No | X32: No aplica | Y32: =COUNTIF(U32:X32,"Si")/(COUNTIF(U32:X32,"Si")+COUNTIF(U32:X32,"No")) -> 0.66666667 | Z32: Migración FICO | AA32: 45930 | AB32: Sistemas Financieros | AC32: Claudia León | AD32: No | AE32: =VLOOKUP(E32,Falcon!B$2:C$558,2,FALSE) -> #REF! | AF32: =VLOOKUP(E32,VisionOne!B$2:C$229,2,FALSE) -> #REF! | AG32: =VLOOKUP(E32,Central!B$2:C$217,2,FALSE) -> #REF! | AH32: No | AJ32: Patricio Alegría | AK32: Si | AL32: x | AM32: =VLOOKUP(D32,'Copia de vInfo 2'!A:A,1,FALSE) -> #REF!
A33: 453 | B33: Sonda Cloud Público | C33: Sonda | D33: MDEDMPQA6 | E33: mdepupqa6 | F33: 172.29.191.40 | G33: QA | H33: DMPS 4 (FICO) | I33: Motor de decisión FICO | J33: Motor de decisión FICO | K33: Encendido | L33: Virtual | M33: Máquina Virtual VmWare | N33: No aplica | O33: Linux | P33: Red Hat Enterprise Linux 7 | Q33: Red Hat Enterprise Linux 7 (64-bit) | R33: =verificarVersionOS(Q33) -> #NAME? | S33: =IFERROR( IF(ISNUMBER(FIND("Soporte hasta: ", R33)), IF(VALUE(MID(R33,16,10))<TODAY(),"🟥 Obsoleto", IF(YEAR(VALUE(MID(R33,16,10)))=YEAR(TODAY()),"Actualizaciones disponibles", IF(YEAR(VALUE(MID(R33,16,10)))-YEAR(TODAY())=1,"Actualizaciones disponibles", IF(YEAR(VALUE(MID(R33,16,10)))-YEAR(TODAY())=2,"Actualizaciones disponibles", "Actualizaciones disponibles" ) ) ) ), "⛔ Sin datos" ), "⛔ Error en fecha" ) -> ⛔ Sin datos | T33: =IF(OR(S33 = "🟥 Obsoleto",S33 = "⛔ Sin datos"), "Ya no cuenta con actualizaciones", IFERROR( CONCATENATE( "E" & IFERROR(CHOOSE(MATCH(INDEX(ControlMensual!H:H, MATCH(F33, ControlMensual!B:B, 0)), {"ok";"no";"pendiente"}, 0),"✅","❌","🕓"), "⛔") & " ", "F" & IFERROR(CHOOSE(MATCH(INDEX(ControlMensual!I:I, MATCH(F33, ControlMensual!B:B, 0)), {"ok";"no";"pendiente"}, 0),"✅","❌","🕓"), "⛔") & " ", "M" & IFERROR(CHOOSE(MATCH(INDEX(ControlMensual!J:J, MATCH(F33, ControlMensual!B:B, 0)), {"ok";"no";"pendiente"}, 0),"✅","❌","🕓"), "⛔") & " ", "A" & IFERROR(CHOOSE(MATCH(INDEX(ControlMensual!K:K, MATCH(F33, ControlMensual!B:B, 0)), {"ok";"no";"pendiente"}, 0),"✅","❌","🕓"), "⛔") & " ", "M" & IFERROR(CHOOSE(MATCH(INDEX(ControlMensual!L:L, MATCH(F33, ControlMensual!B:B, 0)), {"ok";"no";"pendiente"}, 0),"✅","❌","🕓"), "⛔") & " ", "J" & IFERROR(CHOOSE(MATCH(INDEX(ControlMensual!M:M, MATCH(F33, ControlMensual!B:B, 0)), {"ok";"no";"pendiente"}, 0),"✅","❌","🕓"), "⛔") & " ", "J" & IFERROR(CHOOSE(MATCH(INDEX(ControlMensual!N:N, MATCH(F33, ControlMensual!B:B, 0)), {"ok";"no";"pendiente"}, 0),"✅","❌","🕓"), "⛔") & " ", "A" & IFERROR(CHOOSE(MATCH(INDEX(ControlMensual!O:O, MATCH(F33, ControlMensual!B:B, 0)), {"ok";"no";"pendiente"}, 0),"✅","❌","🕓"), "⛔") & " ", "S" & IFERROR(CHOOSE(MATCH(INDEX(ControlMensual!P:P, MATCH(F33, ControlMensual!B:B, 0)), {"ok";"no";"pendiente"}, 0),"✅","❌","🕓"), "⛔") & " ", "O" & IFERROR(CHOOSE(MATCH(INDEX(ControlMensual!Q:Q, MATCH(F33, ControlMensual!B:B, 0)), {"ok";"no";"pendiente"}, 0),"✅","❌","🕓"), "⛔") & " ", "N" & IFERROR(CHOOSE(MATCH(INDEX(ControlMensual!R:R, MATCH(F33, ControlMensual!B:B, 0)), {"ok";"no";"pendiente"}, 0),"✅","❌","🕓"), "⛔") & " ", "D" & IFERROR(CHOOSE(MATCH(INDEX(ControlMensual!S:S, MATCH(F33, ControlMensual!B:B, 0)), {"ok";"no";"pendiente"}, 0),"✅","❌","🕓"), "⛔") ) ,"") ) -> Ya no cuenta con actualizaciones | U33: Si | V33: Si | W33: No | X33: No aplica | Y33: =COUNTIF(U33:X33,"Si")/(COUNTIF(U33:X33,"Si")+COUNTIF(U33:X33,"No")) -> 0.66666667 | Z33: Migración FICO | AA33: 45930 | AB33: Sistemas Financieros | AC33: Claudia León | AD33: No | AE33: =VLOOKUP(E33,Falcon!B$2:C$558,2,FALSE) -> #REF! | AF33: =VLOOKUP(E33,VisionOne!B$2:C$229,2,FALSE) -> #REF! | AG33: =VLOOKUP(E33,Central!B$2:C$217,2,FALSE) -> #REF! | AH33: No | AJ33: Patricio Alegría | AK33: Si | AL33: x | AM33: =VLOOKUP(D33,'Copia de vInfo 2'!A:A,1,FALSE) -> #REF!
A34: 454 | B34: Sonda Cloud Público | C34: Sonda | D34: MDEPUPQA1 | E34: mdepupqa1 | F34: 172.29.191.35 | G34: QA | H34: DMPS 4 (FICO) | I34: Motor de decisión FICO | J34: Motor de decisión FICO | K34: Encendido | L34: Virtual | M34: Máquina Virtual VmWare | N34: No aplica | O34: Linux | P34: Red Hat Enterprise Linux 7 | Q34: Red Hat Enterprise Linux 7 (64-bit) | R34: =verificarVersionOS(Q34) -> #NAME? | S34: =IFERROR( IF(ISNUMBER(FIND("Soporte hasta: ", R34)), IF(VALUE(MID(R34,16,10))<TODAY(),"🟥 Obsoleto", IF(YEAR(VALUE(MID(R34,16,10)))=YEAR(TODAY()),"Actualizaciones disponibles", IF(YEAR(VALUE(MID(R34,16,10)))-YEAR(TODAY())=1,"Actualizaciones disponibles", IF(YEAR(VALUE(MID(R34,16,10)))-YEAR(TODAY())=2,"Actualizaciones disponibles", "Actualizaciones disponibles" ) ) ) ), "⛔ Sin datos" ), "⛔ Error en fecha" ) -> ⛔ Sin datos | T34: =IF(OR(S34 = "🟥 Obsoleto",S34 = "⛔ Sin datos"), "Ya no cuenta con actualizaciones", IFERROR( CONCATENATE( "E" & IFERROR(CHOOSE(MATCH(INDEX(ControlMensual!H:H, MATCH(F34, ControlMensual!B:B, 0)), {"ok";"no";"pendiente"}, 0),"✅","❌","🕓"), "⛔") & " ", "F" & IFERROR(CHOOSE(MATCH(INDEX(ControlMensual!I:I, MATCH(F34, ControlMensual!B:B, 0)), {"ok";"no";"pendiente"}, 0),"✅","❌","🕓"), "⛔") & " ", "M" & IFERROR(CHOOSE(MATCH(INDEX(ControlMensual!J:J, MATCH(F34, ControlMensual!B:B, 0)), {"ok";"no";"pendiente"}, 0),"✅","❌","🕓"), "⛔") & " ", "A" & IFERROR(CHOOSE(MATCH(INDEX(ControlMensual!K:K, MATCH(F34, ControlMensual!B:B, 0)), {"ok";"no";"pendiente"}, 0),"✅","❌","🕓"), "⛔") & " ", "M" & IFERROR(CHOOSE(MATCH(INDEX(ControlMensual!L:L, MATCH(F34, ControlMensual!B:B, 0)), {"ok";"no";"pendiente"}, 0),"✅","❌","🕓"), "⛔") & " ", "J" & IFERROR(CHOOSE(MATCH(INDEX(ControlMensual!M:M, MATCH(F34, ControlMensual!B:B, 0)), {"ok";"no";"pendiente"}, 0),"✅","❌","🕓"), "⛔") & " ", "J" & IFERROR(CHOOSE(MATCH(INDEX(ControlMensual!N:N, MATCH(F34, ControlMensual!B:B, 0)), {"ok";"no";"pendiente"}, 0),"✅","❌","🕓"), "⛔") & " ", "A" & IFERROR(CHOOSE(MATCH(INDEX(ControlMensual!O:O, MATCH(F34, ControlMensual!B:B, 0)), {"ok";"no";"pendiente"}, 0),"✅","❌","🕓"), "⛔") & " ", "S" & IFERROR(CHOOSE(MATCH(INDEX(ControlMensual!P:P, MATCH(F34, ControlMensual!B:B, 0)), {"ok";"no";"pendiente"}, 0),"✅","❌","🕓"), "⛔") & " ", "O" & IFERROR(CHOOSE(MATCH(INDEX(ControlMensual!Q:Q, MATCH(F34, ControlMensual!B:B, 0)), {"ok";"no";"pendiente"}, 0),"✅","❌","🕓"), "⛔") & " ", "N" & IFERROR(CHOOSE(MATCH(INDEX(ControlMensual!R:R, MATCH(F34, ControlMensual!B:B, 0)), {"ok";"no";"pendiente"}, 0),"✅","❌","🕓"), "⛔") & " ", "D" & IFERROR(CHOOSE(MATCH(INDEX(ControlMensual!S:S, MATCH(F34, ControlMensual!B:B, 0)), {"ok";"no";"pendiente"}, 0),"✅","❌","🕓"), "⛔") ) ,"") ) -> Ya no cuenta con actualizaciones | U34: Si | V34: Si | W34: No | X34: No aplica | Y34: =COUNTIF(U34:X34,"Si")/(COUNTIF(U34:X34,"Si")+COUNTIF(U34:X34,"No")) -> 0.66666667 | Z34: Migración FICO | AA34: 45930 | AB34: Sistemas Financieros | AC34: Claudia León | AD34: No | AE34: =VLOOKUP(D34,Falcon!B$2:C$558,2,FALSE) -> #REF! | AF34: =VLOOKUP(E34,VisionOne!B$2:C$229,2,FALSE) -> #REF! | AG34: =VLOOKUP(E34,Central!B$2:C$217,2,FALSE) -> #REF! | AH34: No | AJ34: Patricio Alegría | AK34: Si | AL34: x | AM34: =VLOOKUP(D34,'Copia de vInfo 2'!A:A,1,FALSE) -> #REF!
A35: 455 | B35: Sonda Cloud Público | C35: Sonda | D35: MDEPUPQA2 | E35: mdepupqa2 | F35: 172.29.191.36 | G35: QA | H35: DMPS 4 (FICO) | I35: Motor de decisión FICO | J35: Motor de decisión FICO | K35: Encendido | L35: Virtual | M35: Máquina Virtual VmWare | N35: No aplica | O35: Linux | P35: Red Hat Enterprise Linux 7 | Q35: Red Hat Enterprise Linux 7 (64-bit) | R35: =verificarVersionOS(Q35) -> #NAME? | S35: =IFERROR( IF(ISNUMBER(FIND("Soporte hasta: ", R35)), IF(VALUE(MID(R35,16,10))<TODAY(),"🟥 Obsoleto", IF(YEAR(VALUE(MID(R35,16,10)))=YEAR(TODAY()),"Actualizaciones disponibles", IF(YEAR(VALUE(MID(R35,16,10)))-YEAR(TODAY())=1,"Actualizaciones disponibles", IF(YEAR(VALUE(MID(R35,16,10)))-YEAR(TODAY())=2,"Actualizaciones disponibles", "Actualizaciones disponibles" ) ) ) ), "⛔ Sin datos" ), "⛔ Error en fecha" ) -> ⛔ Sin datos | T35: =IF(OR(S35 = "🟥 Obsoleto",S35 = "⛔ Sin datos"), "Ya no cuenta con actualizaciones", IFERROR( CONCATENATE( "E" & IFERROR(CHOOSE(MATCH(INDEX(ControlMensual!H:H, MATCH(F35, ControlMensual!B:B, 0)), {"ok";"no";"pendiente"}, 0),"✅","❌","🕓"), "⛔") & " ", "F" & IFERROR(CHOOSE(MATCH(INDEX(ControlMensual!I:I, MATCH(F35, ControlMensual!B:B, 0)), {"ok";"no";"pendiente"}, 0),"✅","❌","🕓"), "⛔") & " ", "M" & IFERROR(CHOOSE(MATCH(INDEX(ControlMensual!J:J, MATCH(F35, ControlMensual!B:B, 0)), {"ok";"no";"pendiente"}, 0),"✅","❌","🕓"), "⛔") & " ", "A" & IFERROR(CHOOSE(MATCH(INDEX(ControlMensual!K:K, MATCH(F35, ControlMensual!B:B, 0)), {"ok";"no";"pendiente"}, 0),"✅","❌","🕓"), "⛔") & " ", "M" & IFERROR(CHOOSE(MATCH(INDEX(ControlMensual!L:L, MATCH(F35, ControlMensual!B:B, 0)), {"ok";"no";"pendiente"}, 0),"✅","❌","🕓"), "⛔") & " ", "J" & IFERROR(CHOOSE(MATCH(INDEX(ControlMensual!M:M, MATCH(F35, ControlMensual!B:B, 0)), {"ok";"no";"pendiente"}, 0),"✅","❌","🕓"), "⛔") & " ", "J" & IFERROR(CHOOSE(MATCH(INDEX(ControlMensual!N:N, MATCH(F35, ControlMensual!B:B, 0)), {"ok";"no";"pendiente"}, 0),"✅","❌","🕓"), "⛔") & " ", "A" & IFERROR(CHOOSE(MATCH(INDEX(ControlMensual!O:O, MATCH(F35, ControlMensual!B:B, 0)), {"ok";"no";"pendiente"}, 0),"✅","❌","🕓"), "⛔") & " ", "S" & IFERROR(CHOOSE(MATCH(INDEX(ControlMensual!P:P, MATCH(F35, ControlMensual!B:B, 0)), {"ok";"no";"pendiente"}, 0),"✅","❌","🕓"), "⛔") & " ", "O" & IFERROR(CHOOSE(MATCH(INDEX(ControlMensual!Q:Q, MATCH(F35, ControlMensual!B:B, 0)), {"ok";"no";"pendiente"}, 0),"✅","❌","🕓"), "⛔") & " ", "N" & IFERROR(CHOOSE(MATCH(INDEX(ControlMensual!R:R, MATCH(F35, ControlMensual!B:B, 0)), {"ok";"no";"pendiente"}, 0),"✅","❌","🕓"), "⛔") & " ", "D" & IFERROR(CHOOSE(MATCH(INDEX(ControlMensual!S:S, MATCH(F35, ControlMensual!B:B, 0)), {"ok";"no";"pendiente"}, 0),"✅","❌","🕓"), "⛔") ) ,"") ) -> Ya no cuenta con actualizaciones | U35: Si | V35: Si | W35: No | X35: No aplica | Y35: =COUNTIF(U35:X35,"Si")/(COUNTIF(U35:X35,"Si")+COUNTIF(U35:X35,"No")) -> 0.66666667 | Z35: Migración FICO | AA35: 45930 | AB35: Sistemas Financieros | AC35: Claudia León | AD35: No | AE35: =VLOOKUP(D35,Falcon!B$2:C$558,2,FALSE) -> #REF! | AF35: =VLOOKUP(E35,VisionOne!B$2:C$229,2,FALSE) -> #REF! | AG35: =VLOOKUP(E35,Central!B$2:C$217,2,FALSE) -> #REF! | AH35: No | AJ35: Patricio Alegría | AK35: Si | AL35: x | AM35: =VLOOKUP(D35,'Copia de vInfo 2'!A:A,1,FALSE) -> #REF!
A36: 476 | B36: Sonda Cloud Público | C36: Sonda | D36: COBAPPDES1 | E36: cobappdes1 | F36: 172.29.217.73 | G36: Desarrollo | H36: WebLogic Server Version: 12.2.1.3.0 | I36: Weblogic Transversal | J36: Servicios Transversales MDW | K36: Encendido | L36: Virtual | M36: Máquina Virtual VmWare | N36: No aplica | O36: Linux | P36: Red Hat Enterprise Linux 6 | Q36: Red Hat Enterprise Linux 6 (32-bit) | R36: =verificarVersionOS(Q36) -> #NAME? | S36: =IFERROR( IF(ISNUMBER(FIND("Soporte hasta: ", R36)), IF(VALUE(MID(R36,16,10))<TODAY(),"🟥 Obsoleto", IF(YEAR(VALUE(MID(R36,16,10)))=YEAR(TODAY()),"Actualizaciones disponibles", IF(YEAR(VALUE(MID(R36,16,10)))-YEAR(TODAY())=1,"Actualizaciones disponibles", IF(YEAR(VALUE(MID(R36,16,10)))-YEAR(TODAY())=2,"Actualizaciones disponibles", "Actualizaciones disponibles" ) ) ) ), "⛔ Sin datos" ), "⛔ Error en fecha" ) -> ⛔ Sin datos | T36: =IF(OR(S36 = "🟥 Obsoleto",S36 = "⛔ Sin datos"), "Ya no cuenta con actualizaciones", IFERROR( CONCATENATE( "E" & IFERROR(CHOOSE(MATCH(INDEX(ControlMensual!H:H, MATCH(F36, ControlMensual!B:B, 0)), {"ok";"no";"pendiente"}, 0),"✅","❌","🕓"), "⛔") & " ", "F" & IFERROR(CHOOSE(MATCH(INDEX(ControlMensual!I:I, MATCH(F36, ControlMensual!B:B, 0)), {"ok";"no";"pendiente"}, 0),"✅","❌","🕓"), "⛔") & " ", "M" & IFERROR(CHOOSE(MATCH(INDEX(ControlMensual!J:J, MATCH(F36, ControlMensual!B:B, 0)), {"ok";"no";"pendiente"}, 0),"✅","❌","🕓"), "⛔") & " ", "A" & IFERROR(CHOOSE(MATCH(INDEX(ControlMensual!K:K, MATCH(F36, ControlMensual!B:B, 0)), {"ok";"no";"pendiente"}, 0),"✅","❌","🕓"), "⛔") & " ", "M" & IFERROR(CHOOSE(MATCH(INDEX(ControlMensual!L:L, MATCH(F36, ControlMensual!B:B, 0)), {"ok";"no";"pendiente"}, 0),"✅","❌","🕓"), "⛔") & " ", "J" & IFERROR(CHOOSE(MATCH(INDEX(ControlMensual!M:M, MATCH(F36, ControlMensual!B:B, 0)), {"ok";"no";"pendiente"}, 0),"✅","❌","🕓"), "⛔") & " ", "J" & IFERROR(CHOOSE(MATCH(INDEX(ControlMensual!N:N, MATCH(F36, ControlMensual!B:B, 0)), {"ok";"no";"pendiente"}, 0),"✅","❌","🕓"), "⛔") & " ", "A" & IFERROR(CHOOSE(MATCH(INDEX(ControlMensual!O:O, MATCH(F36, ControlMensual!B:B, 0)), {"ok";"no";"pendiente"}, 0),"✅","❌","🕓"), "⛔") & " ", "S" & IFERROR(CHOOSE(MATCH(INDEX(ControlMensual!P:P, MATCH(F36, ControlMensual!B:B, 0)), {"ok";"no";"pendiente"}, 0),"✅","❌","🕓"), "⛔") & " ", "O" & IFERROR(CHOOSE(MATCH(INDEX(ControlMensual!Q:Q, MATCH(F36, ControlMensual!B:B, 0)), {"ok";"no";"pendiente"}, 0),"✅","❌","🕓"), "⛔") & " ", "N" & IFERROR(CHOOSE(MATCH(INDEX(ControlMensual!R:R, MATCH(F36, ControlMensual!B:B, 0)), {"ok";"no";"pendiente"}, 0),"✅","❌","🕓"), "⛔") & " ", "D" & IFERROR(CHOOSE(MATCH(INDEX(ControlMensual!S:S, MATCH(F36, ControlMensual!B:B, 0)), {"ok";"no";"pendiente"}, 0),"✅","❌","🕓"), "⛔") ) ,"") ) -> Ya no cuenta con actualizaciones | U36: Si | V36: Si | W36: No | X36: No aplica | Y36: =COUNTIF(U36:X36,"Si")/(COUNTIF(U36:X36,"Si")+COUNTIF(U36:X36,"No")) -> 0.66666667 | Z36: Sin Proyecto | AA36: Sin Fecha | AB36: Sistemas de Negocio | AC36: Sin Asignación | AD36: No | AE36: =VLOOKUP(E36,Falcon!B$2:C$558,2,FALSE) -> #REF! | AF36: =VLOOKUP(E36,VisionOne!B$2:C$229,2,FALSE) -> #REF! | AG36: =VLOOKUP(E36,Central!B$2:C$217,2,FALSE) -> #REF! | AH36: No | AJ36: Sin Asignación | AK36: No | AM36: =VLOOKUP(D36,'Copia de vInfo 2'!A:A,1,FALSE) -> #REF!
A37: 477 | B37: Sonda Cloud Público | C37: Sonda | D37: COBAPPQA1 | E37: cobappqa1 | F37: 172.29.217.70 | G37: QA | H37: WebLogic Server Version: 12.2.1.3.0 | I37: Weblogic Transversal | J37: Servicios Transversales MDW | K37: Encendido | L37: Virtual | M37: Máquina Virtual VmWare | N37: No aplica | O37: Linux | P37: Red Hat Enterprise Linux 6 | Q37: Red Hat Enterprise Linux 6 (32-bit) | R37: =verificarVersionOS(Q37) -> #NAME? | S37: =IFERROR( IF(ISNUMBER(FIND("Soporte hasta: ", R37)), IF(VALUE(MID(R37,16,10))<TODAY(),"🟥 Obsoleto", IF(YEAR(VALUE(MID(R37,16,10)))=YEAR(TODAY()),"Actualizaciones disponibles", IF(YEAR(VALUE(MID(R37,16,10)))-YEAR(TODAY())=1,"Actualizaciones disponibles", IF(YEAR(VALUE(MID(R37,16,10)))-YEAR(TODAY())=2,"Actualizaciones disponibles", "Actualizaciones disponibles" ) ) ) ), "⛔ Sin datos" ), "⛔ Error en fecha" ) -> ⛔ Sin datos | T37: =IF(OR(S37 = "🟥 Obsoleto",S37 = "⛔ Sin datos"), "Ya no cuenta con actualizaciones", IFERROR( CONCATENATE( "E" & IFERROR(CHOOSE(MATCH(INDEX(ControlMensual!H:H, MATCH(F37, ControlMensual!B:B, 0)), {"ok";"no";"pendiente"}, 0),"✅","❌","🕓"), "⛔") & " ", "F" & IFERROR(CHOOSE(MATCH(INDEX(ControlMensual!I:I, MATCH(F37, ControlMensual!B:B, 0)), {"ok";"no";"pendiente"}, 0),"✅","❌","🕓"), "⛔") & " ", "M" & IFERROR(CHOOSE(MATCH(INDEX(ControlMensual!J:J, MATCH(F37, ControlMensual!B:B, 0)), {"ok";"no";"pendiente"}, 0),"✅","❌","🕓"), "⛔") & " ", "A" & IFERROR(CHOOSE(MATCH(INDEX(ControlMensual!K:K, MATCH(F37, ControlMensual!B:B, 0)), {"ok";"no";"pendiente"}, 0),"✅","❌","🕓"), "⛔") & " ", "M" & IFERROR(CHOOSE(MATCH(INDEX(ControlMensual!L:L, MATCH(F37, ControlMensual!B:B, 0)), {"ok";"no";"pendiente"}, 0),"✅","❌","🕓"), "⛔") & " ", "J" & IFERROR(CHOOSE(MATCH(INDEX(ControlMensual!M:M, MATCH(F37, ControlMensual!B:B, 0)), {"ok";"no";"pendiente"}, 0),"✅","❌","🕓"), "⛔") & " ", "J" & IFERROR(CHOOSE(MATCH(INDEX(ControlMensual!N:N, MATCH(F37, ControlMensual!B:B, 0)), {"ok";"no";"pendiente"}, 0),"✅","❌","🕓"), "⛔") & " ", "A" & IFERROR(CHOOSE(MATCH(INDEX(ControlMensual!O:O, MATCH(F37, ControlMensual!B:B, 0)), {"ok";"no";"pendiente"}, 0),"✅","❌","🕓"), "⛔") & " ", "S" & IFERROR(CHOOSE(MATCH(INDEX(ControlMensual!P:P, MATCH(F37, ControlMensual!B:B, 0)), {"ok";"no";"pendiente"}, 0),"✅","❌","🕓"), "⛔") & " ", "O" & IFERROR(CHOOSE(MATCH(INDEX(ControlMensual!Q:Q, MATCH(F37, ControlMensual!B:B, 0)), {"ok";"no";"pendiente"}, 0),"✅","❌","🕓"), "⛔") & " ", "N" & IFERROR(CHOOSE(MATCH(INDEX(ControlMensual!R:R, MATCH(F37, ControlMensual!B:B, 0)), {"ok";"no";"pendiente"}, 0),"✅","❌","🕓"), "⛔") & " ", "D" & IFERROR(CHOOSE(MATCH(INDEX(ControlMensual!S:S, MATCH(F37, ControlMensual!B:B, 0)), {"ok";"no";"pendiente"}, 0),"✅","❌","🕓"), "⛔") ) ,"") ) -> Ya no cuenta con actualizaciones | U37: Si | V37: Si | W37: No | X37: No aplica | Y37: =COUNTIF(U37:X37,"Si")/(COUNTIF(U37:X37,"Si")+COUNTIF(U37:X37,"No")) -> 0.66666667 | Z37: Sin Proyecto | AA37: Sin Fecha | AB37: Sistemas de Negocio | AC37: Sin Asignación | AD37: No | AE37: =VLOOKUP(E37,Falcon!B$2:C$558,2,FALSE) -> #REF! | AF37: =VLOOKUP(E37,VisionOne!B$2:C$229,2,FALSE) -> #REF! | AG37: =VLOOKUP(E37,Central!B$2:C$217,2,FALSE) -> #REF! | AH37: No | AJ37: Sin Asignación | AK37: No | AM37: =VLOOKUP(D37,'Copia de vInfo 2'!A:A,1,FALSE) -> #REF!
A38: 478 | B38: Sonda Cloud Público | C38: Sonda | D38: COBAPPQA2 | E38: cobappqa2 | F38: 172.29.217.71 | G38: QA | H38: WebLogic Server Version: 12.2.1.3.0 | I38: Weblogic Transversal | J38: Servicios Transversales MDW | K38: Encendido | L38: Virtual | M38: Máquina Virtual VmWare | N38: No aplica | O38: Linux | P38: Red Hat Enterprise Linux 6 | Q38: Red Hat Enterprise Linux 6 (32-bit) | R38: =verificarVersionOS(Q38) -> #NAME? | S38: =IFERROR( IF(ISNUMBER(FIND("Soporte hasta: ", R38)), IF(VALUE(MID(R38,16,10))<TODAY(),"🟥 Obsoleto", IF(YEAR(VALUE(MID(R38,16,10)))=YEAR(TODAY()),"Actualizaciones disponibles", IF(YEAR(VALUE(MID(R38,16,10)))-YEAR(TODAY())=1,"Actualizaciones disponibles", IF(YEAR(VALUE(MID(R38,16,10)))-YEAR(TODAY())=2,"Actualizaciones disponibles", "Actualizaciones disponibles" ) ) ) ), "⛔ Sin datos" ), "⛔ Error en fecha" ) -> ⛔ Sin datos | T38: =IF(OR(S38 = "🟥 Obsoleto",S38 = "⛔ Sin datos"), "Ya no cuenta con actualizaciones", IFERROR( CONCATENATE( "E" & IFERROR(CHOOSE(MATCH(INDEX(ControlMensual!H:H, MATCH(F38, ControlMensual!B:B, 0)), {"ok";"no";"pendiente"}, 0),"✅","❌","🕓"), "⛔") & " ", "F" & IFERROR(CHOOSE(MATCH(INDEX(ControlMensual!I:I, MATCH(F38, ControlMensual!B:B, 0)), {"ok";"no";"pendiente"}, 0),"✅","❌","🕓"), "⛔") & " ", "M" & IFERROR(CHOOSE(MATCH(INDEX(ControlMensual!J:J, MATCH(F38, ControlMensual!B:B, 0)), {"ok";"no";"pendiente"}, 0),"✅","❌","🕓"), "⛔") & " ", "A" & IFERROR(CHOOSE(MATCH(INDEX(ControlMensual!K:K, MATCH(F38, ControlMensual!B:B, 0)), {"ok";"no";"pendiente"}, 0),"✅","❌","🕓"), "⛔") & " ", "M" & IFERROR(CHOOSE(MATCH(INDEX(ControlMensual!L:L, MATCH(F38, ControlMensual!B:B, 0)), {"ok";"no";"pendiente"}, 0),"✅","❌","🕓"), "⛔") & " ", "J" & IFERROR(CHOOSE(MATCH(INDEX(ControlMensual!M:M, MATCH(F38, ControlMensual!B:B, 0)), {"ok";"no";"pendiente"}, 0),"✅","❌","🕓"), "⛔") & " ", "J" & IFERROR(CHOOSE(MATCH(INDEX(ControlMensual!N:N, MATCH(F38, ControlMensual!B:B, 0)), {"ok";"no";"pendiente"}, 0),"✅","❌","🕓"), "⛔") & " ", "A" & IFERROR(CHOOSE(MATCH(INDEX(ControlMensual!O:O, MATCH(F38, ControlMensual!B:B, 0)), {"ok";"no";"pendiente"}, 0),"✅","❌","🕓"), "⛔") & " ", "S" & IFERROR(CHOOSE(MATCH(INDEX(ControlMensual!P:P, MATCH(F38, ControlMensual!B:B, 0)), {"ok";"no";"pendiente"}, 0),"✅","❌","🕓"), "⛔") & " ", "O" & IFERROR(CHOOSE(MATCH(INDEX(ControlMensual!Q:Q, MATCH(F38, ControlMensual!B:B, 0)), {"ok";"no";"pendiente"}, 0),"✅","❌","🕓"), "⛔") & " ", "N" & IFERROR(CHOOSE(MATCH(INDEX(ControlMensual!R:R, MATCH(F38, ControlMensual!B:B, 0)), {"ok";"no";"pendiente"}, 0),"✅","❌","🕓"), "⛔") & " ", "D" & IFERROR(CHOOSE(MATCH(INDEX(ControlMensual!S:S, MATCH(F38, ControlMensual!B:B, 0)), {"ok";"no";"pendiente"}, 0),"✅","❌","🕓"), "⛔") ) ,"") ) -> Ya no cuenta con actualizaciones | U38: Si | V38: Si | W38: No | X38: No aplica | Y38: =COUNTIF(U38:X38,"Si")/(COUNTIF(U38:X38,"Si")+COUNTIF(U38:X38,"No")) -> 0.66666667 | Z38: Sin Proyecto | AA38: Sin Fecha | AB38: Sistemas de Negocio | AC38: Sin Asignación | AD38: No | AE38: =VLOOKUP(E38,Falcon!B$2:C$558,2,FALSE) -> #REF! | AF38: =VLOOKUP(E38,VisionOne!B$2:C$229,2,FALSE) -> #REF! | AG38: =VLOOKUP(E38,Central!B$2:C$217,2,FALSE) -> #REF! | AH38: No | AJ38: Sin Asignación | AK38: No | AM38: =VLOOKUP(D38,'Copia de vInfo 2'!A:A,1,FALSE) -> #REF!
A39: 479 | B39: Sonda Cloud Público | C39: Sonda | D39: COBAPPQA3 | E39: cobappqa3 | F39: 172.29.217.72 | G39: QA | H39: WebLogic Server Version: 12.2.1.3.0 | I39: Weblogic Transversal | J39: Servicios Transversales MDW | K39: Encendido | L39: Virtual | M39: Máquina Virtual VmWare | N39: No aplica | O39: Linux | P39: Red Hat Enterprise Linux 6 | Q39: Red Hat Enterprise Linux 6 (32-bit) | R39: =verificarVersionOS(Q39) -> #NAME? | S39: =IFERROR( IF(ISNUMBER(FIND("Soporte hasta: ", R39)), IF(VALUE(MID(R39,16,10))<TODAY(),"🟥 Obsoleto", IF(YEAR(VALUE(MID(R39,16,10)))=YEAR(TODAY()),"Actualizaciones disponibles", IF(YEAR(VALUE(MID(R39,16,10)))-YEAR(TODAY())=1,"Actualizaciones disponibles", IF(YEAR(VALUE(MID(R39,16,10)))-YEAR(TODAY())=2,"Actualizaciones disponibles", "Actualizaciones disponibles" ) ) ) ), "⛔ Sin datos" ), "⛔ Error en fecha" ) -> ⛔ Sin datos | T39: =IF(OR(S39 = "🟥 Obsoleto",S39 = "⛔ Sin datos"), "Ya no cuenta con actualizaciones", IFERROR( CONCATENATE( "E" & IFERROR(CHOOSE(MATCH(INDEX(ControlMensual!H:H, MATCH(F39, ControlMensual!B:B, 0)), {"ok";"no";"pendiente"}, 0),"✅","❌","🕓"), "⛔") & " ", "F" & IFERROR(CHOOSE(MATCH(INDEX(ControlMensual!I:I, MATCH(F39, ControlMensual!B:B, 0)), {"ok";"no";"pendiente"}, 0),"✅","❌","🕓"), "⛔") & " ", "M" & IFERROR(CHOOSE(MATCH(INDEX(ControlMensual!J:J, MATCH(F39, ControlMensual!B:B, 0)), {"ok";"no";"pendiente"}, 0),"✅","❌","🕓"), "⛔") & " ", "A" & IFERROR(CHOOSE(MATCH(INDEX(ControlMensual!K:K, MATCH(F39, ControlMensual!B:B, 0)), {"ok";"no";"pendiente"}, 0),"✅","❌","🕓"), "⛔") & " ", "M" & IFERROR(CHOOSE(MATCH(INDEX(ControlMensual!L:L, MATCH(F39, ControlMensual!B:B, 0)), {"ok";"no";"pendiente"}, 0),"✅","❌","🕓"), "⛔") & " ", "J" & IFERROR(CHOOSE(MATCH(INDEX(ControlMensual!M:M, MATCH(F39, ControlMensual!B:B, 0)), {"ok";"no";"pendiente"}, 0),"✅","❌","🕓"), "⛔") & " ", "J" & IFERROR(CHOOSE(MATCH(INDEX(ControlMensual!N:N, MATCH(F39, ControlMensual!B:B, 0)), {"ok";"no";"pendiente"}, 0),"✅","❌","🕓"), "⛔") & " ", "A" & IFERROR(CHOOSE(MATCH(INDEX(ControlMensual!O:O, MATCH(F39, ControlMensual!B:B, 0)), {"ok";"no";"pendiente"}, 0),"✅","❌","🕓"), "⛔") & " ", "S" & IFERROR(CHOOSE(MATCH(INDEX(ControlMensual!P:P, MATCH(F39, ControlMensual!B:B, 0)), {"ok";"no";"pendiente"}, 0),"✅","❌","🕓"), "⛔") & " ", "O" & IFERROR(CHOOSE(MATCH(INDEX(ControlMensual!Q:Q, MATCH(F39, ControlMensual!B:B, 0)), {"ok";"no";"pendiente"}, 0),"✅","❌","🕓"), "⛔") & " ", "N" & IFERROR(CHOOSE(MATCH(INDEX(ControlMensual!R:R, MATCH(F39, ControlMensual!B:B, 0)), {"ok";"no";"pendiente"}, 0),"✅","❌","🕓"), "⛔") & " ", "D" & IFERROR(CHOOSE(MATCH(INDEX(ControlMensual!S:S, MATCH(F39, ControlMensual!B:B, 0)), {"ok";"no";"pendiente"}, 0),"✅","❌","🕓"), "⛔") ) ,"") ) -> Ya no cuenta con actualizaciones | U39: Si | V39: Si | W39: No | X39: No aplica | Y39: =COUNTIF(U39:X39,"Si")/(COUNTIF(U39:X39,"Si")+COUNTIF(U39:X39,"No")) -> 0.66666667 | Z39: Sin Proyecto | AA39: Sin Fecha | AB39: Sistemas de Negocio | AC39: Sin Asignación | AD39: No | AE39: =VLOOKUP(E39,Falcon!B$2:C$558,2,FALSE) -> #REF! | AF39: =VLOOKUP(E39,VisionOne!B$2:C$229,2,FALSE) -> #REF! | AG39: =VLOOKUP(E39,Central!B$2:C$217,2,FALSE) -> #REF! | AH39: No | AJ39: Sin Asignación | AK39: No | AM39: =VLOOKUP(D39,'Copia de vInfo 2'!A:A,1,FALSE) -> #REF!
A40: 481 | B40: sa-santiago-1 | C40: Oracle | D40: laccprdm01apigw | E40: laccprdm01apigw | F40: 10.110.70.111 | G40: Producción | H40: APIGW | I40: APIGW | J40: Legados | K40: Encendido | L40: Virtual | M40: Máquina Virtual Oracle | N40: No aplica | O40: Linux | P40: Oracle Linux 6 | Q40: Oracle Linux 6.10 | R40: =verificarVersionOS(Q40) -> #NAME? | S40: =IFERROR( IF(ISNUMBER(FIND("Soporte hasta: ", R40)), IF(VALUE(MID(R40,16,10))<TODAY(),"🟥 Obsoleto", IF(YEAR(VALUE(MID(R40,16,10)))=YEAR(TODAY()),"Actualizaciones disponibles", IF(YEAR(VALUE(MID(R40,16,10)))-YEAR(TODAY())=1,"Actualizaciones disponibles", IF(YEAR(VALUE(MID(R40,16,10)))-YEAR(TODAY())=2,"Actualizaciones disponibles", "Actualizaciones disponibles" ) ) ) ), "⛔ Sin datos" ), "⛔ Error en fecha" ) -> ⛔ Sin datos | T40: =IF(OR(S40 = "🟥 Obsoleto",S40 = "⛔ Sin datos"), "Ya no cuenta con actualizaciones", IFERROR( CONCATENATE( "E" & IFERROR(CHOOSE(MATCH(INDEX(ControlMensual!H:H, MATCH(F40, ControlMensual!B:B, 0)), {"ok";"no";"pendiente"}, 0),"✅","❌","🕓"), "⛔") & " ", "F" & IFERROR(CHOOSE(MATCH(INDEX(ControlMensual!I:I, MATCH(F40, ControlMensual!B:B, 0)), {"ok";"no";"pendiente"}, 0),"✅","❌","🕓"), "⛔") & " ", "M" & IFERROR(CHOOSE(MATCH(INDEX(ControlMensual!J:J, MATCH(F40, ControlMensual!B:B, 0)), {"ok";"no";"pendiente"}, 0),"✅","❌","🕓"), "⛔") & " ", "A" & IFERROR(CHOOSE(MATCH(INDEX(ControlMensual!K:K, MATCH(F40, ControlMensual!B:B, 0)), {"ok";"no";"pendiente"}, 0),"✅","❌","🕓"), "⛔") & " ", "M" & IFERROR(CHOOSE(MATCH(INDEX(ControlMensual!L:L, MATCH(F40, ControlMensual!B:B, 0)), {"ok";"no";"pendiente"}, 0),"✅","❌","🕓"), "⛔") & " ", "J" & IFERROR(CHOOSE(MATCH(INDEX(ControlMensual!M:M, MATCH(F40, ControlMensual!B:B, 0)), {"ok";"no";"pendiente"}, 0),"✅","❌","🕓"), "⛔") & " ", "J" & IFERROR(CHOOSE(MATCH(INDEX(ControlMensual!N:N, MATCH(F40, ControlMensual!B:B, 0)), {"ok";"no";"pendiente"}, 0),"✅","❌","🕓"), "⛔") & " ", "A" & IFERROR(CHOOSE(MATCH(INDEX(ControlMensual!O:O, MATCH(F40, ControlMensual!B:B, 0)), {"ok";"no";"pendiente"}, 0),"✅","❌","🕓"), "⛔") & " ", "S" & IFERROR(CHOOSE(MATCH(INDEX(ControlMensual!P:P, MATCH(F40, ControlMensual!B:B, 0)), {"ok";"no";"pendiente"}, 0),"✅","❌","🕓"), "⛔") & " ", "O" & IFERROR(CHOOSE(MATCH(INDEX(ControlMensual!Q:Q, MATCH(F40, ControlMensual!B:B, 0)), {"ok";"no";"pendiente"}, 0),"✅","❌","🕓"), "⛔") & " ", "N" & IFERROR(CHOOSE(MATCH(INDEX(ControlMensual!R:R, MATCH(F40, ControlMensual!B:B, 0)), {"ok";"no";"pendiente"}, 0),"✅","❌","🕓"), "⛔") & " ", "D" & IFERROR(CHOOSE(MATCH(INDEX(ControlMensual!S:S, MATCH(F40, ControlMensual!B:B, 0)), {"ok";"no";"pendiente"}, 0),"✅","❌","🕓"), "⛔") ) ,"") ) -> Ya no cuenta con actualizaciones | U40: Si | V40: No | W40: No | X40: No | Y40: =COUNTIF(U40:X40,"Si")/(COUNTIF(U40:X40,"Si")+COUNTIF(U40:X40,"No")) -> 0.25 | Z40: Sin Proyecto | AA40: Sin Fecha | AB40: Sistemas Financieros | AC40: Sin Asignación | AD40: No | AE40: =VLOOKUP(E40,Falcon!B$2:C$558,2,FALSE) -> #REF! | AF40: =VLOOKUP(E40,VisionOne!B$2:C$229,2,FALSE) -> #REF! | AG40: =VLOOKUP(E40,Central!B$2:C$217,2,FALSE) -> #REF! | AH40: No | AJ40: Patricio Alegría | AK40: No | AM40: =VLOOKUP(D40,'Copia de vInfo 2'!A:A,1,FALSE) -> #REF! | AN40: Si
A41: 482 | B41: sa-santiago-1 | C41: Oracle | D41: laccprdm02apigw | E41: laccprdm02apigw | F41: 10.110.71.64 | G41: Producción | H41: APIGW | I41: APIGW | J41: Legados | K41: Encendido | L41: Virtual | M41: Máquina Virtual Oracle | N41: No aplica | O41: Linux | P41: Oracle Linux 6 | Q41: Oracle Linux 6.10 | R41: =verificarVersionOS(Q41) -> #NAME? | S41: =IFERROR( IF(ISNUMBER(FIND("Soporte hasta: ", R41)), IF(VALUE(MID(R41,16,10))<TODAY(),"🟥 Obsoleto", IF(YEAR(VALUE(MID(R41,16,10)))=YEAR(TODAY()),"Actualizaciones disponibles", IF(YEAR(VALUE(MID(R41,16,10)))-YEAR(TODAY())=1,"Actualizaciones disponibles", IF(YEAR(VALUE(MID(R41,16,10)))-YEAR(TODAY())=2,"Actualizaciones disponibles", "Actualizaciones disponibles" ) ) ) ), "⛔ Sin datos" ), "⛔ Error en fecha" ) -> ⛔ Sin datos | T41: =IF(OR(S41 = "🟥 Obsoleto",S41 = "⛔ Sin datos"), "Ya no cuenta con actualizaciones", IFERROR( CONCATENATE( "E" & IFERROR(CHOOSE(MATCH(INDEX(ControlMensual!H:H, MATCH(F41, ControlMensual!B:B, 0)), {"ok";"no";"pendiente"}, 0),"✅","❌","🕓"), "⛔") & " ", "F" & IFERROR(CHOOSE(MATCH(INDEX(ControlMensual!I:I, MATCH(F41, ControlMensual!B:B, 0)), {"ok";"no";"pendiente"}, 0),"✅","❌","🕓"), "⛔") & " ", "M" & IFERROR(CHOOSE(MATCH(INDEX(ControlMensual!J:J, MATCH(F41, ControlMensual!B:B, 0)), {"ok";"no";"pendiente"}, 0),"✅","❌","🕓"), "⛔") & " ", "A" & IFERROR(CHOOSE(MATCH(INDEX(ControlMensual!K:K, MATCH(F41, ControlMensual!B:B, 0)), {"ok";"no";"pendiente"}, 0),"✅","❌","🕓"), "⛔") & " ", "M" & IFERROR(CHOOSE(MATCH(INDEX(ControlMensual!L:L, MATCH(F41, ControlMensual!B:B, 0)), {"ok";"no";"pendiente"}, 0),"✅","❌","🕓"), "⛔") & " ", "J" & IFERROR(CHOOSE(MATCH(INDEX(ControlMensual!M:M, MATCH(F41, ControlMensual!B:B, 0)), {"ok";"no";"pendiente"}, 0),"✅","❌","🕓"), "⛔") & " ", "J" & IFERROR(CHOOSE(MATCH(INDEX(ControlMensual!N:N, MATCH(F41, ControlMensual!B:B, 0)), {"ok";"no";"pendiente"}, 0),"✅","❌","🕓"), "⛔") & " ", "A" & IFERROR(CHOOSE(MATCH(INDEX(ControlMensual!O:O, MATCH(F41, ControlMensual!B:B, 0)), {"ok";"no";"pendiente"}, 0),"✅","❌","🕓"), "⛔") & " ", "S" & IFERROR(CHOOSE(MATCH(INDEX(ControlMensual!P:P, MATCH(F41, ControlMensual!B:B, 0)), {"ok";"no";"pendiente"}, 0),"✅","❌","🕓"), "⛔") & " ", "O" & IFERROR(CHOOSE(MATCH(INDEX(ControlMensual!Q:Q, MATCH(F41, ControlMensual!B:B, 0)), {"ok";"no";"pendiente"}, 0),"✅","❌","🕓"), "⛔") & " ", "N" & IFERROR(CHOOSE(MATCH(INDEX(ControlMensual!R:R, MATCH(F41, ControlMensual!B:B, 0)), {"ok";"no";"pendiente"}, 0),"✅","❌","🕓"), "⛔") & " ", "D" & IFERROR(CHOOSE(MATCH(INDEX(ControlMensual!S:S, MATCH(F41, ControlMensual!B:B, 0)), {"ok";"no";"pendiente"}, 0),"✅","❌","🕓"), "⛔") ) ,"") ) -> Ya no cuenta con actualizaciones | U41: Si | V41: No | W41: No | X41: No | Y41: =COUNTIF(U41:X41,"Si")/(COUNTIF(U41:X41,"Si")+COUNTIF(U41:X41,"No")) -> 0.25 | Z41: Sin Proyecto | AA41: Sin Fecha | AB41: Sistemas Financieros | AC41: Sin Asignación | AD41: No | AE41: =VLOOKUP(E41,Falcon!B$2:C$558,2,FALSE) -> #REF! | AF41: =VLOOKUP(E41,VisionOne!B$2:C$229,2,FALSE) -> #REF! | AG41: =VLOOKUP(E41,Central!B$2:C$217,2,FALSE) -> #REF! | AH41: No | AJ41: Patricio Alegría | AK41: No | AM41: =VLOOKUP(D41,'Copia de vInfo 2'!A:A,1,FALSE) -> #REF! | AN41: Si
A42: 483 | B42: sa-santiago-1 | C42: Oracle | D42: laccprdm03apigw | E42: laccprdm03apigw | F42: 10.110.71.94 | G42: Producción | H42: APIGW | I42: APIGW | J42: Legados | K42: Encendido | L42: Virtual | M42: Máquina Virtual Oracle | N42: No aplica | O42: Linux | P42: Oracle Linux 6 | Q42: Oracle Linux 6.10 | R42: =verificarVersionOS(Q42) -> #NAME? | S42: =IFERROR( IF(ISNUMBER(FIND("Soporte hasta: ", R42)), IF(VALUE(MID(R42,16,10))<TODAY(),"🟥 Obsoleto", IF(YEAR(VALUE(MID(R42,16,10)))=YEAR(TODAY()),"Actualizaciones disponibles", IF(YEAR(VALUE(MID(R42,16,10)))-YEAR(TODAY())=1,"Actualizaciones disponibles", IF(YEAR(VALUE(MID(R42,16,10)))-YEAR(TODAY())=2,"Actualizaciones disponibles", "Actualizaciones disponibles" ) ) ) ), "⛔ Sin datos" ), "⛔ Error en fecha" ) -> ⛔ Sin datos | T42: =IF(OR(S42 = "🟥 Obsoleto",S42 = "⛔ Sin datos"), "Ya no cuenta con actualizaciones", IFERROR( CONCATENATE( "E" & IFERROR(CHOOSE(MATCH(INDEX(ControlMensual!H:H, MATCH(F42, ControlMensual!B:B, 0)), {"ok";"no";"pendiente"}, 0),"✅","❌","🕓"), "⛔") & " ", "F" & IFERROR(CHOOSE(MATCH(INDEX(ControlMensual!I:I, MATCH(F42, ControlMensual!B:B, 0)), {"ok";"no";"pendiente"}, 0),"✅","❌","🕓"), "⛔") & " ", "M" & IFERROR(CHOOSE(MATCH(INDEX(ControlMensual!J:J, MATCH(F42, ControlMensual!B:B, 0)), {"ok";"no";"pendiente"}, 0),"✅","❌","🕓"), "⛔") & " ", "A" & IFERROR(CHOOSE(MATCH(INDEX(ControlMensual!K:K, MATCH(F42, ControlMensual!B:B, 0)), {"ok";"no";"pendiente"}, 0),"✅","❌","🕓"), "⛔") & " ", "M" & IFERROR(CHOOSE(MATCH(INDEX(ControlMensual!L:L, MATCH(F42, ControlMensual!B:B, 0)), {"ok";"no";"pendiente"}, 0),"✅","❌","🕓"), "⛔") & " ", "J" & IFERROR(CHOOSE(MATCH(INDEX(ControlMensual!M:M, MATCH(F42, ControlMensual!B:B, 0)), {"ok";"no";"pendiente"}, 0),"✅","❌","🕓"), "⛔") & " ", "J" & IFERROR(CHOOSE(MATCH(INDEX(ControlMensual!N:N, MATCH(F42, ControlMensual!B:B, 0)), {"ok";"no";"pendiente"}, 0),"✅","❌","🕓"), "⛔") & " ", "A" & IFERROR(CHOOSE(MATCH(INDEX(ControlMensual!O:O, MATCH(F42, ControlMensual!B:B, 0)), {"ok";"no";"pendiente"}, 0),"✅","❌","🕓"), "⛔") & " ", "S" & IFERROR(CHOOSE(MATCH(INDEX(ControlMensual!P:P, MATCH(F42, ControlMensual!B:B, 0)), {"ok";"no";"pendiente"}, 0),"✅","❌","🕓"), "⛔") & " ", "O" & IFERROR(CHOOSE(MATCH(INDEX(ControlMensual!Q:Q, MATCH(F42, ControlMensual!B:B, 0)), {"ok";"no";"pendiente"}, 0),"✅","❌","🕓"), "⛔") & " ", "N" & IFERROR(CHOOSE(MATCH(INDEX(ControlMensual!R:R, MATCH(F42, ControlMensual!B:B, 0)), {"ok";"no";"pendiente"}, 0),"✅","❌","🕓"), "⛔") & " ", "D" & IFERROR(CHOOSE(MATCH(INDEX(ControlMensual!S:S, MATCH(F42, ControlMensual!B:B, 0)), {"ok";"no";"pendiente"}, 0),"✅","❌","🕓"), "⛔") ) ,"") ) -> Ya no cuenta con actualizaciones | U42: Si | V42: No | W42: No | X42: No | Y42: =COUNTIF(U42:X42,"Si")/(COUNTIF(U42:X42,"Si")+COUNTIF(U42:X42,"No")) -> 0.25 | Z42: Sin Proyecto | AA42: Sin Fecha | AB42: Sistemas Financieros | AC42: Sin Asignación | AD42: No | AE42: =VLOOKUP(E42,Falcon!B$2:C$558,2,FALSE) -> #REF! | AF42: =VLOOKUP(E42,VisionOne!B$2:C$229,2,FALSE) -> #REF! | AG42: =VLOOKUP(E42,Central!B$2:C$217,2,FALSE) -> #REF! | AH42: No | AJ42: Patricio Alegría | AK42: No | AM42: =VLOOKUP(D42,'Copia de vInfo 2'!A:A,1,FALSE) -> #REF! | AN42: Si
A43: 522 | B43: sa-santiago-1 | C43: Oracle | D43: laccprdm01adm | E43: laccprdm01adm | F43: 10.110.34.22 | G43: Producción | H43: Flexcube 11 | I43: Flexcube 11 | J43: Pilar Financiero | K43: Encendido | L43: Virtual | M43: Máquina Virtual Oracle | N43: No aplica | O43: Linux | P43: Oracle Linux 6 | Q43: Oracle Linux 6.10 | R43: =verificarVersionOS(Q43) -> #NAME? | S43: =IFERROR( IF(ISNUMBER(FIND("Soporte hasta: ", R43)), IF(VALUE(MID(R43,16,10))<TODAY(),"🟥 Obsoleto", IF(YEAR(VALUE(MID(R43,16,10)))=YEAR(TODAY()),"Actualizaciones disponibles", IF(YEAR(VALUE(MID(R43,16,10)))-YEAR(TODAY())=1,"Actualizaciones disponibles", IF(YEAR(VALUE(MID(R43,16,10)))-YEAR(TODAY())=2,"Actualizaciones disponibles", "Actualizaciones disponibles" ) ) ) ), "⛔ Sin datos" ), "⛔ Error en fecha" ) -> ⛔ Sin datos | T43: =IF(OR(S43 = "🟥 Obsoleto",S43 = "⛔ Sin datos"), "Ya no cuenta con actualizaciones", IFERROR( CONCATENATE( "E" & IFERROR(CHOOSE(MATCH(INDEX(ControlMensual!H:H, MATCH(F43, ControlMensual!B:B, 0)), {"ok";"no";"pendiente"}, 0),"✅","❌","🕓"), "⛔") & " ", "F" & IFERROR(CHOOSE(MATCH(INDEX(ControlMensual!I:I, MATCH(F43, ControlMensual!B:B, 0)), {"ok";"no";"pendiente"}, 0),"✅","❌","🕓"), "⛔") & " ", "M" & IFERROR(CHOOSE(MATCH(INDEX(ControlMensual!J:J, MATCH(F43, ControlMensual!B:B, 0)), {"ok";"no";"pendiente"}, 0),"✅","❌","🕓"), "⛔") & " ", "A" & IFERROR(CHOOSE(MATCH(INDEX(ControlMensual!K:K, MATCH(F43, ControlMensual!B:B, 0)), {"ok";"no";"pendiente"}, 0),"✅","❌","🕓"), "⛔") & " ", "M" & IFERROR(CHOOSE(MATCH(INDEX(ControlMensual!L:L, MATCH(F43, ControlMensual!B:B, 0)), {"ok";"no";"pendiente"}, 0),"✅","❌","🕓"), "⛔") & " ", "J" & IFERROR(CHOOSE(MATCH(INDEX(ControlMensual!M:M, MATCH(F43, ControlMensual!B:B, 0)), {"ok";"no";"pendiente"}, 0),"✅","❌","🕓"), "⛔") & " ", "J" & IFERROR(CHOOSE(MATCH(INDEX(ControlMensual!N:N, MATCH(F43, ControlMensual!B:B, 0)), {"ok";"no";"pendiente"}, 0),"✅","❌","🕓"), "⛔") & " ", "A" & IFERROR(CHOOSE(MATCH(INDEX(ControlMensual!O:O, MATCH(F43, ControlMensual!B:B, 0)), {"ok";"no";"pendiente"}, 0),"✅","❌","🕓"), "⛔") & " ", "S" & IFERROR(CHOOSE(MATCH(INDEX(ControlMensual!P:P, MATCH(F43, ControlMensual!B:B, 0)), {"ok";"no";"pendiente"}, 0),"✅","❌","🕓"), "⛔") & " ", "O" & IFERROR(CHOOSE(MATCH(INDEX(ControlMensual!Q:Q, MATCH(F43, ControlMensual!B:B, 0)), {"ok";"no";"pendiente"}, 0),"✅","❌","🕓"), "⛔") & " ", "N" & IFERROR(CHOOSE(MATCH(INDEX(ControlMensual!R:R, MATCH(F43, ControlMensual!B:B, 0)), {"ok";"no";"pendiente"}, 0),"✅","❌","🕓"), "⛔") & " ", "D" & IFERROR(CHOOSE(MATCH(INDEX(ControlMensual!S:S, MATCH(F43, ControlMensual!B:B, 0)), {"ok";"no";"pendiente"}, 0),"✅","❌","🕓"), "⛔") ) ,"") ) -> Ya no cuenta con actualizaciones | U43: Si | V43: No | W43: No | X43: No | Y43: =COUNTIF(U43:X43,"Si")/(COUNTIF(U43:X43,"Si")+COUNTIF(U43:X43,"No")) -> 0.25 | Z43: New Core | AA43: 46752 | AB43: Sistemas Financieros | AC43: Patricio Alegría | AD43: No | AE43: =VLOOKUP(D43,Falcon!B$2:C$558,2,FALSE) -> #REF! | AF43: =VLOOKUP(E43,VisionOne!B$2:C$229,2,FALSE) -> #REF! | AG43: =VLOOKUP(E43,Central!B$2:C$217,2,FALSE) -> #REF! | AH43: No | AJ43: Patricio Alegría | AK43: Si | AM43: =VLOOKUP(D43,'Copia de vInfo 2'!A:A,1,FALSE) -> #REF! | AN43: Si
A44: 523 | B44: us-ashburn-1 | C44: Oracle | D44: laccprdm01adm-dr | E44: laccprdm01adm-dr | F44: 10.112.34.22 | G44: DR | H44: Flexcube 11 | I44: Flexcube 11 | J44: Pilar Financiero | K44: Encendido | L44: Virtual | M44: Máquina Virtual Oracle | N44: No aplica | O44: Linux | P44: Oracle Linux 6 | Q44: Oracle Linux 6.10 | R44: =verificarVersionOS(Q44) -> #NAME? | S44: =IFERROR( IF(ISNUMBER(FIND("Soporte hasta: ", R44)), IF(VALUE(MID(R44,16,10))<TODAY(),"🟥 Obsoleto", IF(YEAR(VALUE(MID(R44,16,10)))=YEAR(TODAY()),"Actualizaciones disponibles", IF(YEAR(VALUE(MID(R44,16,10)))-YEAR(TODAY())=1,"Actualizaciones disponibles", IF(YEAR(VALUE(MID(R44,16,10)))-YEAR(TODAY())=2,"Actualizaciones disponibles", "Actualizaciones disponibles" ) ) ) ), "⛔ Sin datos" ), "⛔ Error en fecha" ) -> ⛔ Sin datos | T44: =IF(OR(S44 = "🟥 Obsoleto",S44 = "⛔ Sin datos"), "Ya no cuenta con actualizaciones", IFERROR( CONCATENATE( "E" & IFERROR(CHOOSE(MATCH(INDEX(ControlMensual!H:H, MATCH(F44, ControlMensual!B:B, 0)), {"ok";"no";"pendiente"}, 0),"✅","❌","🕓"), "⛔") & " ", "F" & IFERROR(CHOOSE(MATCH(INDEX(ControlMensual!I:I, MATCH(F44, ControlMensual!B:B, 0)), {"ok";"no";"pendiente"}, 0),"✅","❌","🕓"), "⛔") & " ", "M" & IFERROR(CHOOSE(MATCH(INDEX(ControlMensual!J:J, MATCH(F44, ControlMensual!B:B, 0)), {"ok";"no";"pendiente"}, 0),"✅","❌","🕓"), "⛔") & " ", "A" & IFERROR(CHOOSE(MATCH(INDEX(ControlMensual!K:K, MATCH(F44, ControlMensual!B:B, 0)), {"ok";"no";"pendiente"}, 0),"✅","❌","🕓"), "⛔") & " ", "M" & IFERROR(CHOOSE(MATCH(INDEX(ControlMensual!L:L, MATCH(F44, ControlMensual!B:B, 0)), {"ok";"no";"pendiente"}, 0),"✅","❌","🕓"), "⛔") & " ", "J" & IFERROR(CHOOSE(MATCH(INDEX(ControlMensual!M:M, MATCH(F44, ControlMensual!B:B, 0)), {"ok";"no";"pendiente"}, 0),"✅","❌","🕓"), "⛔") & " ", "J" & IFERROR(CHOOSE(MATCH(INDEX(ControlMensual!N:N, MATCH(F44, ControlMensual!B:B, 0)), {"ok";"no";"pendiente"}, 0),"✅","❌","🕓"), "⛔") & " ", "A" & IFERROR(CHOOSE(MATCH(INDEX(ControlMensual!O:O, MATCH(F44, ControlMensual!B:B, 0)), {"ok";"no";"pendiente"}, 0),"✅","❌","🕓"), "⛔") & " ", "S" & IFERROR(CHOOSE(MATCH(INDEX(ControlMensual!P:P, MATCH(F44, ControlMensual!B:B, 0)), {"ok";"no";"pendiente"}, 0),"✅","❌","🕓"), "⛔") & " ", "O" & IFERROR(CHOOSE(MATCH(INDEX(ControlMensual!Q:Q, MATCH(F44, ControlMensual!B:B, 0)), {"ok";"no";"pendiente"}, 0),"✅","❌","🕓"), "⛔") & " ", "N" & IFERROR(CHOOSE(MATCH(INDEX(ControlMensual!R:R, MATCH(F44, ControlMensual!B:B, 0)), {"ok";"no";"pendiente"}, 0),"✅","❌","🕓"), "⛔") & " ", "D" & IFERROR(CHOOSE(MATCH(INDEX(ControlMensual!S:S, MATCH(F44, ControlMensual!B:B, 0)), {"ok";"no";"pendiente"}, 0),"✅","❌","🕓"), "⛔") ) ,"") ) -> Ya no cuenta con actualizaciones | U44: Si | V44: No | W44: No | X44: No | Y44: =COUNTIF(U44:X44,"Si")/(COUNTIF(U44:X44,"Si")+COUNTIF(U44:X44,"No")) -> 0.25 | Z44: New Core | AA44: 46752 | AB44: Sistemas Financieros | AC44: Patricio Alegría | AD44: No | AE44: =VLOOKUP(E44,Falcon!B$2:C$558,2,FALSE) -> #REF! | AF44: =VLOOKUP(E44,VisionOne!B$2:C$229,2,FALSE) -> #REF! | AG44: =VLOOKUP(E44,Central!B$2:C$217,2,FALSE) -> #REF! | AH44: No | AJ44: Patricio Alegría | AK44: Si | AM44: =VLOOKUP(D44,'Copia de vInfo 2'!A:A,1,FALSE) -> #REF! | AN44: Si
A45: 524 | B45: sa-santiago-1 | C45: Oracle | D45: laccprdm01ofx | E45: laccprdm01ofx | F45: 10.110.34.10 | G45: Producción | H45: Flexcube 11 | I45: Flexcube 11 | J45: Pilar Financiero | K45: Encendido | L45: Virtual | M45: Máquina Virtual Oracle | N45: No aplica | O45: Linux | P45: Oracle Linux 6 | Q45: Oracle Linux 6.10 | R45: =verificarVersionOS(Q45) -> #NAME? | S45: =IFERROR( IF(ISNUMBER(FIND("Soporte hasta: ", R45)), IF(VALUE(MID(R45,16,10))<TODAY(),"🟥 Obsoleto", IF(YEAR(VALUE(MID(R45,16,10)))=YEAR(TODAY()),"Actualizaciones disponibles", IF(YEAR(VALUE(MID(R45,16,10)))-YEAR(TODAY())=1,"Actualizaciones disponibles", IF(YEAR(VALUE(MID(R45,16,10)))-YEAR(TODAY())=2,"Actualizaciones disponibles", "Actualizaciones disponibles" ) ) ) ), "⛔ Sin datos" ), "⛔ Error en fecha" ) -> ⛔ Sin datos | T45: =IF(OR(S45 = "🟥 Obsoleto",S45 = "⛔ Sin datos"), "Ya no cuenta con actualizaciones", IFERROR( CONCATENATE( "E" & IFERROR(CHOOSE(MATCH(INDEX(ControlMensual!H:H, MATCH(F45, ControlMensual!B:B, 0)), {"ok";"no";"pendiente"}, 0),"✅","❌","🕓"), "⛔") & " ", "F" & IFERROR(CHOOSE(MATCH(INDEX(ControlMensual!I:I, MATCH(F45, ControlMensual!B:B, 0)), {"ok";"no";"pendiente"}, 0),"✅","❌","🕓"), "⛔") & " ", "M" & IFERROR(CHOOSE(MATCH(INDEX(ControlMensual!J:J, MATCH(F45, ControlMensual!B:B, 0)), {"ok";"no";"pendiente"}, 0),"✅","❌","🕓"), "⛔") & " ", "A" & IFERROR(CHOOSE(MATCH(INDEX(ControlMensual!K:K, MATCH(F45, ControlMensual!B:B, 0)), {"ok";"no";"pendiente"}, 0),"✅","❌","🕓"), "⛔") & " ", "M" & IFERROR(CHOOSE(MATCH(INDEX(ControlMensual!L:L, MATCH(F45, ControlMensual!B:B, 0)), {"ok";"no";"pendiente"}, 0),"✅","❌","🕓"), "⛔") & " ", "J" & IFERROR(CHOOSE(MATCH(INDEX(ControlMensual!M:M, MATCH(F45, ControlMensual!B:B, 0)), {"ok";"no";"pendiente"}, 0),"✅","❌","🕓"), "⛔") & " ", "J" & IFERROR(CHOOSE(MATCH(INDEX(ControlMensual!N:N, MATCH(F45, ControlMensual!B:B, 0)), {"ok";"no";"pendiente"}, 0),"✅","❌","🕓"), "⛔") & " ", "A" & IFERROR(CHOOSE(MATCH(INDEX(ControlMensual!O:O, MATCH(F45, ControlMensual!B:B, 0)), {"ok";"no";"pendiente"}, 0),"✅","❌","🕓"), "⛔") & " ", "S" & IFERROR(CHOOSE(MATCH(INDEX(ControlMensual!P:P, MATCH(F45, ControlMensual!B:B, 0)), {"ok";"no";"pendiente"}, 0),"✅","❌","🕓"), "⛔") & " ", "O" & IFERROR(CHOOSE(MATCH(INDEX(ControlMensual!Q:Q, MATCH(F45, ControlMensual!B:B, 0)), {"ok";"no";"pendiente"}, 0),"✅","❌","🕓"), "⛔") & " ", "N" & IFERROR(CHOOSE(MATCH(INDEX(ControlMensual!R:R, MATCH(F45, ControlMensual!B:B, 0)), {"ok";"no";"pendiente"}, 0),"✅","❌","🕓"), "⛔") & " ", "D" & IFERROR(CHOOSE(MATCH(INDEX(ControlMensual!S:S, MATCH(F45, ControlMensual!B:B, 0)), {"ok";"no";"pendiente"}, 0),"✅","❌","🕓"), "⛔") ) ,"") ) -> Ya no cuenta con actualizaciones | U45: Si | V45: No | W45: No | X45: No | Y45: =COUNTIF(U45:X45,"Si")/(COUNTIF(U45:X45,"Si")+COUNTIF(U45:X45,"No")) -> 0.25 | Z45: New Core | AA45: 46752 | AB45: Sistemas Financieros | AC45: Patricio Alegría | AD45: No | AE45: =VLOOKUP(E45,Falcon!B$2:C$558,2,FALSE) -> #REF! | AF45: =VLOOKUP(E45,VisionOne!B$2:C$229,2,FALSE) -> #REF! | AG45: =VLOOKUP(E45,Central!B$2:C$217,2,FALSE) -> #REF! | AH45: No | AJ45: Patricio Alegría | AK45: Si | AM45: =VLOOKUP(D45,'Copia de vInfo 2'!A:A,1,FALSE) -> #REF! | AN45: Si
A46: 525 | B46: us-ashburn-1 | C46: Oracle | D46: LACCPRDM01OFX | E46: LACCPRDM01OFX | F46: 10.112.34.10 | G46: Producción | H46: Flexcube 11 | I46: Flexcube 11 | J46: Pilar Financiero | K46: Encendido | L46: Virtual | M46: Máquina Virtual Oracle | N46: No aplica | O46: Linux | P46: Oracle Linux 6 | Q46: Oracle Linux 6.10 | R46: =verificarVersionOS(Q46) -> #NAME? | S46: =IFERROR( IF(ISNUMBER(FIND("Soporte hasta: ", R46)), IF(VALUE(MID(R46,16,10))<TODAY(),"🟥 Obsoleto", IF(YEAR(VALUE(MID(R46,16,10)))=YEAR(TODAY()),"Actualizaciones disponibles", IF(YEAR(VALUE(MID(R46,16,10)))-YEAR(TODAY())=1,"Actualizaciones disponibles", IF(YEAR(VALUE(MID(R46,16,10)))-YEAR(TODAY())=2,"Actualizaciones disponibles", "Actualizaciones disponibles" ) ) ) ), "⛔ Sin datos" ), "⛔ Error en fecha" ) -> ⛔ Sin datos | T46: =IF(OR(S46 = "🟥 Obsoleto",S46 = "⛔ Sin datos"), "Ya no cuenta con actualizaciones", IFERROR( CONCATENATE( "E" & IFERROR(CHOOSE(MATCH(INDEX(ControlMensual!H:H, MATCH(F46, ControlMensual!B:B, 0)), {"ok";"no";"pendiente"}, 0),"✅","❌","🕓"), "⛔") & " ", "F" & IFERROR(CHOOSE(MATCH(INDEX(ControlMensual!I:I, MATCH(F46, ControlMensual!B:B, 0)), {"ok";"no";"pendiente"}, 0),"✅","❌","🕓"), "⛔") & " ", "M" & IFERROR(CHOOSE(MATCH(INDEX(ControlMensual!J:J, MATCH(F46, ControlMensual!B:B, 0)), {"ok";"no";"pendiente"}, 0),"✅","❌","🕓"), "⛔") & " ", "A" & IFERROR(CHOOSE(MATCH(INDEX(ControlMensual!K:K, MATCH(F46, ControlMensual!B:B, 0)), {"ok";"no";"pendiente"}, 0),"✅","❌","🕓"), "⛔") & " ", "M" & IFERROR(CHOOSE(MATCH(INDEX(ControlMensual!L:L, MATCH(F46, ControlMensual!B:B, 0)), {"ok";"no";"pendiente"}, 0),"✅","❌","🕓"), "⛔") & " ", "J" & IFERROR(CHOOSE(MATCH(INDEX(ControlMensual!M:M, MATCH(F46, ControlMensual!B:B, 0)), {"ok";"no";"pendiente"}, 0),"✅","❌","🕓"), "⛔") & " ", "J" & IFERROR(CHOOSE(MATCH(INDEX(ControlMensual!N:N, MATCH(F46, ControlMensual!B:B, 0)), {"ok";"no";"pendiente"}, 0),"✅","❌","🕓"), "⛔") & " ", "A" & IFERROR(CHOOSE(MATCH(INDEX(ControlMensual!O:O, MATCH(F46, ControlMensual!B:B, 0)), {"ok";"no";"pendiente"}, 0),"✅","❌","🕓"), "⛔") & " ", "S" & IFERROR(CHOOSE(MATCH(INDEX(ControlMensual!P:P, MATCH(F46, ControlMensual!B:B, 0)), {"ok";"no";"pendiente"}, 0),"✅","❌","🕓"), "⛔") & " ", "O" & IFERROR(CHOOSE(MATCH(INDEX(ControlMensual!Q:Q, MATCH(F46, ControlMensual!B:B, 0)), {"ok";"no";"pendiente"}, 0),"✅","❌","🕓"), "⛔") & " ", "N" & IFERROR(CHOOSE(MATCH(INDEX(ControlMensual!R:R, MATCH(F46, ControlMensual!B:B, 0)), {"ok";"no";"pendiente"}, 0),"✅","❌","🕓"), "⛔") & " ", "D" & IFERROR(CHOOSE(MATCH(INDEX(ControlMensual!S:S, MATCH(F46, ControlMensual!B:B, 0)), {"ok";"no";"pendiente"}, 0),"✅","❌","🕓"), "⛔") ) ,"") ) -> Ya no cuenta con actualizaciones | U46: Si | V46: No | W46: No | X46: No | Y46: =COUNTIF(U46:X46,"Si")/(COUNTIF(U46:X46,"Si")+COUNTIF(U46:X46,"No")) -> 0.25 | Z46: New Core | AA46: 46752 | AB46: Sistemas Financieros | AC46: Patricio Alegría | AD46: No | AE46: =VLOOKUP(E46,Falcon!B$2:C$558,2,FALSE) -> #REF! | AF46: =VLOOKUP(E46,VisionOne!B$2:C$229,2,FALSE) -> #REF! | AG46: =VLOOKUP(E46,Central!B$2:C$217,2,FALSE) -> #REF! | AH46: No | AJ46: Patricio Alegría | AK46: Si | AM46: =VLOOKUP(D46,'Copia de vInfo 2'!A:A,1,FALSE) -> #REF! | AN46: Si
A47: 526 | B47: sa-santiago-1 | C47: Oracle | D47: laccprdm02ofx | E47: laccprdm02ofx | F47: 10.110.34.11 | G47: Producción | H47: Flexcube 11 | I47: Flexcube 11 | J47: Pilar Financiero | K47: Encendido | L47: Virtual | M47: Máquina Virtual Oracle | N47: No aplica | O47: Linux | P47: Oracle Linux 6 | Q47: Oracle Linux 6.10 | R47: =verificarVersionOS(Q47) -> #NAME? | S47: =IFERROR( IF(ISNUMBER(FIND("Soporte hasta: ", R47)), IF(VALUE(MID(R47,16,10))<TODAY(),"🟥 Obsoleto", IF(YEAR(VALUE(MID(R47,16,10)))=YEAR(TODAY()),"Actualizaciones disponibles", IF(YEAR(VALUE(MID(R47,16,10)))-YEAR(TODAY())=1,"Actualizaciones disponibles", IF(YEAR(VALUE(MID(R47,16,10)))-YEAR(TODAY())=2,"Actualizaciones disponibles", "Actualizaciones disponibles" ) ) ) ), "⛔ Sin datos" ), "⛔ Error en fecha" ) -> ⛔ Sin datos | T47: =IF(OR(S47 = "🟥 Obsoleto",S47 = "⛔ Sin datos"), "Ya no cuenta con actualizaciones", IFERROR( CONCATENATE( "E" & IFERROR(CHOOSE(MATCH(INDEX(ControlMensual!H:H, MATCH(F47, ControlMensual!B:B, 0)), {"ok";"no";"pendiente"}, 0),"✅","❌","🕓"), "⛔") & " ", "F" & IFERROR(CHOOSE(MATCH(INDEX(ControlMensual!I:I, MATCH(F47, ControlMensual!B:B, 0)), {"ok";"no";"pendiente"}, 0),"✅","❌","🕓"), "⛔") & " ", "M" & IFERROR(CHOOSE(MATCH(INDEX(ControlMensual!J:J, MATCH(F47, ControlMensual!B:B, 0)), {"ok";"no";"pendiente"}, 0),"✅","❌","🕓"), "⛔") & " ", "A" & IFERROR(CHOOSE(MATCH(INDEX(ControlMensual!K:K, MATCH(F47, ControlMensual!B:B, 0)), {"ok";"no";"pendiente"}, 0),"✅","❌","🕓"), "⛔") & " ", "M" & IFERROR(CHOOSE(MATCH(INDEX(ControlMensual!L:L, MATCH(F47, ControlMensual!B:B, 0)), {"ok";"no";"pendiente"}, 0),"✅","❌","🕓"), "⛔") & " ", "J" & IFERROR(CHOOSE(MATCH(INDEX(ControlMensual!M:M, MATCH(F47, ControlMensual!B:B, 0)), {"ok";"no";"pendiente"}, 0),"✅","❌","🕓"), "⛔") & " ", "J" & IFERROR(CHOOSE(MATCH(INDEX(ControlMensual!N:N, MATCH(F47, ControlMensual!B:B, 0)), {"ok";"no";"pendiente"}, 0),"✅","❌","🕓"), "⛔") & " ", "A" & IFERROR(CHOOSE(MATCH(INDEX(ControlMensual!O:O, MATCH(F47, ControlMensual!B:B, 0)), {"ok";"no";"pendiente"}, 0),"✅","❌","🕓"), "⛔") & " ", "S" & IFERROR(CHOOSE(MATCH(INDEX(ControlMensual!P:P, MATCH(F47, ControlMensual!B:B, 0)), {"ok";"no";"pendiente"}, 0),"✅","❌","🕓"), "⛔") & " ", "O" & IFERROR(CHOOSE(MATCH(INDEX(ControlMensual!Q:Q, MATCH(F47, ControlMensual!B:B, 0)), {"ok";"no";"pendiente"}, 0),"✅","❌","🕓"), "⛔") & " ", "N" & IFERROR(CHOOSE(MATCH(INDEX(ControlMensual!R:R, MATCH(F47, ControlMensual!B:B, 0)), {"ok";"no";"pendiente"}, 0),"✅","❌","🕓"), "⛔") & " ", "D" & IFERROR(CHOOSE(MATCH(INDEX(ControlMensual!S:S, MATCH(F47, ControlMensual!B:B, 0)), {"ok";"no";"pendiente"}, 0),"✅","❌","🕓"), "⛔") ) ,"") ) -> Ya no cuenta con actualizaciones | U47: Si | V47: No | W47: No | X47: No | Y47: =COUNTIF(U47:X47,"Si")/(COUNTIF(U47:X47,"Si")+COUNTIF(U47:X47,"No")) -> 0.25 | Z47: New Core | AA47: 46752 | AB47: Sistemas Financieros | AC47: Patricio Alegría | AD47: No | AE47: =VLOOKUP(E47,Falcon!B$2:C$558,2,FALSE) -> #REF! | AF47: =VLOOKUP(E47,VisionOne!B$2:C$229,2,FALSE) -> #REF! | AG47: =VLOOKUP(E47,Central!B$2:C$217,2,FALSE) -> #REF! | AH47: No | AJ47: Patricio Alegría | AK47: Si | AM47: =VLOOKUP(D47,'Copia de vInfo 2'!A:A,1,FALSE) -> #REF! | AN47: Si
A48: 527 | B48: us-ashburn-1 | C48: Oracle | D48: LACCPRDM02OFX-dr | E48: LACCPRDM02OFX-dr | F48: 10.112.34.11 | G48: DR | H48: Flexcube 11 | I48: Flexcube 11 | J48: Pilar Financiero | K48: Encendido | L48: Virtual | M48: Máquina Virtual Oracle | N48: No aplica | O48: Linux | P48: Oracle Linux 6 | Q48: Oracle Linux 6.10 | R48: =verificarVersionOS(Q48) -> #NAME? | S48: =IFERROR( IF(ISNUMBER(FIND("Soporte hasta: ", R48)), IF(VALUE(MID(R48,16,10))<TODAY(),"🟥 Obsoleto", IF(YEAR(VALUE(MID(R48,16,10)))=YEAR(TODAY()),"Actualizaciones disponibles", IF(YEAR(VALUE(MID(R48,16,10)))-YEAR(TODAY())=1,"Actualizaciones disponibles", IF(YEAR(VALUE(MID(R48,16,10)))-YEAR(TODAY())=2,"Actualizaciones disponibles", "Actualizaciones disponibles" ) ) ) ), "⛔ Sin datos" ), "⛔ Error en fecha" ) -> ⛔ Sin datos | T48: =IF(OR(S48 = "🟥 Obsoleto",S48 = "⛔ Sin datos"), "Ya no cuenta con actualizaciones", IFERROR( CONCATENATE( "E" & IFERROR(CHOOSE(MATCH(INDEX(ControlMensual!H:H, MATCH(F48, ControlMensual!B:B, 0)), {"ok";"no";"pendiente"}, 0),"✅","❌","🕓"), "⛔") & " ", "F" & IFERROR(CHOOSE(MATCH(INDEX(ControlMensual!I:I, MATCH(F48, ControlMensual!B:B, 0)), {"ok";"no";"pendiente"}, 0),"✅","❌","🕓"), "⛔") & " ", "M" & IFERROR(CHOOSE(MATCH(INDEX(ControlMensual!J:J, MATCH(F48, ControlMensual!B:B, 0)), {"ok";"no";"pendiente"}, 0),"✅","❌","🕓"), "⛔") & " ", "A" & IFERROR(CHOOSE(MATCH(INDEX(ControlMensual!K:K, MATCH(F48, ControlMensual!B:B, 0)), {"ok";"no";"pendiente"}, 0),"✅","❌","🕓"), "⛔") & " ", "M" & IFERROR(CHOOSE(MATCH(INDEX(ControlMensual!L:L, MATCH(F48, ControlMensual!B:B, 0)), {"ok";"no";"pendiente"}, 0),"✅","❌","🕓"), "⛔") & " ", "J" & IFERROR(CHOOSE(MATCH(INDEX(ControlMensual!M:M, MATCH(F48, ControlMensual!B:B, 0)), {"ok";"no";"pendiente"}, 0),"✅","❌","🕓"), "⛔") & " ", "J" & IFERROR(CHOOSE(MATCH(INDEX(ControlMensual!N:N, MATCH(F48, ControlMensual!B:B, 0)), {"ok";"no";"pendiente"}, 0),"✅","❌","🕓"), "⛔") & " ", "A" & IFERROR(CHOOSE(MATCH(INDEX(ControlMensual!O:O, MATCH(F48, ControlMensual!B:B, 0)), {"ok";"no";"pendiente"}, 0),"✅","❌","🕓"), "⛔") & " ", "S" & IFERROR(CHOOSE(MATCH(INDEX(ControlMensual!P:P, MATCH(F48, ControlMensual!B:B, 0)), {"ok";"no";"pendiente"}, 0),"✅","❌","🕓"), "⛔") & " ", "O" & IFERROR(CHOOSE(MATCH(INDEX(ControlMensual!Q:Q, MATCH(F48, ControlMensual!B:B, 0)), {"ok";"no";"pendiente"}, 0),"✅","❌","🕓"), "⛔") & " ", "N" & IFERROR(CHOOSE(MATCH(INDEX(ControlMensual!R:R, MATCH(F48, ControlMensual!B:B, 0)), {"ok";"no";"pendiente"}, 0),"✅","❌","🕓"), "⛔") & " ", "D" & IFERROR(CHOOSE(MATCH(INDEX(ControlMensual!S:S, MATCH(F48, ControlMensual!B:B, 0)), {"ok";"no";"pendiente"}, 0),"✅","❌","🕓"), "⛔") ) ,"") ) -> Ya no cuenta con actualizaciones | U48: Si | V48: No | W48: No | X48: No | Y48: =COUNTIF(U48:X48,"Si")/(COUNTIF(U48:X48,"Si")+COUNTIF(U48:X48,"No")) -> 0.25 | Z48: New Core | AA48: 46752 | AB48: Sistemas Financieros | AC48: Patricio Alegría | AD48: No | AE48: =VLOOKUP(E48,Falcon!B$2:C$558,2,FALSE) -> #REF! | AF48: =VLOOKUP(E48,VisionOne!B$2:C$229,2,FALSE) -> #REF! | AG48: =VLOOKUP(E48,Central!B$2:C$217,2,FALSE) -> #REF! | AH48: No | AJ48: Patricio Alegría | AK48: Si | AM48: =VLOOKUP(D48,'Copia de vInfo 2'!A:A,1,FALSE) -> #REF! | AN48: Si
A49: 528 | B49: sa-santiago-1 | C49: Oracle | D49: laccprdm03ofx | E49: laccprdm03ofx | F49: 10.110.34.18 | G49: Producción | H49: Flexcube 11 | I49: Flexcube 11 | J49: Pilar Financiero | K49: Encendido | L49: Virtual | M49: Máquina Virtual Oracle | N49: No aplica | O49: Linux | P49: Oracle Linux 6 | Q49: Oracle Linux 6.10 | R49: =verificarVersionOS(Q49) -> #NAME? | S49: =IFERROR( IF(ISNUMBER(FIND("Soporte hasta: ", R49)), IF(VALUE(MID(R49,16,10))<TODAY(),"🟥 Obsoleto", IF(YEAR(VALUE(MID(R49,16,10)))=YEAR(TODAY()),"Actualizaciones disponibles", IF(YEAR(VALUE(MID(R49,16,10)))-YEAR(TODAY())=1,"Actualizaciones disponibles", IF(YEAR(VALUE(MID(R49,16,10)))-YEAR(TODAY())=2,"Actualizaciones disponibles", "Actualizaciones disponibles" ) ) ) ), "⛔ Sin datos" ), "⛔ Error en fecha" ) -> ⛔ Sin datos | T49: =IF(OR(S49 = "🟥 Obsoleto",S49 = "⛔ Sin datos"), "Ya no cuenta con actualizaciones", IFERROR( CONCATENATE( "E" & IFERROR(CHOOSE(MATCH(INDEX(ControlMensual!H:H, MATCH(F49, ControlMensual!B:B, 0)), {"ok";"no";"pendiente"}, 0),"✅","❌","🕓"), "⛔") & " ", "F" & IFERROR(CHOOSE(MATCH(INDEX(ControlMensual!I:I, MATCH(F49, ControlMensual!B:B, 0)), {"ok";"no";"pendiente"}, 0),"✅","❌","🕓"), "⛔") & " ", "M" & IFERROR(CHOOSE(MATCH(INDEX(ControlMensual!J:J, MATCH(F49, ControlMensual!B:B, 0)), {"ok";"no";"pendiente"}, 0),"✅","❌","🕓"), "⛔") & " ", "A" & IFERROR(CHOOSE(MATCH(INDEX(ControlMensual!K:K, MATCH(F49, ControlMensual!B:B, 0)), {"ok";"no";"pendiente"}, 0),"✅","❌","🕓"), "⛔") & " ", "M" & IFERROR(CHOOSE(MATCH(INDEX(ControlMensual!L:L, MATCH(F49, ControlMensual!B:B, 0)), {"ok";"no";"pendiente"}, 0),"✅","❌","🕓"), "⛔") & " ", "J" & IFERROR(CHOOSE(MATCH(INDEX(ControlMensual!M:M, MATCH(F49, ControlMensual!B:B, 0)), {"ok";"no";"pendiente"}, 0),"✅","❌","🕓"), "⛔") & " ", "J" & IFERROR(CHOOSE(MATCH(INDEX(ControlMensual!N:N, MATCH(F49, ControlMensual!B:B, 0)), {"ok";"no";"pendiente"}, 0),"✅","❌","🕓"), "⛔") & " ", "A" & IFERROR(CHOOSE(MATCH(INDEX(ControlMensual!O:O, MATCH(F49, ControlMensual!B:B, 0)), {"ok";"no";"pendiente"}, 0),"✅","❌","🕓"), "⛔") & " ", "S" & IFERROR(CHOOSE(MATCH(INDEX(ControlMensual!P:P, MATCH(F49, ControlMensual!B:B, 0)), {"ok";"no";"pendiente"}, 0),"✅","❌","🕓"), "⛔") & " ", "O" & IFERROR(CHOOSE(MATCH(INDEX(ControlMensual!Q:Q, MATCH(F49, ControlMensual!B:B, 0)), {"ok";"no";"pendiente"}, 0),"✅","❌","🕓"), "⛔") & " ", "N" & IFERROR(CHOOSE(MATCH(INDEX(ControlMensual!R:R, MATCH(F49, ControlMensual!B:B, 0)), {"ok";"no";"pendiente"}, 0),"✅","❌","🕓"), "⛔") & " ", "D" & IFERROR(CHOOSE(MATCH(INDEX(ControlMensual!S:S, MATCH(F49, ControlMensual!B:B, 0)), {"ok";"no";"pendiente"}, 0),"✅","❌","🕓"), "⛔") ) ,"") ) -> Ya no cuenta con actualizaciones | U49: Si | V49: No | W49: No | X49: No | Y49: =COUNTIF(U49:X49,"Si")/(COUNTIF(U49:X49,"Si")+COUNTIF(U49:X49,"No")) -> 0.25 | Z49: New Core | AA49: 46752 | AB49: Sistemas Financieros | AC49: Patricio Alegría | AD49: No | AE49: =VLOOKUP(E49,Falcon!B$2:C$558,2,FALSE) -> #REF! | AF49: =VLOOKUP(E49,VisionOne!B$2:C$229,2,FALSE) -> #REF! | AG49: =VLOOKUP(E49,Central!B$2:C$217,2,FALSE) -> #REF! | AH49: No | AJ49: Patricio Alegría | AK49: Si | AM49: =VLOOKUP(D49,'Copia de vInfo 2'!A:A,1,FALSE) -> #REF! | AN49: Si
A50: 529 | B50: us-ashburn-1 | C50: Oracle | D50: LACCPRDM03OFX-DR | E50: LACCPRDM03OFX-DR | F50: 10.112.34.18 | G50: DR | H50: Flexcube 11 | I50: Flexcube 11 | J50: Pilar Financiero | K50: Encendido | L50: Virtual | M50: Máquina Virtual Oracle | N50: No aplica | O50: Linux | P50: Oracle Linux 6 | Q50: Oracle Linux 6.10 | R50: =verificarVersionOS(Q50) -> #NAME? | S50: =IFERROR( IF(ISNUMBER(FIND("Soporte hasta: ", R50)), IF(VALUE(MID(R50,16,10))<TODAY(),"🟥 Obsoleto", IF(YEAR(VALUE(MID(R50,16,10)))=YEAR(TODAY()),"Actualizaciones disponibles", IF(YEAR(VALUE(MID(R50,16,10)))-YEAR(TODAY())=1,"Actualizaciones disponibles", IF(YEAR(VALUE(MID(R50,16,10)))-YEAR(TODAY())=2,"Actualizaciones disponibles", "Actualizaciones disponibles" ) ) ) ), "⛔ Sin datos" ), "⛔ Error en fecha" ) -> ⛔ Sin datos | T50: =IF(OR(S50 = "🟥 Obsoleto",S50 = "⛔ Sin datos"), "Ya no cuenta con actualizaciones", IFERROR( CONCATENATE( "E" & IFERROR(CHOOSE(MATCH(INDEX(ControlMensual!H:H, MATCH(F50, ControlMensual!B:B, 0)), {"ok";"no";"pendiente"}, 0),"✅","❌","🕓"), "⛔") & " ", "F" & IFERROR(CHOOSE(MATCH(INDEX(ControlMensual!I:I, MATCH(F50, ControlMensual!B:B, 0)), {"ok";"no";"pendiente"}, 0),"✅","❌","🕓"), "⛔") & " ", "M" & IFERROR(CHOOSE(MATCH(INDEX(ControlMensual!J:J, MATCH(F50, ControlMensual!B:B, 0)), {"ok";"no";"pendiente"}, 0),"✅","❌","🕓"), "⛔") & " ", "A" & IFERROR(CHOOSE(MATCH(INDEX(ControlMensual!K:K, MATCH(F50, ControlMensual!B:B, 0)), {"ok";"no";"pendiente"}, 0),"✅","❌","🕓"), "⛔") & " ", "M" & IFERROR(CHOOSE(MATCH(INDEX(ControlMensual!L:L, MATCH(F50, ControlMensual!B:B, 0)), {"ok";"no";"pendiente"}, 0),"✅","❌","🕓"), "⛔") & " ", "J" & IFERROR(CHOOSE(MATCH(INDEX(ControlMensual!M:M, MATCH(F50, ControlMensual!B:B, 0)), {"ok";"no";"pendiente"}, 0),"✅","❌","🕓"), "⛔") & " ", "J" & IFERROR(CHOOSE(MATCH(INDEX(ControlMensual!N:N, MATCH(F50, ControlMensual!B:B, 0)), {"ok";"no";"pendiente"}, 0),"✅","❌","🕓"), "⛔") & " ", "A" & IFERROR(CHOOSE(MATCH(INDEX(ControlMensual!O:O, MATCH(F50, ControlMensual!B:B, 0)), {"ok";"no";"pendiente"}, 0),"✅","❌","🕓"), "⛔") & " ", "S" & IFERROR(CHOOSE(MATCH(INDEX(ControlMensual!P:P, MATCH(F50, ControlMensual!B:B, 0)), {"ok";"no";"pendiente"}, 0),"✅","❌","🕓"), "⛔") & " ", "O" & IFERROR(CHOOSE(MATCH(INDEX(ControlMensual!Q:Q, MATCH(F50, ControlMensual!B:B, 0)), {"ok";"no";"pendiente"}, 0),"✅","❌","🕓"), "⛔") & " ", "N" & IFERROR(CHOOSE(MATCH(INDEX(ControlMensual!R:R, MATCH(F50, ControlMensual!B:B, 0)), {"ok";"no";"pendiente"}, 0),"✅","❌","🕓"), "⛔") & " ", "D" & IFERROR(CHOOSE(MATCH(INDEX(ControlMensual!S:S, MATCH(F50, ControlMensual!B:B, 0)), {"ok";"no";"pendiente"}, 0),"✅","❌","🕓"), "⛔") ) ,"") ) -> Ya no cuenta con actualizaciones | U50: Si | V50: No | W50: No | X50: No | Y50: =COUNTIF(U50:X50,"Si")/(COUNTIF(U50:X50,"Si")+COUNTIF(U50:X50,"No")) -> 0.25 | Z50: New Core | AA50: 46752 | AB50: Sistemas Financieros | AC50: Patricio Alegría | AD50: No | AE50: =VLOOKUP(E50,Falcon!B$2:C$558,2,FALSE) -> #REF! | AF50: =VLOOKUP(E50,VisionOne!B$2:C$229,2,FALSE) -> #REF! | AG50: =VLOOKUP(E50,Central!B$2:C$217,2,FALSE) -> #REF! | AH50: No | AJ50: Patricio Alegría | AK50: Si | AM50: =VLOOKUP(D50,'Copia de vInfo 2'!A:A,1,FALSE) -> #REF! | AN50: Si
A51: 530 | B51: sa-santiago-1 | C51: Oracle | D51: laccprdm04ofx | E51: laccprdm04ofx | F51: 10.110.34.19 | G51: Producción | H51: Flexcube 11 | I51: Flexcube 11 | J51: Pilar Financiero | K51: Encendido | L51: Virtual | M51: Máquina Virtual Oracle | N51: No aplica | O51: Linux | P51: Oracle Linux 6 | Q51: Oracle Linux 6.10 | R51: =verificarVersionOS(Q51) -> #NAME? | S51: =IFERROR( IF(ISNUMBER(FIND("Soporte hasta: ", R51)), IF(VALUE(MID(R51,16,10))<TODAY(),"🟥 Obsoleto", IF(YEAR(VALUE(MID(R51,16,10)))=YEAR(TODAY()),"Actualizaciones disponibles", IF(YEAR(VALUE(MID(R51,16,10)))-YEAR(TODAY())=1,"Actualizaciones disponibles", IF(YEAR(VALUE(MID(R51,16,10)))-YEAR(TODAY())=2,"Actualizaciones disponibles", "Actualizaciones disponibles" ) ) ) ), "⛔ Sin datos" ), "⛔ Error en fecha" ) -> ⛔ Sin datos | T51: =IF(OR(S51 = "🟥 Obsoleto",S51 = "⛔ Sin datos"), "Ya no cuenta con actualizaciones", IFERROR( CONCATENATE( "E" & IFERROR(CHOOSE(MATCH(INDEX(ControlMensual!H:H, MATCH(F51, ControlMensual!B:B, 0)), {"ok";"no";"pendiente"}, 0),"✅","❌","🕓"), "⛔") & " ", "F" & IFERROR(CHOOSE(MATCH(INDEX(ControlMensual!I:I, MATCH(F51, ControlMensual!B:B, 0)), {"ok";"no";"pendiente"}, 0),"✅","❌","🕓"), "⛔") & " ", "M" & IFERROR(CHOOSE(MATCH(INDEX(ControlMensual!J:J, MATCH(F51, ControlMensual!B:B, 0)), {"ok";"no";"pendiente"}, 0),"✅","❌","🕓"), "⛔") & " ", "A" & IFERROR(CHOOSE(MATCH(INDEX(ControlMensual!K:K, MATCH(F51, ControlMensual!B:B, 0)), {"ok";"no";"pendiente"}, 0),"✅","❌","🕓"), "⛔") & " ", "M" & IFERROR(CHOOSE(MATCH(INDEX(ControlMensual!L:L, MATCH(F51, ControlMensual!B:B, 0)), {"ok";"no";"pendiente"}, 0),"✅","❌","🕓"), "⛔") & " ", "J" & IFERROR(CHOOSE(MATCH(INDEX(ControlMensual!M:M, MATCH(F51, ControlMensual!B:B, 0)), {"ok";"no";"pendiente"}, 0),"✅","❌","🕓"), "⛔") & " ", "J" & IFERROR(CHOOSE(MATCH(INDEX(ControlMensual!N:N, MATCH(F51, ControlMensual!B:B, 0)), {"ok";"no";"pendiente"}, 0),"✅","❌","🕓"), "⛔") & " ", "A" & IFERROR(CHOOSE(MATCH(INDEX(ControlMensual!O:O, MATCH(F51, ControlMensual!B:B, 0)), {"ok";"no";"pendiente"}, 0),"✅","❌","🕓"), "⛔") & " ", "S" & IFERROR(CHOOSE(MATCH(INDEX(ControlMensual!P:P, MATCH(F51, ControlMensual!B:B, 0)), {"ok";"no";"pendiente"}, 0),"✅","❌","🕓"), "⛔") & " ", "O" & IFERROR(CHOOSE(MATCH(INDEX(ControlMensual!Q:Q, MATCH(F51, ControlMensual!B:B, 0)), {"ok";"no";"pendiente"}, 0),"✅","❌","🕓"), "⛔") & " ", "N" & IFERROR(CHOOSE(MATCH(INDEX(ControlMensual!R:R, MATCH(F51, ControlMensual!B:B, 0)), {"ok";"no";"pendiente"}, 0),"✅","❌","🕓"), "⛔") & " ", "D" & IFERROR(CHOOSE(MATCH(INDEX(ControlMensual!S:S, MATCH(F51, ControlMensual!B:B, 0)), {"ok";"no";"pendiente"}, 0),"✅","❌","🕓"), "⛔") ) ,"") ) -> Ya no cuenta con actualizaciones | U51: Si | V51: No | W51: No | X51: No | Y51: =COUNTIF(U51:X51,"Si")/(COUNTIF(U51:X51,"Si")+COUNTIF(U51:X51,"No")) -> 0.25 | Z51: New Core | AA51: 46752 | AB51: Sistemas Financieros | AC51: Patricio Alegría | AD51: No | AE51: =VLOOKUP(E51,Falcon!B$2:C$558,2,FALSE) -> #REF! | AF51: =VLOOKUP(E51,VisionOne!B$2:C$229,2,FALSE) -> #REF! | AG51: =VLOOKUP(E51,Central!B$2:C$217,2,FALSE) -> #REF! | AH51: No | AJ51: Patricio Alegría | AK51: Si | AM51: =VLOOKUP(D51,'Copia de vInfo 2'!A:A,1,FALSE) -> #REF! | AN51: Si
A52: 531 | B52: us-ashburn-1 | C52: Oracle | D52: LACCPRDM04OFX-dr | E52: LACCPRDM04OFX-dr | F52: 10.112.34.19 | G52: DR | H52: Flexcube 11 | I52: Flexcube 11 | J52: Pilar Financiero | K52: Encendido | L52: Virtual | M52: Máquina Virtual Oracle | N52: No aplica | O52: Linux | P52: Oracle Linux 6 | Q52: Oracle Linux 6.10 | R52: =verificarVersionOS(Q52) -> #NAME? | S52: =IFERROR( IF(ISNUMBER(FIND("Soporte hasta: ", R52)), IF(VALUE(MID(R52,16,10))<TODAY(),"🟥 Obsoleto", IF(YEAR(VALUE(MID(R52,16,10)))=YEAR(TODAY()),"Actualizaciones disponibles", IF(YEAR(VALUE(MID(R52,16,10)))-YEAR(TODAY())=1,"Actualizaciones disponibles", IF(YEAR(VALUE(MID(R52,16,10)))-YEAR(TODAY())=2,"Actualizaciones disponibles", "Actualizaciones disponibles" ) ) ) ), "⛔ Sin datos" ), "⛔ Error en fecha" ) -> ⛔ Sin datos | T52: =IF(OR(S52 = "🟥 Obsoleto",S52 = "⛔ Sin datos"), "Ya no cuenta con actualizaciones", IFERROR( CONCATENATE( "E" & IFERROR(CHOOSE(MATCH(INDEX(ControlMensual!H:H, MATCH(F52, ControlMensual!B:B, 0)), {"ok";"no";"pendiente"}, 0),"✅","❌","🕓"), "⛔") & " ", "F" & IFERROR(CHOOSE(MATCH(INDEX(ControlMensual!I:I, MATCH(F52, ControlMensual!B:B, 0)), {"ok";"no";"pendiente"}, 0),"✅","❌","🕓"), "⛔") & " ", "M" & IFERROR(CHOOSE(MATCH(INDEX(ControlMensual!J:J, MATCH(F52, ControlMensual!B:B, 0)), {"ok";"no";"pendiente"}, 0),"✅","❌","🕓"), "⛔") & " ", "A" & IFERROR(CHOOSE(MATCH(INDEX(ControlMensual!K:K, MATCH(F52, ControlMensual!B:B, 0)), {"ok";"no";"pendiente"}, 0),"✅","❌","🕓"), "⛔") & " ", "M" & IFERROR(CHOOSE(MATCH(INDEX(ControlMensual!L:L, MATCH(F52, ControlMensual!B:B, 0)), {"ok";"no";"pendiente"}, 0),"✅","❌","🕓"), "⛔") & " ", "J" & IFERROR(CHOOSE(MATCH(INDEX(ControlMensual!M:M, MATCH(F52, ControlMensual!B:B, 0)), {"ok";"no";"pendiente"}, 0),"✅","❌","🕓"), "⛔") & " ", "J" & IFERROR(CHOOSE(MATCH(INDEX(ControlMensual!N:N, MATCH(F52, ControlMensual!B:B, 0)), {"ok";"no";"pendiente"}, 0),"✅","❌","🕓"), "⛔") & " ", "A" & IFERROR(CHOOSE(MATCH(INDEX(ControlMensual!O:O, MATCH(F52, ControlMensual!B:B, 0)), {"ok";"no";"pendiente"}, 0),"✅","❌","🕓"), "⛔") & " ", "S" & IFERROR(CHOOSE(MATCH(INDEX(ControlMensual!P:P, MATCH(F52, ControlMensual!B:B, 0)), {"ok";"no";"pendiente"}, 0),"✅","❌","🕓"), "⛔") & " ", "O" & IFERROR(CHOOSE(MATCH(INDEX(ControlMensual!Q:Q, MATCH(F52, ControlMensual!B:B, 0)), {"ok";"no";"pendiente"}, 0),"✅","❌","🕓"), "⛔") & " ", "N" & IFERROR(CHOOSE(MATCH(INDEX(ControlMensual!R:R, MATCH(F52, ControlMensual!B:B, 0)), {"ok";"no";"pendiente"}, 0),"✅","❌","🕓"), "⛔") & " ", "D" & IFERROR(CHOOSE(MATCH(INDEX(ControlMensual!S:S, MATCH(F52, ControlMensual!B:B, 0)), {"ok";"no";"pendiente"}, 0),"✅","❌","🕓"), "⛔") ) ,"") ) -> Ya no cuenta con actualizaciones | U52: Si | V52: No | W52: No | X52: No | Y52: =COUNTIF(U52:X52,"Si")/(COUNTIF(U52:X52,"Si")+COUNTIF(U52:X52,"No")) -> 0.25 | Z52: New Core | AA52: 46752 | AB52: Sistemas Financieros | AC52: Patricio Alegría | AD52: No | AE52: =VLOOKUP(E52,Falcon!B$2:C$558,2,FALSE) -> #REF! | AF52: =VLOOKUP(E52,VisionOne!B$2:C$229,2,FALSE) -> #REF! | AG52: =VLOOKUP(E52,Central!B$2:C$217,2,FALSE) -> #REF! | AH52: No | AJ52: Patricio Alegría | AK52: Si | AM52: =VLOOKUP(D52,'Copia de vInfo 2'!A:A,1,FALSE) -> #REF! | AN52: Si
A53: 596 | B53: sa-santiago-1 | C53: Oracle | D53: laccm01pr2-lb-1 | E53: laccm01pr2-lb-1 | F53: 10.110.67.200 | G53: Producción | H53: OTD | I53: Oracle Service Bus 12.2.1.4 | J53: Servicios Transversales MDW | K53: Encendido | L53: Virtual | M53: Máquina Virtual Oracle | N53: No aplica | O53: Linux | P53: Oracle Linux 6 | Q53: Oracle Linux 6.10 | R53: =verificarVersionOS(Q53) -> #NAME? | S53: =IFERROR( IF(ISNUMBER(FIND("Soporte hasta: ", R53)), IF(VALUE(MID(R53,16,10))<TODAY(),"🟥 Obsoleto", IF(YEAR(VALUE(MID(R53,16,10)))=YEAR(TODAY()),"Actualizaciones disponibles", IF(YEAR(VALUE(MID(R53,16,10)))-YEAR(TODAY())=1,"Actualizaciones disponibles", IF(YEAR(VALUE(MID(R53,16,10)))-YEAR(TODAY())=2,"Actualizaciones disponibles", "Actualizaciones disponibles" ) ) ) ), "⛔ Sin datos" ), "⛔ Error en fecha" ) -> ⛔ Sin datos | U53: Si | V53: No | W53: No | X53: No | Y53: =COUNTIF(U53:X53,"Si")/(COUNTIF(U53:X53,"Si")+COUNTIF(U53:X53,"No")) -> 0.25 | Z53: Sin Proyecto | AA53: Sin Fecha | AB53: Sistemas Financieros | AC53: Sin Asignación | AD53: No | AE53: =VLOOKUP(E53,Falcon!B$2:C$558,2,FALSE) -> #REF! | AF53: =VLOOKUP(E53,VisionOne!B$2:C$229,2,FALSE) -> #REF! | AG53: =VLOOKUP(E53,Central!B$2:C$217,2,FALSE) -> #REF! | AH53: No | AJ53: Patricio Alegría | AK53: No | AM53: =VLOOKUP(D53,'Copia de vInfo 2'!A:A,1,FALSE) -> #REF!
A54: 897 | B54: us-ashburn-1 | C54: Oracle | D54: LACCPRDM05OFX-dr | E54: LACCPRDM05OFX-dr | F54: 10.112.34.17 | G54: DR | H54: Flexcube 11 | I54: Flexcube 11 | J54: Pilar Financiero | K54: Encendido | L54: Virtual | M54: Máquina Virtual Oracle | N54: No aplica | O54: Linux | P54: Oracle Linux 6 | Q54: Oracle Linux 6.10 | R54: =verificarVersionOS(Q54) -> #NAME? | S54: =IFERROR( IF(ISNUMBER(FIND("Soporte hasta: ", R54)), IF(VALUE(MID(R54,16,10))<TODAY(),"🟥 Obsoleto", IF(YEAR(VALUE(MID(R54,16,10)))=YEAR(TODAY()),"Actualizaciones disponibles", IF(YEAR(VALUE(MID(R54,16,10)))-YEAR(TODAY())=1,"Actualizaciones disponibles", IF(YEAR(VALUE(MID(R54,16,10)))-YEAR(TODAY())=2,"Actualizaciones disponibles", "Actualizaciones disponibles" ) ) ) ), "⛔ Sin datos" ), "⛔ Error en fecha" ) -> ⛔ Sin datos | T54: =IF(OR(S54 = "🟥 Obsoleto",S54 = "⛔ Sin datos"), "Ya no cuenta con actualizaciones", IFERROR( CONCATENATE( "E" & IFERROR(CHOOSE(MATCH(INDEX(ControlMensual!H:H, MATCH(F54, ControlMensual!B:B, 0)), {"ok";"no";"pendiente"}, 0),"✅","❌","🕓"), "⛔") & " ", "F" & IFERROR(CHOOSE(MATCH(INDEX(ControlMensual!I:I, MATCH(F54, ControlMensual!B:B, 0)), {"ok";"no";"pendiente"}, 0),"✅","❌","🕓"), "⛔") & " ", "M" & IFERROR(CHOOSE(MATCH(INDEX(ControlMensual!J:J, MATCH(F54, ControlMensual!B:B, 0)), {"ok";"no";"pendiente"}, 0),"✅","❌","🕓"), "⛔") & " ", "A" & IFERROR(CHOOSE(MATCH(INDEX(ControlMensual!K:K, MATCH(F54, ControlMensual!B:B, 0)), {"ok";"no";"pendiente"}, 0),"✅","❌","🕓"), "⛔") & " ", "M" & IFERROR(CHOOSE(MATCH(INDEX(ControlMensual!L:L, MATCH(F54, ControlMensual!B:B, 0)), {"ok";"no";"pendiente"}, 0),"✅","❌","🕓"), "⛔") & " ", "J" & IFERROR(CHOOSE(MATCH(INDEX(ControlMensual!M:M, MATCH(F54, ControlMensual!B:B, 0)), {"ok";"no";"pendiente"}, 0),"✅","❌","🕓"), "⛔") & " ", "J" & IFERROR(CHOOSE(MATCH(INDEX(ControlMensual!N:N, MATCH(F54, ControlMensual!B:B, 0)), {"ok";"no";"pendiente"}, 0),"✅","❌","🕓"), "⛔") & " ", "A" & IFERROR(CHOOSE(MATCH(INDEX(ControlMensual!O:O, MATCH(F54, ControlMensual!B:B, 0)), {"ok";"no";"pendiente"}, 0),"✅","❌","🕓"), "⛔") & " ", "S" & IFERROR(CHOOSE(MATCH(INDEX(ControlMensual!P:P, MATCH(F54, ControlMensual!B:B, 0)), {"ok";"no";"pendiente"}, 0),"✅","❌","🕓"), "⛔") & " ", "O" & IFERROR(CHOOSE(MATCH(INDEX(ControlMensual!Q:Q, MATCH(F54, ControlMensual!B:B, 0)), {"ok";"no";"pendiente"}, 0),"✅","❌","🕓"), "⛔") & " ", "N" & IFERROR(CHOOSE(MATCH(INDEX(ControlMensual!R:R, MATCH(F54, ControlMensual!B:B, 0)), {"ok";"no";"pendiente"}, 0),"✅","❌","🕓"), "⛔") & " ", "D" & IFERROR(CHOOSE(MATCH(INDEX(ControlMensual!S:S, MATCH(F54, ControlMensual!B:B, 0)), {"ok";"no";"pendiente"}, 0),"✅","❌","🕓"), "⛔") ) ,"") ) -> Ya no cuenta con actualizaciones | U54: Si | V54: No | W54: No | X54: No | Y54: =COUNTIF(U54:X54,"Si")/(COUNTIF(U54:X54,"Si")+COUNTIF(U54:X54,"No")) -> 0.25 | Z54: New Core | AA54: 46752 | AB54: Sistemas Financieros | AC54: Patricio Alegría | AD54: No | AE54: =VLOOKUP(E54,Falcon!B$2:C$558,2,FALSE) -> #REF! | AF54: =VLOOKUP(E54,VisionOne!B$2:C$229,2,FALSE) -> #REF! | AG54: =VLOOKUP(E54,Central!B$2:C$217,2,FALSE) -> #REF! | AH54: No | AJ54: Patricio Alegría | AK54: Si | AM54: =VLOOKUP(D54,'Copia de vInfo 2'!A:A,1,FALSE) -> #REF! | AN54: Si
A55: 1199 | B55: GCP | C55: Google | D55: instance-1-conecta | E55: instance-1-conecta | F55: 172.31.2.26 | G55: Sin Información | H55: Sin Software MDW | I55: Crédito Digital | J55: Nicanor | K55: Encendido | L55: Virtual | M55: Máquina Virtual Google | N55: No aplica | O55: Linux | P55: Centos 4/5/6/7 | Q55: centos 7 | R55: =verificarVersionOS(Q55) -> #NAME? | S55: =IFERROR( IF(ISNUMBER(FIND("Soporte hasta: ", R55)), IF(VALUE(MID(R55,16,10))<TODAY(),"🟥 Obsoleto", IF(YEAR(VALUE(MID(R55,16,10)))=YEAR(TODAY()),"Actualizaciones disponibles", IF(YEAR(VALUE(MID(R55,16,10)))-YEAR(TODAY())=1,"Actualizaciones disponibles", IF(YEAR(VALUE(MID(R55,16,10)))-YEAR(TODAY())=2,"Actualizaciones disponibles", "Actualizaciones disponibles" ) ) ) ), "⛔ Sin datos" ), "⛔ Error en fecha" ) -> ⛔ Sin datos | T55: =IF(OR(S55 = "🟥 Obsoleto",S55 = "⛔ Sin datos"), "Ya no cuenta con actualizaciones", IFERROR( CONCATENATE( "E" & IFERROR(CHOOSE(MATCH(INDEX(ControlMensual!H:H, MATCH(F55, ControlMensual!B:B, 0)), {"ok";"no";"pendiente"}, 0),"✅","❌","🕓"), "⛔") & " ", "F" & IFERROR(CHOOSE(MATCH(INDEX(ControlMensual!I:I, MATCH(F55, ControlMensual!B:B, 0)), {"ok";"no";"pendiente"}, 0),"✅","❌","🕓"), "⛔") & " ", "M" & IFERROR(CHOOSE(MATCH(INDEX(ControlMensual!J:J, MATCH(F55, ControlMensual!B:B, 0)), {"ok";"no";"pendiente"}, 0),"✅","❌","🕓"), "⛔") & " ", "A" & IFERROR(CHOOSE(MATCH(INDEX(ControlMensual!K:K, MATCH(F55, ControlMensual!B:B, 0)), {"ok";"no";"pendiente"}, 0),"✅","❌","🕓"), "⛔") & " ", "M" & IFERROR(CHOOSE(MATCH(INDEX(ControlMensual!L:L, MATCH(F55, ControlMensual!B:B, 0)), {"ok";"no";"pendiente"}, 0),"✅","❌","🕓"), "⛔") & " ", "J" & IFERROR(CHOOSE(MATCH(INDEX(ControlMensual!M:M, MATCH(F55, ControlMensual!B:B, 0)), {"ok";"no";"pendiente"}, 0),"✅","❌","🕓"), "⛔") & " ", "J" & IFERROR(CHOOSE(MATCH(INDEX(ControlMensual!N:N, MATCH(F55, ControlMensual!B:B, 0)), {"ok";"no";"pendiente"}, 0),"✅","❌","🕓"), "⛔") & " ", "A" & IFERROR(CHOOSE(MATCH(INDEX(ControlMensual!O:O, MATCH(F55, ControlMensual!B:B, 0)), {"ok";"no";"pendiente"}, 0),"✅","❌","🕓"), "⛔") & " ", "S" & IFERROR(CHOOSE(MATCH(INDEX(ControlMensual!P:P, MATCH(F55, ControlMensual!B:B, 0)), {"ok";"no";"pendiente"}, 0),"✅","❌","🕓"), "⛔") & " ", "O" & IFERROR(CHOOSE(MATCH(INDEX(ControlMensual!Q:Q, MATCH(F55, ControlMensual!B:B, 0)), {"ok";"no";"pendiente"}, 0),"✅","❌","🕓"), "⛔") & " ", "N" & IFERROR(CHOOSE(MATCH(INDEX(ControlMensual!R:R, MATCH(F55, ControlMensual!B:B, 0)), {"ok";"no";"pendiente"}, 0),"✅","❌","🕓"), "⛔") & " ", "D" & IFERROR(CHOOSE(MATCH(INDEX(ControlMensual!S:S, MATCH(F55, ControlMensual!B:B, 0)), {"ok";"no";"pendiente"}, 0),"✅","❌","🕓"), "⛔") ) ,"") ) -> Ya no cuenta con actualizaciones | U55: Si | V55: No | W55: No | X55: No | Y55: =COUNTIF(U55:X55,"Si")/(COUNTIF(U55:X55,"Si")+COUNTIF(U55:X55,"No")) -> 0.25 | Z55: Sin Proyecto | AA55: Sin Fecha | AB55: Data | AC55: Sin Asignación | AD55: No | AE55: =VLOOKUP(E55,Falcon!B$2:C$558,2,FALSE) -> #REF! | AF55: =VLOOKUP(E55,VisionOne!B$2:C$229,2,FALSE) -> #REF! | AG55: =VLOOKUP(E55,Central!B$2:C$217,2,FALSE) -> #REF! | AH55: No | AJ55: Nicolas García | AK55: No | AM55: =VLOOKUP(D55,'Copia de vInfo 2'!A:A,1,FALSE) -> #REF!
A56: 1298 | B56: GCP | C56: Google | D56: vm-gateway-sql | E56: vm-gateway-sql | F56: 172.31.2.2 | G56: Producción | H56: Sin Software MDW | I56: ccr-credito-digital-prd | J56: Crédito Digital | K56: Encendido | L56: Virtual | M56: Máquina Virtual Google | N56: No aplica | O56: Linux | P56: Centos 4/5/6/7 | Q56: centos 7 | R56: =verificarVersionOS(Q56) -> #NAME? | S56: =IFERROR( IF(ISNUMBER(FIND("Soporte hasta: ", R56)), IF(VALUE(MID(R56,16,10))<TODAY(),"🟥 Obsoleto", IF(YEAR(VALUE(MID(R56,16,10)))=YEAR(TODAY()),"Actualizaciones disponibles", IF(YEAR(VALUE(MID(R56,16,10)))-YEAR(TODAY())=1,"Actualizaciones disponibles", IF(YEAR(VALUE(MID(R56,16,10)))-YEAR(TODAY())=2,"Actualizaciones disponibles", "Actualizaciones disponibles" ) ) ) ), "⛔ Sin datos" ), "⛔ Error en fecha" ) -> ⛔ Sin datos | U56: Si | V56: No | W56: No | X56: No | Y56: =COUNTIF(U56:X56,"Si")/(COUNTIF(U56:X56,"Si")+COUNTIF(U56:X56,"No")) -> 0.25 | Z56: Sin Proyecto | AA56: Sin Fecha | AB56: Sistemas Financieros | AC56: Sin Asignación | AI56: Patricio Alegría | AJ56: Patricio Alegría | AK56: No
A57: 1299 | B57: GCP | C57: Google | D57: vm-gateway-sql | E57: vm-gateway-sql | F57: 172.31.1.21 | G57: Producción | H57: Sin Software MDW | I57: credito-digital-prd | J57: Crédito Digital | K57: Encendido | L57: Virtual | M57: Máquina Virtual Google | N57: No aplica | O57: Linux | P57: Centos 4/5/6/7 | Q57: centos 7 | R57: =verificarVersionOS(Q57) -> #NAME? | S57: =IFERROR( IF(ISNUMBER(FIND("Soporte hasta: ", R57)), IF(VALUE(MID(R57,16,10))<TODAY(),"🟥 Obsoleto", IF(YEAR(VALUE(MID(R57,16,10)))=YEAR(TODAY()),"Actualizaciones disponibles", IF(YEAR(VALUE(MID(R57,16,10)))-YEAR(TODAY())=1,"Actualizaciones disponibles", IF(YEAR(VALUE(MID(R57,16,10)))-YEAR(TODAY())=2,"Actualizaciones disponibles", "Actualizaciones disponibles" ) ) ) ), "⛔ Sin datos" ), "⛔ Error en fecha" ) -> ⛔ Sin datos | U57: Si | V57: No | W57: No | X57: No | Y57: =COUNTIF(U57:X57,"Si")/(COUNTIF(U57:X57,"Si")+COUNTIF(U57:X57,"No")) -> 0.25 | Z57: Sin Proyecto | AA57: Sin Fecha | AB57: Sistemas Financieros | AC57: Sin Asignación | AJ57: Patricio Alegría | AK57: No | AM57: =VLOOKUP(D57,'Copia de vInfo 2'!A:A,1,FALSE) -> #REF!
A58: 1300 | B58: GCP | C58: Google | D58: vm-gateway-sql | E58: vm-gateway-sql | F58: 172.31.0.3 | G58: QA | H58: Sin Software MDW | I58: credito-digital-qa | J58: Crédito Digital | K58: Encendido | L58: Virtual | M58: Máquina Virtual Google | N58: No aplica | O58: Linux | P58: Centos 4/5/6/7 | Q58: centos 7 | R58: =verificarVersionOS(Q58) -> #NAME? | S58: =IFERROR( IF(ISNUMBER(FIND("Soporte hasta: ", R58)), IF(VALUE(MID(R58,16,10))<TODAY(),"🟥 Obsoleto", IF(YEAR(VALUE(MID(R58,16,10)))=YEAR(TODAY()),"Actualizaciones disponibles", IF(YEAR(VALUE(MID(R58,16,10)))-YEAR(TODAY())=1,"Actualizaciones disponibles", IF(YEAR(VALUE(MID(R58,16,10)))-YEAR(TODAY())=2,"Actualizaciones disponibles", "Actualizaciones disponibles" ) ) ) ), "⛔ Sin datos" ), "⛔ Error en fecha" ) -> ⛔ Sin datos | U58: Si | V58: No | W58: No | X58: No | Y58: =COUNTIF(U58:X58,"Si")/(COUNTIF(U58:X58,"Si")+COUNTIF(U58:X58,"No")) -> 0.25 | Z58: Sin Proyecto | AA58: Sin Fecha | AB58: Sistemas Financieros | AC58: Sin Asignación | AJ58: Patricio Alegría | AK58: No | AM58: =VLOOKUP(D58,'Copia de vInfo 2'!A:A,1,FALSE) -> #REF!
A59: 1301 | B59: GCP | C59: Google | D59: vm-gateway-sql | E59: vm-gateway-sql | F59: 172.18.70.33 | G59: Producción | H59: Sin Software MDW | I59: creditos-prd | J59: Crédito Digital | K59: Encendido | L59: Virtual | M59: Máquina Virtual Google | N59: No aplica | O59: Linux | P59: Centos 4/5/6/7 | Q59: centos 7 | R59: =verificarVersionOS(Q59) -> #NAME? | S59: =IFERROR( IF(ISNUMBER(FIND("Soporte hasta: ", R59)), IF(VALUE(MID(R59,16,10))<TODAY(),"🟥 Obsoleto", IF(YEAR(VALUE(MID(R59,16,10)))=YEAR(TODAY()),"Actualizaciones disponibles", IF(YEAR(VALUE(MID(R59,16,10)))-YEAR(TODAY())=1,"Actualizaciones disponibles", IF(YEAR(VALUE(MID(R59,16,10)))-YEAR(TODAY())=2,"Actualizaciones disponibles", "Actualizaciones disponibles" ) ) ) ), "⛔ Sin datos" ), "⛔ Error en fecha" ) -> ⛔ Sin datos | U59: Si | V59: No | W59: No | X59: No | Y59: =COUNTIF(U59:X59,"Si")/(COUNTIF(U59:X59,"Si")+COUNTIF(U59:X59,"No")) -> 0.25 | Z59: Sin Proyecto | AA59: Sin Fecha | AB59: Sistemas Financieros | AC59: Sin Asignación | AJ59: Patricio Alegría | AK59: No | AM59: =VLOOKUP(D59,'Copia de vInfo 2'!A:A,1,FALSE) -> #REF!

Sheet Sistemas Credito
A1: linea | B1: Integrado con DevSecOps | C1: Automatizable | D1: Sistema / Plataforma / Herramienta | E1: Obsoleto? | F1: Contador | G1: Modulos | H1: Fábrica | I1: Será Decomisado? | J1: Decomisado en | K1: Año Decomiso | L1: Decomisado Q | M1: Estado | N1: Detalle Estado | O1: Detalle nuevo sistema | P1: ¿Tiene Componente Oracle? | Q1: llave | R1: Contador Modulos | S1: Responsable TI | T1: Responsable Negocio | U1: JIRA | V1: Comentario | W1: Descripción | X1: Plataforma | Y1: Servicio de negocio | Z1: Lenguaje programación | AA1: Función | AB1: Dominio Funcional (Capa/Contexto) | AC1: Package/Custom | AD1: Distribución | AE1: Tipo Origen | AF1: Proveedor | AG1: Responsable Mantenimiento | AH1: Ubicación | AI1: Tipo | AJ1: Tecnología Comunicación (MQ, socket, WS) | AK1: Calidad Técnica / Ajuste Técnico (Valor 1 a 5) | AL1: TIME | AM1: Valor de Negocio (Valor de 1 a 5) | AN1: TCO (UF) | AO1: Observación Arquitectura | AP1: Dominio Level 0 | AQ1: Dominio Level 1 | AR1: Dominio Level 2
A2: 10 | B2: No | C2: Parcialmente | D2: Base Preaprobados | E2: Si | F2: =IF(D2=D3,0,1) -> 1 | G2: Base Preaprobados | H2: Financieros | I2: S | J2: 2026 Q3 | K2: 2026 | L2: Q3 | M2: En Proceso | N2: Se mantiene | P2: Si | Q2: =D2&G2 -> Base PreaprobadosBase Preaprobados | R2: =IF(Q2=Q3,0,1) -> 1 | S2: Patricio Alegria | V2: Dorian Patricio Alegria. Mayo se revisará como continua. | X2: Web Service aparece pop up , base de datos con riesgo y genera pre aprobaciones, Web Logic, se ejecuta una vez al mes, la oferta la deja en Siebel (canal) | Y2: Base Preaprobados | AL2: T | AO2: Se mantiene | AP2: Productos | AQ2: Marketing | AR2: Campañas
A3: 18 | B3: Si | C3: Si | D3: Cartola Crédito | E3: No | F3: =IF(D3=D4,0,1) -> 1 | H3: Financieros | I3: N | J3: Sin Decomiso | M3: No será decomisado | N3: Se mantiene | P3: Si | Q3: =D3&G3 -> Cartola Crédito | R3: =IF(Q3=Q4,0,1) -> 1 | S3: Patricio Alegria | U3: Isabelle Bellet | W3: Sistema Automatizado de Generación masiva de Cartolas Credito y envió a Salesforce para notificación a los afiliados por vía email. Dictamen SUSESO | X3: Backend:Proyecto GCP Api Multi-Tenant Namespace: ms-credito Nodo: creditos-pool | Y3: Multi-Tenant | Z3: NJS | AB3: ms-creditos | AC3: Custom | AD3: Cloud GKE | AE3: Interno | AF3: GCP | AG3: CLA | AH3: GCP | AI3: Backend | AL3: T | AP3: Productos | AQ3: Productos Financieros | AR3: Crédito
A4: 27 | B4: No | C4: No | D4: Crédito de Emergencia | E4: Si | F4: =IF(D4=D5,0,1) -> 1 | H4: Financieros | I4: N | J4: Sin Decomiso | M4: No será decomisado | N4: Se mantiene | P4: Si | Q4: =D4&G4 -> Crédito de Emergencia | R4: =IF(Q4=Q5,0,1) -> 1 | S4: Patricio Alegria | AL4: T | AP4: Productos | AQ4: Productos Financieros | AR4: Crédito
A5: 28 | B5: Si | C5: Si | D5: Credito Social Digital CLA Digital | E5: No | F5: =IF(D5=D6,0,1) -> 0 | G5: Credito Canales Remotos | H5: Financieros | I5: S | J5: 2025 Q3 | K5: 2025 | L5: Q3 | M5: Con Plan de Decomiso | N5: Será reemplazado por un existente | O5: Flex | P5: Si | Q5: =D5&G5 -> Credito Social Digital CLA DigitalCredito Canales Remotos | R5: =IF(Q5=Q6,0,1) -> 1 | S5: Patricio Alegria | V5: Argenis Rojas | W5: Obtención de un credito de forma antigua | X5: Desconocido | Y5: Crédito digital | Z5: NJS | AA5: creditodigital | AB5: GPC Cloud Storages | AC5: Custom | AD5: GPC Cloud Storages | AE5: Interno | AF5: GCP | AG5: CLA | AH5: GCP | AI5: Backend | AL5: M | AP5: Productos | AQ5: Productos Financieros | AR5: Crédito
A6: 29 | B6: Si | C6: Si | D6: Credito Social Digital CLA Digital | E6: No | F6: =IF(D6=D7,0,1) -> 1 | G6: Credito Digital Mambu | H6: Financieros | I6: S | J6: 2025 Q4 | K6: 2025 | L6: Q4 | M6: Con Plan de Decomiso | N6: Será reemplazado por un existente | O6: Flex | P6: Si | Q6: =D6&G6 -> Credito Social Digital CLA DigitalCredito Digital Mambu | R6: =IF(Q6=Q7,0,1) -> 1 | S6: Patricio Alegria | W6: Iniciativa de la Filial CLA Digital, obtención de crédito mediante virtualización canal Tapp | X6: Backend:Proyecto GCP Api credito-social-cladigital Namespace: ms-credito-social-cladigital Nodo: node-credito-social-pool | Y6: CLA Digital | Z6: Java | AA6: msdocumentos | AB6: credito social | AC6: Custom | AD6: Cloud GKE | AE6: Interno | AF6: GCP | AG6: CLA | AH6: GCP | AI6: Backend | AL6: M | AP6: Productos | AQ6: Productos Financieros | AR6: Crédito
A7: 49 | B7: No | C7: No | D7: Histórico WCC PF | E7: Si | F7: =IF(D7=D8,0,1) -> 1 | H7: Financieros | I7: N | J7: Sin Decomiso | M7: En Analisis | P7: Si | Q7: =D7&G7 -> Histórico WCC PF | R7: =IF(Q7=Q8,0,1) -> 1 | S7: Patricio Alegria | V7: Dorian Patricio Alegria Patricio Cortez. Definición debería estar en Q3 2025. Junto con migración PF. | W7: Aplicación para la instalación y gestión de documentos históricos. | AH7: On Premise | AL7: M | AO7: Se debe decomisionar y migrar a wcc | AP7: Operaciones | AQ7: Custodia y Documentos | AR7: Gestor Documental
A8: 52 | B8: Si | C8: Si | D8: IFRS9 | E8: No | F8: =IF(D8=D9,0,1) -> 1 | H8: Financieros | I8: N | J8: Sin Decomiso | M8: No será decomisado | N8: Se mantiene | P8: Si | Q8: =D8&G8 -> IFRS9 | R8: =IF(Q8=Q9,0,1) -> 1 | S8: Patricio Alegria | Y8: IFRS | AH8: GCP | AL8: T | AO8: Se mantiene | AP8: Operaciones | AQ8: Servicios de Operación | AR8: Reportes Normativos
A9: 58 | B9: No | C9: No | D9: Línea de Crédito | F9: =IF(D9=D10,0,1) -> 1 | H9: Financieros | I9: S | M9: En Analisis | N9: Será reemplazado por uno nuevo | P9: Si | Q9: =D9&G9 -> Línea de Crédito | R9: =IF(Q9=Q10,0,1) -> 1 | S9: Patricio Alegria | AL9: T | AP9: Productos | AQ9: Productos Financieros | AR9: Crédito
A10: 97 | B10: No | C10: Parcialmente | D10: Motor de Decisión FICO | E10: Si | F10: =IF(D10=D11,0,1) -> 1 | G10: Migración Fico a Cloud + DRP (Motor de Evaluación) | H10: Financieros | I10: N | J10: Sin Decomiso | M10: No será decomisado | N10: Se mantiene | P10: Si | Q10: =D10&G10 -> Motor de Decisión FICOMigración Fico a Cloud + DRP (Motor de Evaluación) | R10: =IF(Q10=Q11,0,1) -> 1 | S10: Patricio Alegria | V10: Patricio Alegría | W10: Migrar la plataforma FICO a la nube OCI junto con realizar el Upgrade a la nueva Versión de la herramienta y mejorar en las integraciones. Esto permitirá a nuestro ejecutivos tener alta disponibilidad del sistema de evaluación y a TI tener una mejor Observabilidad del sistema. | Y10: Motor de Decisión FICO | AH10: On Premise | AL10: I | AO10: Upgrade a new Fico | AP10: Dominio Tecnologico Transversal
A11: 110 | B11: Si | C11: Parcialmente | D11: Pilar Financiero | E11: Si | F11: =IF(D11=D12,0,1) -> 0 | G11: Autoservicio | H11: Financieros | I11: S | J11: 2026 Q3 | K11: 2026 | L11: Q3 | M11: Upgrade | N11: Será reemplazado por un existente | P11: Si | Q11: =D11&G11 -> Pilar FinancieroAutoservicio | R11: =IF(Q11=Q12,0,1) -> 1 | S11: Patricio Alegria | X11: Autoservicio en sucursales | Y11: Pilar Financiero | Z11: Visual Basic | AB11: Canales | AC11: Custom | AD11: OnPremise | AE11: Interno | AF11: CLA | AH11: OCI | AI11: Aplicación | AL11: T | AP11: Productos | AQ11: Productos Financieros | AR11: Crédito
A12: 111 | B12: Si | C12: Parcialmente | D12: Pilar Financiero | E12: Si | F12: =IF(D12=D13,0,1) -> 0 | G12: Crédito Social | H12: Financieros | I12: S | J12: 2026 Q3 | K12: 2026 | L12: Q3 | M12: Upgrade | N12: Será reemplazado por un existente | P12: Si | Q12: =D12&G12 -> Pilar FinancieroCrédito Social | R12: =IF(Q12=Q13,0,1) -> 1 | S12: Patricio Alegria | X12: WCC Repositorio documental | Y12: Pilar Financiero | AH12: OCI | AL12: M | AO12: DEbe ser migrado por PRoyecto New Core | AP12: Productos | AQ12: Productos Financieros | AR12: Crédito
A13: 112 | B13: Si | C13: Parcialmente | D13: Pilar Financiero | E13: Si | F13: =IF(D13=D14,0,1) -> 0 | G13: FlexCube | H13: Financieros | I13: S | J13: 2026 Q3 | K13: 2026 | L13: Q3 | M13: Upgrade | N13: Será reemplazado por un existente | P13: Si | Q13: =D13&G13 -> Pilar FinancieroFlexCube | R13: =IF(Q13=Q14,0,1) -> 1 | S13: Patricio Alegria | X13: Pilar Financiero. Plataforma bancaria | Y13: Pilar Financiero | AB13: Prestaciones Financieras | AC13: Package | AD13: IaaS | AE13: Externo | AF13: Oracle | AG13: Oracle | AH13: OCI | AI13: Aplicación | AL13: M | AO13: Debe ser considerada su migración en proyecto New Core | AP13: Productos | AQ13: Productos Financieros | AR13: Crédito
A14: 113 | B14: Si | C14: Parcialmente | D14: Pilar Financiero | E14: Si | F14: =IF(D14=D15,0,1) -> 0 | G14: Scoring | H14: Financieros | I14: S | J14: 2026 Q3 | K14: 2026 | L14: Q3 | M14: Upgrade | N14: Será reemplazado por un existente | P14: Si | Q14: =D14&G14 -> Pilar FinancieroScoring | R14: =IF(Q14=Q15,0,1) -> 1 | S14: Patricio Alegria | X14: Pilar Financiero. Sistema de evaluación de riesgo?* | Y14: Pilar Financiero | AB14: Prestaciones Financieras | AC14: Package | AD14: IaaS | AE14: Externo | AF14: Oracle | AG14: Oracle | AH14: OCI | AI14: Aplicación | AL14: M | AO14: Se migra en contexto de proyecto de Upgrade FICO Cloud y en contexto de New Core | AP14: Productos | AQ14: Productos Financieros | AR14: Crédito
A15: 114 | B15: Si | C15: Parcialmente | D15: Pilar Financiero | E15: Si | F15: =IF(D15=D16,0,1) -> 0 | G15: Siebel | H15: Financieros | I15: S | J15: 2026 Q3 | K15: 2026 | L15: Q3 | M15: Upgrade | N15: Será reemplazado por un existente | P15: Si | Q15: =D15&G15 -> Pilar FinancieroSiebel | R15: =IF(Q15=Q16,0,1) -> 1 | S15: Patricio Alegria | X15: Pilar Financiero. Solución de gestión de relaciones con clientes (CRM) | Y15: Pilar Financiero | AB15: Prestaciones Financieras | AC15: Package | AD15: IaaS | AE15: Externo | AF15: Oracle | AG15: Oracle | AH15: OCI | AI15: Aplicación | AL15: M | AO15: Se migra a Salesforce | AP15: Productos | AQ15: Productos Financieros | AR15: Crédito
A16: 115 | B16: Si | C16: Parcialmente | D16: Pilar Financiero | E16: Si | F16: =IF(D16=D17,0,1) -> 0 | G16: SOA PF | H16: Financieros | I16: S | J16: 2026 Q3 | K16: 2026 | L16: Q3 | M16: Upgrade | N16: Será reemplazado por un existente | P16: Si | Q16: =D16&G16 -> Pilar FinancieroSOA PF | R16: =IF(Q16=Q17,0,1) -> 1 | S16: Patricio Alegria | X16: Pilar Financiero. Herramienta de integración (Oracle Service Bus) | Y16: Pilar Financiero | AB16: Prestaciones Financieras | AC16: Package | AD16: PaaS | AE16: Externo | AF16: Oracle | AG16: Oracle | AH16: OCI | AI16: Aplicación | AL16: M | AO16: Se debe Decomisar por Integración de Salesforce con Flexcube | AP16: Productos | AQ16: Productos Financieros | AR16: Crédito
A17: 116 | B17: Si | C17: Parcialmente | D17: Pilar Financiero | E17: Si | F17: =IF(D17=D18,0,1) -> 0 | G17: Gestión de Reprogramaciones INIC-413 | H17: Financieros | I17: N | J17: Sin Decomiso | M17: No será decomisado | N17: Se mantiene | P17: Si | Q17: =D17&G17 -> Pilar FinancieroGestión de Reprogramaciones INIC-413 | R17: =IF(Q17=Q18,0,1) -> 1 | S17: Patricio Alegria | W17: Considerando que gran parte del alcance de este viaje será abordado por el Nuevo Core Financiero, se requiere avanzar con un alcance intermedio que permita favorecer el recupero a través de los distintos canales de atención disponibilizando las herramientas necesarias para ofertar, simular y cerrar las condiciones de las Reprogramación acordadas con nuestros clientes, que luego sean inyectadas a nuestro sistemas de crédito para dar continuidad al flujo de aprobación y curse. | X17: Backend:Proyecto GCP Api Multi-Tenant Namespace: ms-creditos-reprogramacion Nodo: creditos-pool | AE17: Interno | AF17: GCP | AG17: CLA | AH17: OCI | AI17: Backend | AL17: M | AO17: Se debe migrar a la Venta de Credito por Salesforce | AP17: Productos | AQ17: Productos Financieros | AR17: Crédito
A18: 117 | B18: Si | C18: Parcialmente | D18: Pilar Financiero | E18: Si | F18: =IF(D18=D19,0,1) -> 0 | G18: Historico WebCenterContent PF | H18: Financieros | I18: N | J18: Sin Decomiso | M18: Upgrade | N18: Será reemplazado por un existente | P18: Si | Q18: =D18&G18 -> Pilar FinancieroHistorico WebCenterContent PF | R18: =IF(Q18=Q19,0,1) -> 1 | S18: Patricio Alegria | Y18: Historico WCC PF | AH18: OCI | AL18: M | AO18: Se debe migrar en contexto de proyecto New Core | AP18: Productos | AQ18: Productos Financieros | AR18: Crédito
A19: 118 | B19: Si | C19: Parcialmente | D19: Pilar Financiero | E19: Si | F19: =IF(D19=D20,0,1) -> 0 | G19: APB (Plan de Bienestar) | H19: Financieros | I19: N | J19: Sin Decomiso | M19: En Analisis | N19: Será reemplazado por un existente | O19: Flex | P19: Si | Q19: =D19&G19 -> Pilar FinancieroAPB (Plan de Bienestar) | R19: =IF(Q19=Q20,0,1) -> 1 | S19: Patricio Alegria | V19: Revisar a que corresponde | X19: APB (Becas de Estudio) | Y19: Pilar Financiero | Z19: Java | AB19: Complementarias | AC19: Custom | AD19: OnPremise | AE19: Interno | AF19: CLA | AH19: OCI | AI19: Aplicación | AL19: M | AO19: Se debe migrar en contexto de proyecto New Core | AP19: Productos | AQ19: Productos Financieros | AR19: Crédito
A20: 119 | B20: Si | C20: Parcialmente | D20: Pilar Financiero | E20: Si | F20: =IF(D20=D21,0,1) -> 1 | G20: DMS | H20: Financieros | I20: N | J20: Sin Decomiso | M20: En Analisis | N20: Será reemplazado por un existente | O20: Flex | P20: Si | Q20: =D20&G20 -> Pilar FinancieroDMS | R20: =IF(Q20=Q21,0,1) -> 1 | S20: Patricio Alegria | W20: DMS o CPC es un proceso que genera un archivo plano desde pilar 2 veces al dia (contiene listsa de creditos) y se transfiere a proveedor "megaarchivo" | X20: Control Documentos Creditos | Y20: Pilar Financiero | Z20: Java | AB20: Prestaciones Financieras | AC20: Custom | AD20: OnPremise | AE20: Interno | AF20: Storbox | AG20: CLA | AH20: OCI | AI20: Aplicación | AL20: M | AO20: Se debe migrar en contexto de proyecto New Core | AP20: Productos | AQ20: Productos Financieros | AR20: Crédito
A21: 122 | B21: No | C21: Si | D21: Portabilidad Financiera | E21: Si | F21: =IF(D21=D22,0,1) -> 1 | G21: Portabilidad Financiera | H21: Financieros | I21: S | J21: 2026 Q3 | K21: 2026 | L21: Q3 | M21: Upgrade | N21: Será reemplazado por uno nuevo | P21: Si | Q21: =D21&G21 -> Portabilidad FinancieraPortabilidad Financiera | R21: =IF(Q21=Q22,0,1) -> 1 | S21: Patricio Alegria | X21: portabilidad-financiera-dev portabilidad-financiera-qa portabilidad-financiera-prd portabilidad-backend-prd portabilidad-backend-dev portabilidad-backend-qa | Y21: Portabilidad Financiera | AH21: On Premise | AL21: T | AP21: Productos | AQ21: Productos Financieros | AR21: Crédito
A22: 156 | B22: No | C22: No | D22: Sinacaf | F22: 1 | G22: Sinacaf | H22: Financieros | I22: S | J22: 2025 Q3 | K22: 2025 | L22: Q4 | M22: En Proceso | N22: Será reemplazado por uno nuevo | P22: Si | R22: 1 | S22: Patricio Alegria | AL22: I | AP22: Productos | AQ22: Productos Financieros | AR22: Crédito

Sheet TIME TOBE Tecnológico
B1: AS IS | W1: TO BE
A2: Correlativo | B2: Sistema / Plataforma | C2: Obsoleto? | D2: Modulos | E2: Fábrica | F2: Será Decomisado? | G2: Decomisado en | H2: Año Decomiso | I2: Decomisado Q | J2: Estado | K2: Responsable TI | L2: Responsable Negocio | M2: Comentario | N2: Descripción | O2: Plataforma | P2: Distribución | Q2: Tipo Origen | R2: Proveedor | S2: Responsable Mantenimiento | T2: Ubicación | U2: Calidad Técnica / Ajuste Técnico (Valor 1 a 5) | V2: Tobe Nuevo | W2: Sistema/Plataforma | X2: Modulos | Y2: TIME T: Tolerar I: Invertir/Potenciar M: Migrar E: Eliminar | Z2: Observación Arquitectura | AA2: Dominio Level 0 | AB2: Dominio Level 1 | AC2: Dominio Level 2
A3: 17 | B3: Cartola Crédito | C3: No | E3: Financieros | F3: N | G3: Sin Decomiso | J3: No será decomisado | K3: Patricio Alegria | N3: Sistema Automatizado de Generación masiva de Cartolas Credito y envió a Salesforce para notificación a los afiliados por vía email. Dictamen SUSESO | O3: Backend:Proyecto GCP Api Multi-Tenant Namespace: ms-credito Nodo: creditos-pool | P3: Cloud GKE | Q3: Interno | R3: GCP | S3: CLA | T3: GCP | W3: Cartola Crédito | Y3: T | AA3: Productos | AB3: Productos Financieros | AC3: Crédito
A4: 23 | B4: Crédito de Emergencia | C4: Si | E4: Financieros | F4: N | G4: Sin Decomiso | J4: No será decomisado | K4: Patricio Alegria | W4: Crédito de Emergencia | Y4: T | AA4: Productos | AB4: Productos Financieros | AC4: Crédito
A5: 24 | B5: Credito Social Digital CLA Digital | C5: No | D5: Credito Canales Remotos | E5: Financieros | F5: S | G5: 2025 Q3 | H5: 2025 | I5: Q3 | J5: Con Plan de Decomiso | K5: Patricio Alegria | M5: Argenis Rojas | N5: Obtención de un credito de forma antigua | O5: Desconocido | P5: GPC Cloud Storages | Q5: Interno | R5: GCP | S5: CLA | T5: GCP | W5: Pilar Financiero | X5: Flexcube 11.3, Siebel | Y5: M | AA5: Productos | AB5: Productos Financieros | AC5: Crédito
A6: 25 | B6: Credito Social Digital CLA Digital | C6: No | D6: Credito Digital Mambu | E6: Financieros | F6: S | G6: 2025 Q4 | H6: 2025 | I6: Q4 | J6: Con Plan de Decomiso | K6: Patricio Alegria | N6: Iniciativa de la Filial CLA Digital, obtención de crédito mediante virtualización canal Tapp | O6: Backend:Proyecto GCP Api credito-social-cladigital Namespace: ms-credito-social-cladigital Nodo: node-credito-social-pool | P6: Cloud GKE | Q6: Interno | R6: GCP | S6: CLA | T6: GCP | W6: Pilar Financiero | X6: Flexcube 11.3, Siebel | Y6: M | AA6: Productos | AB6: Productos Financieros | AC6: Crédito
A7: 33 | B7: Hipotecario | C7: Si | D7: Hipotecario | E7: Automatizaciones | F7: S | G7: 2025 Q4 | H7: 2025 | I7: Q4 | J7: Con Plan de Decomiso | K7: Cristian Cofre | M7: Cristian Cofre - 19-nov-2024: CCofré - En esta línea, no podemos identificar con precisión a qué se refiere, por lo que no debe ser decomizada | N7: Última cuota de un crédito Hipotecario es el 2049 | O7: Hipotecario | P7: OnPremise | Q7: Interno | S7: CLA | T7: On Premise | W7: Hipotecario | X7: Hipotecario | Y7: T | AA7: Productos | AB7: Productos Financieros | AC7: Crédito
A8: 34 | B8: Hipotecario | C8: Si | D8: Mantención de Tasas de Interés | E8: Automatizaciones | F8: S | G8: 2025 Q4 | H8: 2025 | I8: Q4 | J8: Con Plan de Decomiso | K8: Cristian Cofre | M8: Cristian Cofre - 19-nov-2024: CCofré - No sabemos a que se refieren estos desarrollos de ASP - Pero esta funcionalidad no debería estar en uso dada la descripción, ya que esta acción ya no se requere | N8: Última cuota de un crédito Hipotecario es el 2049 | O8: Mantención de Tasas de Interés | P8: OnPremise | Q8: Interno | R8: CLA | S8: CLA | T8: On Premise | W8: Hipotecario | X8: Mantención de Tasas de Interés | Y8: T | AA8: Productos | AB8: Productos Financieros | AC8: Crédito
A9: 35 | B9: Hipotecario | C9: Si | D9: Edición de parámetros y tasas | E9: Automatizaciones | F9: S | G9: 2025 Q4 | H9: 2025 | I9: Q4 | J9: Con Plan de Decomiso | K9: Cristian Cofre | M9: Cristian Cofre - 19-nov-2024: CCofré - No sabemos a que se refieren estos desarrollos de ASP - Pero esta funcionalidad no debería estar en uso dada la descripción, ya que esta acción ya no se requere | N9: Última cuota de un crédito Hipotecario es el 2049 | O9: Edición de parámetros y tasas | P9: OnPremise | Q9: Interno | R9: CLA | S9: CLA | T9: On Premise | W9: Hipotecario | X9: Edición de parámetros y tasas | Y9: T | AA9: Productos | AB9: Productos Financieros | AC9: Crédito
A10: 36 | B10: Hipotecario | C10: Si | D10: Creación de parámetros y tasas | E10: Automatizaciones | F10: S | G10: 2025 Q4 | H10: 2025 | I10: Q4 | J10: Con Plan de Decomiso | K10: Cristian Cofre | M10: Cristian Cofre - 19-nov-2024: CCofré - No sabemos a que se refieren estos desarrollos de ASP - Pero esta funcionalidad no debería estar en uso dada la descripción, ya que esta acción ya no se requere | N10: Última cuota de un crédito Hipotecario es el 2049 | O10: Creación de parámetros y tasas | P10: OnPremise | Q10: Interno | R10: CLA | S10: CLA | T10: On Premise | W10: Hipotecario | X10: Creación de parámetros y tasas | Y10: T | AA10: Productos | AB10: Productos Financieros | AC10: Crédito
A11: 37 | B11: Hipotecario | C11: Si | D11: Prefactibilidad (NUEVO) | E11: Automatizaciones | F11: S | G11: 2025 Q4 | H11: 2025 | I11: Q4 | J11: Con Plan de Decomiso | K11: Cristian Cofre | M11: Cristian Cofre - 19-nov-2024: CCofré - No sabemos a que se refieren estos desarrollos de ASP - Pero esta funcionalidad no debería estar en uso dada la descripción, ya que esta acción ya no se requere | N11: Última cuota de un crédito Hipotecario es el 2049 | O11: Prefactibilidad (NUEVO) | P11: OnPremise | Q11: Interno | R11: CLA | S11: CLA | T11: On Premise | Y11: E | AA11: Productos | AB11: Productos Financieros | AC11: Crédito
A12: 38 | B12: Hipotecario | C12: Si | D12: Prefactibilidad (NUEVO 08-06-2010) | E12: Automatizaciones | F12: S | G12: 2025 Q4 | H12: 2025 | I12: Q4 | J12: Con Plan de Decomiso | K12: Cristian Cofre | M12: Cristian Cofre - 19-nov-2024: CCofré - No sabemos a que se refieren estos desarrollos de ASP - Pero esta funcionalidad no debería estar en uso dada la descripción, ya que esta acción ya no se requere | N12: Última cuota de un crédito Hipotecario es el 2049 | O12: Prefactibilidad (NUEVO 08-06-2010) | P12: OnPremise | Q12: Interno | R12: CLA | S12: CLA | T12: On Premise | Y12: E | AA12: Productos | AB12: Productos Financieros | AC12: Crédito
A13: 39 | B13: Hipotecario | C13: Si | D13: EJECUTIVOS | E13: Automatizaciones | F13: S | G13: 2025 Q4 | H13: 2025 | I13: Q4 | J13: Con Plan de Decomiso | K13: Cristian Cofre | M13: Cristian Cofre | N13: Última cuota de un crédito Hipotecario es el 2049 | O13: EJECUTIVOS | P13: OnPremise | Q13: Interno | R13: CLA | S13: CLA | T13: On Premise | W13: Hipotecario | X13: EJECUTIVOS | Y13: T | AA13: Productos | AB13: Productos Financieros | AC13: Crédito
A14: 40 | B14: Hipotecario | C14: Si | D14: CREDITO HIPOTECARIO | E14: Automatizaciones | F14: S | G14: 2025 Q4 | H14: 2025 | I14: Q4 | J14: Con Plan de Decomiso | K14: Cristian Cofre | M14: Cristian Cofre | N14: Última cuota de un crédito Hipotecario es el 2049 | O14: CREDITO HIPOTECARIO | P14: OnPremise | Q14: Interno | R14: CLA | S14: CLA | T14: On Premise | W14: Hipotecario | X14: CREDITO HIPOTECARIO | Y14: T | AA14: Productos | AB14: Productos Financieros | AC14: Crédito
A15: 41 | B15: Hipotecario | C15: Si | D15: CREDITO HIPOTECARIO | E15: Automatizaciones | F15: S | G15: 2025 Q4 | H15: 2025 | I15: Q4 | J15: Con Plan de Decomiso | K15: Cristian Cofre | M15: Cristian Cofre | N15: Última cuota de un crédito Hipotecario es el 2049 | O15: CREDITO HIPOTECARIO | P15: OnPremise | Q15: Interno | R15: CLA | S15: CLA | T15: On Premise | W15: Hipotecario | X15: CREDITO HIPOTECARIO | Y15: T | AA15: Productos | AB15: Productos Financieros | AC15: Crédito
A16: 45 | B16: IFRS9 | C16: No | E16: Financieros | F16: N | G16: Sin Decomiso | J16: No será decomisado | K16: Patricio Alegria | T16: GCP | W16: IFRS9 | Y16: T | Z16: Se mantiene | AA16: Operaciones | AB16: Servicios de Operación | AC16: Reportes Normativos
A17: 51 | B17: Línea de Crédito | E17: Financieros | F17: S | J17: En Analisis | K17: Patricio Alegria | W17: Línea de Crédito | Y17: T | AA17: Productos | AB17: Productos Financieros | AC17: Crédito
