Workbook

Sheet Iniciativas (2)
A1: INI | B1: Iniciativa | C1: Descripción | D1: Objetivos generales | E1: Orden de magnitud USD | F1: PILAR | G1: Tipo de cliente (flujo) | H1: Ámbito funcional/negocio/gobierno (conceptos) que priorizan el esfuerzo, luego lo técnico se alinea a esto | I1: Beneficios | J1: Detalle actividades | K1: Entregables | L1: Prerrequisitos INI / ALT | M1: Otros Prerrequisitos (no iniciativas) | N1: Prerrequisitos ACTUALIZADOS (ANTIGUO) | O1: Prerrequisitos y dependencia entre iniciativas (ANTIGUO) | P1: Plan de trabajo | Q1: Responsables | R1: Categoría | S1: Etapa del flujo | T1: Dominio | U1: estado PWC | V1: Etapa TO-BE (Imagen) | W1: Etapa Simplificada | X1: Justificación Mapeo | Y1: Pilar Aplicativo Principal | Z1: Pilar Aplicativo Secundario | AA1: Grupo Tecnológico | AB1: Capa de Arquitectura | AC1: Plataforma / Infra | AD1: Componentes Impactados | AE1: Servicios EAI | AF1: Notas Revisión Duplicidad | AG1: Estado Revisión
A2: INI-01 | B2: Pre-evaluación FICO para Cliente Sin Oferta en Campaña | C2: Nodo diferenciado de pre-evaluación con FICO para clientes sin oferta en campaña. Si FICO rechaza → Fin inmediato (ahorra recursos). Si aprueba → pasa a "Nuevo servicio" + Simulación. | D2: Implementar nodo diferenciado de pre-evaluación que filtre tempranamente clientes sin oferta → ahorra ~30-40% de evaluaciones innecesarias | E2: =SUMIF('Por actividad (2)'!A:A,'Iniciativas (2)'!A2,'Por actividad (2)'!N:N) -> 155636.77 | F2: Funcional/Negocio | G2: Cliente sin oferta aprobada | I2: B1: Ahorro de recursos (menos llamadas a servicios/motores posteriores y menos procesamiento) al cortar tempranamente los rechazados por FICO. B2: Mejor control de riesgo al aplicar un filtro estándar y consistente antes de ofertar dinámicamente. B3: Mejora la eficiencia del flujo al separar clientes “viables” vs “no viables” desde el inicio. B4: Mejor experiencia para no elegibles (respuesta rápida) y para elegibles (pasan a oferta + simulación sin pasos innecesarios). B5: Trazabilidad de decisiones (motivos FICO y derivación a siguiente etapa) para monitoreo y auditoría. | J2: A1: Definir el segmento “cliente sin oferta” y condiciones de entrada al nodo (qué casos aplican y cuáles no). A2: Definir reglas de decisión FICO (umbral(es), códigos de rechazo, vigencia, tratamiento de “sin score / error / data insuficiente”). A3: Diseñar el flujo de orquestación: FICO → (rechazo y fin) / (aprobación y derivación a INI-02 + simulación). A4: Implementar integración técnica con FICO (API, seguridad, timeouts, retries) + manejo de contingencias/fallback. A5: Implementar mensajería y motivos para canal (rechazo inmediato vs continúa) y registrar auditoría/logs. A6: Ejecutar pruebas y piloto (funcionales, performance, caída de servicios) y calibrar umbrales si corresponde. | K2: E1: Documento de alcance y requerimientos del nodo de pre-evaluación (incluye criterios “sin oferta”). E2: Diseño del flujo (diagrama del nodo FICO + derivación a INI-02 + simulación). E3: Política/parametría FICO: umbrales, tratamiento de excepciones (“no hit”, error, data incompleta) y motivos. E4: Catálogo de motivos/códigos para fin inmediato y para derivación (mensajes por canal). E5: Especificación de integración/API con FICO (contratos, seguridad, timeouts, reintentos). E6: Implementación del nodo en el orquestador/flujo (configuración por ambiente + feature flags si aplica). E7: Plan y evidencias de pruebas (unitarias, integración, E2E con INI-02, performance/contingencia) + UAT firmado. E8: Monitoreo/KPIs (tasa de rechazo FICO, latencia, errores, derivación a INI-02, ahorro estimado de llamadas) + alertas. E9: Informe de piloto/despliegue con resultados y ajustes recomendados. | L2: INI-02, INI-04, INI-05, INI-07, INI-09, INI-12, INI-18, INI-20 | M2: accesos/conectividad a ambientes FICO, definición de umbrales/reglas y manejo de excepciones por Riesgo (no-hit/error/data insuficiente) y trazabilidad/auditoría | N2: Requiere accesos/conectividad a ambientes FICO, definición de umbrales/reglas y manejo de excepciones por Riesgo (no-hit/error/data insuficiente) y trazabilidad/auditoría; depende de INI-12 y se integra con INI-05 (ruteo “Sin oferta”), INI-02 (si aprueba pasa a oferta dinámica), INI-07 (persistencia/retoma), INI-04 (doc antes de curse) y medición INI-09/INI-09 (ex INI-10). 🔗 DEPENDENCIAS CRUZADAS (Func↔Téc): INI-18 (FICO v7 estable para pre-evaluación); INI-29 (Gobierno E2E técnico); INI-20 (Precálculo oferta viable). | O2: Requiere accesos/conectividad a ambientes FICO, definición de umbrales/reglas y manejo de excepciones por Riesgo (no-hit/error/data insuficiente) y trazabilidad/auditoría; depende de INI-12 y se integra con INI-05 (ruteo “Sin oferta”), INI-02 (si aprueba pasa a oferta dinámica), INI-07 (persistencia/retoma), INI-04 (doc antes de curse) y medición INI-09/INI-09 (ex INI-10). | P2: PENDIENTE EN CASO DE PRIORIZACIÓN | Q2: Ger. Riesgo, Ger. Comercial/Producto, Proveedor FICO/Ventiv, TI Integración/Arquitectura, Sonda (infra/OCI-OKE), Canales (TAPP/SVP), Operaciones | R2: Funcional | S2: Generación de Oferta | T2: 🔴 Riesgo | V2: Generación de Oferta | W2: Generación de Oferta | X2: Pre-evaluación FICO para cliente sin oferta → nodo antes de simulación | Y2: Motor FICO (DMPS/Blaze) | Z2: Base Aprobados, MenuAndes | AA2: Motor de Decisión | AB2: Lógica de Negocio | AC2: OCI Santiago → OCI/OKE | AD2: FICO DMPS, Blaze v4/v7, Orquestador Gateway | AE2: — | AG2: Sin cambios
A3: INI-02 | B3: Nuevo Servicio de Generación de Oferta Dinámica - | C3: Servicio post pre-evaluación que genera oferta dinámica para clientes sin oferta pre-aprobada. Hoy estos clientes van directo al motor o son rechazados. | D3: Diseñar, construir e implementar un servicio post pre-evaluación que genere una oferta dinámica para clientes que no cuentan con oferta pre-aprobada, de modo que en lugar de enviarlos directamente al motor o rechazarlos, se les presente una alternativa de oferta (monto/plazo/tasa/condiciones) acorde a su perfil de riesgo y políticas vigentes, mejorando conversión sin deteriorar el riesgo. | E3: =SUMIF('Por actividad (2)'!A:A,'Iniciativas (2)'!A3,'Por actividad (2)'!N:N) -> 104192.83 | F3: Funcional/Negocio | G3: Cliente sin oferta aprobada | I3: B1: Aumenta la conversión/originación al capturar clientes que hoy quedan sin oferta o rechazados. B2: Mejora la experiencia del cliente al entregar alternativas en vez de un rechazo inmediato. B3: Permite gestionar apetito de riesgo con parámetros (límites, pricing, reglas) ajustables. B4: Reduce derivaciones y fricción operativa (menos re-trabajo y reintentos). B5: Entrega trazabilidad y control (motivos, auditoría, versionado de reglas) para riesgo y compliance. | J3: A1: Levantar flujo actual y definir casos de uso para clientes sin pre-aprobación (ofertar / pedir datos / no ofertar). A2: Definir políticas y reglas de elegibilidad + parámetros de oferta (monto/plazo/tasa/condiciones) y “motivos de no oferta”. A3: Diseñar el modelo de generación de oferta (segmentación por riesgo/score, matriz de oferta, 1 vs N ofertas). A4: Diseñar e implementar el servicio/API e integraciones (pre-evaluación, datos internos/externos, pricing, motor si aplica) + auditoría. A5: Ejecutar pruebas y calibración (funcionales, integración, performance) con histórico/simulación y ajustes de parámetros. A6: Implementar piloto y despliegue gradual por canal/segmento, con monitoreo de KPIs y mejora continua. | K3: E1: Documento de requerimientos y alcance (funcional / no funcional). E2: Diseño de proceso/journey objetivo (sin pre-aprobación → oferta dinámica → siguiente paso). E3: Reglas de elegibilidad + matriz/estrategia de oferta (parámetros por segmento/score) y versionado. E4: Catálogo de motivos/códigos (no oferta, rechazo, derivación) y mensajes para canal. E5: Especificación de API (OpenAPI) + arquitectura e integraciones + lineamientos de auditoría/logging. E6: Implementación del servicio (código + configuración por ambiente / feature flags). E7: Plan y evidencias de pruebas (unitarias, integración, E2E, performance) + UAT firmado. E8: Tablero de monitoreo (conversión, % con oferta, aceptación, latencia/errores, mora temprana si aplica) + alertas. E9: Informe de piloto/despliegue con resultados, ajustes y recomendación de escalamiento. | L3: INI-01, INI-04, INI-07, INI-09, INI-11, INI-12, INI-18, INI-20 | M3: definición de política/matriz de oferta dinámica (monto/plazo/tasa/condiciones), fuentes de datos y catálogo de motivos/auditoría; y normalmente de , se apalanca opcionalmente en , y se integra con , y medición | N3: Requiere definición de política/matriz de oferta dinámica (monto/plazo/tasa/condiciones), fuentes de datos y catálogo de motivos/auditoría; depende de INI-12 y normalmente de INI-01 (gate pre-FICO en “Sin oferta”), se apalanca opcionalmente en INI-11 (parametrización de reglas), y se integra con INI-07, INI-04 y medición INI-09/INI-09 (ex INI-10). 🔗 DEPENDENCIAS CRUZADAS (Func↔Téc): INI-18 (FICO v7 para evaluación); INI-20 (Precálculo como base de oferta). | O3: Requiere definición de política/matriz de oferta dinámica (monto/plazo/tasa/condiciones), fuentes de datos y catálogo de motivos/auditoría; depende de INI-12 y normalmente de INI-01 (gate pre-FICO en “Sin oferta”), se apalanca opcionalmente en INI-11 (parametrización de reglas), y se integra con INI-07, INI-04 y medición INI-09/INI-09 (ex INI-10). | P3: PENDIENTE EN CASO DE PRIORIZACIÓN | Q3: Ger. Comercial/Producto, Ger. Riesgo (políticas/umbrales), TI Arquitectura/Integración, Proveedor FICO/Ventiv (si participa en decisión/scoring), Canales (TAPP/SVP/Sucursal), Data/BI (seguimiento) | R3: Funcional | S3: Generación de Oferta | T3: 🟢 Producto🔴 Riesgo | V3: Generación de Oferta | W3: Generación de Oferta | X3: Oferta dinámica post pre-evaluación → genera oferta viable | Y3: Motor FICO (DMPS/Blaze) | Z3: FlexCube, MenuAndes | AA3: Motor de Decisión | AB3: Lógica de Negocio | AC3: GCP (nuevo servicio) | AD3: Nuevo Servicio Oferta Dinámica, FICO, FlexCube | AE3: — | AG3: Sin cambios
A4: INI-03 | B4: Flujo aprobado express | C4: Camino directo para "Aprobados Express": Paquete oferta → Simulación → (sin evaluación FICO) → Documentación → Curse. Bypass del motor para clientes de buen comportamiento. (2 OPCIONES) | D4: Implementar un camino “Fast Track Express” que permita a clientes identificados como Aprobados Express (por buen comportamiento y criterios definidos) avanzar desde paquete de oferta → simulación → documentación → curse, sin pasar por la evaluación FICO / motor tradicional, manteniendo controles mínimos de riesgo, fraude y cumplimiento para reducir tiempos y fricción sin deteriorar calidad de cartera. | E4: =SUMIF('Por actividad (2)'!A:A,'Iniciativas (2)'!A4,'Por actividad (2)'!N:N) -> 109578.48 | F4: Funcional/Negocio | G4: Cliente oferta aprobada express | I4: B1: Aumenta la conversión al reducir pasos y fricción del proceso estándar. B2: Disminuye el time-to-yes / time-to-cash (aprobación y desembolso más rápidos). B3: Reduce costo operativo (menos validaciones redundantes, menos re-trabajo). B4: Mejora la experiencia y fidelización de clientes de buen comportamiento. B5: Mantiene control y trazabilidad (reglas claras, auditoría, límites y derivación a flujo estándar cuando aplique). | J4: A1: Definir criterios “Aprobado Express” (elegibilidad, exclusiones, vigencia, límites por monto/plazo). A2: Diseñar el flujo Fast Track y puntos de decisión (Express vs derivación a flujo estándar). A3: Acordar e implementar controles mínimos (KYC/AML, identidad, antifraude, políticas internas) para permitir el bypass. A4: Definir e implementar paquete de oferta + simulación (condiciones, vigencia, validaciones de límites). A5: Implementar servicios/APIs e integraciones (canales, data comportamiento, KYC/AML, documental, curse) + manejo de errores/fallback. A6: Ejecutar pruebas y piloto (UAT, performance, seguridad), monitoreo de KPIs y calibración de reglas. | K4: E1: Documento de política Express: criterios, exclusiones, vigencia, límites y gobierno de cambios. E2: Diseño del proceso Fast Track (diagrama de flujo + derivación a estándar + mensajes/motivos). E3: Matriz de controles mínimos (riesgo/fraude/compliance) + “stop conditions”. E4: Definición del paquete de oferta y reglas de simulación (parámetros, vigencia, restricciones). E5: Especificación técnica/API (OpenAPI) + arquitectura e integraciones. E6: Implementación (servicios, configuración de reglas, feature flags). E7: Plan y evidencias de pruebas (unitarias, integración, E2E, performance, seguridad) + UAT firmado. E8: Tablero de monitoreo (KPIs operativos y de riesgo) + alertas. E9: Informe de piloto y versión final calibrada (recomendaciones y parámetros finales). | L4: INI-04, INI-05, INI-07, INI-09, INI-11, INI-12, INI-34 | M4: criterios “Aprobado Express”, límites/exclusiones y controles mínimos KYC/AML/antifraude definidos por Riesgo/Compliance y trazabilidad; y de , se integra con y , se mide con y puede apalancarse en para parametría | N4: Requiere criterios “Aprobado Express”, límites/exclusiones y controles mínimos KYC/AML/antifraude definidos por Riesgo/Compliance y trazabilidad; depende de INI-12 y de INI-05 (clasificación Express), se integra con INI-04 (doc) y INI-07 (retoma), se mide con INI-09/INI-09 (ex INI-10) y puede apalancarse en INI-11 para parametría. 🔗 DEPENDENCIAS CRUZADAS (Func↔Téc): INI-34 (BD Corporativa para datos de cliente express); INI-29 (Gobierno E2E). | O4: Requiere criterios “Aprobado Express”, límites/exclusiones y controles mínimos KYC/AML/antifraude definidos por Riesgo/Compliance y trazabilidad; depende de INI-12 y de INI-05 (clasificación Express), se integra con INI-04 (doc) y INI-07 (retoma), se mide con INI-09/INI-09 (ex INI-10) y puede apalancarse en INI-11 para parametría. | P4: PENDIENTE EN CASO DE PRIORIZACIÓN | Q4: Ger. Riesgo, Ger. Comercial/Producto, Canales Digitales (TAPP/SVP), TI Arquitectura/Integración, Proveedor FICO/Ventiv (para definir bypass/control mínimo), Compliance/Seguridad | R4: Funcional | S4: Simulación → Curse | T4: 🔴 Riesgo🟡 Canal | V4: Evaluación → Documentación (Bypass) | W4: Evaluación (Bypass → Documentación) | X4: Fast Track: Express salta Evaluación FICO, va directo Simulación → Documentación | Y4: Motor FICO (DMPS/Blaze) | Z4: Siebel, TAPP, Base Aprobados | AA4: Motor de Decisión | AB4: Lógica de Negocio + Canal | AC4: OCI + GCP | AD4: Blaze Advisor (bypass rules), Siebel, TAPP BFF | AE4: — | AG4: Sin cambios
A5: INI-04 | B5: Orquestación Documentación Digital - | C5: Etapa explícita de "Generación, firma y Control doc." previa al curse. Hoy la documentación y firma están fuera del proceso de onboarding — el flujo la integra. | D5: Implementar e integrar en el onboarding una etapa explícita y orquestada de “Generación, firma y control documental” previa al curse, incorporando la documentación y firma digital dentro del flujo end-to-end para asegurar completitud, trazabilidad y cumplimiento, reduciendo fricción operativa y reprocesos. | E5: =SUMIF('Por actividad (2)'!A:A,'Iniciativas (2)'!A5,'Por actividad (2)'!N:N) -> 60430.493 | F5: Funcional/Negocio | G5: Transversal (Express + Normal + Sin oferta) | I5: B1: Asegura cumplimiento y control: documentos correctos, firmados y validados antes del curse. B2: Reduce reprocesos y errores (documentación incompleta/faltante) al estandarizar la etapa. B3: Mejora tiempos de cierre/curse al automatizar generación, firma y verificación. B4: Entrega trazabilidad/auditoría end-to-end (qué se generó, quién firmó, cuándo, estado y evidencias). B5: Habilita una experiencia digital y omnicanal consistente (mismo flujo para web/app/sucursal/call center, según aplique). | J5: A1: Levantar el proceso actual y definir el alcance documental por producto/canal (qué documentos, cuándo aplican). A2: Definir la orquestación de estados: generar → enviar → firmar → validar → almacenar → habilitar curse (y qué pasa si falla). A3: Diseñar plantillas y parametría (variables, versiones, idioma, condiciones, anexos) y reglas de selección de documentos. A4: Integrar con servicios de firma digital y gestión documental (repositorio, evidencias, sellado de tiempo si aplica). A5: Implementar controles: completitud, consistencia de datos, validación de identidad/consentimiento, reintentos y vencimientos. A6: Pruebas end-to-end + piloto: generación masiva, firma, trazabilidad, contingencias (firma caída / cliente no firma / expiración). | K5: E1: Documento de alcance y catálogo documental (por producto/canal/segmento) + reglas de aplicabilidad. E2: Diseño del flujo de orquestación (estados, transiciones, errores, SLAs, reintentos, vencimientos). E3: Modelo de datos documental (metadatos, versionado, evidencias, auditoría). E4: Plantillas de documentos parametrizadas + matriz de selección (qué se genera en cada caso). E5: Especificación de integraciones/APIs (firma digital, repositorio documental, onboarding/orquestador, curse). E6: Implementación de la etapa documental (servicios, colas/eventos si aplica, configuración por ambiente). E7: Catálogo de motivos/códigos de estado documental (pendiente firma, rechazado, expirado, validación fallida, etc.). E8: Plan y evidencias de pruebas (funcionales, seguridad, performance, contingencias) + UAT firmado. E9: Tablero de monitoreo/KPIs (tasa de firma, tiempos por etapa, caídas, reprocesos, % curse habilitado) + alertas. | L5: INI-12, INI-21, INI-24 | M5: set documental por producto/canal, proveedor de firma digital, repositorio documental/evidencias y aprobaciones Legal/Compliance; y es transversal como paso previo a curse para rutas que cursan (Express/Normal/Sin oferta) | N5: Requiere set documental por producto/canal, proveedor de firma digital, repositorio documental/evidencias y aprobaciones Legal/Compliance; depende de INI-12 y es transversal como paso previo a curse para rutas que cursan (Express/Normal/Sin oferta). 🔗 DEPENDENCIAS CRUZADAS (Func↔Téc): INI-24 (Camel orquestador para flujo documentación); INI-21 (MS Lógica Crédito reemplaza Svc 147). | O5: Requiere set documental por producto/canal, proveedor de firma digital, repositorio documental/evidencias y aprobaciones Legal/Compliance; depende de INI-12 y es transversal como paso previo a curse para rutas que cursan (Express/Normal/Sin oferta). | P5: PENDIENTE EN CASO DE PRIORIZACIÓN | Q5: Operaciones (BackOffice/Admisión), Legal/Compliance, Proveedor Firma Digital/ECM (si existe), TI Integración/Arquitectura, Canales (TAPP/SVP/Sucursal) | R5: Funcional | S5: Documentación | T5: 🟡 Canal | V5: Documentación | W5: Documentación | X5: Orquestación de generación, firma y control documental | Y5: Siebel / Salesforce | Z5: FlexCube, eSign, BI Publisher | AA5: CRM + Documental | AB5: Proceso de Negocio | AC5: OCI Santiago | AD5: Siebel CRM, FlexCube, eSign, BI Publisher | AE5: — | AG5: Sin cambios
A6: INI-05 | B6: Segmentación de Campaña No Cliente | C6: Punto de decisión inteligente al inicio que clasifica: Express / Normal / Sin oferta / NO OK. Hoy Siebel lo hace parcialmente. En TO-BE debería ser un microservicio. | D6: Diseñar e implementar un microservicio de derivación al inicio del onboarding que clasifique inteligentemente a cada cliente en Express / Normal / Sin oferta / NO OK, sustituyendo o complementando la clasificación parcial actual de Siebel, para enrutar al flujo TO-BE correcto con consistencia, trazabilidad y control (incluyendo criterios de elegibilidad y exclusión). | E6: =SUMIF('Por actividad (2)'!A:A,'Iniciativas (2)'!A6,'Por actividad (2)'!N:N) -> 71089.686 | F6: Funcional/Negocio | G6: Transversal (Express + Normal + Sin oferta + No ok) | I6: B1: Reduce fricción y mejora conversión al enrutar correctamente desde el inicio (menos desvíos y re-trabajo). B2: Aumenta la eficiencia operativa y tecnológica (menos lógica dispersa en canales/Siebel, menor complejidad). B3: Mejora el control de riesgo/compliance con criterios centralizados (incluye “NO OK” temprano). B4: Entrega consistencia omnicanal (misma clasificación para web/app/sucursal/call center). B5: Habilita evolución rápida (reglas parametrizables, versionado, feature flags) sin cambios grandes en canales. B6: Provee trazabilidad/auditoría (por qué fue Express/Normal/Sin oferta/NO OK, con variables y reglas aplicadas). | J6: A1: Definir la taxonomía y criterios de cada tipo: Express / Normal / Sin oferta / NO OK (reglas y exclusiones). A2: Levantar la lógica actual en Siebel y diseñar el TO-BE (qué se migra, qué se elimina, qué queda temporalmente). A3: Diseñar el microservicio: API, entradas/salidas, performance, seguridad, idempotencia y manejo de errores. A4: Definir e integrar fuentes de datos necesarias (CRM/Siebel, comportamiento, KYC/AML, antifraude, ofertas, etc.). A5: Implementar motor de reglas parametrizable + versionado + auditoría (logs, motivos, rule-id). A6: Pruebas + piloto: exactitud de clasificación, latencia, contingencias (data faltante/servicios caídos) y calibración. | K6: E1: Documento de alcance y criterios de clasificación (reglas por tipo, exclusiones, prioridades). E2: Diseño TO-BE de enrutamiento (diagrama end-to-end: punto de decisión → flujos INI-01/02/03/04/normal). E3: Contrato de API del microservicio (OpenAPI) + modelo de datos (request/response). E4: Matriz de fuentes de datos e integraciones (qué se consulta, para qué, SLA/timeout). E5: Catálogo de motivos/códigos de clasificación (Express/Normal/Sin oferta/NO OK) y mensajes por canal. E6: Implementación del microservicio (reglas parametrizables, versionado, feature flags). E7: Plan y evidencias de pruebas (unitarias, integración, performance, resiliencia) + UAT firmado. E8: Tablero de monitoreo/KPIs (distribución por tipo, latencia, errores, derivaciones, precisión vs Siebel) + alertas. E9: Plan de migración desde Siebel (coexistencia, corte, rollback) + reporte de piloto/despliegue. | L6: INI-01, INI-02, INI-03, INI-09, INI-11, INI-12, INI-22 | M6: definición unívoca de tipología Express/Normal/Sin oferta/NO OK, señales de clasificación (incluyendo qué se consulta vía FICO y qué se toma de Siebel en presencial), API con performance y auditoría; se apalanca opcionalmente en , y habilita ruteo hacia y hacia /; su efectividad se mide con | N6: Requiere definición unívoca de tipología Express/Normal/Sin oferta/NO OK, señales de clasificación (incluyendo qué se consulta vía FICO y qué se toma de Siebel en presencial), API con performance y auditoría; depende de INI-12, se apalanca opcionalmente en INI-11, y habilita ruteo hacia INI-03 y hacia INI-01/INI-02; su efectividad se mide con INI-09/INI-09 (ex INI-10). 🔗 DEPENDENCIAS CRUZADAS (Func↔Téc): INI-22 (Apigee para convergencia canales); INI-29 (Gobierno E2E). | O6: Requiere definición unívoca de tipología Express/Normal/Sin oferta/NO OK, señales de clasificación (incluyendo qué se consulta vía FICO y qué se toma de Siebel en presencial), API con performance y auditoría; depende de INI-12, se apalanca opcionalmente en INI-11, y habilita ruteo hacia INI-03 y hacia INI-01/INI-02; su efectividad se mide con INI-09/INI-09 (ex INI-10). | P6: PENDIENTE EN CASO DE PRIORIZACIÓN | Q6: TI Arquitectura/Integración (owner técnico), Ger. Riesgo (reglas de clasificación), Ger. Comercial/Producto, Canales (TAPP/SVP), Equipo Siebel (Sucursal Presencial), Proveedor FICO/Ventiv (si es fuente de señales) | R6: Funcional | S6: Punto de Entrada | T6: 🟣 Cliente🔴 Riesgo | V6: Punto de Entrada | W6: Punto de Entrada | X6: Segmentación campaña No Cliente → define tipo de cliente antes del flujo | Y6: Siebel / Salesforce | Z6: TAPP, Base Aprobados | AA6: CRM + Canal | AB6: Lógica de Negocio | AC6: OCI + GCP | AD6: Siebel (segmentación), TAPP, Base Aprobados | AE6: — | AG6: Sin cambios
A7: INI-06 | B7: Ajuste del Proceso de Derivación de Canales | C7: TAPP opera con modelo binario: aprueba o rechaza. 277.407 solicitudes/mes que en sucursal podrían haberse trabajado se pierden porque el digital no puede derivar a analista. | D7: Habilitar en el canal digital un mecanismo de derivación a gestión humana (analista/sucursal/contact center) para solicitudes que hoy quedan en un modelo binario (aprueba/rechaza), permitiendo rescatar oportunidades y trabajar casos “recuperables” mediante un handoff orquestado, con colas, SLA, trazabilidad y retroalimentación al flujo digital. | E7: =SUMIF('Por actividad (2)'!A:A,'Iniciativas (2)'!A7,'Por actividad (2)'!N:N) -> 62013.453 | F7: Funcional/Negocio | G7: Cliente no ok | I7: B1: Recupera solicitudes perdidas en digital al habilitar tratamiento humano (ej. parte de las 277.407 solicitudes/mes). B2: Incrementa conversión/originación al re-trabajar casos no aprobados automáticamente pero potencialmente viables. B3: Mejora la experiencia del cliente (no termina en rechazo definitivo; se ofrece alternativa/seguimiento). B4: Reduce abandono al dar continuidad (“te contactaremos / agenda / derivación a sucursal”). B5: Aumenta control y trazabilidad (motivos de derivación, tiempos, resultado, auditoría). B6: Permite optimizar reglas del motor digital con aprendizaje (insights sobre qué casos se recuperan). | J7: A1: Definir casos de derivación y criterios (qué se deriva vs qué se rechaza definitivo; motivos y priorización). A2: Diseñar el modelo operativo: quién atiende (analista/call center/sucursal), colas, SLA, horarios, capacidad y escalamiento. A3: Diseñar el handoff digital: captura mínima de datos, consentimiento, agendamiento/contactabilidad, estado visible al cliente. A4: Implementar la gestión de casos (creación de caso/ticket/lead en CRM o herramienta), asignación y trazabilidad end-to-end. A5: Integrar notificaciones y estados: actualizaciones al canal digital (en revisión, solicitado documento, aprobado, rechazado). A6: Piloto y calibración: medir recuperación, tiempos y causas; ajustar reglas de derivación y dotación. | K7: E1: Documento de alcance y reglas de derivación (criterios, exclusiones, motivos/códigos, priorización). E2: Diseño del proceso operativo (colas, SLA, roles, RACI, capacidad, escalamiento). E3: Journey/UX del cliente en digital para derivación (mensajes, consentimiento, agendamiento, tracking de estado). E4: Modelo de caso y datos mínimos (campos, adjuntos, estados, trazabilidad, auditoría). E5: Especificación de integraciones/APIs (digital ↔ CRM/case management ↔ notificaciones ↔ repositorios si aplica). E6: Implementación de creación/asignación de casos + bandeja/cola para analistas (o configuración si es herramienta existente). E7: Catálogo de estados y motivos (derivado, pendiente contacto, requiere docs, aprobado, rechazado) + plantillas de comunicación. E8: Plan y evidencias de pruebas (E2E, SLA, seguridad/PII, contingencias) + UAT firmado. E9: Tablero de KPIs (tasa de derivación, tasa de recuperación, TAT, contactabilidad, conversión, causas) + reporte de piloto. | L7: INI-07, INI-09, INI-12, INI-13, INI-22, INI-27 | M7: modelo operativo de atención humana (roles, colas, SLA, capacidad), herramienta de casos (posiblemente Siebel u otra) y consentimientos/contactabilidad; se apalanca en , se mide con (reconversión) y funciona como fallback junto con | N7: Requiere modelo operativo de atención humana (roles, colas, SLA, capacidad), herramienta de casos (posiblemente Siebel u otra) y consentimientos/contactabilidad; depende de INI-12, se apalanca en INI-07 (handoff con contexto/retoma), se mide con INI-09 (ex INI-10) (reconversión) y funciona como fallback junto con INI-13. 🔗 DEPENDENCIAS CRUZADAS (Func↔Téc): INI-22 (Apigee para derivación entre canales); INI-27 (Observabilidad para medir reconversión). | O7: Requiere modelo operativo de atención humana (roles, colas, SLA, capacidad), herramienta de casos (posiblemente Siebel u otra) y consentimientos/contactabilidad; depende de INI-12, se apalanca en INI-07 (handoff con contexto/retoma), se mide con INI-09 (ex INI-10) (reconversión) y funciona como fallback junto con INI-13. | P7: PENDIENTE EN CASO DE PRIORIZACIÓN | Q7: Operaciones/Admisión (dueño del proceso y SLAs), Canales Digitales (TAPP/SVP), Ger. Sucursal Presencial (si recibe derivaciones), Equipo Siebel/CRM, Ger. Comercial, Data/BI (medición de recuperación) | R7: Funcional | S7: FG-19 | T7: 🟡 Canal📊 Negocio | V7: Evaluación → Simulación (Derivación) | W7: Simulación + Evaluación | X7: FG-19: Derivación a atención humana cuando TAPP rechaza. Aplica en decisión post-evaluación | Y7: TAPP (Canal Digital) | Z7: Siebel, BFF, Kafka | AA7: Canal Digital | AB7: Canal + Proceso | AC7: GCP (GKE) | AD7: TAPP, BFF, Kafka, Siebel (derivación) | AE7: — | AG7: Sin cambios
A8: INI-07 | B8: Retomabilidad Omnicanal (Persistencia de Estado) - digital y presencial | C8: Un cliente que inicia en digital y no completa, hoy reinicia desde cero en sucursal. El flujo requiere que el estado se persista entre Simulación y Evaluación para retomar en otro canal. [PASO 1 — Base Técnica Compartida] Esta iniciativa construye la capa de persistencia de estado que es PRERREQUISITO para INI-15 (Session Recovery ante caída) e INI-16 (Notificación post-caída). El servicio de persistencia que aquí se desarrolla es reutilizado por ambas iniciativas dependientes. | D8: Implementar persistencia de estado y retomabilidad omnicanal para que un cliente que inicia el onboarding en un canal (p. ej. digital) y no completa, pueda retomar el proceso en otro canal (p. ej. sucursal) sin reiniciar desde cero, persistiendo especialmente el estado y datos clave entre Simulación y Evaluación (y, idealmente, hasta Documentación), con trazabilidad, vigencia y controles de seguridad/consentimiento. | E8: =SUMIF('Por actividad (2)'!A:A,'Iniciativas (2)'!A8,'Por actividad (2)'!N:N) -> 78654.709 | F8: Funcional/Negocio | G8: Transversal (Express + Normal + Sin oferta) | I8: B1: Incrementa conversión al reducir abandono por tener que reiniciar el flujo en otro canal. B2: Mejora la experiencia omnicanal (continuidad y consistencia de la solicitud). B3: Reduce tiempos y fricción en sucursal/call center (menos captura repetida). B4: Disminuye errores de data por reingreso manual y mejora calidad de información. B5: Aporta trazabilidad del journey (qué se hizo, dónde se quedó, qué falta). B6: Habilita analítica de funnel real omnicanal (abandono, retomabilidad, cuellos de botella). | J8: A1: Definir el alcance de estado a persistir (datos mínimos, decisiones, oferta simulada, documentos pendientes) y en qué hitos (Simulación/Evaluación/Doc). A2: Definir identificador de continuidad (ID solicitud) y reglas de vinculación cliente-solicitud (login, OTP, documento, etc.). A3: Diseñar la arquitectura de persistencia (store de estado, modelo de datos, APIs de lectura/escritura, versionado). A4: Definir vigencias y caducidades (TTL de simulación/oferta, refresh de datos, re-evaluación si expira). A5: Integrar canales y backends para guardar/recuperar estado (digital, sucursal, CRM/Siebel, orquestador, motor/FICO si aplica). A6: Pruebas end-to-end omnicanal + piloto (casos de retoma, expiración, concurrencia, seguridad). | K8: E1: Documento de alcance funcional de retomabilidad (hitos, casos de uso, qué se persiste y qué no). E2: Modelo de datos de estado (campos, estructura, versionado, evidencias y auditoría). E3: Definición de ID de solicitud y reglas de reconciliación (cómo se “encuentra” la solicitud en otro canal). E4: Especificación de APIs de persistencia/retoma (crear, actualizar, consultar, reanudar, cerrar/cancelar). E5: Política de vigencia/expiración (TTL, revalidaciones, cuándo se fuerza nueva evaluación). E6: Implementación del servicio/store de estado + integraciones con canales y orquestador. E7: Journey omnicanal (mensajes al cliente y al ejecutivo: “solicitud en curso”, “pendiente”, “expirada”). E8: Plan y evidencias de pruebas (E2E omnicanal, concurrencia, seguridad/PII, contingencias) + UAT firmado. E9: Monitoreo/KPIs (tasa de retoma, conversión post-retoma, abandono por etapa, tiempos entre canales) + reporte de piloto. | L8: INI-06, INI-09, INI-12, INI-13, INI-15, INI-25, INI-34 | M8: ID único de solicitud, store de estado seguro (PII), TTL/vigencias y definición de qué se persiste entre Simulación↔Evaluación para TAPP/SVP/Presencial (Siebel); habilita (reconversión), potencia , se complementa con y soporta continuidad en | N8: Requiere ID único de solicitud, store de estado seguro (PII), TTL/vigencias y definición de qué se persiste entre Simulación↔Evaluación para TAPP/SVP/Presencial (Siebel); depende de INI-12, habilita INI-09 (ex INI-10) (reconversión), potencia INI-06 (derivación con contexto), se complementa con INI-15 (recovery fino) y soporta continuidad en INI-13. 🔗 DEPENDENCIAS CRUZADAS (Func↔Téc): INI-25 (Redis caché para persistir estado); INI-34 (BD Corporativa para datos unificados). | O8: Requiere ID único de solicitud, store de estado seguro (PII), TTL/vigencias y definición de qué se persiste entre Simulación↔Evaluación para TAPP/SVP/Presencial (Siebel); depende de INI-12, habilita INI-09 (ex INI-10) (reconversión), potencia INI-06 (derivación con contexto), se complementa con INI-15 (recovery fino) y soporta continuidad en INI-13. | P8: PENDIENTE EN CASO DE PRIORIZACIÓN | Q8: TI Arquitectura/Integración (owner), Canales (TAPP/SVP), Ger. Sucursal Presencial + Equipo Siebel, Seguridad/Ciber (PII/controles), Operaciones, Data/BI | R8: Funcional | S8: FG-19 FG-36 | T8: 🟡 Canal🟣 Cliente | V8: Simulación → Evaluación (Transversal) | W8: Simulación + Evaluación | X8: FG-19/FG-36: Persistencia de estado entre Simulación y Evaluación para retomar en otro canal | Y8: TAPP (Canal Digital) | Z8: Siebel, Redis (caché estado) | AA8: Canal Digital + Integración | AB8: Canal + Datos | AC8: GCP + OCI | AD8: TAPP, Siebel, Redis, MS Estado (nuevo) | AE8: — | AF8: 🟡 PASO 1: Construye la capa base de persistencia de estado. Prerrequisito de INI-15 e INI-16. | AG8: Paso 1 declarado
A9: INI-09 | B9: Seguimiento y Trazabilidad de Data para Información de Negocio | C9: El flujo tiene 5 etapas claras, pero hoy no existen métricas de funnel ni instrumentación para medir abandono, reconversión o conversión por etapa/canal. De 565.297 pre-evaluaciones solo 28.280 se convierten en ventas (5%). No se sabe cuántos clientes abandonan en cada nodo digital ni si retoman en sucursal. Esta iniciativa unifica el seguimiento de data E2E (funnel de conversión + trazabilidad de abandono + reconversión omnicanal) en una sola macro-iniciativa, habilitando la información de negocio necesaria para tomar decisiones basadas en datos. | D9: Diseñar e implementar una plataforma de seguimiento y trazabilidad de data end-to-end que: (1) mida la conversión por etapa del flujo (5 etapas) y por canal (TAPP, SVP, Sucursal Presencial); (2) instrumente el abandono en cada nodo del flujo digital y la reconversión/retoma en Sucursal Presencial; (3) identifique el impacto del 'No' en Simulación y Evaluación (rechazo vs abandono vs caída técnica); (4) habilite visibilidad, gestión del desempeño y acciones de recuperación basadas en datos, mejorando la conversión actual (565.297 pre-evaluaciones → 28.280 ventas = 5%) y la información disponible para negocio. | E9: =SUMIF('Por actividad (2)'!A:A,'Iniciativas (2)'!A9,'Por actividad (2)'!N:N) -> 131116.59 | F9: Funcional/Negocio | G9: Transversal (todos los flujos) | I9: B1: Visibilidad de dónde se cae la conversión (por etapa, canal, producto y motivo). B2: Cuantifica el abandono real por nodo digital (dónde se pierden clientes y en qué magnitud). B3: Mide la reconversión omnicanal: cuántos abandonan digital y terminan vendiendo en sucursal (atribución). B4: Permite entender el impacto del 'No' en Simulación/Evaluación (rechazo vs abandono vs derivación). B5: Permite priorizar iniciativas con impacto real (optimización basada en datos, no percepciones). B6: Habilita acciones de recuperación (contacto, derivación, recordatorios, ofertas alternativas) basadas en triggers. B7: Mejora la gestión operativa con alertas y seguimiento de SLAs (tiempos por etapa, colas, caídas técnicas). B8: Habilita comparabilidad omnicanal (TAPP vs SVP vs Presencial) y detección de brechas de experiencia. B9: Reduce 'caja negra' de decisiones al incorporar motivos/códigos estandarizados. B10: Soporta gobierno y mejora continua (A/B tests, calibración de reglas, seguimiento post-cambios). | J9: A1: Definir el modelo de funnel: etapas estándar, eventos de entrada/salida y transiciones obligatorias (incluye abandonos y rechazos). A2: Definir diccionario de métricas y KPIs (conversión etapa-etapa, tasa de caída, TAT por etapa, tasa de error, % derivación, abandono por nodo). A3: Acordar el identificador único de solicitud y reglas para deduplicación/omnichannel (una solicitud que migra de canal). A4: Definir qué es 'abandono' por nodo digital (timeout, cierre app, drop-off, 'No', error) y el modelo de eventos (start/finish/decision/error) + motivos/códigos. A5: Instrumentar eventos en sistemas/canales (TAPP, SVP, Presencial/orquestador, FICO, documental, curse) con códigos de estado/motivo. A6: Integrar con datos de Sucursal Presencial para detectar retoma/venta posterior y construir atribución omnicanal. A7: Implementar pipeline de datos (ingesta, calidad, reconciliación, dimensiones: canal/etapa/producto/segmento) y almacenamiento. A8: Construir dashboards y alertas (funnel de conversión + abandono por nodo + reconversión); ejecutar piloto de medición, ajustar definiciones y cerrar gobierno de datos. | K9: E1: Definición del funnel TO-BE (5 etapas) con mapa de eventos y transiciones por canal. E2: Definición de abandono por nodo (criterios, ventanas de tiempo, reglas de conteo) y mapa de nodos digitales. E3: Diccionario de métricas/KPIs unificado (funnel + abandono + reconversión: fórmulas, ventanas, segmentaciones, ownership). E4: Definición del ID único de solicitud + reglas de deduplicación y continuidad omnicanal (TAPP/SVP/Presencial). E5: Catálogo estandarizado de estados y motivos por etapa (aprobado/rechazado/abandono/error/pendiente) para analítica. E6: Especificación de tracking/instrumentación (event schema, payload mínimo, fuentes, frecuencia, validaciones de calidad). E7: Implementación del pipeline de datos (ingesta → validación → modelo analítico → dataset de funnel + abandono + reconversión). E8: Dashboards integrados: conversión por etapa/canal, abandono por nodo, reconversión a sucursal, cohortes, tendencias + alertas operativas. E9: Validación de datos (reconciliación vs sistemas fuente, completitud, latencia, consistencia) + evidencias de prueba. E10: Reporte baseline (situación actual: 565.297 → 28.280 + niveles de abandono) y playbook de acciones de recuperación. E11: Plan de seguimiento post-mejoras (gobierno, cadencia, triggers para derivar/contactar). | L9: INI-07, INI-08, INI-12, INI-26, INI-27, INI-28 | M9: definición oficial de las 5 etapas y eventos, instrumentación de TAPP/SVP, data platform/pipeline, estándar de IDs para unir TAPP/SVP/Siebel, definición de abandono y catálogo de motivos (especialmente 'No' en sim/eval), y mecanismo de match con sucursal para reconversión; se apalanca en y es base de análisis para . Absorbe el alcance completo de la anterior | N9: Requiere definición oficial de las 5 etapas y eventos, instrumentación de TAPP/SVP, data platform/pipeline, estándar de IDs para unir TAPP/SVP/Siebel, definición de abandono y catálogo de motivos (especialmente 'No' en sim/eval), y mecanismo de match con sucursal para reconversión; depende de INI-12 (gobierno), se apalanca en INI-07 (omnicanalidad/retoma) y es base de análisis para INI-08. Absorbe el alcance completo de la anterior INI-09 (ex INI-10). 🔗 DEPENDENCIAS CRUZADAS (Func↔Téc): INI-26 (BigQuery para analytics); INI-27 (Observabilidad base); INI-28 (Trazabilidad E2E). | O9: Requiere definición oficial de las 5 etapas y eventos, instrumentación de TAPP/SVP, data platform/pipeline, estándar de IDs para unir TAPP/SVP/Siebel, definición de abandono y catálogo de motivos (especialmente 'No' en sim/eval), y mecanismo de match con sucursal para reconversión; depende de INI-12 (gobierno), se apalanca en INI-07 (omnicanalidad/retoma) y es base de análisis para INI-08. Absorbe el alcance completo de la anterior INI-09 (ex INI-10). | P9: PENDIENTE EN CASO DE PRIORIZACIÓN | Q9: Data/BI / Analytics (owner), TI Data/Plataforma, Canales Digitales (TAPP/SVP), Ger. Sucursal Presencial + Equipo Siebel (match reconversión), TI Integración (eventos/IDs), Operaciones, Ger. Comercial, Ger. Riesgo (para motivos/estados) | R9: Funcional | S9: FG-19 FG-31 | T9: 📊 Negocio | V9: Transversal (todo el flujo) | W9: Transversal | X9: FG-19/FG-31: Trazabilidad de funnel E2E, mide abandono por etapa | Y9: BigQuery / GCP Analytics | Z9: TAPP, Siebel, FICO | AA9: Datos y Analítica | AB9: Datos / BI | AC9: GCP | AD9: BigQuery, Looker/DataStudio, Dashboards | AE9: — | AG9: Sin cambios
A10: INI-11 | B10: Desacople Lógica de Negocio del Motor + Gobierno de Reglas | C10: Reglas de knockout y scoring están embebidas en FICO sin interfaz de negocio. Cambiar una regla toma semanas vía TI. Se necesita capa de parametrización donde Riesgo gestione reglas autónomamente. [Ampliación — Gobierno de Reglas] Definir el modelo de gobierno para la gestión de reglas desacopladas: responsables por tipo de regla (knockout, scoring, oferta), protocolo de solicitud/aprobación/despliegue de cambios, flujo de autorización (quién solicita, quién valida impacto, quién aprueba, quién ejecuta), ventanas de cambio permitidas, y trazabilidad de cada modificación con auditoría. | D10: Implementar una capa de parametrización/gestión de reglas (interfaz de negocio) que desacople las reglas de knockout y scoring hoy embebidas en FICO/motor técnico, permitiendo que Riesgo administre y publique cambios de reglas de forma autónoma, controlada y auditable, reduciendo el time-to-change de semanas a ciclos cortos sin depender de TI para cada ajuste. | E10: =SUMIF('Por actividad (2)'!A:A,'Iniciativas (2)'!A10,'Por actividad (2)'!N:N) -> 93206.278 | F10: Funcional/Negocio | G10: Transversal (Express + Normal + Sin oferta) | I10: B1: Reduce drásticamente el tiempo de cambio de reglas (de semanas a días/horas según gobernanza). B2: Aumenta la agilidad del negocio para ajustar apetito de riesgo, pricing y campañas. B3: Mejora la gobernanza y auditoría (versionado, aprobaciones, trazabilidad de qué regla aplicó). B4: Disminuye riesgo operativo por cambios “hardcodeados” y despliegues frecuentes de TI. B5: Habilita pruebas y simulación de cambios (impacto antes de publicar) y rollback seguro. B6: Facilita consistencia omnicanal al centralizar reglas consumidas por los flujos (INI-01/02/03/05/08). | J10: A1: Levantar reglas actuales en FICO/motor (knockouts, thresholds, segmentos) y definir qué se externaliza a la capa de reglas. A2: Definir el modelo de reglas (tipos de regla, prioridad, condiciones, acciones, motivos/códigos) y requerimientos no funcionales (latencia, disponibilidad). A3: Diseñar la interfaz de negocio: edición, validaciones, workflow de aprobación, versionado, comentarios, publicación por ambiente. A4: Diseñar el runtime: cómo el motor técnico consume reglas (API/config), caching, idempotencia, y compatibilidad con FICO. A5: Implementar simulador/sandbox y controles de despliegue (feature flags, canary, rollback). A6: Piloto: migrar un set acotado de reglas, medir tiempos de cambio, errores, performance y ajustar gobernanza. A7: Definir modelo de gobierno de reglas: asignar responsables por tipo de regla (knockout → Ger. Riesgo, scoring → Ger. Riesgo, oferta → Ger. Producto), definir protocolo de solicitud/aprobación/despliegue de cambios, ventanas de cambio permitidas y mecanismo de auditoría y trazabilidad de cada modificación. | K10: E1: Inventario de reglas actuales + decisión de externalización (qué queda en FICO vs qué pasa a capa negocio). E2: Modelo de reglas y estándar de motivos/códigos (estructura, prioridades, condiciones/acciones). E3: Diseño e implementación de la Interfaz de Reglas (UI) con workflow (creación, revisión, aprobación, publicación). E4: API/Contrato para consumo de reglas por el motor/orquestador (OpenAPI) + estrategia de caching y resiliencia. E5: Versionado y auditoría: trazas por decisión (rule-id, versión, variables usadas), bitácora de cambios y permisos. E6: Sandbox/Simulador de impacto (pruebas con histórico, comparativo antes/después, reportes). E7: Implementación de controles de despliegue (feature flags, canary, rollback) y guía operativa. E8: Plan y evidencias de pruebas (funcionales, seguridad, performance, regresión) + UAT con Riesgo. E9: Gobierno/RACI y manual de operación (roles, permisos, cadencia de cambios, checklist de publicación). | L10: INI-01, INI-12, INI-13, INI-18, INI-23, INI-33 | M10: seleccionar solución de reglas (BRMS/DMN o capa propia), IAM/roles, workflow de aprobación, versionado/auditoría/rollback y sandbox de simulación; y habilita agilidad/parametría para /02/03/05/08 y potencialmente umbrales/validaciones de | N10: Requiere seleccionar solución de reglas (BRMS/DMN o capa propia), IAM/roles, workflow de aprobación, versionado/auditoría/rollback y sandbox de simulación; depende de INI-12 y habilita agilidad/parametría para INI-01/02/03/05/08 y potencialmente umbrales/validaciones de INI-13 (ex INI-17). 🔗 DEPENDENCIAS CRUZADAS (Func↔Téc): INI-18 (FICO v7 para desacoplar); INI-33 (Parametrización reglas + IA); INI-23 (Jobs separados). | O10: Requiere seleccionar solución de reglas (BRMS/DMN o capa propia), IAM/roles, workflow de aprobación, versionado/auditoría/rollback y sandbox de simulación; depende de INI-12 y habilita agilidad/parametría para INI-01/02/03/05/08 y potencialmente umbrales/validaciones de INI-13 (ex INI-17). | P10: PENDIENTE EN CASO DE PRIORIZACIÓN | Q10: Ger. Riesgo (owner funcional de reglas), TI Arquitectura/Integración (owner técnico), Proveedor FICO/Ventiv, Seguridad/Ciber (roles/auditoría), Compliance, Data/BI (simulación/impacto) | R10: Funcional | S10: FG-29 FG-33 | T10: 🔴 Riesgo📊 Negocio | V10: Evaluación | W10: Evaluación | X10: FG-29/FG-33: Desacople reglas del motor FICO → interfaz parametrización | Y10: Motor FICO (DMPS/Blaze) | Z10: Blaze Advisor, OSB | AA10: Motor de Decisión | AB10: Lógica de Negocio | AC10: OCI Santiago / OKE | AD10: Blaze Advisor v7 (120+ reglas), DMPS | AE10: — | AF10: ✅ AMPLIADA: Se agrega gobierno de reglas (responsables, protocolo cambios, flujo autorización, auditoría). Prerrequisito de INI-33. | AG10: Ampliada
A11: INI-12 | B11: Gobierno Integral E2E del Proceso de Crédito (Blueprint + Owner + RACI + Cadencias) | C11: [Componente Funcional — ex INI-12] El flujo To-Be propuesto es el blueprint, pero hoy cada área tiene comprensión parcial y distinta del proceso. Se debe documentar, socializar y mantener como activo vivo con ownership asignado. [Componente Técnico-Operativo — ex INI-29] Designación de owner E2E del proceso de otorgamiento de crédito. Matriz RACI por componente y gerencia. Cadencias formales: daily operativo, semanal táctica, quincenal estratégica. Gobierno incremental en cada TO-BE. | D11: Documentar, socializar y establecer gobierno del Blueprint E2E del flujo de admisión (TO-BE) como un activo vivo, asegurando una comprensión única y alineada entre áreas (Negocio, Riesgo, TI, Operaciones y Canales: TAPP, SVP, Sucursal Presencial), con ownership, versionado y mecanismo de actualización continua. | E11: =SUMIF('Por actividad (2)'!A:A,'Iniciativas (2)'!A11,'Por actividad (2)'!N:N) -> 58565.022 | F11: Gobierno y Personas | G11: Transversal (todos los flujos) | I11: B1: Alineamiento transversal: reduce interpretaciones distintas del proceso y evita retrabajo. B2: Mejora la ejecución de iniciativas (INI-01 a INI-11) al tener una referencia única de flujo, decisiones y dependencias. B3: Facilita gestión del cambio: comunicación y capacitación más rápida y consistente por canal/área. B4: Reduce riesgos operativos y de compliance al clarificar controles, responsables y evidencias por etapa. B5: Habilita mejora continua con versionado: se puede comparar “as-is vs to-be” y medir impacto por release. | J11: A1: Consolidar el flujo TO-BE en un modelo único (E2E) con etapas, decisiones, variantes por tipo de cliente/canal. A2: Documentar RACI/ownership por etapa (quién define, ejecuta, aprueba cambios; puntos de control). A3: Definir estándares de documentación: BPMN, glosario, catálogos (estados/motivos), y definición de interfaces entre áreas/sistemas. A4: Realizar talleres de socialización/validación con stakeholders y cerrar acuerdos (Riesgo, Canales, Ops, TI, Legal/Compliance). A5: Publicar en repositorio corporativo con versionado (control de cambios, releases, calendario de revisiones). A6: Implementar mecanismo de mantenimiento: cadencia de actualización, comité de cambios y “definition of done” documental por iniciativa. A7: Definir cadencias operativas formales: daily operativo, semanal táctico, quincenal estratégico. Establecer Owner E2E del proceso de crédito con autoridad para resolver conflictos entre áreas. A8: Implementar modelo de gobierno incremental: medir madurez baseline (AS-IS) con scoring COBIT y definir metas por cada ciclo TO-BE. | K11: E1: Blueprint E2E (diagrama principal) del flujo de admisión TO-BE con variantes (Express/Normal/Sin oferta/NO OK; TAPP/SVP/Presencial). E2: Paquete de documentación por etapa (Generación de oferta, Simulación, Evaluación, Documentación, Curse): objetivos, entradas/salidas, controles. E3: RACI y ownership (dueño del proceso, dueños por etapa, aprobadores, operación). E4: Glosario y diccionario de términos (etapas, estados, “No”, motivos, IDs, SLA). E5: Mapa de integraciones e interfaces (sistemas involucrados, APIs, datos, SLAs, puntos de fallo). E6: Catálogo estándar de estados/motivos (para operación y analítica: INI-09/10). E7: Materiales de socialización: presentaciones, minutas, FAQs y capacitaciones por área/canal. E8: Repositorio publicado (Confluence/SharePoint/etc.) con control de versiones y plantilla estándar. E9: Modelo de gobierno y cadencia (comité, proceso de cambios, checklist y calendario de revisión). | M11: sponsor, dueños por etapa, repositorio y cadencia de actualización | N11: Requiere sponsor, dueños por etapa, repositorio y cadencia de actualización; no depende de otras INI y actúa como base/gobierno para el resto. 🔗 DEPENDENCIAS CRUZADAS (Func↔Téc): INI-29 (Gobierno E2E técnico — contraparte técnica). | O11: Requiere sponsor, dueños por etapa, repositorio y cadencia de actualización; no depende de otras INI y actúa como base/gobierno para el resto. | P11: PENDIENTE EN CASO DE PRIORIZACIÓN | Q11: PMO / Gestión de Procesos (owner), Ger. Comercial, Ger. Riesgo, Operaciones, TI Arquitectura, Canales (TAPP/SVP/Sucursal), Legal/Compliance | R11: Funcional + Técnica | S11: FG-35 | T11: Gobierno | V11: Transversal (Gobierno) | W11: Transversal | X11: FG-35: Gobierno del proceso E2E, no es una etapa específica | Y11: Gobierno / Proceso (no aplicativo) | Z11: Todos los sistemas | AA11: Gobierno y Operación | AB11: Gobierno | AC11: N/A (organizacional) | AD11: RACI, cadencias, owner E2E | AE11: — | AF11: ✅ FUSIÓN: Absorbe INI-29 (Owner+RACI+Cadencias). Ahora cubre blueprint funcional + modelo operativo gobierno. INI-29 eliminada. | AG11: Fusionada (absorbió INI-29)
A12: INI-13 | B12: Resiliencia Operativa | C12: Hoy si un componente falla (crítico o no) el flujo completo se detiene sin rutas alternativas. No existe clasificación de dependencias por criticidad, ni fallbacks definidos, ni monitoreo proactivo de la salud de componentes clave (como la Base de Aprobados y su batch nocturno). Esta iniciativa aborda: (1) resiliencia funcional con modos degradados y fallbacks por etapa/canal; y (2) sensor de salud de componentes críticos (Base de Aprobados, batch, campañas), para asegurar continuidad parcial controlada del servicio de crédito. | D12: Diseñar e implementar un marco de resiliencia operativa para el proceso de admisión de crédito que: (1) clasifique dependencias por criticidad; (2) defina modos degradados y fallbacks controlados por etapa, canal y tipo de cliente; (3) establezca lineamientos para mantener continuidad operativa ante contingencias, minimizando interrupciones totales; y (4) asegure el mantenimiento de controles de riesgo y compliance durante la operación degradada. | E12: =SUMIF('Por actividad (2)'!A:A,'Iniciativas (2)'!A12,'Por actividad (2)'!N:N) -> 142044.84 | F12: Técnico | G12: Transversal (todos los flujos) | I12: B1: Reduce caídas completas del onboarding cuando falla un componente no crítico (modos degradados). B2: Detección temprana de incidentes en componentes clave (Base de Aprobados, batch, campañas) antes de impacto masivo. B3: Mejora la conversión al evitar pérdidas por indisponibilidad parcial o fallas silenciosas. B4: Aumenta la continuidad operativa (TAPP, SVP, Sucursal) con rutas alternativas controladas. B5: Reduce pérdida de conversión por fallas silenciosas. B6: Reduce impacto en SLA/TAT al permitir avanzar o aparcar casos con reintentos automáticos. B7: Mantiene control y cumplimiento al definir qué fallbacks son permitidos y cuáles requieren derivación humana o stop. B9: Mejora observabilidad y gestión de incidentes. B10: Aumenta confiabilidad de campañas y canal banner al asegurar calidad y disponibilidad de datos. B11: Entrega trazabilidad para análisis de causa raíz. | J12: A1: Clasificar dependencias por criticidad (críticas / no críticas) por etapa. A2: Definir estrategias de fallback por falla: reintento, cola y reproceso, caché/último valor válido, bypass controlado, derivación humana o pausa con retoma. A3: Definir reglas de degradación permitida por tipo de cliente y canal. A4: Definir qué es validación y falla en componentes clave (Base de Aprobados, batch nocturno, campañas). A5: Definir métricas del sensor de salud: % fallas, volumen, frescura del batch, distribución por motivo, umbrales y ventanas de tiempo. A7: Implementar controles técnicos: timeouts, circuit breaker, colas, idempotencia, almacenamiento de estado para retoma. A8: Implementar sensor de salud de componentes críticos. A9: Implementar alertamiento operacional, rutas de escalamiento y runbooks por tipo de falla. A10: Implementar trazabilidad de eventos, motivos y métricas de modo degradado y sensor de salud. A11: Pruebas de resiliencia, simulación de fallas, calibración de umbrales y piloto controlado. | K12: E1: Matriz de dependencias y criticidad por etapa/canal. E2: Catálogo de modos degradados y fallbacks aprobados. E3: Reglas de continuidad vs stop. E4: Especificación del sensor de salud. E5: Definición de reglas de validación y catálogo de fallas/motivos. E7: Diseño técnico de resiliencia. E8: Implementación del motor de monitoreo/sensor. E9: Catálogo de motivos/códigos de fallas y fallback activado. E10: Implementación en orquestador/microservicios/canales. E11: Configuración de alertas y escalamiento + runbooks operativos. E12: Dashboard integrado de salud y resiliencia. E13: Plan y evidencias de pruebas de resiliencia + UAT. E14: Plan de operación. | L12: INI-06, INI-07, INI-09, INI-12, INI-24, INI-27, INI-31 | M12: clasificación de dependencias críticas/no críticas patrones de resiliencia (timeouts / circuit breaker / colas / retry) instrumentación de validación en FICO/Base Aprobados definición de umbrales y ventanas runbooks y aprobación de fallbacks por Riesgo absorbe el alcance del sensor de salud Base Aprobados | N12: Requiere clasificación de dependencias críticas/no críticas, patrones de resiliencia (timeouts/circuit breaker/colas/retry), instrumentación de validación en FICO/Base Aprobados (éxito/falla+motivo), definición de umbrales y ventanas, runbooks y aprobación de fallbacks por Riesgo; depende de INI-12 (gobierno), se apalanca en INI-07 (pausar/retomar), INI-06 (derivación a canales) y se mide con INI-09. Absorbe el alcance completo de la anterior INI-13 (ex INI-17) (sensor de salud Base Aprobados). Los flujos de excepción por deprecación son clave para los ciclos TO-BE 2 y 3 (migración OSB→Camel, Siebel→Salesforce). 🔗 DEPENDENCIAS CRUZADAS (Func↔Téc): INI-24 (Camel con circuit breaker); INI-27 (Observabilidad para detectar fallas); INI-31 (Runbooks técnicos). | O12: Requiere clasificación de dependencias críticas/no críticas, patrones de resiliencia (timeouts/circuit breaker/colas/retry), instrumentación de validación en FICO/Base Aprobados (éxito/falla+motivo), definición de umbrales y ventanas, runbooks y aprobación de fallbacks por Riesgo; depende de INI-12 (gobierno), se apalanca en INI-07 (pausar/retomar), INI-06 (derivación a canales) y se mide con INI-09. Absorbe el alcance completo de la anterior INI-13 (ex INI-17) (sensor de salud Base Aprobados). Los flujos de excepción por deprecación son clave para los ciclos TO-BE 2 y 3 (migración OSB→Camel, Siebel→Salesforce). | P12: PENDIENTE EN CASO DE PRIORIZACIÓN | Q12: TI Arquitectura/Plataforma Operaciones Sonda Canales Proveedor FICO/Ventiv Ger. Riesgo Ger. Comercial Data/BI | R12: Técnica | S12: Transversal | T12: Gobierno📊 Negocio | V12: Transversal (todo el flujo) | W12: Transversal | X12: Resiliencia operativa aplicable a todas las etapas | Y12: Gobierno / Proceso (no aplicativo) | Z12: Todos los sistemas | AA12: Gobierno y Operación | AB12: Gobierno | AC12: N/A (organizacional) | AD12: Resiliencia operativa, continuidad | AE12: — | AF12: 🟢 OK: Nombre confirmado. Delimita QUÉ hacer ante falla (reglas negocio). Complementa INI-30 (proveedores) e INI-31 (runbooks). | AG12: Sin cambios
A13: INI-50 | B13: Flujos de Excepción | C13: Hoy no existe un flujo formal para operar cuando un sistema se depreca, migra o presenta una falla prolongada. Esto dificulta mantener el nivel de servicio y tomar decisiones controladas durante transiciones tecnológicas o contingencias extendidas. Esta iniciativa define flujos de excepción para escenarios de deprecación, migración o falla prolongada de sistemas, estableciendo cómo sostener continuidad parcial, quién activa/desactiva medidas excepcionales y cómo ejecutar rollback o derivación controlada. | D13: Diseñar e implementar flujos de excepción para el proceso de admisión de crédito que: (1) definan cómo operar ante deprecación, migración o falla prolongada de sistemas; (2) establezcan criterios de activación, desactivación, escalamiento y rollback; (3) aseguren continuidad parcial controlada del servicio; y (4) resguarden controles de riesgo, compliance y trazabilidad durante escenarios excepcionales. | E13: =SUMIF('Por actividad (2)'!A:A,'Iniciativas (2)'!A13,'Por actividad (2)'!N:N) -> 0 | F13: Funcional/Negocio | G13: Transversal (todos los flujos) | I13: B4: Aumenta la continuidad operativa con rutas alternativas controladas. B7: Mantiene control y cumplimiento al definir qué excepciones son permitidas y cuáles requieren derivación humana o stop. B8: Habilita plan de transición controlada cuando se depreca o migra un sistema (ej: OSB→Camel, Siebel→Salesforce). B9: Mejora observabilidad y gestión de incidentes al formalizar qué excepción se activó y su impacto. B11: Entrega trazabilidad para análisis posterior y auditoría. | J13: A6: Diseñar flujos de excepción formales para escenarios de deprecación/migración de sistemas: qué pasa durante la transición, cómo se mantiene servicio parcial, quién decide activar/desactivar, rollback. Definir escenarios tipo de excepción: deprecación, migración, caída prolongada, degradación severa. Definir criterios de activación y desactivación. Definir responsables de decisión y escalamiento. Definir alternativas operativas por canal/etapa. Definir criterios de rollback y retorno a operación normal. Definir comunicaciones, trazabilidad y evidencia de activación. Ejecutar pruebas / simulaciones de escenarios excepcionales. | K13: E6: Diseño de flujos de excepción para deprecación/migración de sistemas (procedimiento, criterios activación, rollback, comunicación). Matriz de escenarios excepcionales y respuesta esperada. Protocolo de activación/desactivación. Runbook de operación excepcional. Matriz RACI de decisiones. Evidencias de prueba / simulación. | L13: INI-06, INI-07, INI-09, INI-12, INI-24, INI-27, INI-31 | M13: lineamientos de transición tecnológica definición de responsables de activación aprobación de operación excepcional por Riesgo/Negocio runbooks operativos dependencia con ciclos TO-BE 2 y 3 migración OSB→Camel, Siebel→Salesforce | N13: Requiere clasificación de dependencias críticas/no críticas, patrones de resiliencia (timeouts/circuit breaker/colas/retry), instrumentación de validación en FICO/Base Aprobados (éxito/falla+motivo), definición de umbrales y ventanas, runbooks y aprobación de fallbacks por Riesgo; depende de INI-12 (gobierno), se apalanca en INI-07 (pausar/retomar), INI-06 (derivación a canales) y se mide con INI-09. Absorbe el alcance completo de la anterior INI-13 (ex INI-17) (sensor de salud Base Aprobados). Los flujos de excepción por deprecación son clave para los ciclos TO-BE 2 y 3 (migración OSB→Camel, Siebel→Salesforce). 🔗 DEPENDENCIAS CRUZADAS (Func↔Téc): INI-24 (Camel con circuit breaker); INI-27 (Observabilidad para detectar fallas); INI-31 (Runbooks técnicos). | O13: Requiere clasificación de dependencias críticas/no críticas, patrones de resiliencia (timeouts/circuit breaker/colas/retry), instrumentación de validación en FICO/Base Aprobados (éxito/falla+motivo), definición de umbrales y ventanas, runbooks y aprobación de fallbacks por Riesgo; depende de INI-12 (gobierno), se apalanca en INI-07 (pausar/retomar), INI-06 (derivación a canales) y se mide con INI-09. Absorbe el alcance completo de la anterior INI-13 (ex INI-17) (sensor de salud Base Aprobados). Los flujos de excepción por deprecación son clave para los ciclos TO-BE 2 y 3 (migración OSB→Camel, Siebel→Salesforce). | P13: PENDIENTE EN CASO DE PRIORIZACIÓN | Q13: TI Arquitectura/Plataforma Operaciones Canales Ger. Riesgo Ger. Comercial dueños de sistemas en migración | R13: Funcional | S13: Transversal | T13: Gobierno📊 Negocio | V13: Transversal (todo el flujo) | W13: Transversal | X13: Resiliencia operativa aplicable a todas las etapas | Y13: Gobierno / Proceso (no aplicativo) | Z13: Todos los sistemas | AA13: Gobierno y Operación | AB13: Gobierno | AC13: N/A (organizacional) | AD13: Resiliencia operativa, continuidad | AE13: — | AF13: 🟢 OK: Nombre confirmado. Delimita QUÉ hacer ante falla (reglas negocio). Complementa INI-30 (proveedores) e INI-31 (runbooks). | AG13: Sin cambios
A14: INI-14 | B14: Módulo de Solicitud de Crédito en TAPP (Sin Banner) — | C14: Habilitar un módulo permanente en TAPP para solicitar crédito sin depender del banner de oferta pre-aprobada. Hoy si el cliente no tiene oferta en Base de Aprobados, no puede iniciar el flujo desde la app. Separa el canal banner (Express/Normal) del canal por demanda (Sin oferta → Pre-evaluación FICO). | D14: Habilitar en TAPP un módulo permanente para iniciar una solicitud de crédito sin depender del banner de oferta pre-aprobada, permitiendo que clientes sin oferta en Base de Aprobados también puedan comenzar el flujo desde la app, separando claramente: (i) canal banner (Express/Normal con oferta) y (ii) canal por demanda (Sin oferta → Pre-evaluación FICO → oferta dinámica/siguiente etapa). | E14: =SUMIF('Por actividad (2)'!A:A,'Iniciativas (2)'!A14,'Por actividad (2)'!N:N) -> 59560.538 | F14: Funcional/Negocio | G14: Cliente sin oferta aprobada | I14: B1: Aumenta el acceso al crédito desde TAPP para clientes sin oferta (hoy no pueden iniciar). B2: Incrementa volumen de oportunidades y conversión al habilitar un canal “por demanda” siempre disponible. B3: Reduce dependencia del banner (menos estacionalidad/campañas para originar). B4: Mejora la experiencia: el cliente encuentra una opción clara y estable (“Solicitar crédito”). B5: Permite enrutar correctamente al TO-BE: con oferta → Express/Normal; sin oferta → INI-01 (pre-FICO) y luego INI-02 si aplica. B6: Habilita mejor medición del funnel digital (base para INI-09/10) al instrumentar inicio y abandonos en el módulo. | J14: A1: Definir el alcance UX/UI del módulo (entry point permanente, elegibilidad, copy, consentimientos) y su convivencia con el banner. A2: Diseñar el ruteo TO-BE en TAPP: con oferta → Express/Normal; sin oferta → pre-evaluación FICO; NO OK → mensaje/fin. A3: Definir datos mínimos a capturar en TAPP para iniciar “por demanda” (identificación, contacto, autorización, etc.). A4: Implementar integraciones: microservicio de derivación (INI-05 si aplica), pre-evaluación FICO (INI-01), y continuidad hacia simulación/oferta dinámica. A5: Implementar instrumentación de eventos (inicio, paso de etapa, decisión, abandono, errores) para funnel y abandono (INI-09/10). A6: Pruebas, piloto y despliegue gradual (feature flags, cohortes, monitoreo de conversión y performance). | K14: E1: Diseño UX/UI del módulo permanente en TAPP (wireframes, copy, reglas de visibilidad y navegación). E2: Diseño funcional de ruteo TO-BE en TAPP (con oferta/Express/Normal vs sin oferta/pre-FICO vs NO OK). E3: Requerimientos y modelo de datos mínimos + consentimientos/autorizaciones para iniciar solicitud. E4: Especificación de integraciones/APIs (derivación INI-05, pre-FICO INI-01, INI-02 si corresponde, simulación). E5: Implementación en TAPP (front + back) con feature flags y configuración por ambiente. E6: Esquema de instrumentación (eventos y motivos) alineado a funnel/abandono (INI-09/10). E7: Plan y evidencias de pruebas (funcionales, seguridad, performance, E2E) + UAT. E8: Tablero de monitoreo (uso del módulo, conversión por ruta, abandonos, errores, latencia) + alertas. E9: Reporte de piloto y plan de escalamiento (segmentos, mejoras UX, ajustes de ruteo). | L14: INI-01, INI-02, INI-05, INI-09, INI-12, INI-15, INI-20, INI-22 | M14: UX/UI del módulo permanente en TAPP, consentimientos y ruteo “con oferta vs por demanda”, más integraciones de decisión (vía FICO) y telemetría; y usualmente , se mide con y se recomienda complementar con para evitar pérdida de avance en simulación | N14: Requiere UX/UI del módulo permanente en TAPP, consentimientos y ruteo “con oferta vs por demanda”, más integraciones de decisión (vía FICO) y telemetría; depende de INI-12, INI-05 (derivación), INI-01 (pre-FICO sin oferta) y usualmente INI-02 (oferta dinámica), se mide con INI-09/INI-09 (ex INI-10) y se recomienda complementar con INI-15 para evitar pérdida de avance en simulación. 🔗 DEPENDENCIAS CRUZADAS (Func↔Téc): INI-22 (Apigee como gateway para TAPP); INI-20 (Precálculo de oferta viable). | O14: Requiere UX/UI del módulo permanente en TAPP, consentimientos y ruteo “con oferta vs por demanda”, más integraciones de decisión (vía FICO) y telemetría; depende de INI-12, INI-05 (derivación), INI-01 (pre-FICO sin oferta) y usualmente INI-02 (oferta dinámica), se mide con INI-09/INI-09 (ex INI-10) y se recomienda complementar con INI-15 para evitar pérdida de avance en simulación. | P14: PENDIENTE EN CASO DE PRIORIZACIÓN | Q14: Canales Digitales (TAPP) (owner), Ger. Comercial/Producto, TI Mobile/Integración, Ger. Riesgo (ruteo sin oferta), Proveedor FICO/Ventiv, Data/BI (medición) | R14: Funcional | S14: Punto de Entrada | T14: 🟡 Canal 🟣 Cliente | V14: Punto de Entrada | W14: Punto de Entrada | X14: Módulo solicitud en TAPP sin banner → entrada al flujo | Y14: TAPP (Canal Digital) | Z14: Apigee, BFF | AA14: Canal Digital | AB14: Canal (Frontend) | AC14: GCP (GKE) | AD14: TAPP (React), Apigee | AE14: — | AG14: Sin cambios
A15: INI-15 | B15: Recuperación de Simulación ante Caída (Session Recovery) — | C15: Persistir el estado de la simulación en tiempo real para que, si el sistema cae, el cliente retome exactamente donde quedó al volver el servicio. Hoy se pierde todo el avance y debe reiniciar desde cero. | D15: Implementar persistencia en tiempo real del estado de Simulación (especialmente en TAPP y SVP) para que, ante una caída del sistema/app o pérdida de sesión, el cliente pueda retomar exactamente donde quedó al reingresar, sin reiniciar desde cero, con controles de vigencia, seguridad y trazabilidad. | E15: =SUMIF('Por actividad (2)'!A:A,'Iniciativas (2)'!A15,'Por actividad (2)'!N:N) -> 70748.879 | F15: Técnico | G15: Transversal (Express + Normal + Sin oferta) | I15: B1: Reduce abandono en Simulación al evitar que el cliente pierda el avance por caídas/desconexiones. B2: Mejora la experiencia digital (continuidad “exacta” de la simulación). B3: Aumenta conversión al disminuir fricción en el paso Simulación → Evaluación. B4: Disminuye reprocesos y carga en canales/soporte (menos reclamos y reintentos). B5: Aporta resiliencia funcional (complementa modo degradado / continuidad del flujo). B6: Habilita analítica de estabilidad: identificación de puntos de falla y su impacto en el funnel. | J15: A1: Definir qué significa “retomar exactamente”: datos a persistir (inputs, oferta seleccionada, resultados parciales, pantalla/paso). A2: Definir el modelo de sesión: ID de simulación, vinculación a cliente, multi-dispositivo, concurrencia, y caducidad (TTL). A3: Diseñar e implementar el session store (API guardar/leer), con guardado incremental (autosave) y versionado. A4: Integrar TAPP/SVP para autosave y resume (al abrir: detectar sesión vigente y rehidratar pantalla/estado). A5: Definir manejo de errores y seguridad: cifrado, PII, consentimiento, límites de reintentos, “limpiar sesión” si corresponde. A6: Pruebas de recuperación: caída de app, timeout, caída backend, reconexión, performance y casos límite. | K15: E1: Definición funcional de estado de simulación a persistir + criterios de “resume” (exactitud, caducidad, restricciones). E2: Diseño del modelo de sesión (IDs, TTL, concurrencia, multi-canal si aplica) y reglas de recuperación. E3: Especificación de APIs de Session Recovery (guardar incremental, obtener estado, cerrar/cancelar, expiración). E4: Implementación del Session Store (persistencia, cifrado, auditoría, configuración por ambiente). E5: Implementación en TAPP y SVP (autosave, rehidratación de UI, mensajes al cliente). E6: Catálogo de motivos/estados de recuperación (recuperada, expirada, inconsistente, no encontrada) para analítica. E7: Plan y evidencias de pruebas (E2E, performance, resiliencia, seguridad/PII) + UAT. E8: Monitoreo/KPIs (tasa de recovery, abandono en simulación, errores de resume, latencia de guardado) + alertas. E9: Guía operativa (runbook) y criterios de soporte: cuándo resetear sesión, cómo diagnosticar fallas. | L15: INI-07, INI-09, INI-12, INI-13, INI-16, INI-25 | M15: definir estado exacto de simulación a persistir, session store seguro y performance de autosave, TTL y mecanismo de retoma; y se alinea con , habilita y refuerza continuidad de; su impacto se observa en | N15: Requiere definir estado exacto de simulación a persistir, session store seguro y performance de autosave, TTL y mecanismo de retoma; depende de INI-12 y se alinea con INI-07 (ideal compartir ID/store), habilita INI-16 (notificación post-caída) y refuerza continuidad de INI-13; su impacto se observa en INI-09 (ex INI-10). 🔗 DEPENDENCIAS CRUZADAS (Func↔Téc): INI-25 (Redis como session store). [Dependencia] INI-07 (persistencia de estado) debe estar implementada. INI-15 reutiliza esa capa para el caso de falla de sistema. | O15: Requiere definir estado exacto de simulación a persistir, session store seguro y performance de autosave, TTL y mecanismo de retoma; depende de INI-12 y se alinea con INI-07 (ideal compartir ID/store), habilita INI-16 (notificación post-caída) y refuerza continuidad de INI-13; su impacto se observa en INI-09 (ex INI-10). | P15: PENDIENTE EN CASO DE PRIORIZACIÓN | Q15: Canales Digitales (TAPP/SVP), TI Arquitectura/Integración, TI Mobile, Seguridad/Ciber (PII), Data/BI (impacto en abandono), Operaciones (soporte) | R15: Funcional | S15: Simulación → Curse | T15: 🟡 Canal 🟣 Cliente | V15: Simulación | W15: Simulación | X15: Session recovery: recuperación ante caída durante simulación | Y15: TAPP (Canal Digital) | Z15: BFF, Kafka, FICO | AA15: Canal Digital + Integración | AB15: Canal + Integración | AC15: GCP (GKE) | AD15: TAPP, BFF, Kafka (consumer recovery) | AE15: — | AF15: 🟡 DEPENDENCIA: Requiere INI-07 (persistencia de estado). Reutiliza capa base para recovery ante caída. | AG15: Dependencia agregada
A16: INI-16 | B16: Notificación Proactiva Post-Caída — | C16: Al recuperarse el sistema, notificar automáticamente (push TAPP, email o SMS) a los clientes con solicitudes interrumpidas que ya pueden retomar su proceso, incluyendo acceso directo a la pantalla donde quedaron. | D16: Implementar un mecanismo de notificación proactiva (push en TAPP, email y/o SMS) que, cuando el sistema se recupere tras una caída/incidente, identifique automáticamente a los clientes con solicitudes interrumpidas y les envíe un mensaje para retomar el proceso, incluyendo un acceso directo (deep link) a la pantalla/etapa donde quedaron. | E16: =SUMIF('Por actividad (2)'!A:A,'Iniciativas (2)'!A16,'Por actividad (2)'!N:N) -> 52968.61 | F16: Funcional/Negocio | G16: Transversal (Express + Normal + Sin oferta) | I16: B1: Reduce abandono post-incidente al reactivar clientes que quedaron interrumpidos. B2: Incrementa conversión al facilitar el retorno inmediato con acceso directo al punto exacto del flujo. B3: Mejora la experiencia (comunicación transparente y oportuna; menos frustración). B4: Disminuye carga en soporte/canales (menos consultas “no pude terminar / se cayó”). B5: Aporta resiliencia funcional y continuidad (complementa INI-15 Session Recovery e INI-07 retomabilidad). B6: Habilita medición del impacto de incidentes (tasa de notificados, retoma, conversión post-caída). | J16: A1: Definir qué es “solicitud interrumpida” y reglas de elegibilidad para notificar (etapas, TTL, opt-in, canal disponible). A2: Definir el gatillo de recuperación (cómo se detecta “servicio restablecido”: monitoreo, evento ITSM, health-check) y ventanas de envío. A3: Diseñar el listado de afectados (consulta a store de estado/solicitudes: INI-15/INI-07) y deduplicación por cliente. A4: Diseñar mensajes y journeys: contenido por canal (push/email/SMS), deep link a TAPP/SVP, y manejo de “link expirado”. A5: Implementar orquestación de notificaciones (proveedor push, gateway SMS/email), seguridad y trazabilidad de envíos. A6: Pruebas y piloto: escenarios de caída/recuperación, volumen, reintentos, tasas de entrega y conversión post-notificación. | K16: E1: Definición funcional: criterios de interrupción, elegibilidad, ventanas, opt-in/consentimiento y TTL de retoma. E2: Diseño del mecanismo de gatillo post-recuperación (evento, fuente, gobernanza con TI/Operaciones). E3: Diseño del modelo de selección de afectados (query, deduplicación, priorización por etapa/canal). E4: Plantillas de mensajería (push/email/SMS) + reglas de personalización y copy legal/compliance. E5: Especificación de deep links y experiencia de retoma (pantalla destino, validación, expiración). E6: Implementación del servicio/orquestador de notificaciones + integraciones con proveedores y stores de estado. E7: Catálogo de estados/motivos de notificación (enviada, entregada, rebotada, opt-out, expirada) para analítica. E8: Plan y evidencias de pruebas (E2E, carga, seguridad/PII, contingencias) + UAT. E9: Dashboard de KPIs (tasa de entrega, CTR/deep link, retoma, conversión post-caída) + runbook operativo. | L16: INI-07, INI-09, INI-13, INI-15, INI-27 | M16: canales de notificación (push TAPP/SMS/email), opt-in/compliance, trigger oficial de “servicio recuperado” y deep links; se mide con y complementa | N16: Requiere canales de notificación (push TAPP/SMS/email), opt-in/compliance, trigger oficial de “servicio recuperado” y deep links; depende de INI-15 (y opcionalmente INI-07 si la retoma es por etapa), se mide con INI-09/INI-09 (ex INI-10) y complementa INI-13. 🔗 DEPENDENCIAS CRUZADAS (Func↔Téc): INI-27 (Observabilidad para trigger de recuperación). [Dependencia] INI-07 + INI-15. La notificación proactiva requiere que exista la persistencia de estado (INI-07) y la capacidad de detectar la caída y recovery (INI-15). | O16: Requiere canales de notificación (push TAPP/SMS/email), opt-in/compliance, trigger oficial de “servicio recuperado” y deep links; depende de INI-15 (y opcionalmente INI-07 si la retoma es por etapa), se mide con INI-09/INI-09 (ex INI-10) y complementa INI-13. | P16: PENDIENTE EN CASO DE PRIORIZACIÓN | Q16: Canales Digitales (TAPP/SVP), TI Integración/Arquitectura, Operaciones (gatillo operacional y comunicaciones), Proveedor mensajería (Push/SMS/Email), Seguridad/Compliance (opt-in y contenido) | R16: Funcional | S16: Simulación → Curse | T16: Canal, Cliente | V16: Simulación → Curse | W16: Simulación → Curse | X16: Notificación post-caída aplica a cualquier etapa post-simulación | Y16: TAPP (Canal Digital) | Z16: Kafka, FICO | AA16: Canal Digital | AB16: Canal (UX) | AC16: GCP | AD16: TAPP (notificaciones), Kafka | AE16: — | AF16: 🟡 DEPENDENCIA: Requiere INI-07 + INI-15. Notificación post-recovery. | AG16: Dependencia agregada
A17: INI-18 | B17: Consolidación Motor FICO v7 + Deprecación v4/Nashorn + Paridad y Apagado Definitivo | C17: Estabilización de FICO Blaze Advisor v7 como motor único de decisión. Deprecación completa de Blaze v4 y Nashorn. Incluye migración de reglas remanentes a v7, validación de paridad funcional y apagado definitivo de componentes legacy. [Fusión INI-19] Migración completa de todas las reglas, modelos y configuraciones remanentes de Blaze v4 a v7. Validación de paridad funcional con pruebas A/B en paralelo. Apagado definitivo de la instancia v4 y liberación de infraestructura. | D17: Eliminar la dualidad de motores v4/v7 que genera inestabilidad. Consolidar un motor único con 3 puntos de entrada Blaze (reglas → modelo → oferta). Reducir los 134.446 errores registrados en 5 meses por conflictos de versiones. | E17: =SUMIF('Por actividad (2)'!A:A,'Iniciativas (2)'!A17,'Por actividad (2)'!N:N) -> 64358.744 | F17: Técnico | G17: Transversal (todos los flujos) | I17: B1 🟢 Cuantitativo Reducción de errores FICO Eliminación de errores por dualidad v4/v7 (134.446 errores en 5 meses) B2 🟢 Cuantitativo Simplificación operativa Un solo motor = una sola configuración, un solo monitoreo, un solo equipo B3 🟡 Cualitativo Base para evolución Habilita parametrización (INI-33) e IA sobre motor estable | J17: A1 Inventario de reglas v4 pendientes de migración Levantar todas las reglas, modelos y configuraciones que aún residen en Blaze v4/Nashorn A2 Migración y validación de paridad funcional Migrar cada regla a v7, ejecutar pruebas A/B comparando resultados v4 vs v7 con mismo set de datos A3 Apagado de v4 y Nashorn Plan de deprecación con rollback, fecha de corte, comunicación a equipos A4 Estabilización post-migración Monitoreo reforzado 30 días post-apagado, validación de métricas de error | K17: E1 Inventario de reglas v4 con estado de migración E2 Reporte de pruebas de paridad funcional A/B E3 Plan de deprecación v4 con cronograma y rollback E4 Reporte post-mortem de estabilización | L17: INI-12 | M17: Accesos a ambientes FICO (OCI + OKE) | N17: Accesos a ambientes FICO (OCI + OKE), INI-29 (Gobierno E2E para coordinar migración) 🔗 DEPENDENCIAS CRUZADAS (Téc→Func): INI-12 (Gobierno funcional para coordinar migración v7). | O17: Accesos a ambientes FICO (OCI + OKE), INI-29 (Gobierno E2E para coordinar migración) | P17: PENDIENTE EN CASO DE PRIORIZACIÓN | Q17: Ger. Riesgo (owner funcional), Proveedor FICO/Ventiv (ejecución técnica), Sonda (infra OCI) | R17: Técnica | S17: Generación de Oferta | T17: 🔴 Riesgo | V17: Generación de Oferta + Evaluación | W17: Generación de Oferta + Evaluación | X17: FICO v7 se usa tanto en pre-evaluación (Gen. Oferta) como en Evaluación | Y17: Motor FICO (DMPS/Blaze) | Z17: OSB, FlexCube, Blaze v4→v7 | AA17: Motor de Decisión | AB17: Lógica de Negocio + Infraestructura | AC17: OCI Santiago → OKE | AD17: FICO DMPS, Blaze v4/v7, Nashorn deprecation | AE17: — | AF17: ✅ FUSIÓN: Absorbe INI-19 (Paridad Blaze v7 + Apagado v4). INI-19 eliminada. | AG17: Fusionada (absorbió INI-19)
A18: INI-20 | B18: Servicio de Precálculo de Oferta Viable (GCP) / disponibilizar servicio de oferta aprobados | C18: Nuevo servicio front de precálculo desplegado en GCP que calcula la oferta viable antes de invocar al motor FICO. Incluye 4 Jobs separados por gobierno funcional: Job Cliente (afiliación/MenuAndes), Job Producto (tasas/condiciones), Job Riesgo (scoring/knockout) y Job Cobranza (reprof). | D18: Reducir invocaciones innecesarias al motor FICO filtrando clientes sin viabilidad tempranamente. Separar la responsabilidad funcional de cada Job por gerencia. | E18: =SUMIF('Por actividad (2)'!A:A,'Iniciativas (2)'!A18,'Por actividad (2)'!N:N) -> 45170.404 | F18: Técnico | G18: Transversal (todos los flujos) | I18: B1 🟢 Cuantitativo Reducción de carga FICO ~30-40% menos evaluaciones innecesarias B2 🟢 Cuantitativo Gobierno por gerencia Cada Job tiene owner claro (Cliente, Producto, Riesgo, Cobranza) B3 🟡 Cualitativo Desacople funcional Cada gerencia gestiona su lógica de forma independiente | J18: A1 Diseño del servicio de precálculo Arquitectura GCP, contratos API, lógica de filtrado A2 Desarrollo de 4 Jobs por dominio Job Cliente, Job Producto, Job Riesgo, Job Cobranza A3 Configuración de 3 puntos de entrada Blaze Reglas → Modelo → Oferta A4 Integración con flujo existente Conexión con OSB (TO-BE 1) o Camel (TO-BE 2) A5 Pruebas de carga y validación Simular volúmenes reales con clientes sin oferta | K18: E1 Documento de diseño del servicio de precálculo E2 4 Jobs desarrollados y desplegados en GCP E3 Contratos API documentados E4 Reporte de pruebas de carga | L18: INI-02, INI-05, INI-12, INI-18 | N18: INI-18 (FICO v7 estable), INI-29 (Gobierno E2E), Acceso a GCP 🔗 DEPENDENCIAS CRUZADAS (Téc→Func): INI-02 (Definición funcional de oferta dinámica); INI-05 (Segmentación que define quién recibe precálculo). | O18: INI-18 (FICO v7 estable), INI-29 (Gobierno E2E), Acceso a GCP | P18: PENDIENTE EN CASO DE PRIORIZACIÓN | Q18: Ger. Riesgo, Ger. Producto, Ger. Clientes, Ger. Cobranza, TI Desarrollo | R18: Técnica | S18: Punto de Entrada | T18: 🔴 Riesgo🟡 Canal 🟢 Producto | V18: Punto de Entrada → Generación de Oferta | W18: Punto de Entrada → Generación de Oferta | X18: Precálculo previo a generación de oferta | Y18: GCP Microservicios (nuevo) | Z18: FICO, FlexCube, MenuAndes | AA18: Microservicios GCP | AB18: Lógica de Negocio (nuevo) | AC18: GCP (GKE) | AD18: MS Precálculo (nuevo), FICO, FlexCube, MenuAndes | AE18: — | AF18: 🟢 OK: Separada. Servicio precálculo + arquitectura Jobs. Depende de INI-23 para datos. | AG18: Dependencia agregada
A19: INI-21 | B19: MS Lógica Crédito (Reemplazo Servicio 147)/mejora del servicio 147 | C19: Desarrollo del microservicio MS Lógica Crédito en GCP que reemplaza al Servicio 147 del bus. Incluye la extracción de evalScoring fuera de Siebel y su incorporación como servicio independiente. | D19: Eliminar la dependencia del Servicio 147 (monolítico). Sacar evalScoring de Siebel para desacoplar lógica de scoring del CRM. Permitir evolución independiente de la lógica de crédito. | E19: =SUMIF('Por actividad (2)'!A:A,'Iniciativas (2)'!A19,'Por actividad (2)'!N:N) -> 104147.98 | F19: Técnico | G19: Cliente oferta aprobada normal | I19: B1 🟢 Cuantitativo Eliminación Servicio 147 Componente legacy eliminado del bus B2 🟢 Cuantitativo Desacople evalScoring Logica de scoring independiente del CRM B3 🟡 Cualitativo Evolución independiente MS Lógica Crédito puede escalar y evolucionar sin tocar Siebel | J19: A1 Análisis del Servicio 147 Mapear todas las funciones, dependencias y consumidores del Servicio 147 A2 Diseño del MS Lógica Crédito Arquitectura microservicio GCP, contratos, circuit breaker A3 Extracción de evalScoring de Siebel Desarrollar servicio independiente de scoring A4 Desarrollo y despliegue en GCP Implementación, testing, despliegue A5 Migración de consumidores Redirigir todos los consumidores del Servicio 147 al MS nuevo | K19: E1 Análisis de impacto del Servicio 147 E2 MS Lógica Crédito desplegado en GCP E3 evalScoring como servicio independiente E4 Plan de migración de consumidores | L19: INI-08, INI-13, INI-18, INI-24 | N19: INI-24 (Camel como orquestador), INI-18 (FICO v7 estable) 🔗 DEPENDENCIAS CRUZADAS (Téc→Func): INI-08 (Racionalización journey para definir lógica del MS); INI-13 (Flujos de excepción que el MS debe manejar). | O19: INI-24 (Camel como orquestador), INI-18 (FICO v7 estable) | P19: PENDIENTE EN CASO DE PRIORIZACIÓN | Q19: TI Desarrollo, Ger. Riesgo, Proveedor Siebel | R19: Técnica | S19: Generación de Oferta | T19: 🔴 Riesgo🟡 Canal | V19: Generación de Oferta | W19: Generación de Oferta | X19: MS que reemplaza Servicio 147 (cálculo oferta) | Y19: GCP Microservicios (nuevo) | Z19: OSB (Servicio 147), Siebel | AA19: Microservicios GCP | AB19: Lógica de Negocio (nuevo) | AC19: GCP (GKE) | AD19: MS Lógica Crédito (reemplaza Svc 147), OSB, Siebel | AE19: Servicio 147 (reemplazado) | AG19: Sin cambios
A20: INI-22 | B20: Convergencia de Canales a Apigee (API Gateway) | C20: Convergencia de todos los canales de entrada (presencial/Siebel y digital/TAPP) hacia API Gateway Apigee. Estandarización de contratos de entrada/salida y rate limiting centralizado para proteger al motor FICO. | D20: Unificar la capa de entrada de todos los canales. Implementar rate limiting centralizado. Estandarizar contratos API para facilitar incorporación de nuevos canales. | E20: =SUMIF('Por actividad (2)'!A:A,'Iniciativas (2)'!A20,'Por actividad (2)'!N:N) -> 46174.888 | F20: Técnico | G20: Transversal (todos los flujos) | I20: B1 🟢 Cuantitativo Rate limiting centralizado Protección del motor FICO contra picos de concurrencia (hoy colapsa a 15-17 usuarios) B2 🟡 Cualitativo Estandarización de contratos Todos los canales hablan el mismo idioma B3 🟡 Cualitativo Facilita nuevos canales Cualquier canal nuevo se conecta vía Apigee | J20: A1 Mapeo de canales actuales y contratos Inventario de endpoints, formatos, protocolos por canal A2 Diseño de API Gateway en Apigee Políticas de rate limiting, throttling, seguridad, contratos estándar A3 Migración de canales a Apigee Presencial (Siebel) y Digital (TAPP) convergen a Apigee A4 Pruebas de carga con rate limiting Validar que Apigee protege al motor bajo picos | K20: E1 Diseño de API Gateway con políticas E2 Canales migrados a Apigee E3 Reporte de pruebas de carga | L20: INI-06, INI-12, INI-14 | M20: Acceso a Apigee (GCP) | N20: Acceso a Apigee (GCP), INI-29 (Gobierno E2E) 🔗 DEPENDENCIAS CRUZADAS (Téc→Func): INI-06 (Modelo de derivación de canales); INI-14 (Módulo TAPP sin banner). | O20: Acceso a Apigee (GCP), INI-29 (Gobierno E2E) | P20: PENDIENTE EN CASO DE PRIORIZACIÓN | Q20: TI Arquitectura, TI Desarrollo, Ger. Digital | R20: Técnica | S20: Punto de Entrada | T20: 🟡 Canal | V20: Punto de Entrada | W20: Punto de Entrada | X20: Convergencia canales a Apigee → gateway de entrada | Y20: Apigee (API Gateway) | Z20: TAPP, Siebel, BFF | AA20: Canal Digital + Integración | AB20: Integración (API Gateway) | AC20: GCP | AD20: Apigee (convergencia canales), TAPP, Siebel | AE20: — | AG20: Sin cambios
A21: INI-23 | B21: Desarrollo de Flujos para Jobs + Análisis Servicios Bus | C21: Desarrollo de los flujos de datos que alimentan los 4 Jobs (Cliente, Producto, Riesgo, Cobranza). Análisis detallado de los +25 servicios del bus OSB para planificar la migración a microservicios. [Gobierno de Jobs] Además del desarrollo de flujos de datos, esta iniciativa define los responsables funcionales de cada Job según dominio: Job Cliente → Ger. Clientes, Job Producto → Ger. Producto, Job Riesgo → Ger. Riesgo, Job Cobranza → Ger. Cobranza. Establece quién es owner de la calidad de datos de entrada de cada Job y el protocolo de escalamiento si un Job falla o entrega datos inconsistentes. | D21: Habilitar los flujos de datos para los Jobs del precálculo. Generar inventario completo de servicios del bus con dependencias para migración ordenada a microservicios. | E21: =SUMIF('Por actividad (2)'!A:A,'Iniciativas (2)'!A21,'Por actividad (2)'!N:N) -> 31919.283 | F21: Técnico | G21: Transversal (todos los flujos) | I21: B1 🟢 Cuantitativo Inventario de servicios del bus Mapa completo de +25 servicios con dependencias para migración B2 🟡 Cualitativo Habilitación de Jobs Flujos de datos listos para los 4 Jobs del precálculo | J21: A1 Desarrollo de flujos de datos para cada Job Conexiones a fuentes de datos por dominio A2 Inventario completo de servicios OSB Cada servicio EAI con: función, dependencias, consumidores, volumetría A3 Análisis de migración a microservicios Priorización de servicios para migración, complejidad, riesgo A4 Documentación de contratos actuales Contratos de entrada/salida de cada servicio EAI A5 Definición de responsables funcionales por Job Asignar owner por dominio: Job Cliente → Ger. Clientes, Job Producto → Ger. Producto, Job Riesgo → Ger. Riesgo, Job Cobranza → Ger. Cobranza. | K21: E1 Flujos de datos para 4 Jobs implementados E2 Inventario de servicios OSB documentado E3 Plan de migración priorizado a microservicios | L21: INI-12, INI-20 | N21: INI-20 (Precálculo), INI-29 (Gobierno E2E) 🔗 DEPENDENCIAS CRUZADAS (Téc→Func): INI-12 (Gobierno funcional para definir owners de jobs). | O21: INI-20 (Precálculo), INI-29 (Gobierno E2E) | P21: PENDIENTE EN CASO DE PRIORIZACIÓN | Q21: TI Desarrollo, TI Arquitectura, Ger. Riesgo, Ger. Producto | R21: Técnica | S21: Transversal | T21: 🔴 Riesgo 🟢 Producto🟣 Cliente | V21: Generación de Oferta (Transversal) | W21: Generación de Oferta | X21: Jobs alimentan datos para generación de oferta pero impactan todo el flujo | Y21: Jobs Batch / Control-M | Z21: MenuAndes, FlexCube, Siebel, Base Aprobados | AA21: Batch + Datos Maestros | AB21: Datos (ETL/Batch) | AC21: OCI Santiago (Control-M) | AD21: Jobs EIM, GITU, Control-M, shells FlexCube | AE21: — | AF21: 🟡 DELIMITADA + AMPLIADA: Inventario servicios bus + flujos datos Jobs + gobierno de responsables por Job/dominio. Prerrequisito de INI-24 y INI-20. | AG21: Delimitada + Ampliada
A22: INI-24 | B22: Integracion de orquestador con Circuit Breaker | C22: Implementación de Apache Camel en GCP como nuevo orquestador con circuit breaker nativo. Convive con OSB en TO-BE 2, elimina OSB en TO-BE 3. Incluye catálogo SOA de servicios migrados. [Owner eliminación OSB] Esta iniciativa es responsable de la migración lógica de TODOS los servicios fuera de OSB hacia Camel. Incluye desconexión de los +25 servicios EAI que hoy pasan por el bus. La desconexión es progresiva: TO-BE 2 (convivencia Camel+OSB) → TO-BE 3 (OSB apagado). El decomiso de la infraestructura física (WebLogic, licencias) es responsabilidad de INI-32. | D22: Reemplazar Oracle Service Bus por orquestador open-source sin vendor lock-in. Implementar circuit breaker para evitar cascada de fallos. Habilitar migración progresiva de servicios. | E22: =SUMIF('Por actividad (2)'!A:A,'Iniciativas (2)'!A22,'Por actividad (2)'!N:N) -> 91466.368 | F22: Técnico | G22: Transversal (todos los flujos) | I22: B1 🟢 Cuantitativo Eliminación vendor lock-in Oracle Camel es open-source, portable entre nubes B2 🟢 Cuantitativo Circuit breaker nativo Evita cascada de fallos que hoy degrada todo el sistema B3 🟡 Cualitativo Migración progresiva Convivencia con OSB permite migrar sin big-bang | J22: A1 Diseño de arquitectura Camel en GCP Topología, circuit breaker, retry, dead letter queue A2 Desarrollo de rutas Camel para primeros servicios Migrar servicios prioritarios del bus A3 Configuración de convivencia Camel + OSB Proxy y routing para que ambos coexistan A4 Catálogo SOA de servicios migrados Documentar cada servicio en el catálogo A5 (TO-BE 3) Apagado definitivo de OSB Migración completa y decomisión de OSB | K22: E1 Arquitectura Camel documentada E2 Rutas Camel desplegadas en GCP E3 Configuración de convivencia E4 Catálogo SOA de servicios E5 Acta de decomisión de OSB | L22: ALT-02, INI-12, INI-13, INI-23 | N22: INI-23 (inventario servicios bus), INI-29 (Gobierno E2E), Decisión de ALT-02 (Camel vs OIC vs Workflows) 🔗 DEPENDENCIAS CRUZADAS (Téc→Func): INI-13 (Resiliencia operativa — define qué flujos de excepción). | O22: INI-23 (inventario servicios bus), INI-29 (Gobierno E2E), Decisión de ALT-02 (Camel vs OIC vs Workflows) | P22: PENDIENTE EN CASO DE PRIORIZACIÓN | Q22: TI Arquitectura, TI Desarrollo, Sonda (infra) | R22: Técnica | S22: Transversal | T22: 🔴 Riesgo 🟢 Producto🟣 Cliente 🟡 Canal | V22: Transversal (Infraestructura) | W22: Transversal | X22: Orquestador con circuit breaker aplica a toda la cadena | Y22: Apache Camel (nuevo orquestador) | Z22: OSB (reemplazado), todos los servicios EAI | AA22: Integración / Orquestación | AB22: Integración (Orquestador) | AC22: GCP (nuevo) | AD22: Apache Camel, Circuit Breaker, OSB (apagar) | AE22: 14 servicios EAI migrados a Camel | AF22: 🟡 OWNER OSB: Responsable de migración lógica de servicios fuera de OSB → Camel. Desconexión progresiva +25 servicios. Decomiso infra → INI-32. | AG22: Owner OSB declarado
A23: INI-25 | B23: Caché Redis + Auditoría (Redis → Job → BD Corporativa) | C23: Capa de caché con Redis para reducir invocaciones repetidas al bus. Pipeline de auditoría: Redis → Job → BD Corporativa para registrar toda transacción con fines de auditoría y prevención de fraude. | D23: Reducir latencia y carga sobre servicios EAI mediante caché. Crear trail de auditoría completo E2E. Habilitar detección de fraude con datos en BD Corporativa. | E23: =SUMIF('Por actividad (2)'!A:A,'Iniciativas (2)'!A23,'Por actividad (2)'!N:N) -> 48336.323 | F23: Técnico | G23: Transversal (todos los flujos) | I23: B1 🟢 Cuantitativo Reducción de invocaciones EAI Caché elimina llamadas repetidas al bus (~14 por evaluación) B2 🟢 Cuantitativo Trail de auditoría completo Toda transacción queda registrada B3 🟡 Cualitativo Capacidades anti-fraude Datos centralizados permiten detección de patrones | J23: A1 Diseño de capa de caché Redis Políticas de TTL, invalidación, warm-up A2 Desarrollo de pipeline Redis → Job → BD Corporativa Flujo asíncrono de auditoría A3 Integración con flujo de crédito Caché en puntos de alta invocación A4 Dashboard de auditoría Visualización de transacciones registradas | K23: E1 Capa de caché Redis desplegada E2 Pipeline de auditoría operativo E3 Dashboard de auditoría E4 Documentación de políticas de caché | L23: INI-07, INI-08, INI-24, INI-34 | M23: Acceso a Redis (GCP) | N23: INI-24 (Camel), INI-34 (BD Corporativa), Acceso a Redis (GCP) 🔗 DEPENDENCIAS CRUZADAS (Téc→Func): INI-07 (Retomabilidad — define qué estado persistir); INI-08 (Racionalización — define qué cachear). | O23: INI-24 (Camel), INI-34 (BD Corporativa), Acceso a Redis (GCP) | P23: PENDIENTE EN CASO DE PRIORIZACIÓN | Q23: TI Desarrollo, TI Arquitectura, Ger. Riesgo (fraude) | R23: Técnica | S23: Transversal | T23: 📊 Negocio🔴 Riesgo | V23: Transversal (Infraestructura) | W23: Transversal | X23: Caché Redis + auditoría aplica a todos los servicios | Y23: Redis / GCP Caché | Z23: OSB, FICO, FlexCube | AA23: Integración / Performance | AB23: Datos (Caché) + Auditoría | AC23: GCP | AD23: Redis, BD Corporativa (auditoría/fraude) | AE23: — | AG23: Sin cambios
A24: INI-27 | B24: Observabilidad y Base para Cuadro de Mando Integral | C24: Levantamiento del estado actual de observabilidad de los +25 sistemas. Definición de métricas clave (disponibilidad, latencia, error rate, throughput) por componente. Diseño de la base del cuadro de mando integral E2E. [Delimitación de Scope] Esta iniciativa cubre SOLO el diseño y definición de métricas. La implementación de dashboards y trazas es parte de INI-28. | D24: Obtener visibilidad E2E del proceso de crédito que hoy no existe. Definir baseline de métricas para medir progreso de cada TO-BE. Identificar puntos ciegos en monitoreo actual. | E24: =SUMIF('Por actividad (2)'!A:A,'Iniciativas (2)'!A24,'Por actividad (2)'!N:N) -> 51551.57 | F24: Técnico | G24: Transversal (todos los flujos) | I24: B1 🟢 Cuantitativo Visibilidad E2E Por primera vez se tendrá visión completa del flujo de crédito B2 🟢 Cuantitativo Baseline medible Métricas AS-IS para comparar con cada TO-BE B3 🟡 Cualitativo Detección temprana Alertas antes de que el usuario sienta la degradación | J24: A1 Levantamiento de herramientas de monitoreo actuales Qué se monitorea hoy, con qué herramientas, qué gaps hay A2 Definición de métricas clave por componente KPIs técnicos y de negocio por cada sistema A3 Diseño del cuadro de mando integral Dashboard que integre métricas de todos los componentes A4 Implementación de alertas básicas Reglas de alerta para métricas críticas | K24: E1 Diagnóstico de observabilidad actual E2 Catálogo de métricas clave por componente E3 Diseño del cuadro de mando integral E4 Alertas básicas configuradas | L24: INI-12 | N24: INI-29 (Gobierno E2E para definir qué medir) 🔗 DEPENDENCIAS CRUZADAS (Téc→Func): INI-12 (Gobierno funcional para definir qué medir). | O24: INI-29 (Gobierno E2E para definir qué medir) | P24: PENDIENTE EN CASO DE PRIORIZACIÓN | Q24: TI Operaciones, TI Arquitectura | R24: Técnica | S24: Transversal | T24: 📊 Negocio | V24: Transversal (Observabilidad) | W24: Transversal | X24: Cuadro de mando integral aplica a todo el flujo | Y24: BigQuery / GCP Analytics | Z24: Cloud Monitoring, Looker | AA24: Observabilidad | AB24: Observabilidad / Monitoreo | AC24: GCP | AD24: Cloud Monitoring, Dashboards, alertas | AE24: — | AF24: 🟡 DELIMITADA: Solo diseño y definición de métricas. No incluye implementación de dashboards (→ INI-28). | AG24: Delimitada
A25: INI-28 | B25: Trazabilidad E2E con OpenTelemetry + Dashboards + CMDB | C25: Implementación de OpenTelemetry para trazas distribuidas E2E cubriendo GCP y legacy (OCI/on-premise). Dashboards operativos y de negocio. Actualización de CMDB con inventario real de servicios. | D25: Lograr trazabilidad completa desde solicitud hasta respuesta cruzando todos los componentes. Crear dashboards accionables. Mantener CMDB actualizada. | E25: =SUMIF('Por actividad (2)'!A:A,'Iniciativas (2)'!A25,'Por actividad (2)'!N:N) -> 58941.704 | F25: Técnico | G25: Transversal (todos los flujos) | I25: B1 🟢 Cuantitativo Trazabilidad E2E Cada solicitud se puede rastrear de punta a punta B2 🟢 Cuantitativo CMDB actualizada Inventario real de servicios como fuente de verdad B3 🟡 Cualitativo Diagnóstico rápido Tiempo de resolución de incidentes reducido significativamente | J25: A1 Implementación de OpenTelemetry en componentes GCP Instrumentación de microservicios y Camel A2 Instrumentación de componentes legacy Agentes/exporters para OCI, OSB, Siebel A3 Desarrollo de dashboards operativos y de negocio Grafana/Cloud Monitoring con métricas técnicas y funcionales A4 Actualización de CMDB Inventario completo de servicios, dependencias, owners | K25: E1 OpenTelemetry desplegado en GCP y legacy E2 Dashboards operativos y de negocio E3 CMDB actualizada E4 Documentación de instrumentación | L25: INI-09, INI-24, INI-27 | N25: INI-27 (Observabilidad base), INI-24 (Camel para instrumentar) 🔗 DEPENDENCIAS CRUZADAS (Téc→Func): INI-09 (Define las 5 etapas y eventos a trazar). [Dependencia] INI-27 (diseño métricas y cuadro de mando) debe completarse antes de implementar OpenTelemetry. | O25: INI-27 (Observabilidad base), INI-24 (Camel para instrumentar) | P25: PENDIENTE EN CASO DE PRIORIZACIÓN | Q25: TI Operaciones, TI Desarrollo, TI Arquitectura | R25: Técnica | S25: Transversal | T25: 📊 Negocio | V25: Transversal (Observabilidad) | W25: Transversal | X25: Trazabilidad E2E aplica a todas las etapas | Y25: OpenTelemetry / GCP Observability | Z25: Todos los componentes | AA25: Observabilidad | AB25: Observabilidad / Trazabilidad | AC25: GCP + OCI | AD25: OpenTelemetry, CMDB, trace E2E | AE25: — | AF25: 🟡 DEPENDENCIA: Requiere INI-27 completada. Implementación OpenTelemetry + dashboards + CMDB. | AG25: Dependencia agregada
A26: INI-30 | B26: Fortalecer gestion de Proveedores (FICO, Oracle, Sonda, Experian) | C26: Negociación y formalización de SLAs con proveedores críticos: FICO (motor), Oracle (BD, bus), Sonda (operación), Experian (bureau). Definición de penalties, tiempos de respuesta y escalamiento. | D26: Establecer compromisos contractuales de disponibilidad y tiempos de respuesta. Crear mecanismo formal de escalamiento. Reducir dependencia de proveedores sin gobierno. | E26: =SUMIF('Por actividad (2)'!A:A,'Iniciativas (2)'!A26,'Por actividad (2)'!N:N) -> 33905.83 | F26: Gobierno y Personas | G26: Transversal (todos los flujos) | I26: B1 🟢 Cuantitativo SLAs medibles Compromisos de disponibilidad con penalties contractuales B2 🟡 Cualitativo Escalamiento formal Ruta clara cuando un proveedor incumple | J26: A1 Revisión de contratos actuales Identificar qué SLAs existen y cuáles faltan A2 Definición de métricas de SLA por proveedor Disponibilidad, tiempo de respuesta, tiempo de resolución A3 Negociación con proveedores Nuevos SLAs con penalties y escalamiento A4 Implementación de monitoreo de SLAs Dashboard de cumplimiento de SLAs | K26: E1 Diagnóstico de SLAs actuales E2 Contratos de SLA firmados por proveedor E3 Dashboard de monitoreo de SLAs | L26: INI-12, INI-13 | M26: Área Legal/Contratos | N26: INI-29 (Gobierno E2E), Área Legal/Contratos 🔗 DEPENDENCIAS CRUZADAS (Téc→Func): INI-12 (Gobierno funcional); INI-13 (Resiliencia — define SLAs esperados). | O26: INI-29 (Gobierno E2E), Área Legal/Contratos | P26: PENDIENTE EN CASO DE PRIORIZACIÓN | Q26: Ger. TI, Área Legal, Proveedores | R26: Técnica | S26: Transversal | T26: Gobierno | V26: Transversal (Gobierno) | W26: Transversal | X26: Gestión de proveedores transversal | Y26: Gobierno / Proceso (no aplicativo) | Z26: FICO (proveedor), Oracle, Sonda | AA26: Gobierno y Operación | AB26: Gobierno (proveedores) | AC26: N/A (organizacional) | AD26: SLAs FICO, Oracle, Sonda, Experian | AE26: — | AF26: 🟢 OK: Separada. CON QUIÉN escalar (SLAs proveedores). | AG26: Sin cambios
A27: INI-31 | B27: Fortalecer Runbooks + DRP + Backups de Personas Clave | C27: Documentación de runbooks operativos para cada componente crítico. Plan de recuperación ante desastres (DRP). Formación de backups para personas clave con conocimiento exclusivo (bus factor). | D27: Eliminar dependencia de personas únicas (bus factor). Documentar procedimientos de operación y recuperación. Garantizar continuidad operativa. | E27: =SUMIF('Por actividad (2)'!A:A,'Iniciativas (2)'!A27,'Por actividad (2)'!N:N) -> 13071.749 | F27: Gobierno y Personas | G27: Transversal (todos los flujos) | I27: B1 🟡 Cualitativo Eliminación bus factor Conocimiento documentado, no en cabezas individuales B2 🟡 Cualitativo Continuidad operativa DRP probado para escenarios de falla catastrófica B3 🟢 Cuantitativo Reducción tiempo resolución Runbooks aceleran resolución de incidentes | J27: A1 Identificación de personas clave y conocimiento exclusivo Mapear quién sabe qué y qué pasa si no está A2 Desarrollo de runbooks por componente Procedimientos paso a paso para operación y recuperación A3 Diseño y prueba de DRP Plan de recuperación ante desastres con simulacro A4 Programa de formación de backups Capacitación cruzada para eliminar dependencias | K27: E1 Mapa de personas clave y conocimiento crítico E2 Runbooks por componente E3 DRP documentado y probado E4 Plan de capacitación cruzada | L27: INI-12, INI-13, INI-27 | N27: INI-29 (Gobierno E2E), INI-27 (Observabilidad para alimentar runbooks) 🔗 DEPENDENCIAS CRUZADAS (Téc→Func): INI-13 (Resiliencia operativa — define flujos de excepción a documentar). | O27: INI-29 (Gobierno E2E), INI-27 (Observabilidad para alimentar runbooks) | P27: PENDIENTE EN CASO DE PRIORIZACIÓN | Q27: TI Operaciones, Sonda, RRHH (capacitación) | R27: Técnica | S27: Transversal | T27: Gobierno | V27: Transversal (Gobierno) | W27: Transversal | X27: Runbooks, DRP, backup personas clave | Y27: Gobierno / Proceso (no aplicativo) | Z27: Todos los sistemas | AA27: Gobierno y Operación | AB27: Gobierno (contingencia) | AC27: N/A (organizacional) | AD27: Runbooks, DRP, backups personas clave | AE27: — | AF27: 🟢 OK: Separada. CÓMO hacerlo (runbooks + DRP + backups personas). | AG27: Sin cambios
A28: INI-32 | B28: Modernización Tecnológica (Oracle, WebLogic, Java) + Decomiso Infraestructura Legacy | C28: Actualización de componentes obsoletos: Oracle 12 → versión soportada, WebLogic → containerizado, Java 8 → versión LTS. Migración de servicios legacy a stack moderno en GCP. [Delimitación OSB — Post análisis duplicidad] La migración lógica de servicios fuera de OSB y la orquestación con Camel es responsabilidad de INI-24. INI-32 se encarga del decomiso de la INFRAESTRUCTURA donde corre OSB (WebLogic, licencias Oracle) una vez que INI-24 haya completado la migración. Secuencia: INI-23 (inventario) → INI-24 (Camel + migración lógica) → INI-32 (apagado infra Oracle/WebLogic asociada a OSB). | D28: Romper la cadena de obsolescencia tecnológica. Habilitar escalabilidad horizontal. Reducir costos de licenciamiento Oracle. (Priorizar esta modernizacion, que tengo que actualizar primero, etc) | E28: =SUMIF('Por actividad (2)'!A:A,'Iniciativas (2)'!A28,'Por actividad (2)'!N:N) -> 145632.29 | F28: Técnico | G28: Transversal (todos los flujos) | I28: B1 🟢 Cuantitativo Reducción costos licenciamiento Menos componentes Oracle = menos licencias B2 🟢 Cuantitativo Escalabilidad Containers permiten escalar horizontalmente B3 🟡 Cualitativo Soporte vigente Todos los componentes con soporte del fabricante | J28: A1 Inventario de componentes obsoletos Versión actual, soporte, riesgo, alternativa A2 Plan de actualización priorizado Orden de migración por criticidad y complejidad A3 Migración de Oracle 12 + WebLogic Actualizar o reemplazar por alternativas containerizadas A4 Migración de Java 8 Actualizar aplicaciones a Java LTS vigente A5 Eliminación definitiva de OSB Post-migración completa a Camel | K28: E1 Inventario de obsolescencia con riesgos E2 Plan de modernización priorizado E3 Componentes actualizados/reemplazados E4 Acta de decomisión de componentes legacy | L28: INI-12, INI-24, INI-35 | N28: INI-24 (Camel operativo para eliminar OSB), INI-35 (Microservicios para absorber servicios del bus) 🔗 DEPENDENCIAS CRUZADAS (Téc→Func): INI-12 (Gobierno funcional para coordinar eliminación obsolescencia). | O28: INI-24 (Camel operativo para eliminar OSB), INI-35 (Microservicios para absorber servicios del bus) | P28: PENDIENTE EN CASO DE PRIORIZACIÓN | Q28: TI Infraestructura, TI Arquitectura, Sonda, Oracle | R28: Técnica | S28: Transversal | T28: 🔴 Riesgo🟡 Canal 🟢 Producto | V28: Transversal (Infraestructura) | W28: Transversal | X28: Modernización tecnológica aplica a todo | Y28: Infraestructura OCI/OKE | Z28: FICO, OSB, WebLogic, Oracle DB | AA28: Infraestructura | AB28: Infraestructura | AC28: OCI Santiago / OKE | AD28: WebLogic 11g/10.3.6, Oracle DB 12, pods OKE | AE28: — | AF28: 🟡 DELIMITADA: Se retira 'Eliminación de OSB' como entregable lógico (→INI-24). Mantiene decomiso INFRAESTRUCTURA (WebLogic, licencias) post-migración Camel. | AG28: Delimitada (sin OSB lógico)
A29: INI-33 | B29: Herramienta de Parametrización de Reglas de Negocio + IA | C29: [Componente Técnico — ex INI-33] Capa de parametrización para que gerencias de negocio modifiquen reglas del motor sin TI. Integración de IA para análisis de impacto ante cambios de reglas. Habilitada por separación de Jobs (INI-20). [Componente Herramienta — ex INI-45] INI-11 define QUÉ reglas parametrizar. INI-33 propone +IA. Ninguna aborda LA HERRAMIENTA para que Riesgo modifique reglas sin TI. Hoy cualquier cambio requiere Ventiv/FICO + deploy + ventana. | D29: Reducir time-to-market de cambios de reglas de semanas a horas. Empoderar a negocio para gestionar sus reglas. Usar IA para predecir impacto de cambios. | E29: =SUMIF('Por actividad (2)'!A:A,'Iniciativas (2)'!A29,'Por actividad (2)'!N:N) -> 45511.211 | F29: Técnico | G29: Transversal (todos los flujos) | I29: B1 🟢 Cuantitativo Time-to-market de reglas De semanas a horas para cambios de parámetros B2 🟡 Cualitativo Empoderamiento de negocio Riesgo y Producto cambian sus reglas sin depender de TI B3 🟡 Cualitativo Análisis de impacto con IA Gemini predice efecto de cambios antes de implementar | J29: A1 Diseño de capa de parametrización Interfaz para que negocio modifique reglas A2 Integración con Jobs separados Cada Job expone sus parámetros configurables A3 Integración con Gemini IA para análisis de impacto de cambios de reglas A4 Desarrollo de interfaz de usuario UI para gerencias de negocio A5 Capacitación a usuarios de negocio Entrenamiento en uso de parametrización | K29: E1 Capa de parametrización implementada E2 Integración con Gemini operativa E3 UI de gestión de reglas para negocio E4 Manual y capacitación de usuarios | L29: INI-01, INI-11, INI-18, INI-20 | M29: Acceso a Vertex AI/Gemini | N29: INI-20 (Jobs separados), INI-18 (FICO v7 estable), INI-19 (v4 apagada), Acceso a Vertex AI/Gemini 🔗 DEPENDENCIAS CRUZADAS (Téc→Func): INI-11 (Desacople lógica negocio — capa funcional de reglas); INI-01 (Pre-evaluación — reglas FICO a parametrizar). | O29: INI-20 (Jobs separados), INI-18 (FICO v7 estable), INI-19 (v4 apagada), Acceso a Vertex AI/Gemini | P29: PENDIENTE EN CASO DE PRIORIZACIÓN | Q29: Ger. Riesgo, Ger. Producto, TI Desarrollo, TI Datos (IA) | R29: Técnica | S29: Generación de Oferta | T29: 📊 Negocio🔴 Riesgo | V29: Evaluación | W29: Evaluación | X29: Parametrización reglas + IA → reglas del motor en evaluación | Y29: Motor FICO (DMPS/Blaze) | Z29: Blaze Advisor, IA/ML | AA29: Motor de Decisión + IA | AB29: Lógica de Negocio | AC29: OCI/OKE + GCP (IA) | AD29: Blaze Advisor v7, Vertex AI (futuro), 120+ reglas | AE29: — | AF29: ✅ FUSIÓN: Absorbe INI-45 (Herramienta parametrización). Ahora cubre capa técnica + herramienta + IA. INI-45 eliminada. Depende de INI-11. | AG29: Fusionada (absorbió INI-45)
A30: INI-34 | B30: Base Corporativa (MDM) — Maestro Único de Datos | C30: BD Corporativa en GCP que absorbe Base de Aprobados, MenuAndes y otras fuentes dispersas. Modelo MDM como fuente única de verdad. Empieza en TO-BE 2, se consolida en TO-BE 3. | D30: Eliminar dispersión de datos entre múltiples fuentes. Crear maestro de datos único para clientes, productos y riesgo. Habilitar gobierno de datos con linaje y calidad. | E30: =SUMIF('Por actividad (2)'!A:A,'Iniciativas (2)'!A30,'Por actividad (2)'!N:N) -> 133964.13 | F30: Técnico | G30: Transversal (todos los flujos) | I30: B1 🟢 Cuantitativo Fuente única de verdad Un solo lugar para datos de cliente, producto, riesgo B2 🟢 Cuantitativo Eliminación de inconsistencias No más datos distintos entre Base Aprobados, MenuAndes, etc. B3 🟡 Cualitativo Gobierno de datos Linaje, calidad y ownership formalizados | J30: A1 Inventario de fuentes de datos dispersas Base Aprobados, MenuAndes, FlexCube, etc. A2 Diseño del modelo MDM Entidades maestras, relaciones, reglas de calidad A3 Migración de Base de Aprobados ETL + validación de datos migrados A4 Absorción de MenuAndes Consolidación en BD Corporativa A5 Implementación de gobierno de datos Linaje, calidad, ownership, métricas | K30: E1 Inventario de fuentes de datos E2 Modelo MDM documentado E3 BD Corporativa desplegada en GCP E4 Migración de Base de Aprobados completada E5 Framework de gobierno de datos | L30: ALT-01, INI-12 | M30: Decisión de , Acceso a GCP (CloudSQL/Spanner) | N30: INI-29 (Gobierno E2E), Decisión de ALT-01 (Base de Aprobados), Acceso a GCP (CloudSQL/Spanner) 🔗 DEPENDENCIAS CRUZADAS (Téc→Func): INI-12 (Gobierno funcional para MDM). | O30: INI-29 (Gobierno E2E), Decisión de ALT-01 (Base de Aprobados), Acceso a GCP (CloudSQL/Spanner) | P30: PENDIENTE EN CASO DE PRIORIZACIÓN | Q30: TI Datos, Ger. Riesgo, Ger. Clientes, Ger. Producto | R30: Técnica | S30: Punto de Entrada | T30: 🔴 Riesgo 🟢 Producto 🟣 Cliente | V30: Punto de Entrada → Generación de Oferta | W30: Punto de Entrada → Generación de Oferta | X30: MDM alimenta datos maestros para todo el flujo, concentrado al inicio | Y30: MenuAndes → BD Corporativa (MDM) | Z30: FlexCube, Siebel, Base Aprobados | AA30: Datos Maestros (MDM) | AB30: Datos (Maestro) | AC30: OCI → GCP (migración) | AD30: MenuAndes DB, BD Corporativa (nueva), FlexCube, Siebel | AE30: — | AG30: Sin cambios
A31: INI-35 | B31: Microservicios por Dominio (ms-cliente, ms-producto, ms-riesgo, ms-cobranza) | C31: 4 microservicios en GCP: ms-cliente 🟣 (EAI-074, 106, 110, 105, 080), ms-producto 🟢 (EAI-005, 122, 055), ms-riesgo 🔴 (EAI-003, 004, 138), ms-cobranza 🟡 (EAI-079). Cada uno absorbe servicios EAI del bus. | D31: Descomponer el monolito del bus en microservicios por dominio con ownership por gerencia. Permitir despliegue y escalamiento independiente. Eliminar dependencia de OSB. | E31: =SUMIF('Por actividad (2)'!A:A,'Iniciativas (2)'!A31,'Por actividad (2)'!N:N) -> 193156.95 | F31: Técnico | G31: Transversal (todos los flujos) | I31: B1 🟢 Cuantitativo Despliegue independiente Cada microservicio se despliega sin afectar a los demás B2 🟢 Cuantitativo Escalamiento por dominio Se escala solo el dominio que lo necesita B3 🟡 Cualitativo Ownership claro Cada gerencia es dueña de su microservicio | J31: A1 Diseño de arquitectura de microservicios 4 MS por dominio, contratos, comunicación A2 Desarrollo de ms-cliente Absorbe EAI-074, 106, 110, 105, 080 A3 Desarrollo de ms-producto Absorbe EAI-005, 122, 055 A4 Desarrollo de ms-riesgo Absorbe EAI-003, 004, 138 A5 Desarrollo de ms-cobranza Absorbe EAI-079 A6 Migración de consumidores del bus a microservicios Redirigir tráfico progresivamente | K31: E1 Arquitectura de microservicios documentada E2 4 microservicios desplegados en GCP E3 Contratos API documentados por MS E4 Plan de migración de consumidores del bus E5 Reporte de pruebas de carga por MS | L31: INI-12, INI-23, INI-24 | N31: INI-24 (Camel como orquestador), INI-23 (inventario servicios bus), INI-29 (Gobierno E2E) 🔗 DEPENDENCIAS CRUZADAS (Téc→Func): INI-12 (Gobierno funcional — define dominios y owners). | O31: INI-24 (Camel como orquestador), INI-23 (inventario servicios bus), INI-29 (Gobierno E2E) | P31: PENDIENTE EN CASO DE PRIORIZACIÓN | Q31: TI Desarrollo, TI Arquitectura, Ger. Clientes, Ger. Producto, Ger. Riesgo, Ger. Cobranza | R31: Técnica | S31: Transversal | T31: 🔴 Riesgo 🟢 Producto🟣 Cliente 🟡 Canal | V31: Transversal (Arquitectura) | W31: Transversal | X31: Microservicios por dominio aplican a todo el flujo | Y31: GCP Microservicios (nuevo) | Z31: OSB (reemplazado), FICO, FlexCube, MenuAndes | AA31: Microservicios GCP | AB31: Lógica de Negocio (nuevo) | AC31: GCP (GKE) | AD31: ms-cliente, ms-producto, ms-riesgo, ms-cobranza | AE31: EAI-074,106,110,105,080 (cliente), EAI-005,122,055 (producto), EAI-003,004,138 (riesgo), EAI-079 (cobranza) | AG31: Sin cambios
A32: INI-36 | B32: Observabilidad Operativa del Motor FICO (Estabilización AS-IS) | C32: Paquete de mejoras de observabilidad sobre el motor FICO On Premise y sus componentes activos (Kafka, Ignite) que seguirán operando durante TO-BE 1 y TO-BE 2 (mínimo 12-18 meses). Agrupa 7 ARIs despriorizadas que, en conjunto, eliminan la operación a ciegas del motor: habilitar GC logs en producción (ARI-01), alertas automáticas en Kafka ante pérdida de consumidores (ARI-02), corregir health check que reporta falsos OK ante errores 504 (ARI-03), desencapsular los 134.446 errores genéricos "Error Motor FICO" para exponer causas reales (ARI-04), habilitar acceso del equipo funcional a Elasticsearch/Grafana en producción (ARI-10), corregir sampling rate que monitorea el 100% de transacciones generando sobrecosto de memoria (ARI-12), y habilitar métricas de Apache Ignite para monitoreo de la caché distribuida (ARI-56). Sin estas acciones, la estabilización del TO-BE 1 se ejecutará sin capacidad diagnóstica. | D32: Dotar al equipo técnico y funcional de capacidad diagnóstica real sobre el motor FICO durante la transición al TO-BE. Reducir el tiempo medio de detección de incidentes (MTTD) de horas a minutos. Eliminar los 134.446 errores genéricos transformándolos en información accionable. Habilitar al equipo de negocio para monitorear el proceso sin depender de TI. | E32: =SUMIF('Por actividad (2)'!A:A,'Iniciativas (2)'!A32,'Por actividad (2)'!N:N) -> 126614.35 | F32: Técnico | G32: Transversal (todos los flujos) | I32: B1 🟢 Cuantitativo Reducción MTTD De horas a minutos en detección de degradación del motor FICO B2 🟢 Cuantitativo Errores desencapsulados 134.446 errores genéricos se transforman en causas raíz accionables B3 🟢 Cuantitativo Reducción sobrecosto memoria Sampling rate corregido libera recursos JVM (hoy monitorea 100%) B4 🟡 Cualitativo Autonomía funcional Equipo de negocio con acceso directo a dashboards sin depender de TI B5 🟡 Cualitativo Base para INI-27 e INI-28 Prerequisito para observabilidad E2E y trazabilidad OpenTelemetry | J32: A1 Habilitar GC logs en JVM FICO producción (ARI-01) Configurar -Xloggc con rotación en todos los nodos FICO ONP A2 Configurar alertas Kafka (ARI-02) Alertas automáticas ante consumer lag >umbral y pérdida de consumidores A3 Corregir health check FICO (ARI-03) Modificar endpoint /health para reflejar estado real ante 504/timeout A4 Desencapsular errores genéricos FICO (ARI-04) Mapear códigos internos, exponer causa raíz en logs y dashboards A5 Habilitar acceso funcional a Elasticsearch/Grafana (ARI-10) Crear roles read-only, dashboards de negocio, capacitación A6 Corregir sampling rate producción ONP (ARI-12) Ajustar de 100% a 5-10% con muestreo representativo A7 Habilitar métricas Apache Ignite (ARI-56) Activar JMX/exporters para caché hits, misses, latencia, nodos activos | K32: E1 GC logs habilitados y rotación configurada en nodos FICO E2 Alertas Kafka operativas con umbrales definidos E3 Health check corregido y validado con pruebas de fallo E4 Mapa de errores FICO desencapsulados (código → causa raíz) E5 Roles y dashboards funcionales en Grafana/Elasticsearch E6 Sampling rate ajustado y validado en producción E7 Métricas Ignite visibles en dashboards operativos | L32: INI-12, INI-27, INI-28 | M32: Accesos a servidores FICO ONP (producción), Acceso admin a Kafka, Acceso admin a Elasticsearch/Grafana, Acceso a configuración Apache Ignite. Complementa e . ARIs origen: ARI-01, ARI-02, ARI-03, ARI-04, ARI-10, ARI-12, ARI-56 | N32: Accesos a servidores FICO ONP (producción), Acceso admin a Kafka, Acceso admin a Elasticsearch/Grafana, Acceso a configuración Apache Ignite. Complementa INI-27 (Observabilidad base) e INI-28 (Trazabilidad E2E). ARIs origen: ARI-01, ARI-02, ARI-03, ARI-04, ARI-10, ARI-12, ARI-56 🔗 DEPENDENCIAS CRUZADAS (Téc→Func): INI-12 (Gobierno funcional para definir qué monitorear). | O32: Accesos a servidores FICO ONP (producción), Acceso admin a Kafka, Acceso admin a Elasticsearch/Grafana, Acceso a configuración Apache Ignite. Complementa INI-27 (Observabilidad base) e INI-28 (Trazabilidad E2E). ARIs origen: ARI-01, ARI-02, ARI-03, ARI-04, ARI-10, ARI-12, ARI-56 | P32: PENDIENTE EN CASO DE PRIORIZACIÓN | Q32: TI Operaciones (ejecución), Sonda (infra ONP), Proveedor FICO/Ventiv (config motor), Ger. Riesgo (validación funcional) | R32: Técnica (desde ARIs) | S32: Transversal | T32: 📊 Negocio🔴 Riesgo | V32: Evaluación (Observabilidad) | W32: Evaluación | X32: Observabilidad específica del motor FICO (evaluación) | Y32: Motor FICO (DMPS/Blaze) | Z32: Cloud Monitoring, Kafka | AA32: Observabilidad | AB32: Observabilidad / Monitoreo | AC32: OCI + GCP | AD32: FICO DMPS, Kafka, health check, GC logs, thread dumps | AE32: — | AG32: Sin cambios
A33: INI-37 | B33: Estabilización de Sincronización de Datos (MenuAndes, FlexCube, Siebel EIM) | C33: Paquete de correcciones a los procesos batch de sincronización de datos que hoy generan 12.493 knockouts falsos por datos inexistentes, incompletos o desincronizados entre MenuAndes, FlexCube y Siebel. Agrupa 7 ARIs despriorizadas: encadenar jobs Siebel EIM en Control-M respetando dependencias (ARI-29), implementar lógica de delta en MenuAndes para empresas (ARI-30), loteo/chunking en shells FlexCube (ARI-31), condicionar sincronización FlexCube al EOD (ARI-32), separar shells monolíticas FlexCube en etapas independientes (ARI-33), elaborar plan de desacoplamiento de MenuAndes (ARI-39), y documentar acoplamiento tabla RP_CONTAR con FlexCube (ARI-41). Esta iniciativa es el puente operativo hasta que la BD Corporativa (INI-34) absorba estas fuentes en TO-BE 2. | D33: Reducir los 12.493 knockouts falsos por datos desincronizados que hoy rechazan clientes con oferta válida. Estabilizar los procesos batch de carga que operan sin orden de dependencia ni control de errores. Generar el plan de desacoplamiento de MenuAndes como input directo para el diseño de la BD Corporativa (INI-34). | E33: =SUMIF('Por actividad (2)'!A:A,'Iniciativas (2)'!A33,'Por actividad (2)'!N:N) -> 52708.52 | F33: Técnico | G33: Cliente oferta aprobada normal | I33: B1 🟢 Cuantitativo Reducción knockouts falsos De 12.493 knockouts por datos a <1.000 (reducción >90% estimada) B2 🟢 Cuantitativo Recuperación de negocio Clientes rechazados falsamente que ahora podrán acceder a crédito B3 🟢 Cuantitativo Reducción MTTR sincronización Shells separadas permiten re-ejecución parcial (hoy es todo o nada) B4 🟡 Cualitativo Input para BD Corporativa Plan de desacoplamiento MenuAndes = diseño base de INI-34 B5 🟡 Cualitativo Documentación de dependencias ocultas RP_CONTAR/FlexCube documentado para migración futura | J33: A1 Encadenar jobs Siebel EIM en Control-M (ARI-29) Forzar secuencia: Empresa → Sucursal → Persona → Afiliación A2 Implementar lógica de delta en MenuAndes (ARI-30) Detección de cambios para procesar solo deltas vs. carga completa A3 Implementar loteo/chunking en shells FlexCube (ARI-31) Procesamiento por bloques para volúmenes variables sin pérdida A4 Condicionar sincronización FlexCube al EOD (ARI-32) Dependencia explícita con cierre de día y proceso de pagos A5 Separar shells monolíticas FlexCube (ARI-33) Descomponer en etapas: depuración → carga → validación (re-ejecutables) A6 Plan de desacoplamiento MenuAndes (ARI-39) Documentar dependencias, diseñar migración a BD Corporativa A7 Documentar acoplamiento RP_CONTAR/FlexCube (ARI-41) Mapear trigger + webservice + impacto en datos maestros | K33: E1 Jobs Siebel EIM encadenados en Control-M con secuencia correcta E2 Lógica de delta implementada en MenuAndes para Empresas E3 Shells FlexCube con loteo/chunking E4 Dependencia EOD configurada en Control-M E5 Shells FlexCube separadas en etapas independientes E6 Plan de desacoplamiento de MenuAndes (input para INI-34) E7 Documentación técnica de acoplamiento RP_CONTAR/FlexCube | L33: INI-12, INI-34 | M33: Acceso a Control-M (orquestador batch), Acceso a MenuAndes (código fuente shells), Acceso a FlexCube (shells de sincronización), Coordinación con equipo EOD. Input directo para . ARIs origen: ARI-29, ARI-30, ARI-31, ARI-32, ARI-33, ARI-39, ARI-41 | N33: Acceso a Control-M (orquestador batch), Acceso a MenuAndes (código fuente shells), Acceso a FlexCube (shells de sincronización), Coordinación con equipo EOD. Input directo para INI-34 (BD Corporativa MDM). ARIs origen: ARI-29, ARI-30, ARI-31, ARI-32, ARI-33, ARI-39, ARI-41 🔗 DEPENDENCIAS CRUZADAS (Téc→Func): INI-12 (Gobierno funcional para coordinar sincronización). | O33: Acceso a Control-M (orquestador batch), Acceso a MenuAndes (código fuente shells), Acceso a FlexCube (shells de sincronización), Coordinación con equipo EOD. Input directo para INI-34 (BD Corporativa MDM). ARIs origen: ARI-29, ARI-30, ARI-31, ARI-32, ARI-33, ARI-39, ARI-41 | P33: PENDIENTE EN CASO DE PRIORIZACIÓN | Q33: TI Datos (owner), Sonda (ejecución batch), Ger. Riesgo (validación knockouts), Ger. Clientes (MenuAndes) | R33: Técnica (desde ARIs) | S33: Punto de Entrada | T33: 🟣 Cliente, 🟢 Producto, 🔴 Riesgo | V33: Punto de Entrada → Generación de Oferta | W33: Punto de Entrada → Generación de Oferta | X33: Sincronización datos de entrada (MenuAndes, FlexCube, Siebel) | Y33: Jobs Batch / Control-M | Z33: MenuAndes, FlexCube, Siebel | AA33: Batch + Datos Maestros | AB33: Datos (ETL/Batch) | AC33: OCI Santiago | AD33: Jobs EIM, GITU, shells FlexCube, Control-M | AE33: — | AG33: Sin cambios
A34: INI-38 | B34: Limpieza de Deuda Técnica y Servicios Sin Valor | C34: Eliminación de configuraciones residuales y servicios sin valor que contaminan el monitoreo y consumen recursos innecesariamente. Agrupa 2 ARIs despriorizadas: limpiar configuración residual de Mambu dado de baja que genera 3.694 errores fantasma en el monitoreo (ARI-05), y verificar/eliminar invocaciones a servicios DUMMY (EAI-029, EAI-055, EAI-074) que consumen hilos y recursos sin aportar al flujo de crédito (ARI-06). Son quick wins de bajo esfuerzo que mejoran inmediatamente la señal/ruido del monitoreo. | D34: Eliminar 3.694 errores fantasma del monitoreo causados por sistema Mambu dado de baja. Liberar hilos y recursos consumidos por servicios DUMMY sin valor funcional. Mejorar ratio señal/ruido en logs y dashboards para que las alertas reales se detecten rápido. | E34: =SUMIF('Por actividad (2)'!A:A,'Iniciativas (2)'!A34,'Por actividad (2)'!N:N) -> 26632.287 | F34: Técnico | G34: Transversal (todos los flujos) | I34: B1 🟢 Cuantitativo Eliminación errores fantasma 3.694 errores Mambu eliminados del monitoreo B2 🟢 Cuantitativo Liberación de recursos Hilos y CPU liberados por eliminar invocaciones DUMMY B3 🟡 Cualitativo Mejora señal/ruido Dashboards muestran solo problemas reales, no residuos legacy | J34: A1 Limpiar configuración Mambu (ARI-05) Eliminar js-errorRoutingMambu y referencias asociadas en config FICO A2 Identificar servicios DUMMY activos (ARI-06) Verificar EAI-029, EAI-055, EAI-074: consumidores, volumetría, impacto A3 Eliminar invocaciones DUMMY Remover llamadas desde el flujo, validar que no hay dependencias ocultas A4 Validar en QA y producción Pruebas de regresión post-limpieza | K34: E1 Configuración Mambu eliminada de FICO E2 Análisis de servicios DUMMY con impacto documentado E3 Invocaciones DUMMY eliminadas E4 Reporte de pruebas de regresión post-limpieza | L34: INI-12, INI-23, INI-27 | M34: Acceso a configuración FICO ONP, Acceso a configuración de flujos EAI en el bus. Complementa e . ARIs origen: ARI-05, ARI-06 | N34: Acceso a configuración FICO ONP, Acceso a configuración de flujos EAI en el bus. Complementa INI-23 (Análisis Servicios Bus) e INI-27 (Observabilidad). ARIs origen: ARI-05, ARI-06 🔗 DEPENDENCIAS CRUZADAS (Téc→Func): INI-12 (Gobierno funcional para aprobar eliminación de servicios). | O34: Acceso a configuración FICO ONP, Acceso a configuración de flujos EAI en el bus. Complementa INI-23 (Análisis Servicios Bus) e INI-27 (Observabilidad). ARIs origen: ARI-05, ARI-06 | P34: PENDIENTE EN CASO DE PRIORIZACIÓN | Q34: TI Desarrollo (ejecución), Ventiv/FICO (config motor), Sonda (despliegue) | R34: Técnica (desde ARIs) | S34: Generación de Oferta | T34: 🔴 Riesgo | V34: Generación de Oferta + Evaluación | W34: Generación de Oferta + Evaluación | X34: Limpieza flujos EAI/FICO que operan en generación y evaluación | Y34: OSB (Bus de Integración) | Z34: FICO, servicios EAI, Siebel | AA34: Integración / Orquestación | AB34: Integración | AC34: OCI Santiago | AD34: OSB 11g, 14 servicios EAI, FICO | AE34: 14 servicios EAI (limpiar flujos redundantes) | AG34: Sin cambios
A35: INI-39 | B35: Contención de Vulnerabilidades Activas (APM Parásito + Ignite Sin Backup) | C35: Resolución de 3 vulnerabilidades activas que seguirán existiendo durante todo TO-BE 1 y TO-BE 2: el agente Elastic APM inactivo que genera 12,57% del tráfico HTTP del DPC con 79,9% de errores — equivalente a 309.078 conexiones/hora desperdiciadas (ARI-53 bloqueo firewall IP principal, ARI-54 bloqueo IPs adicionales con RST continuos ~30/min), y Apache Ignite configurado con 0 backups (ARI-57) donde si un nodo cae se pierden TODOS los datos de caché distribuida. Son vulnerabilidades críticas que agravan cualquier incidente de degradación del motor. | D35: Eliminar el 12,57% de tráfico HTTP parásito generado por el agente APM inactivo (309.078 conexiones/hora). Cortar las ~30 conexiones/minuto con RST continuo hacia IPs que ya no responden. Configurar al menos 1 backup en Ignite para evitar pérdida total de caché ante caída de un nodo. | E35: =SUMIF('Por actividad (2)'!A:A,'Iniciativas (2)'!A35,'Por actividad (2)'!N:N) -> 76511.211 | F35: Técnico | G35: Transversal (todos los flujos) | I35: B1 🟢 Cuantitativo Reducción tráfico parásito 309.078 conexiones/hora eliminadas del DPC B2 🟢 Cuantitativo Recursos liberados 12,57% de capacidad HTTP devuelta al tráfico productivo B3 🟢 Cuantitativo Resiliencia Ignite Caída de 1 nodo no pierde datos de caché (hoy pierde 100%) B4 🟡 Cualitativo Reducción superficie de fallo Menos puntos de falla en cascada durante degradación | J35: A1 Bloqueo firewall IP agente APM principal (ARI-53) Regla en puertos 443 y 9243 hacia IP del agente inactivo A2 Bloqueo firewall IPs adicionales con RST (ARI-54) Identificar y bloquear IPs con rechazos continuos (~30/min) A3 Validar reducción de tráfico post-bloqueo Medición de red para confirmar eliminación de conexiones parásitas A4 Configurar backup=1 en Apache Ignite (ARI-57) Modificar configuración de caché para mantener 1 réplica por partición A5 Prueba de resiliencia Ignite Simular caída de nodo y verificar que los datos se mantienen | K35: E1 Reglas de firewall aplicadas y documentadas E2 Medición de red post-bloqueo (antes/después) E3 Configuración Ignite con backup=1 E4 Reporte de prueba de resiliencia Ignite E5 Documentación de vulnerabilidades cerradas | L35: INI-12, INI-18, INI-28 | M35: Acceso a firewall de red (equipo seguridad/Sonda), Acceso a configuración Apache Ignite, Ventana de mantenimiento para cambio Ignite (requiere reinicio de cluster). Complementa e . ARIs origen: ARI-53, ARI-54, ARI-57 | N35: Acceso a firewall de red (equipo seguridad/Sonda), Acceso a configuración Apache Ignite, Ventana de mantenimiento para cambio Ignite (requiere reinicio de cluster). Complementa INI-18 (FICO v7 Estabilización) e INI-28 (Trazabilidad E2E). ARIs origen: ARI-53, ARI-54, ARI-57 🔗 DEPENDENCIAS CRUZADAS (Téc→Func): INI-12 (Gobierno funcional para aprobar ventanas de mantenimiento). | O35: Acceso a firewall de red (equipo seguridad/Sonda), Acceso a configuración Apache Ignite, Ventana de mantenimiento para cambio Ignite (requiere reinicio de cluster). Complementa INI-18 (FICO v7 Estabilización) e INI-28 (Trazabilidad E2E). ARIs origen: ARI-53, ARI-54, ARI-57 | P35: PENDIENTE EN CASO DE PRIORIZACIÓN | Q35: TI Seguridad/Redes (firewall), Sonda (infra Ignite), Ventiv/FICO (validación motor) | R35: Técnica (desde ARIs) | S35: Transversal | T35: 🔴 Riesgo | V35: Transversal (Seguridad) | W35: Transversal | X35: Vulnerabilidades APM + Ignite son transversales | Y35: Infraestructura OCI/OKE | Z35: APM, Ignite, FICO | AA35: Seguridad + Infraestructura | AB35: Seguridad / Infraestructura | AC35: OCI / OKE | AD35: APM, Ignite, tokens OAG/Apigee, red | AE35: — | AG35: Sin cambios
A36: INI-40 | B36: Gobierno de Contingencia, Base Aprobados Online y Documentación de Obsolescencia | C36: Tres acciones habilitadoras que son prerequisitos directos de iniciativas TO-BE ya definidas: (1) Definir protocolo formal de contingencia ante caída FICO para canales digital y presencial (ARI-09) — hoy no existe procedimiento y cada caída se gestiona ad-hoc; (2) Implementar microservicio de baja en línea en Base de Aprobados para TAPP (ARI-13) — actualmente la gestión es solo batch, el canal digital no puede dar de baja registros en tiempo real; (3) Evaluar y documentar formalmente el riesgo de obsolescencia de Oracle 12 congelada por dependencia con Oracle Forms (ARI-40) — la BD lleva años sin soporte pero no se puede actualizar por Forms. Cada acción alimenta directamente una INI del roadmap principal. | D36: Formalizar el protocolo de contingencia FICO como prerequisito de gobernanza (INI-29 e INI-31). Habilitar gestión en tiempo real de Base de Aprobados para canal digital como puente hasta BD Corporativa (INI-34). Documentar formalmente el riesgo Oracle 12/Forms como input para el plan de modernización (INI-32). | E36: =SUMIF('Por actividad (2)'!A:A,'Iniciativas (2)'!A36,'Por actividad (2)'!N:N) -> 65134.529 | F36: Gobierno y Personas | G36: Transversal (todos los flujos) | I36: B1 🟡 Cualitativo Protocolo contingencia Procedimiento formal que hoy no existe → actuación coordinada ante caída FICO B2 🟢 Cuantitativo Baja online Base Aprobados Canal digital puede gestionar registros en tiempo real (hoy solo batch) B3 🟡 Cualitativo Riesgo Oracle documentado Visibilidad formal para gerencia sobre deuda técnica Oracle 12/Forms B4 🟡 Cualitativo Prerequisitos desbloqueados INI-29, INI-31, INI-32 e INI-34 pueden avanzar con estos inputs | J36: A1 Diseñar protocolo contingencia FICO (ARI-09) Procedimiento para canal digital (TAPP) y presencial (Siebel) ante caída motor A2 Validar protocolo con simulacro Ejercicio tabletop con equipos de operaciones, negocio y soporte A3 Diseñar MS baja online Base Aprobados (ARI-13) API para TAPP que permite dar de baja registros en tiempo real A4 Desarrollar y desplegar MS baja online Microservicio en GCP con endpoint REST para TAPP A5 Documentar riesgo Oracle 12/Forms (ARI-40) Análisis formal: versión, soporte, dependencia Forms, alternativas, costo de no actuar A6 Presentar a gerencia para decisión Informe ejecutivo con recomendación y opciones de migración | K36: E1 Protocolo de contingencia FICO documentado (digital + presencial) E2 Resultado del simulacro tabletop E3 MS baja online Base Aprobados desplegado E4 API documentada para TAPP E5 Informe de riesgo Oracle 12/Forms con recomendaciones E6 Presentación ejecutiva para toma de decisión | L36: INI-12, INI-13, INI-31, INI-32, INI-34 | M36: A1-A2: Participación de Ger. Riesgo, Ger. Digital, TI Operaciones, Sonda. A3-A4: Acceso a Base de Aprobados (esquema actual), Acceso a GCP para despliegue, API TAPP. A5-A6: Acceso a contratos Oracle, información de Forms, equipo DBA. Input para: , , , . ARIs origen: ARI-09, ARI-13, ARI-40 | N36: A1-A2: Participación de Ger. Riesgo, Ger. Digital, TI Operaciones, Sonda. A3-A4: Acceso a Base de Aprobados (esquema actual), Acceso a GCP para despliegue, API TAPP. A5-A6: Acceso a contratos Oracle, información de Forms, equipo DBA. Input para: INI-29 (Gobierno), INI-31 (Runbooks), INI-32 (Modernización), INI-34 (BD Corporativa). ARIs origen: ARI-09, ARI-13, ARI-40 🔗 DEPENDENCIAS CRUZADAS (Téc→Func): INI-12 (Gobierno funcional); INI-13 (Resiliencia — flujos de contingencia). | O36: A1-A2: Participación de Ger. Riesgo, Ger. Digital, TI Operaciones, Sonda. A3-A4: Acceso a Base de Aprobados (esquema actual), Acceso a GCP para despliegue, API TAPP. A5-A6: Acceso a contratos Oracle, información de Forms, equipo DBA. Input para: INI-29 (Gobierno), INI-31 (Runbooks), INI-32 (Modernización), INI-34 (BD Corporativa). ARIs origen: ARI-09, ARI-13, ARI-40 | P36: PENDIENTE EN CASO DE PRIORIZACIÓN | Q36: TI Operaciones (contingencia), TI Desarrollo (MS baja), DBA/TI Infra (Oracle), Ger. Riesgo + Ger. Digital (validación) | R36: Técnica (desde ARIs) | S36: Transversal | T36: 🔴 Riesgo, 🟡 Canal, 🏛️ Gobierno | V36: Transversal (Gobierno + Contingencia) | W36: Transversal | X36: Base Aprobados Online + documentación obsolescencia | Y36: Base de Aprobados | Z36: FlexCube, Siebel, TAPP | AA36: Datos + Contingencia | AB36: Datos + Gobierno | AC36: OCI Santiago | AD36: Base Aprobados DB, baja online, FlexCube (cierre) | AE36: — | AG36: Sin cambios
A37: INI-41 | B37: Implementar Buenas Prácticas de Ciberseguridad | C37: ⏸️ PAUSADA — Pendiente reuniones con equipo de Ciberseguridad. Abordará gestión de identidades, tokens OAG/Apigee, cifrado, segmentación de red, hardening. Se diferencia de INI-39 (contención vulnerabilidades activas) en que esta es estratégica y de largo plazo. | D37: Establecer marco de ciberseguridad para ecosistema onboarding crédito alineado a ISO 27001/NIST. | E37: =SUMIF('Por actividad (2)'!A:A,'Iniciativas (2)'!A37,'Por actividad (2)'!N:N) -> 4789.2377 | F37: Técnico | G37: Transversal (todos los flujos) | I37: Reducción superficie de ataque, cumplimiento normativo, confianza digital | J37: ⏸️ PAUSADA — Pendiente definición | K37: ⏸️ PAUSADA — Pendiente definición | L37: INI-24, INI-39 | M37: Reuniones con equipo Ciber | N37: Reuniones con equipo Ciber. INI-39, INI-24 | O37: INI-39 (contención), INI-24 (Camel), INI-22 (Apigee) | P37: ⏸️ Pausada | Q37: Equipo Ciberseguridad CLA, TI Seguridad/Redes | R37: ⏸️ Por definir | S37: Transversal | T37: 🛡️ Seguridad | U37: ⏸️ Pausada | V37: Transversal (Seguridad) | W37: Transversal | X37: Ciberseguridad aplica a todos los componentes. Pausada hasta reuniones con ciber. | Y37: Gobierno / Proceso (no aplicativo) | Z37: APM, Ignite, Apigee, FICO, Camel | AA37: Seguridad | AB37: Seguridad / Gobierno | AC37: ⏸️ Pendiente | AD37: ⏸️ Pendiente reuniones con equipo Ciber | AE37: — | AG37: Sin cambios
A38: INI-42 | B38: Modernización del CRM (Siebel → Salesforce) | C38: Reemplazo planificado de Siebel CRM por Salesforce. Siebel hoy opera como CRM + orquestador (Svc 147) + motor segmentación. En TO-BE 2 se desacopla evalScoring y muere Svc 147. En TO-BE 3, Siebel se reemplaza completamente. Formaliza ALT-05. | D38: Reemplazar Siebel por plataforma CRM moderna sin restricciones contractuales/técnicas actuales. | E38: =SUMIF('Por actividad (2)'!A:A,'Iniciativas (2)'!A38,'Por actividad (2)'!N:N) -> 242659.19 | F38: Técnico | G38: Transversal (todos los flujos) | I38: Eliminación costo licencia Siebel, eliminación cuello botella Svc 147, plataforma moderna, desacople orquestación | J38: A1 Evaluación de alternativas CRM Analizar opciones (Salesforce, Dynamics, mantener Siebel), costos, capacidades, integración con ecosistema CLA A2 Diseño de modelo de coexistencia Siebel+Salesforce Definir qué funciones migran primero, cuáles conviven, y por cuánto tiempo A3 Desacople de evalScoring de Siebel (TO-BE 2) Extraer lógica de evaluación de scoring fuera de Siebel hacia MS Lógica Crédito (INI-21) A4 Desarrollo de MVP Salesforce Configurar Salesforce para funciones CRM core: gestión de clientes, seguimiento de solicitudes, reportes A5 Migración de datos y procesos de Siebel a Salesforce ETL de datos, mapeo de campos, validación de integridad, pruebas de paridad A6 Cutover y apagado de Siebel Plan de cutover con rollback, comunicación a usuarios, capacitación, monitoreo post-migración | K38: E1 Informe de evaluación de alternativas CRM con recomendación E2 Diseño del modelo de coexistencia Siebel + Salesforce E3 evalScoring desacoplado de Siebel y operativo en MS Lógica Crédito E4 Salesforce MVP desplegado con funciones CRM core E5 Migración completa de datos Siebel → Salesforce validada E6 Acta de apagado de Siebel y liberación de licencias | L38: INI-04, INI-21, INI-24, INI-34 | N38: INI-21 (MS Lógica Crédito), INI-04 (evalScoring), INI-24 (Camel), INI-34 (BD Corporativa) | O38: INI-21, INI-04, INI-24, INI-34 | P38: Evaluación TO-BE 2 (6-12m), Implementación TO-BE 3 (12-24m) | Q38: Ger. Comercial, TI Desarrollo, Proveedor Salesforce | R38: Funcional + Técnica | S38: Transversal (CRM impacta todo) | T38: 🟣 Cliente + 🟡 Canal | U38: Propuesta nueva | V38: Transversal (CRM) | W38: Transversal | X38: Siebel opera en todas las etapas. Su reemplazo es transversal. Formaliza ALT-05. | Y38: Siebel / Salesforce | Z38: Camel, FlexCube, TAPP, BD Corporativa | AA38: CRM + Canal | AB38: Proceso de Negocio + Integración | AC38: OCI (Siebel) → Cloud/SaaS (Salesforce) | AD38: Siebel CRM (apagar), Salesforce (nuevo), Camel (integración), Servicio 147 (ya muerto) | AE38: — | AG38: Sin cambios
A39: INI-43 | B39: Ambiente de Pruebas, QA, Automatización y Datos de Prueba | C39: No existe ambiente de pruebas replicable ni datos sanitizados. Todas las INIs asumen testing que NO existe (FG-18). Crea capacidad QA: ambiente espejo, datos sanitizados, regresión automatizada, CI/CD. | D39: Establecer ambiente pruebas replicable con datos sanitizados, automatización regresión y CI/CD. | E39: =SUMIF('Por actividad (2)'!A:A,'Iniciativas (2)'!A39,'Por actividad (2)'!N:N) -> 56479.821 | F39: Técnico | G39: Transversal (todos los flujos) | I39: Reducción riesgo regresión, pruebas carga reales (800+ sol/día), velocidad entrega, cumplimiento datos | J39: A1 Relevamiento de requerimientos de ambientes Mapear necesidades por INI técnica: ambientes, datos, herramientas QA A2 Diseño de arquitectura de ambiente espejo Arquitectura replicable de producción (OCI+GCP) con datos sanitizados A3 Generación de datos de prueba sanitizados Framework de generación/anonimización de datos representativos del volumen real A4 Desarrollo de suite de regresión automatizada Casos de prueba E2E automatizados para cada servicio crítico del flujo de crédito A5 Implementación de CI/CD para ambientes Pipeline automatizado para deploy en ambientes de prueba (Jenkins/CloudBuild) A6 Piloto con INIs técnicas priorizadas Validar ambiente con INI-18, INI-24 y INI-35 como primeros usuarios | K39: E1 Mapa de requerimientos de ambientes por INI E2 Arquitectura de ambiente espejo documentada y desplegada E3 Generador de datos sanitizados operativo E4 Suite de regresión automatizada con cobertura de servicios críticos E5 Pipeline CI/CD configurado para ambientes de prueba E6 Reporte de piloto con resultados y ajustes | L39: INI-12 | M39: Acceso OCI y GCP. . Es PREREQUISITO de todas las INIs técnicas | N39: Acceso OCI y GCP. INI-29 (gobierno). Es PREREQUISITO de todas las INIs técnicas. | O39: INI-29. Prerequisito habilitador de TODAS las INIs técnicas. | P39: H1 (TO-BE 1, 0-6m) — arrancar en paralelo con primeras INIs | Q39: TI QA, TI Desarrollo, TI Infraestructura | R39: Técnica + Funcional | S39: Transversal (habilita todas) | T39: ⚙️ Infraestructura + Gobierno | U39: Propuesta nueva | V39: Transversal (Habilitador) | W39: Transversal | X39: QA/Testing es prerequisito de todas las INIs. FG-18 confirma gap. | Y39: GCP + OCI (Infraestructura QA) | Z39: FICO staging, FlexCube mock, Camel test, TAPP test | AA39: Infraestructura + DevOps | AB39: Infraestructura (Ambientes) + CI/CD | AC39: GCP + OCI (ambientes espejo) | AD39: Jenkins/Cloud Build, ambiente espejo OCI+GCP, generador datos sanitizados, suite regresión | AE39: — | AG39: Sin cambios
A40: INI-44 | B40: Implementación Progresiva de TOGAF como Marco de Arquitectura Empresarial | C40: Scoring TOGAF actual 1.21/5. TO-BE define evolución incremental: Ciclo 1 (proceso+owner), Ciclo 2 (SOA+catálogo+MDM), Ciclo 3 (arquitectura completa). INI-29/INI-12 cubren gobierno pero NO TOGAF como framework. | D40: Elevar madurez TOGAF de 1.21 a 3.0+ mediante ADM cycle, building blocks, principios y governance board. | E40: =SUMIF('Por actividad (2)'!A:A,'Iniciativas (2)'!A40,'Por actividad (2)'!N:N) -> 45139.013 | F40: Gobierno y Personas | G40: Transversal (todos los flujos) | I40: Madurez medible (1.21→3.0+), decisiones documentadas (ADR), catálogo servicios, gobierno arquitectónico | J40: A1 Constituir Architecture Board Definir miembros, charter, cadencia y autoridad del comité de arquitectura A2 Adaptar ciclo ADM de TOGAF a CLA Simplificar ADM para contexto CLA: fases priorizadas, plantillas, governance gates A3 Definir building blocks del proceso de crédito Catalogar componentes de negocio y técnicos como building blocks reutilizables A4 Desarrollar catálogo SOA de servicios Inventariar y catalogar todos los servicios (EAI, microservicios, APIs) con metadata A5 Medir madurez con scoring TOGAF Aplicar scoring por dominio (Negocio, Datos, Aplicaciones, Tecnología) y comparar con baseline A6 Consolidar arquitectura empresarial TO-BE Integrar los 4 dominios TOGAF en una vista consolidada alineada a los 5 TO-BE | K40: E1 Charter del Architecture Board con miembros y cadencia E2 ADM simplificado adaptado a CLA con plantillas E3 Catálogo de building blocks (negocio + técnicos) E4 Catálogo SOA de servicios con metadata E5 Reportes de scoring de madurez TOGAF por dominio E6 Vista consolidada de arquitectura empresarial TO-BE | L40: INI-12 | M40: Complementa ambas con framework TOGAF | N40: INI-29 (gobierno E2E), INI-12 (gobierno TI). Complementa ambas con framework TOGAF. | O40: INI-29, INI-12 | P40: H1 → H2 → H3 incremental por ciclo | Q40: Arquitectura TI CLA, PwC, Ger. TI | R40: Funcional + Técnica | S40: Transversal (marco arquitectura) | T40: 🏛️ Arquitectura Empresarial | U40: Propuesta nueva | V40: Transversal (Gobierno + Arquitectura) | W40: Transversal | X40: TOGAF aplica a toda la arquitectura E2E. Scoring 1.21/5. Evolución incremental. | Y40: Gobierno / Proceso (no aplicativo) | Z40: Todos los componentes (catálogo building blocks) | AA40: Gobierno y Operación | AB40: Gobierno (Arquitectura Empresarial) | AC40: N/A (organizacional + repositorio) | AD40: Architecture Board, ADM cycle, catálogo building blocks, catálogo SOA, scoring TOGAF | AE40: — | AG40: Sin cambios
A41: INI-46 | B41: Ajuste al Proceso de Creación de Bases de Campaña (ex-Preaprobados) | C41: Proceso actual (PR-05, enero 2021) es manual con múltiples handoffs: Riesgo → Inteligencia Afiliados → Digital Insight → CEOCRM → Ejecutivos. Sin SLAs, sin integración con Base Aprobados ni TAPP. INI-34/INI-40 abordan la BD, NO el proceso funcional. | D41: Optimizar proceso creación/distribución bases campaña: reducir handoffs, establecer SLAs, conectar con BD Corporativa y canal digital. "Poner reglas en el borde" | E41: =SUMIF('Por actividad (2)'!A:A,'Iniciativas (2)'!A41,'Por actividad (2)'!N:N) -> 34757.848 | F41: Funcional/Negocio | G41: Cliente oferta aprobada normal + Cliente oferta aprobada express | I41: Reducción time-to-campaign, eliminación errores manuales, SLAs entre áreas, conexión canal digital | J41: A1 Levantar proceso AS-IS de creación de bases de campaña Documentar el flujo actual con handoffs, tiempos, responsables y puntos de dolor A2 Diagnosticar pain points y pérdidas operativas Identificar cuellos de botella, errores frecuentes, tiempos muertos y falta de SLAs A3 Diseñar proceso TO-BE con SLAs y automatización Flujo optimizado con SLAs por etapa, integración con BD Corporativa y TAPP A4 Integrar con BD Corporativa (INI-34) y TAPP Conectar el proceso con la fuente única de datos y el canal digital A5 Implementar proceso TO-BE Desarrollar automatizaciones, validaciones y controles del nuevo flujo A6 Piloto y ajustes Ejecutar piloto con una campaña real, medir mejoras vs AS-IS, ajustar | K41: E1 Mapeo AS-IS del proceso de creación de bases de campaña E2 Diagnóstico de pain points con métricas de impacto E3 Diseño TO-BE con SLAs por etapa y modelo de integración E4 Integración operativa con BD Corporativa + TAPP E5 Proceso TO-BE implementado con automatizaciones E6 Reporte de piloto con resultados y recomendaciones | L41: INI-23, INI-34, INI-40 | N41: INI-34 (BD Corporativa), INI-40 (gobierno Base Aprobados), INI-23 (Jobs) | O41: INI-34, INI-40, INI-23 | P41: H1-H2 (TO-BE 1-2, 0-12m) | Q41: Ger. Riesgo, Inteligencia Afiliados, Digital Insight, Ger. Comercial | R41: Funcional | S41: Punto de Entrada → Generación de Oferta | T41: 🔴 Riesgo + 🟣 Cliente | U41: Propuesta nueva | V41: Punto de Entrada → Generación de Oferta | W41: Punto de Entrada → Generación de Oferta | X41: Bases campaña definen qué clientes entran al flujo y con qué oferta. Proceso PR-05 CLA. | Y41: Base de Aprobados + BD Corporativa | Z41: FlexCube, Siebel/Salesforce, TAPP, CEOCRM | AA41: Datos + Proceso Operativo | AB41: Proceso de Negocio + Datos | AC41: OCI + GCP | AD41: Base Aprobados, BD Corporativa (INI-34), CEOCRM, Jobs EIM, canal digital TAPP | AE41: — | AG41: Sin cambios
A42: INI-47 | B42: Modificación de Canales y Ajustes a Integraciones por INIs Técnicas | C42: Múltiples INIs técnicas generan cambios que requieren ajustes en canales (TAPP, Siebel/Salesforce, Apigee): INI-21, INI-24, INI-34, INI-35, INI-42. Catch-all del delta de canal que cada INI técnica genera como efecto cascada. | D42: Centralizar y gestionar todos los ajustes en canales consecuencia de INIs técnicas del roadmap. | E42: =SUMIF('Por actividad (2)'!A:A,'Iniciativas (2)'!A42,'Por actividad (2)'!N:N) -> 46991.031 | F42: Gobierno y Personas | G42: Transversal (todos los flujos) | I42: Gestión centralizada cambios canal, reducción riesgo regresión, planificación ventanas cambio, reducción re-trabajo | J42: A1 Inventariar ajustes de canal requeridos por INIs técnicas Recopilar delta de cambios en canales generados por INI-21, INI-24, INI-34, INI-35, INI-42 A2 Plan consolidado de ajustes de canal Priorizar y secuenciar ajustes en un plan único coordinado con cada INI origen A3 Ajustes en TAPP (canal digital) Modificaciones en flujos TAPP derivadas de nuevos microservicios y orquestador A4 Ajustes en Apigee (API Gateway) Actualizar rutas, contratos y rate limiting en Apigee por cambios en backend A5 Ajustes en canal presencial (SVP/Sucursales) Adaptar flujos presenciales a los nuevos servicios y orquestación A6 Pruebas E2E de canales ajustados Validar que todos los canales operan correctamente con los nuevos componentes | K42: E1 Inventario de ajustes de canal por INI origen E2 Plan consolidado de ajustes de canal priorizado E3 TAPP ajustado y validado con nuevos servicios E4 Apigee actualizado (rutas, contratos, rate limiting) E5 Canal presencial adaptado a nueva arquitectura E6 Reporte de pruebas E2E de canales con evidencias | L42: INI-21, INI-24, INI-34, INI-35, INI-42 | M42: Se ejecuta en paralelo | N42: INI-21, INI-24, INI-34, INI-35, INI-42. Se ejecuta en paralelo. | O42: INI-21, INI-24, INI-34, INI-35, INI-42, INI-06, INI-07, INI-14 | P42: H1-H2-H3 continuo, en paralelo con cada INI técnica | Q42: TI Desarrollo Canal, TI Integración, Ger. Comercial | R42: Técnica | S42: Transversal (canales) | T42: 🟡 Canal | U42: Propuesta nueva | V42: Transversal (Canal) | W42: Transversal | X42: Canales atraviesan todas las etapas. Ajustes son efecto cascada de INIs técnicas. | Y42: TAPP (Canal Digital) + Apigee | Z42: Camel, MS Lógica Crédito, BD Corporativa, Salesforce | AA42: Canal Digital + Integración | AB42: Canal (Frontend + API Gateway) + Integración | AC42: GCP (TAPP, Apigee) + SaaS (Salesforce) | AD42: TAPP BFF, TAPP frontend, Apigee rutas/políticas, canal presencial, integraciones Camel | AE42: — | AG42: Sin cambios
A43: INI-48 | B43: Reenganche Automático por Simulación Abandonada | C43: Capturar simulaciones abandonadas en TAPP, persistir contexto, y al D+1 enviar oferta proactiva con rango aproximado del monto simulado. El afiliado ingresa directo al flujo TAPP_APB (cliente aprobado) sin re-evaluación FICO. | D43: Recuperar abandonos post-simulación, mejorar conversión digital, reducir carga FICO, ofrecer experiencia proactiva personalizada | E43: =SUMIF('Por actividad (2)'!A:A,'Iniciativas (2)'!A43,'Por actividad (2)'!N:N) -> 233744.39 | F43: Funcional/Negocio | G43: Cliente oferta aprobada normal + Cliente oferta aprobada express | I43: +8-15% conversión sobre abandonos, 0 llamadas FICO extra, journey de 7-10 pasos a 3-4, data de intención comercial | J43: A1 Diseño evento de abandono (captura RUT, monto, plazo, cuota, timestamp, canal) A2 Persistencia contexto en Redis/BD (ms-abandono-captura en GCP) A3 Job de Reenganche diario (07:00 AM D+1 — valida oferta vigente, calcula rango ±10%, genera oferta proactiva) A4 Motor de notificaciones (push TAPP + email personalizado con deep link) A5 Flujo de aceptación express (ingreso directo a TAPP_APB, saltando simulación y evaluación) A6 Reglas de negocio de reenganche (exclusiones, vigencia 72h, máx 1 por ciclo, horario envío) A7 Dashboard de seguimiento (BigQuery/Looker: abandonos, reenganches, conversión, monto recuperado) A8 Testing E2E + piloto controlado (5% de abandonos, 2 semanas, criterio go/no-go >5% conversión) | K43: E1 Especificación funcional evento de abandono + modelo de datos E2 Microservicio ms-abandono-captura desplegado en GCP E3 Job reenganche desplegado (GCP Cloud Scheduler / Control-M) E4 Plantillas de notificación (push + email) + integración API notificaciones E5 Flujo express en TAPP + pantalla de oferta proactiva + lógica de derivación E6 Documento de reglas de negocio aprobado por Ger. Riesgo + Ger. Comercial E7 Dashboard operativo + reportería semanal automatizada E8 Informe piloto con métricas + decisión go/no-go para rollout | L43: INI-07, INI-09, INI-12, INI-20, INI-22, INI-24, INI-25, INI-34, INI-43 | M43: Definición de reglas de negocio de reenganche aprobadas por Ger. Riesgo + Ger. Comercial (exclusiones, vigencia 72h, máx 1 reenganche por ciclo, horario de envío). Acceso a APIs de notificaciones push (TAPP) y email. Revisión Legal/Compliance: consentimiento para contacto proactivo y uso de data de simulación abandonada. Acceso a GCP (Cloud Run, Cloud Scheduler, Redis, BigQuery). Deep link habilitado en TAPP para flujo de aceptación express. | N43: - | O43: - | P43: PENDIENTE EN CASO DE PRIORIZACIÓN | Q43: Ger. Comercial (owner), Ger. Riesgo (co-owner), TI/Arq, Equipo TAPP, Datos/BI, Legal, QA | R43: Conversión + Retención + Experiencia Cliente | S43: Post-Simulación / Pre-Contratación (reenganche D+1) | T43: 🟡 Canal + 🔴 Riesgo + 🟣 Cliente | U43: Nueva (complementa hallazgos H3 y H6) | V43: TO-BE 2 (Ciclo 2: Convivencia Camel + Bus) | W43: Ciclo 2 — H2 (6-12 meses) | X43: Mapeo Ataca brecha de conversión digital (3.6% vs 11%) usando infra de INI-08/INI-18 | Y43: TAPP (App Digital) | Z43: Base de Aprobados / BD Corporativa | AA43: GCP (Cloud Run + Cloud Scheduler + Redis + BigQuery) | AB43: Servicios + Datos + Presentación | AC43: GCP + TAPP | AD43: TAPP, Redis, Base Aprobados/BD Corp, Notificaciones, Apigee, BigQuery, Control-M/Cloud Scheduler, Siebel/Salesforce | AE43: — | AG43: Sin cambios
A44: INI-49 | B44: Evaluación UX: Paquetización de Oferta vs Experiencia Actual | C44: Se ejecuta una evaluación UX completa (research + prototipado + test A/B) para medir y comparar cómo percibe el afiliado tres variantes de presentación de oferta de crédito: Variante A (Control / AS-IS): Oferta simple actual — monto, cuota, tasa, plazo — sin desglose de productos asociados (seguro, comisiones). Variante B (Paquete integrado): Oferta como 'paquete completo' donde se muestra crédito + seguro de desgravamen + seguro de cesantía + productos asociados como un todo, con precio total mensual visible y badge 'todo incluido'. Variante C (Desglose transparente): Oferta desglosada donde el afiliado ve cada componente por separado — cuota crédito puro ($X), cuota seguro desgravamen ($Y), comisión ($Z), total ($T) — con opción de toggle on/off para productos opcionales (lo que la normativa permita). El resultado es un informe con recomendación fundamentada de qué modelo de presentación maximiza conversión + comprensión + NPS, con prototipos de alta fidelidad validados y listos para implementar en TAPP y SVP. El foco es entender: ¿cuál prefiere el afiliado? ¿cuál lo frustra menos? ¿cuál genera mayor confianza y menor abandono? | D44: O1: Determinar la variante de presentación de oferta (simple / paquete / desglose) que maximiza la tasa de conversión en el canal digital y presencial, validada con test A/B (n≥500 por variante). O2: Alcanzar un nivel de comprensión ≥85% entre los afiliados sobre qué incluye la oferta que están aceptando (crédito + seguros + comisiones), medido con test de usabilidad. O3: Entregar prototipos de alta fidelidad (Figma) validados y listos para implementar por el equipo TAPP, con la variante ganadora definida y aprobada por Ger. Producto, Ger. Comercial y Ger. Riesgo. O4: Reducir la tasa de abandono en la pantalla de oferta al presentar información completa y comprensible desde el primer momento (upfront), eliminando la sorpresa por 'costos ocultos' en etapas tardías. O5: Reducir los reclamos post-venta asociados a 'no sabía qué incluía mi crédito'. O6: Cerrar la brecha de experiencia entre canal digital y presencial: lograr que la oferta en TAPP sea autoexplicativa sin necesidad de ejecutivo. O7: Habilitar decisiones de diseño de producto/canal basadas en evidencia UX cuantitativa y cualitativa. | E44: =SUMIF('Por actividad (2)'!A:A,'Iniciativas (2)'!A44,'Por actividad (2)'!N:N) -> 78294.127 | F44: Funcional/Negocio | G44: Transversal (Express + Normal + Sin oferta) | I44: B1: Comprensión de la oferta — Afiliado entiende el 100% de la oferta en pantalla de simulación. B2: Conversión en etapa de oferta — Información completa upfront → decisión informada → menos abandono tardío. B3: Reclamos post-venta — Reducción de reclamos por transparencia desde la oferta. B4: Cross-sell de productos asociados — Presentación como beneficio del paquete → afiliado valora y acepta. B5: Paridad canal digital vs presencial — UX digital autoexplicativa, reduce brecha canal. B6: Decisiones basadas en evidencia — Research UX con datos reales para decidir cómo presentar oferta. B7: Cumplimiento normativo (SERNAC/CMF) — Oferta 100% transparente alineada a normativa. | J44: A1: Benchmark + Análisis heurístico AS-IS — Auditoría UX de la experiencia actual de presentación de oferta en TAPP y SVP. Benchmark con 3-5 referentes (bancos/cajas/fintech). A2: Research cualitativo con afiliados — Entrevistas en profundidad (8-12 afiliados, mix digital + presencial). ¿Qué entienden que incluye su crédito? ¿Saben que pagan seguro? ¿Qué los frustra? A3: Diseño de 3 variantes de oferta — Prototipos alta fidelidad para Variante A (Control), B (Paquete integrado), C (Desglose transparente). Cada una para TAPP (móvil) y SVP (web). A4: Test de usabilidad + comprensión — Test con 12-15 afiliados (4-5 por variante). Métricas: comprensión, tiempo en pantalla, confianza percibida, preferencia declarada. A5: Test A/B cuantitativo en TAPP — 2 variantes ganadoras como feature flags, 2-4 semanas. Medir: avance post-oferta, abandono, contratación completa, reclamo D+30. Min 500 sesiones por variante. A6: Análisis de impacto en reclamos y post-venta — Cruce con datos reclamos SERNAC/internos últimos 12 meses. Revisión con Legal/Cumplimiento. A7: Informe final + recomendación + prototipos definitivos — Consolidar hallazgos A1-A6, variante recomendada, quick wins de copy/layout, roadmap de implementación UX. A8: Presentación a gerencias + decisión go/no-go — Workshop 2h con Ger. Producto, Comercial, Canales, Riesgo, Cumplimiento. Decisión formal de variante a implementar. | K44: E1: Informe de auditoría heurística + benchmark competitivo (3-5 referentes). E2: Informe de research cualitativo: insights, personas, pain points, verbatims clave. E3: 3 prototipos alta fidelidad (Figma/Adobe XD): Variante A + B + C para TAPP y SVP. E4: Informe de test de usabilidad: métricas por variante, matriz de preferencia, recomendación preliminar. E5: Informe de test A/B cuantitativo: métricas de conversión, significancia estadística, variante ganadora. E6: Análisis de reclamos + estimación de reducción + checklist de cumplimiento normativo. E7: Informe ejecutivo final + prototipos definitivos + roadmap de implementación UX. E8: Minuta de decisión firmada + variante aprobada + plan de acción. | L44: INI-09 🟡 (Funnel + Trazabilidad: datos de abandono en pantalla de oferta). INI-12 🟡 (Gobierno Funcional: foro para aprobar variante ganadora). INI-03 🟡 (Fast Track Express: entender cómo se presenta oferta Express vs Normal). Nota: Todos deseables, ninguno bloqueante. Puede arrancar en H1 sin dependencias técnicas. | N44: Depende de INI-12 para formalizar la decisión de variante ganadora. Se apalanca en INI-09 para datos de abandono por nodo. Se integra con INI-03 (cómo se presenta oferta Express). Alimenta a INI-02 (Oferta Dinámica: cómo se muestra al cliente), INI-14 (Módulo TAPP: UX del entry point) e INI-06 (Derivación: información previa a derivar). 🔗 DEPENDENCIAS CRUZADAS (Func↔Téc): INI-27 (Observabilidad para medir impacto post-implementación). | P44: PENDIENTE EN CASO DE PRIORIZACIÓN | Q44: Ger. Producto (owner funcional: composición de oferta), Ger. Canales Digitales (co-owner: analytics TAPP + feature flags), UX Researcher (ejecución: research + diseño + test), Data/BI (análisis cuantitativo test A/B + reclamos), Ger. Comercial (viabilidad comercial + cross-sell), Ger. Riesgo (validación: seguro obligatorio vs opcional), Legal/Cumplimiento (checklist CMF/SERNAC), Equipo TAPP (implementación feature flags + ajustes pantalla) | R44: Funcional | S44: Simulación → Presentación de Oferta | T44: 🟡 Canal 🟢 Producto 🟣 Cliente | U44: Nueva (complementa hallazgos H3 y H6) | V44: TO-BE 1 (Ciclo 1: Estabilización) | W44: Ciclo 1 — H1 (0-6 meses) | X44: El diagnóstico PwC identifica que la conversión digital es significativamente menor que la presencial (TAPP_NOR 3.6% vs TAPP_APB 11%). Una hipótesis no explorada es si la forma de presentar la oferta (simple vs paquetizada vs desglosada) impacta en la decisión del afiliado. En sucursal, el ejecutivo explica la composición de la oferta; en digital, nadie lo hace. Esta iniciativa cierra esa brecha con evidencia UX. Bajo costo, alto impacto potencial, ejecutable en H1 sin dependencias técnicas bloqueantes. | Y44: TAPP (App Digital) — Pantalla de presentación de oferta | Z44: SVP (Sucursal Virtual Presencial) — Pantalla de oferta en escritorio ejecutivo | AA44: Frontend (TAPP mobile + SVP web) + Analytics (Google Analytics / Firebase) | AB44: Capa de Presentación (UI/UX) — No impacta servicios ni datos en fase research | AC44: TAPP (frontend móvil) + SVP (frontend web) + Figma (prototipado) + Feature flags + Analytics | AD44: TAPP (pantalla de oferta, flujo de simulación) · SVP (pantalla de oferta ejecutivo) · Analytics TAPP (eventos de pantalla) · Feature flags (variantes A/B) · Capa de presentación de oferta (datos mostrados: monto, cuota, tasa, seguros, comisiones) | AE44: No impacta servicios EAI en fase research. Post-implementación: podría requerir EAI-005 (condiciones producto), EAI-122 (tasas/comisiones) si pantalla necesita desglose que hoy no consume. | AF44: NO duplica INI-02 (Oferta Dinámica): INI-02 genera la oferta; INI-49 evalúa CÓMO se presenta al afiliado. NO duplica INI-03 (Fast Track Express): INI-03 define el flujo; INI-49 evalúa la UX de la pantalla de oferta. NO duplica INI-14 (Módulo TAPP sin banner): INI-14 define el entry point; INI-49 evalúa la presentación dentro. Complementa INI-09 (Funnel): INI-09 mide dónde abandona; INI-49 investiga POR QUÉ abandona en pantalla de oferta. | AG44: Sin cambios

Sheet Sheet1
A1: Row Labels | B1: Sum of Costo estimado en USD | D1: Row Labels | E1: Sum of Costo estimado en USD | G1: Row Labels | H1: Sum of Costo estimado en USD
A2: Funcional/Negocio | B2: 1467289.6 | D2: Cliente sin oferta aprobada | E2: 319390.13 | G2: Cliente sin oferta aprobada | H2: 319390.13
A3: Gobierno y Personas | B3: 262807.17 | D3: (blank) | G3: (blank)
A4: Técnico | B4: 1859520.2 | D4: Cliente oferta aprobada express | E4: 109578.48 | G4: Cliente oferta aprobada express | H4: 109578.48
A5: (blank) | D5: Transversal (Express + Normal + Sin oferta) | E5: 434303.1 | G5: Transversal (Express + Normal + Sin oferta) | H5: 434303.1
A6: Grand Total | B6: 3589617 | D6: Transversal (Express + Normal + Sin oferta + No ok) | E6: 71089.686 | G6: Transversal (Express + Normal + Sin oferta + No ok) | H6: 71089.686
D7: Cliente no ok | E7: 62013.453 | G7: Cliente no ok | H7: 62013.453
D8: Transversal (todos los flujos) | E8: 2167883.4 | G8: Transversal (todos los flujos) | H8: 2167883.4
D9: Cliente oferta aprobada normal | E9: 191614.35 | G9: Cliente oferta aprobada normal | H9: 191614.35
D10: Cliente oferta aprobada normal + Cliente oferta aprobada express | E10: 233744.39 | G10: Cliente oferta aprobada normal + Cliente oferta aprobada express | H10: 233744.39
D11: Grand Total | E11: 3589617 | G11: Grand Total | H11: 3589617

Sheet Por actividad (2)
A1: INI | B1: Actividad | C1: Objetivo y resultado esperado X ACTIVIDAD | D1: Entregable X ACTIVIDAD | E1: Áreas involucradas X ACTIVIDAD | F1: Tipo Actividad | G1: Justificación Tipo | H1: Plazo X ACTIVIDAD | I1: Equipo de trabajo X ACTIVIDAD | J1: Plazo (semanas) | K1: FTEs equivalentes | L1: Costo estimado (UF) | M1: Al 45% UF | N1: <- USD
A2: INI-01 | B2: A1: Definir el segmento “cliente sin oferta” y condiciones de entrada al nodo (qué casos aplican y cuáles no). | C2: Objetivo: Definir el segmento “cliente sin oferta” y condiciones de entrada al nodo (qué casos aplican y cuáles no). | D2: Documento de alcance y requerimientos del nodo de pre-evaluación (incluye criterios “sin oferta”). | Diseño del flujo (diagrama del nodo FICO + derivación a INI-02 + simulación). | E2: Ger. Riesgo, Ger. Comercial/Producto, Canales (TAPP/SVP), Operaciones | F2: Funcional | G2: Define reglas, políticas, criterios o diseño de proceso/journey | H2: 1-2 semanas | I2: 1 Analista Funcional (100%) | 1 Especialista Riesgo (50%) | 1 Especialista Producto/Comercial (25%) | J2: 1.5 | K2: 1.75 | L2: 50.7 | M2: 117 | N2: =(40000/892)*M2 -> 5246.6368
A3: INI-01 | B3: A2: Definir reglas de decisión FICO (umbral(es), códigos de rechazo, vigencia, tratamiento de “sin score / error / data insuficiente”). | C3: Objetivo: Definir reglas de decisión FICO (umbral(es), códigos de rechazo, vigencia, tratamiento de “sin score / error / data insuficiente”). | D3: Política/parametría FICO: umbrales, tratamiento de excepciones (“no hit”, error, data incompleta) y motivos. | Monitoreo/KPIs (tasa de rechazo FICO, latencia, errores, derivación a INI-02, ahorro estimado de llamadas) + alertas. | E3: Proveedor FICO/Ventiv, TI Integración/Arquitectura, Sonda (infra/OCI-OKE) | F3: Técnica | G3: Implementa código, APIs, servicios, infraestructura o integración | H3: 2-3 semanas | I3: 1 Desarrollador Backend (100%) | 1 QA/Tester (25%) | 1 Especialista FICO/Blaze (50%) | 1 Coordinador Proveedor Sonda (25%) | 1 Coordinador Proveedor FICO/Ventiv (25%) | J3: 2.5 | K3: 2.25 | L3: 129.2 | M3: 302.4 | N3: =(40000/892)*M3 -> 13560.538
A4: INI-01 | B4: A3: Diseñar el flujo de orquestación: FICO → (rechazo y fin) / (aprobación y derivación a INI-02 + simulación). | C4: Objetivo: Diseñar el flujo de orquestación: FICO → (rechazo y fin) / (aprobación y derivación a INI-02 + simulación). | D4: Diseño del flujo (diagrama del nodo FICO + derivación a INI-02 + simulación). | Implementación del nodo en el orquestador/flujo (configuración por ambiente + feature flags si aplica). | E4: Ger. Riesgo, Ger. Comercial/Producto, Canales (TAPP/SVP), Operaciones | F4: Funcional | G4: Define reglas, políticas, criterios o diseño de proceso/journey | H4: 2-4 semanas | I4: 1 Analista Funcional (100%) | 1 Product Owner / Líder Negocio (50%) | 1 Especialista Riesgo (50%) | 1 Especialista Producto/Comercial (25%) | J4: 3 | K4: 2.25 | L4: 137.7 | M4: 323.7 | N4: =(40000/892)*M4 -> 14515.695
A5: INI-01 | B5: A4: Implementar integración técnica con FICO (API, seguridad, timeouts, retries) + manejo de contingencias/fallback. | C5: Objetivo: Implementar integración técnica con FICO (API, seguridad, timeouts, retries) + manejo de contingencias/fallback. | D5: Especificación de integración/API con FICO (contratos, seguridad, timeouts, reintentos). | Plan y evidencias de pruebas (unitarias, integración, E2E con INI-02, performance/contingencia) + UAT firmado. | E5: Proveedor FICO/Ventiv, TI Integración/Arquitectura, Sonda (infra/OCI-OKE) | F5: Técnica | G5: Implementa código, APIs, servicios, infraestructura o integración | H5: 5-8 semanas | I5: 1 PM/Scrum Master (25%) | 1 Arquitecto de Soluciones (50%) | 2 Desarrolladores Backend (100%) | 1 QA/Tester (50%) | 1 Especialista FICO/Blaze (50%) | 1 Especialista Ciberseguridad (25%) | 1 Coordinador Proveedor Sonda (25%) | 1 Coordinador Proveedor FICO/Ventiv (25%) | J5: 6.5 | K5: 4.5 | L5: 688.7 | M5: 1641.9 | N5: =(40000/892)*M5 -> 73627.803
A6: INI-01 | B6: A5: Implementar mensajería y motivos para canal (rechazo inmediato vs continúa) y registrar auditoría/logs. | C6: Objetivo: Implementar mensajería y motivos para canal (rechazo inmediato vs continúa) y registrar auditoría/logs. | D6: Catálogo de motivos/códigos para fin inmediato y para derivación (mensajes por canal). | Implementación del nodo en el orquestador/flujo (configuración por ambiente + feature flags si aplica). | E6: Proveedor FICO/Ventiv, TI Integración/Arquitectura, Sonda (infra/OCI-OKE) | F6: Técnica | G6: Implementa código, APIs, servicios, infraestructura o integración | H6: 3-5 semanas | I6: 1 Arquitecto de Soluciones (25%) | 1 Desarrollador Backend (100%) | 1 Desarrollador Frontend (50%) | 1 QA/Tester (50%) | 1 Especialista FICO/Blaze (50%) | 1 Coordinador Proveedor Sonda (25%) | 1 Coordinador Proveedor FICO/Ventiv (25%) | J6: 4 | K6: 3.25 | L6: 296.8 | M6: 697.9 | N6: =(40000/892)*M6 -> 31295.964
A7: INI-01 | B7: A6: Ejecutar pruebas y piloto (funcionales, performance, caída de servicios) y calibrar umbrales si corresponde. | C7: Objetivo: Ejecutar pruebas y piloto (funcionales, performance, caída de servicios) y calibrar umbrales si corresponde. | D7: Plan y evidencias de pruebas (unitarias, integración, E2E con INI-02, performance/contingencia) + UAT firmado. | Política/parametría FICO: umbrales, tratamiento de excepciones (“no hit”, error, data incompleta) y motivos. | E7: Ger. Riesgo, Ger. Comercial/Producto, Proveedor FICO/Ventiv, TI Integración/Arquitectura, Sonda (infra/OCI-OKE), Canales (TAPP/SVP), Operaciones | F7: Transversal | G7: Pruebas E2E, piloto, calibración, socialización o gobierno cruzado | H7: 2-4 semanas | I7: 1 Líder/PM de Iniciativa (50%) | 1 Analista Funcional (50%) | 1 Desarrollador Backend (50%) | 1 QA/Tester (50%) | 1 QA Lead (50%) | Usuarios de Negocio para UAT (25%) | J7: 3 | K7: 2.75 | L7: 168 | M7: 387.8 | N7: =(40000/892)*M7 -> 17390.135
A8: INI-02 | B8: A1: Levantar flujo actual y definir casos de uso para clientes sin pre-aprobación (ofertar / pedir datos / no ofertar). | C8: Objetivo: Levantar flujo actual y definir casos de uso para clientes sin pre-aprobación (ofertar / pedir datos / no ofertar). | D8: Diseño de proceso/journey objetivo (sin pre-aprobación → oferta dinámica → siguiente paso). | Catálogo de motivos/códigos (no oferta, rechazo, derivación) y mensajes para canal. | E8: Ger. Comercial/Producto, Ger. Riesgo (políticas/umbrales), Canales (TAPP/SVP/Sucursal) | F8: Funcional | G8: Define reglas, políticas, criterios o diseño de proceso/journey | H8: 1-2 semanas | I8: 1 Analista Funcional (100%) | 1 Especialista Riesgo (50%) | 1 Especialista Producto/Comercial (25%) | J8: 1.5 | K8: 1.75 | L8: 50.7 | M8: 117 | N8: =(40000/892)*M8 -> 5246.6368
A9: INI-02 | B9: A2: Definir políticas y reglas de elegibilidad + parámetros de oferta (monto/plazo/tasa/condiciones) y “motivos de no oferta”. | C9: Objetivo: Definir políticas y reglas de elegibilidad + parámetros de oferta (monto/plazo/tasa/condiciones) y “motivos de no oferta”. | D9: Reglas de elegibilidad + matriz/estrategia de oferta (parámetros por segmento/score) y versionado. | Catálogo de motivos/códigos (no oferta, rechazo, derivación) y mensajes para canal. | E9: Ger. Comercial/Producto, Ger. Riesgo (políticas/umbrales), Canales (TAPP/SVP/Sucursal) | F9: Funcional | G9: Define reglas, políticas, criterios o diseño de proceso/journey | H9: 1-2 semanas | I9: 1 Analista Funcional (100%) | 1 Especialista Riesgo (50%) | 1 Especialista Producto/Comercial (25%) | J9: 1.5 | K9: 1.75 | L9: 50.7 | M9: 117 | N9: =(40000/892)*M9 -> 5246.6368
A10: INI-02 | B10: A3: Diseñar el modelo de generación de oferta (segmentación por riesgo/score, matriz de oferta, 1 vs N ofertas). | C10: Objetivo: Diseñar el modelo de generación de oferta (segmentación por riesgo/score, matriz de oferta, 1 vs N ofertas). | D10: Diseño de proceso/journey objetivo (sin pre-aprobación → oferta dinámica → siguiente paso). | Reglas de elegibilidad + matriz/estrategia de oferta (parámetros por segmento/score) y versionado. | E10: Ger. Comercial/Producto, Ger. Riesgo (políticas/umbrales), Canales (TAPP/SVP/Sucursal) | F10: Funcional | G10: Define reglas, políticas, criterios o diseño de proceso/journey | H10: 1-2 semanas | I10: 1 Analista Funcional (100%) | 1 Especialista Riesgo (50%) | 1 Especialista Producto/Comercial (25%) | J10: 1.5 | K10: 1.75 | L10: 50.7 | M10: 117 | N10: =(40000/892)*M10 -> 5246.6368
A11: INI-02 | B11: A4: Diseñar e implementar el servicio/API e integraciones (pre-evaluación, datos internos/externos, pricing, motor si aplica) + auditoría. | C11: Objetivo: Diseñar e implementar el servicio/API e integraciones (pre-evaluación, datos internos/externos, pricing, motor si aplica) + auditoría. | D11: Especificación de API (OpenAPI) + arquitectura e integraciones + lineamientos de auditoría/logging. | Implementación del servicio (código + configuración por ambiente / feature flags). | E11: TI Arquitectura/Integración, Proveedor FICO/Ventiv (si participa en decisión/scoring) | F11: Técnica | G11: Implementa código, APIs, servicios, infraestructura o integración | H11: 5-8 semanas | I11: 1 PM/Scrum Master (25%) | 1 Arquitecto de Soluciones (50%) | 2 Desarrolladores Backend (100%) | 1 QA/Tester (50%) | 1 Especialista FICO/Blaze (50%) | 1 Coordinador Proveedor FICO/Ventiv (25%) | J11: 6.5 | K11: 4 | L11: 611.7 | M11: 1458 | N11: =(40000/892)*M11 -> 65381.166
A12: INI-02 | B12: A5: Ejecutar pruebas y calibración (funcionales, integración, performance) con histórico/simulación y ajustes de parámetros. | C12: Objetivo: Ejecutar pruebas y calibración (funcionales, integración, performance) con histórico/simulación y ajustes de parámetros. | D12: Plan y evidencias de pruebas (unitarias, integración, E2E, performance) + UAT firmado. | Especificación de API (OpenAPI) + arquitectura e integraciones + lineamientos de auditoría/logging. | E12: Ger. Comercial/Producto, Ger. Riesgo (políticas/umbrales), TI Arquitectura/Integración, Proveedor FICO/Ventiv (si participa en decisión/scoring), Canales (TAPP/SVP/Sucursal), Data/BI (seguimiento) | F12: Transversal | G12: Pruebas E2E, piloto, calibración, socialización o gobierno cruzado | H12: 1-2 semanas | I12: 1 Líder/PM de Iniciativa (50%) | 1 Analista Funcional (50%) | 1 QA Lead (50%) | Usuarios de Negocio para UAT (25%) | J12: 1.5 | K12: 1.75 | L12: 53.7 | M12: 126.7 | N12: =(40000/892)*M12 -> 5681.6143
A13: INI-02 | B13: A6: Implementar piloto y despliegue gradual por canal/segmento, con monitoreo de KPIs y mejora continua. | C13: Objetivo: Implementar piloto y despliegue gradual por canal/segmento, con monitoreo de KPIs y mejora continua. | D13: Tablero de monitoreo (conversión, % con oferta, aceptación, latencia/errores, mora temprana si aplica) + alertas. | Implementación del servicio (código + configuración por ambiente / feature flags). | E13: Ger. Comercial/Producto, Ger. Riesgo (políticas/umbrales), TI Arquitectura/Integración, Proveedor FICO/Ventiv (si participa en decisión/scoring), Canales (TAPP/SVP/Sucursal), Data/BI (seguimiento) | F13: Transversal | G13: Pruebas E2E, piloto, calibración, socialización o gobierno cruzado | H13: 2-4 semanas | I13: 1 Líder/PM de Iniciativa (50%) | 1 Analista Funcional (50%) | 1 Desarrollador Backend (50%) | 1 QA/Tester (50%) | 1 QA Lead (50%) | Usuarios de Negocio para UAT (25%) | J13: 3 | K13: 2.75 | L13: 168 | M13: 387.8 | N13: =(40000/892)*M13 -> 17390.135
... A203: INI-40 | B203: A6: Presentar a gerencia para decisión: Informe ejecutivo con recomendación y opciones de migración | C203: Objetivo: Presentar a gerencia para decisión. Resultado esperado: Informe ejecutivo con recomendación y opciones de migración | D203: Presentación ejecutiva para toma de decisión | API documentada para TAPP | E203: TI Operaciones (contingencia), Ger. Riesgo + Ger. Digital (validación) | F203: Funcional | G203: Define reglas, políticas, criterios o diseño de proceso/journey | H203: 1-2 semanas | I203: 1 Analista Funcional (100%) | 1 Especialista Riesgo (50%) | J203: 1.5 | K203: 1.5 | L203: 43.3 | M203: 101 | N203: =(40000/892)*M203 -> 4529.148
A204: INI-41 | B204: (Sin actividades definidas) | E204: Equipo Ciberseguridad CLA, TI Seguridad/Redes | F204: TBD | G204: Pendiente definición | H204: 2-3 semanas | I204: 1 Analista Funcional (50%) | 1 Desarrollador (50%) | J204: 2.5 | K204: 1 | L204: 47.6 | M204: 106.8 | N204: =(40000/892)*M204 -> 4789.2377
A205: INI-42 | B205: A1: Evaluación de alternativas CRM: Analizar opciones (Salesforce, Dynamics, mantener Siebel), costos, capacidades, integración con ecosistema CLA | C205: Objetivo: Evaluación de alternativas CRM. Resultado esperado: Analizar opciones (Salesforce, Dynamics, mantener Siebel), costos, capacidades, integración con ecosistema CLA | D205: Informe de evaluación de alternativas CRM con recomendación | Diseño del modelo de coexistencia Siebel + Salesforce | E205: Ger. Comercial | F205: Funcional | G205: Define reglas, políticas, criterios o diseño de proceso/journey | H205: 1-2 semanas | I205: 1 Analista Funcional (100%) | 1 Especialista Producto/Comercial (25%) | J205: 1.5 | K205: 1.25 | L205: 33.3 | M205: 74.2 | N205: =(40000/892)*M205 -> 3327.3543
A206: INI-42 | B206: A2: Diseño de modelo de coexistencia Siebel+Salesforce: Definir qué funciones migran primero, cuáles conviven, y por cuánto tiempo | C206: Objetivo: Diseño de modelo de coexistencia Siebel+Salesforce. Resultado esperado: Definir qué funciones migran primero, cuáles conviven, y por cuánto tiempo | D206: Diseño del modelo de coexistencia Siebel + Salesforce | Migración completa de datos Siebel → Salesforce validada | E206: Ger. Comercial | F206: Funcional | G206: Define reglas, políticas, criterios o diseño de proceso/journey | H206: 2-4 semanas | I206: 1 Analista Funcional (100%) | 1 Especialista Producto/Comercial (25%) | 1 Consultor Salesforce (50%) | 1 Especialista Siebel (50%) | J206: 3 | K206: 2.25 | L206: 146.4 | M206: 341.7 | N206: =(40000/892)*M206 -> 15322.87
A207: INI-42 | B207: A3: Desacople de evalScoring de Siebel (TO-BE 2): Extraer lógica de evaluación de scoring fuera de Siebel hacia MS Lógica Crédito (INI-21) | C207: Objetivo: Desacople de evalScoring de Siebel (TO-BE 2). Resultado esperado: Extraer lógica de evaluación de scoring fuera de Siebel hacia MS Lógica Crédito (INI-21) | D207: evalScoring desacoplado de Siebel y operativo en MS Lógica Crédito | Informe de evaluación de alternativas CRM con recomendación | E207: TI Desarrollo, Proveedor Salesforce | F207: Técnica | G207: Implementa código, APIs, servicios, infraestructura o integración | H207: 4-6 semanas | I207: 1 Desarrollador Backend (100%) | 1 QA/Tester (25%) | 1 Arquitecto de Soluciones (50%) | 1 Especialista Siebel (100%) | J207: 5 | K207: 2.75 | L207: 334.9 | M207: 811.8 | N207: =(40000/892)*M207 -> 36403.587
A208: INI-42 | B208: A4: Desarrollo de MVP Salesforce: Configurar Salesforce para funciones CRM core: gestión de clientes, seguimiento de solicitudes, reportes | C208: Objetivo: Desarrollo de MVP Salesforce. Resultado esperado: Configurar Salesforce para funciones CRM core: gestión de clientes, seguimiento de solicitudes, reportes | D208: Salesforce MVP desplegado con funciones CRM core | Diseño del modelo de coexistencia Siebel + Salesforce | E208: TI Desarrollo, Proveedor Salesforce | F208: Técnica | G208: Implementa código, APIs, servicios, infraestructura o integración | H208: 3-5 semanas | I208: 1 Arquitecto de Soluciones (25%) | 1 Desarrollador Backend (100%) | 1 Desarrollador Frontend (50%) | 1 QA/Tester (50%) | 1 Consultor Salesforce (100%) | J208: 4 | K208: 3.25 | L208: 307.2 | M208: 717.1 | N208: =(40000/892)*M208 -> 32156.951
A209: INI-42 | B209: A5: Migración de datos y procesos de Siebel a Salesforce: ETL de datos, mapeo de campos, validación de integridad, pruebas de paridad | C209: Objetivo: Migración de datos y procesos de Siebel a Salesforce. Resultado esperado: ETL de datos, mapeo de campos, validación de integridad, pruebas de paridad | D209: Migración completa de datos Siebel → Salesforce validada | Diseño del modelo de coexistencia Siebel + Salesforce | E209: Ger. Comercial, TI Desarrollo, Proveedor Salesforce | F209: Transversal | G209: Pruebas E2E, piloto, calibración, socialización o gobierno cruzado | H209: 6-10 semanas | I209: 1 Líder/PM de Iniciativa (50%) | 1 Analista Funcional (50%) | 1 Desarrollador Backend (50%) | 1 QA/Tester (50%) | 1 QA Lead (50%) | Usuarios de Negocio para UAT (25%) | 1 Arquitecto de Datos (50%) | 1 Consultor Salesforce (100%) | 1 Especialista Siebel (100%) | 1 Ingeniero ETL (100%) | J209: 8 | K209: 6.25 | L209: 1168.6 | M209: 2775.5 | N209: =(40000/892)*M209 -> 124461.88
A210: INI-42 | B210: A6: Cutover y apagado de Siebel: Plan de cutover con rollback, comunicación a usuarios, capacitación, monitoreo post-migración | C210: Objetivo: Cutover y apagado de Siebel. Resultado esperado: Plan de cutover con rollback, comunicación a usuarios, capacitación, monitoreo post-migración | D210: Migración completa de datos Siebel → Salesforce validada | Acta de apagado de Siebel y liberación de licencias | E210: Ger. Comercial, TI Desarrollo, Proveedor Salesforce | F210: Transversal | G210: Pruebas E2E, piloto, calibración, socialización o gobierno cruzado | H210: 3-5 semanas | I210: 1 Líder/PM de Iniciativa (50%) | 1 Analista Funcional (50%) | 1 Especialista Change Management (50%) | 1 Consultor Salesforce (50%) | 1 Especialista Siebel (50%) | 1 DevOps/SRE (50%) | J210: 4 | K210: 3 | L210: 286.4 | M210: 691 | N210: =(40000/892)*M210 -> 30986.547
A211: INI-43 | B211: A1: Relevamiento de requerimientos de ambientes: Mapear necesidades por INI técnica: ambientes, datos, herramientas QA | C211: Objetivo: Relevamiento de requerimientos de ambientes. Resultado esperado: Mapear necesidades por INI técnica: ambientes, datos, herramientas QA | D211: Mapa de requerimientos de ambientes por INI | Generador de datos sanitizados operativo | E211: TI QA, TI Desarrollo | F211: Funcional | G211: Define reglas, políticas, criterios o diseño de proceso/journey | H211: 1-2 semanas | I211: 1 Analista Funcional (100%) | J211: 1.5 | K211: 1 | L211: 26 | M211: 58.2 | N211: =(40000/892)*M211 -> 2609.8655
A212: INI-43 | B212: A2: Diseño de arquitectura de ambiente espejo: Arquitectura replicable de producción (OCI+GCP) con datos sanitizados | C212: Objetivo: Diseño de arquitectura de ambiente espejo. Resultado esperado: Arquitectura replicable de producción (OCI+GCP) con datos sanitizados | D212: Arquitectura de ambiente espejo documentada y desplegada | Generador de datos sanitizados operativo | E212: TI QA, TI Desarrollo, TI Infraestructura | F212: Técnica | G212: Implementa código, APIs, servicios, infraestructura o integración | H212: 2-3 semanas | I212: 1 Desarrollador Backend (100%) | 1 QA/Tester (25%) | 1 Ingeniero Cloud GCP (50%) | 1 Especialista Oracle/OCI (50%) | J212: 2.5 | K212: 2.25 | L212: 134.2 | M212: 313.5 | N212: =(40000/892)*M212 -> 14058.296
A213: INI-43 | B213: A3: Generación de datos de prueba sanitizados: Framework de generación/anonimización de datos representativos del volumen real | C213: Objetivo: Generación de datos de prueba sanitizados. Resultado esperado: Framework de generación/anonimización de datos representativos del volumen real | D213: Pipeline CI/CD configurado para ambientes de prueba | Generador de datos sanitizados operativo | E213: TI QA, TI Desarrollo | F213: Funcional | G213: Define reglas, políticas, criterios o diseño de proceso/journey | H213: 1-2 semanas | I213: 1 Analista Funcional (100%) | J213: 1.5 | K213: 1 | L213: 26 | M213: 58.2 | N213: =(40000/892)*M213 -> 2609.8655
A214: INI-43 | B214: A4: Desarrollo de suite de regresión automatizada: Casos de prueba E2E automatizados para cada servicio crítico del flujo de crédito | C214: Objetivo: Desarrollo de suite de regresión automatizada. Resultado esperado: Casos de prueba E2E automatizados para cada servicio crítico del flujo de crédito | D214: Pipeline CI/CD configurado para ambientes de prueba | Suite de regresión automatizada con cobertura de servicios críticos | E214: TI QA, TI Desarrollo, TI Infraestructura | F214: Técnica | G214: Implementa código, APIs, servicios, infraestructura o integración | H214: 2-3 semanas | I214: 1 Desarrollador Backend (100%) | 1 QA/Tester (25%) | 1 Ingeniero Cloud GCP (50%) | 1 Especialista Oracle/OCI (50%) | J214: 2.5 | K214: 2.25 | L214: 134.2 | M214: 313.5 | N214: =(40000/892)*M214 -> 14058.296
A215: INI-43 | B215: A5: Implementación de CI/CD para ambientes: Pipeline automatizado para deploy en ambientes de prueba (Jenkins/CloudBuild) | C215: Objetivo: Implementación de CI/CD para ambientes. Resultado esperado: Pipeline automatizado para deploy en ambientes de prueba (Jenkins/CloudBuild) | D215: Pipeline CI/CD configurado para ambientes de prueba | Mapa de requerimientos de ambientes por INI | E215: TI QA, TI Desarrollo, TI Infraestructura | F215: Técnica | G215: Implementa código, APIs, servicios, infraestructura o integración | H215: 2-3 semanas | I215: 1 Desarrollador Backend (100%) | 1 QA/Tester (25%) | 1 Ingeniero Cloud GCP (50%) | 1 Especialista Oracle/OCI (50%) | 1 DevOps/SRE (50%) | J215: 2.5 | K215: 2.75 | L215: 166 | M215: 389.4 | N215: =(40000/892)*M215 -> 17461.883
A216: INI-43 | B216: A6: Piloto con INIs técnicas priorizadas: Validar ambiente con INI-18, INI-24 y INI-35 como primeros usuarios | C216: Objetivo: Piloto con INIs técnicas priorizadas. Resultado esperado: Validar ambiente con INI-18, INI-24 y INI-35 como primeros usuarios | D216: Arquitectura de ambiente espejo documentada y desplegada | Reporte de piloto con resultados y ajustes | E216: TI QA, TI Desarrollo, TI Infraestructura | F216: Transversal | G216: Pruebas E2E, piloto, calibración, socialización o gobierno cruzado | H216: 1-2 semanas | I216: 1 Líder/PM de Iniciativa (50%) | 1 Analista Funcional (50%) | 1 QA Lead (50%) | Usuarios de Negocio para UAT (25%) | J216: 1.5 | K216: 1.75 | L216: 53.7 | M216: 126.7 | N216: =(40000/892)*M216 -> 5681.6143
... A242: INI-48 | B242: A8: Testing E2E + piloto controlado: Ejecutar pruebas end-to-end del flujo completo (abandono → captura → job → notificación → aceptación express). Piloto con 5% de abandonos durante 2 semanas. Criterio go/no-go: >5% conversión sobre reenganches enviados. | C242: Objetivo: Validar el flujo completo en condiciones reales antes del rollout. Resultado esperado: Informe de piloto con métricas reales, decisión go/no-go fundamentada, y ajustes identificados para rollout masivo. | D242: Plan de pruebas E2E + evidencias de ejecución | Informe de piloto con métricas + decisión go/no-go para rollout | E242: QA, TI Desarrollo, Ger. Comercial, Ger. Riesgo, Ger. Digital | F242: Transversal | G242: Pruebas E2E, piloto, calibración, socialización o actividad que cruza capas | H242: 1-2 semanas | I242: 1 Líder/PM de Iniciativa (50%) | 1 Analista Funcional (50%) | 1 QA Lead (50%) | Usuarios de Negocio para UAT (25%) | J242: 1.5 | K242: 1.75 | L242: 53.7 | M242: 126.7 | N242: =(40000/892)*M242 -> 5681.6143
A243: INI-49 | B243: A1 — Benchmark + Análisis heurístico AS-IS | C243: OBJETIVO: Auditar la experiencia actual de presentación de oferta en TAPP (digital) y SVP (presencial). Evaluar: ¿qué ve el afiliado? ¿en qué orden? ¿qué información falta? ¿cuándo se entera de los seguros/comisiones? Benchmark con 3-5 referentes (bancos/cajas/fintech). RESULTADO: Mapeo de pantallas de oferta TAPP y SVP, gaps de información, puntos de fricción, benchmark competitivo con 3-5 referentes documentados (capturas + análisis heurístico). | D243: E1 — Informe auditoría heurística + benchmark competitivo (3-5 referentes) | E243: Ger. Producto Ger. Canales Digitales UX/Experiencia de Cliente | F243: Research / Discovery | G243: Análisis documental y de competencia. No requiere desarrollo ni cambio de sistemas. Se ejecuta con herramientas existentes. Cero impacto en producción. | H243: 2 semanas | I243: UX Researcher (líder): 100% × 2 sem Analista de Producto: 20% × 2 sem Analista Canales: 20% × 2 sem | J243: 2 | K243: 1,4 | L243: 75 | M243: =L243*2.35940409683426 -> 176.95531 | N243: =(40000/892)*M243 -> 7935.2156
A244: INI-49 | B244: A2 — Research cualitativo con afiliados | C244: OBJETIVO: Entrevistas en profundidad con 8-12 afiliados (mix: 4-6 digital + 4-6 presencial; abandonaron + contrataron). ① ¿Qué entienden que incluye su crédito? ② ¿Saben que pagan seguro desgravamen? ③ ¿Prefieren ver todo junto o separado? ④ ¿Qué les genera desconfianza? ⑤ ¿Qué los haría abandonar? ⑥ ¿Cuál formato los frustra menos? RESULTADO: Insights cualitativos validados: personas, pain points priorizados, verbatims clave, preferencias declaradas (paquete vs desglose vs simple), drivers de confianza/desconfianza, momentos de frustración. | D244: E2 — Informe research cualitativo: insights, personas, pain points, verbatims, preferencias | E244: UX/Experiencia de Cliente Ger. Comercial Ger. Canales Digitales | F244: Research / Discovery | G244: Entrevistas cualitativas con afiliados reales. No requiere desarrollo ni cambio técnico. Necesita reclutamiento participantes e incentivos (~1.5 UF/persona). | H244: 2-3 semanas | I244: UX Researcher (líder): 100% × 3 sem Reclutador participantes: 50% × 1 sem Nota-taker: 50% × 1.5 sem | J244: 3 | K244: 1,6 | L244: 115 | M244: =L244*2.35940409683426 -> 271.33147 | N244: =(40000/892)*M244 -> 12167.331
A245: INI-49 | B245: A3 — Diseño de 3 variantes de oferta | C245: OBJETIVO: Diseñar prototipos alta fidelidad (Figma) para 3 variantes: • Variante A (Control/AS-IS): Oferta simple — monto, cuota, plazo, tasa. • Variante B (Paquete integrado): 'Tu crédito incluye' — crédito + seguro + productos, precio total, badge 'todo incluido'. • Variante C (Desglose transparente): Componentes separados — cuota crédito ($X), seguro ($Y), comisión ($Z), total ($T). Toggle on/off opcionales. Cada variante para TAPP (móvil) y SVP (web). RESULTADO: 3 prototipos alta fidelidad Figma, clickeables, flujo completo pantalla de oferta por variante para TAPP (mobile) y SVP (desktop). Validados con Ger. Producto antes de testeo. | D245: E3 — 3 prototipos alta fidelidad (Figma): Variante A + B + C para TAPP y SVP | E245: UX/Experiencia de Cliente Ger. Producto Ger. Canales Digitales Ger. Riesgo | F245: Diseño UX / Prototipado | G245: Trabajo de diseño en Figma. No requiere desarrollo en producción. Prototipos interactivos no conectados a sistemas reales. Validación interna antes de exponer a afiliados. | H245: 2-3 semanas | I245: UX Designer (líder): 100% × 3 sem UX Researcher: 30% × 3 sem Product Manager: 20% × 3 sem | J245: 3 | K245: 1,5 | L245: 110 | M245: =L245*2.35940409683426 -> 259.53445 | N245: =(40000/892)*M245 -> 11638.316
A246: INI-49 | B246: A4 — Test de usabilidad + comprensión (cualitativo) | C246: OBJETIVO: Test moderado con 12-15 afiliados (4-5 por variante). Protocolo think-aloud + cuestionario post-tarea. Métricas: ① Tasa de comprensión ('¿qué incluye tu cuota?') ② Tiempo en pantalla ③ Confianza percibida (1-5) ④ Preferencia declarada ⑤ Puntos de confusión/fricción ⑥ Nivel de frustración (1-5). RESULTADO: Métricas comparativas por variante: comprensión (% correcto), confianza, frustración, tiempo en pantalla, preferencia. Matriz de decisión con las 2 variantes a llevar al test A/B. Clips de video highlight. | D246: E4 — Informe test usabilidad: métricas por variante, matriz preferencia, recomendación 2 variantes para A/B | E246: UX/Experiencia de Cliente Ger. Comercial Ger. Producto | F246: Research / Testing cualitativo | G246: Test con usuarios reales sobre prototipos Figma (no producción). Necesita sala/remoto para sesiones, herramienta grabación. Incentivos participantes. | H246: 1-2 semanas | I246: UX Researcher (líder): 100% × 2 sem Nota-taker/observador: 50% × 1 sem Data Analyst: 20% × 0.5 sem | J246: 2 | K246: 1,2 | L246: 80 | M246: =L246*2.35940409683426 -> 188.75233 | N246: =(40000/892)*M246 -> 8464.2299
A247: INI-49 | B247: A5 — Test A/B cuantitativo (piloto en TAPP) | C247: OBJETIVO: Implementar 2 variantes ganadoras como feature flags en TAPP, 2-4 semanas, distribución 50/50. Medir con datos reales: ① Tasa de avance post-oferta ② Tasa de abandono en pantalla de oferta ③ Tasa de contratación completa (hasta desembolso) ④ Tiempo en pantalla ⑤ Tasa de reclamo post-venta (D+30) Mínimo 500 sesiones por variante (p<0.05). RESULTADO: Informe cuantitativo con significancia estadística: variante ganadora en conversión, delta abandono, delta reclamos D+30. Tablas de contingencia, intervalos de confianza, Cohen's d. Decisión data-driven. | D247: E5 — Informe test A/B: conversión por variante, significancia estadística, variante ganadora | E247: Ger. Canales Digitales Data/BI UX/Experiencia Equipo TAPP / proveedor | F247: Testing cuantitativo / Piloto productivo | G247: ÚNICA actividad que toca producción: feature flags en TAPP para variantes al 50% tráfico. Impacto controlado, reversible. No modifica lógica de negocio ni backend, solo capa de presentación. | H247: 3-5 semanas | I247: Data Analyst (líder): 80% × 4 sem Dev TAPP (flags): 50% × 1.5 sem UX Researcher: 30% × 1 sem Product Manager: 20% × 4 sem | J247: 4 | K247: 2 | L247: 165 | M247: =L247*2.35940409683426 -> 389.30168 | N247: =(40000/892)*M247 -> 17457.474
A248: INI-49 | B248: A6 — Análisis de impacto en reclamos y post-venta | C248: OBJETIVO: Cruzar reclamos SERNAC/internos (12 meses) con tipo de oferta. Categorizar: ① 'No sabía que incluía seguro' ② 'Cuota mayor a la esperada' ③ 'Cobros no informados' Estimar reducción con Variante B o C. Revisión Legal/Cumplimiento sobre transparencia CMF/SERNAC. RESULTADO: N reclamos por categoría, % atribuible a falta de transparencia, estimación reducción por variante. Checklist cumplimiento CMF/SERNAC validado con Legal. Productos obligatorios vs opcionales. | D248: E6 — Análisis reclamos (12 meses) + estimación reducción + checklist normativo CMF/SERNAC | E248: Legal/Cumplimiento Ger. Producto Data/BI Atención al Cliente | F248: Análisis de datos / Compliance | G248: Análisis datos históricos + revisión normativa. No requiere desarrollo. Se ejecuta en PARALELO con A5. Requiere acceso base reclamos SERNAC/internos. | H248: 1-2 semanas | I248: Data Analyst (líder): 60% × 2 sem Abogado/Compliance: 40% × 2 sem Analista Reclamos: 30% × 1 sem | J248: 2 | K248: 1,1 | L248: 70 | M248: =L248*2.35940409683426 -> 165.15829 | N248: =(40000/892)*M248 -> 7406.2012
A249: INI-49 | B249: A7 — Informe final + recomendación + prototipos definitivos | C249: OBJETIVO: Consolidar hallazgos A1-A6: ① Variante recomendada (evidencia cuanti + cuali) ② Impacto estimado en conversión, comprensión, NPS, reclamos ③ Prototipos definitivos ajustados por feedback A/B ④ Roadmap implementación UX (TAPP/SVP) ⑤ Quick wins de copy/layout aplicables inmediatamente ⑥ Recomendaciones largo plazo RESULTADO: Informe ejecutivo (<30 págs) con recomendación fundamentada, prototipos finales Figma, roadmap implementación, lista quick wins. Listo para workshop gerencias (A8). | D249: E7 — Informe ejecutivo final + prototipos definitivos Figma + roadmap UX + quick wins | E249: UX/Experiencia de Cliente Ger. Producto Ger. Canales Digitales Data/BI | F249: Consolidación / Documentación | G249: Síntesis y documentación. No requiere desarrollo. Es el entregable principal que habilita la decisión de gerencias. Incluye ajuste prototipos Figma por feedback A/B. | H249: 1-2 semanas | I249: UX Researcher (líder): 100% × 2 sem UX Designer: 60% × 2 sem Data Analyst: 30% × 1 sem Product Manager: 20% × 1 sem | J249: 2 | K249: 1,6 | L249: 95 | M249: =L249*2.35940409683426 -> 224.14339 | N249: =(40000/892)*M249 -> 10051.273
A250: INI-49 | B250: A8 — Presentación a gerencias + decisión go/no-go | C250: OBJETIVO: Workshop 2h con Ger. Producto, Comercial, Canales, Riesgo y Cumplimiento: ① Hallazgos clave (15 min) ② Prototipos en vivo (20 min) ③ Implicancias: ¿se puede quitar seguro? ¿qué es obligatorio? (20 min) ④ Impacto conversión y reclamos (15 min) ⑤ Decisión formal: variante + horizonte + recursos (30 min) ⑥ ¿Quién lidera implementación TAPP? (10 min) RESULTADO: Decisión formal: variante aprobada, horizonte implementación, responsable asignado, recursos comprometidos. Minuta firmada por 5 gerencias. Plan de acción con fechas. | D250: E8 — Minuta decisión firmada por 5 gerencias + variante aprobada + plan acción + responsable | E250: Ger. Producto Ger. Comercial Ger. Canales Digitales Ger. Riesgo Legal/Cumplimiento | F250: Governance / Decisión ejecutiva | G250: Sesión de decisión ejecutiva. Gate de aprobación que habilita implementación. Sin esta decisión formal, no hay mandato para cambiar pantalla de oferta. | H250: 1-2 semanas | I250: UX Researcher (presentador): 100% × 0.5 sem Product Manager (co-presentador): 100% × 0.5 sem 5 Gerentes: 2 horas cada uno | J250: 1 | K250: 0,5 | L250: 30 | M250: =L250*2.35940409683426 -> 70.782123 | N250: =(40000/892)*M250 -> 3174.0862

Sheet Resumen Tipo x INI (2)
A1: INI | B1: Iniciativa | C1: Total Actividades | D1: 🟢 Funcional | E1: 🔴 Técnica | F1: 🟠 Transversal | G1: % Funcional | H1: % Técnica | I1: % Transversal | J1: Perfil Predominante
A2: INI-42 | B2: Modernización del CRM (Siebel → Salesforce) | C2: 6 | D2: 2 | E2: 2 | F2: 2 | G2: 33% | H2: 33% | I2: 33% | J2: Equilibrada
A3: INI-33 | B3: Herramienta de Parametrización de Reglas de Negocio + IA | C3: 5 | D3: 2 | E3: 2 | F3: 1 | G3: 40% | H3: 40% | I3: 20% | J3: Equilibrada Funcional-Técnica
A4: INI-18 | B4: Consolidación Motor FICO v7 + Deprecación v4/Nashorn + Paridad y Apagado Definitivo | C4: 4 | D4: 2 | E4: 0 | F4: 2 | G4: 50% | H4: 0% | I4: 50% | J4: Equilibrada Funcional-Transversal
A5: INI-02 | B5: Nuevo Servicio de Generación de Oferta Dinámica - | C5: 6 | D5: 3 | E5: 1 | F5: 2 | G5: 50% | H5: 17% | I5: 33% | J5: Mayoritariamente Funcional
A6: INI-06 | B6: Ajuste del Proceso de Derivación de Canales | C6: 6 | D6: 3 | E6: 2 | F6: 1 | G6: 50% | H6: 33% | I6: 17% | J6: Mayoritariamente Funcional
A7: INI-07 | B7: Retomabilidad Omnicanal (Persistencia de Estado) - | C7: 6 | D7: 3 | E7: 2 | F7: 1 | G7: 50% | H7: 33% | I7: 17% | J7: Mayoritariamente Funcional
A8: INI-08 | B8: Racionalización del Journey Pre-evaluación / Evaluación - | C8: 6 | D8: 4 | E8: 1 | F8: 1 | G8: 67% | H8: 17% | I8: 17% | J8: Mayoritariamente Funcional
A9: INI-11 | B9: Desacople Lógica de Negocio del Motor + Gobierno de Reglas | C9: 7 | D9: 3 | E9: 2 | F9: 2 | G9: 43% | H9: 29% | I9: 29% | J9: Mayoritariamente Funcional
A10: INI-12 | B10: Gobierno Integral E2E del Proceso de Crédito (Blueprint + Owner + RACI + Cadencias) | C10: 8 | D10: 4 | E10: 3 | F10: 1 | G10: 50% | H10: 38% | I10: 12% | J10: Mayoritariamente Funcional
A11: INI-13 | B11: Resiliencia Operativa y Flujos de Excepción | C11: 11 | D11: 5 | E11: 4 | F11: 2 | G11: 45% | H11: 36% | I11: 18% | J11: Mayoritariamente Funcional
A12: INI-14 | B12: Módulo de Solicitud de Crédito en TAPP (Sin Banner) — | C12: 6 | D12: 3 | E12: 2 | F12: 1 | G12: 50% | H12: 33% | I12: 17% | J12: Mayoritariamente Funcional
A13: INI-15 | B13: Recuperación de Simulación ante Caída (Session Recovery) — | C13: 6 | D13: 3 | E13: 2 | F13: 1 | G13: 50% | H13: 33% | I13: 17% | J13: Mayoritariamente Funcional
... A42: INI-47 | B42: Modificación de Canales y Ajustes a Integraciones por INIs Técnicas | C42: 6 | D42: 1 | E42: 4 | F42: 1 | G42: 17% | H42: 67% | I42: 17% | J42: Mayoritariamente Técnica
A43: INI-48 | B43: Reenganche Automático por Simulación Abandonada | C43: 8 | D43: 2 | E43: 5 | F43: 1 | G43: 0.25 | H43: 0.63 | I43: 0.12 | J43: Mayoritariamente Técnica
A44: INI-41 | B44: Implementar Buenas Prácticas de Ciberseguridad | C44: 1 | D44: 0 | E44: 0 | F44: 0 | G44: 0% | H44: 0% | I44: 0% | J44: Pendiente definición

Sheet Eliminadas (Trazabilidad)
